Workbook

Sheet GESTION MOMENTUM
A1: FONDOS COMUNES DE INVERSION
A2: 30/10/2026
A3: 10:19:45
A4: Informe de Gestión al 29/10/2026 | K4: MOMENTUM
A5: FCI ABIERTO MOMENTUM PYMES | K5: COMAFI $ Nº 24148/3
A6: Todos los importes están expresados en Pesos | K6: BANCO DEL SOL
C7: (4) | D7: (1) | L7: 46325 | M7: =WORKDAY(L7,1,$R:$R) -> 46328 | N7: =WORKDAY(M7,1,$R:$R) -> 46329 | R7: 45719 | S7: Lista de feriados 2025
A8: ACTIVO | B8: 8.2418646e+10 | C8: 100 | K8: Caucion MAV | L8: 2.0011378e+09 | R8: 45720
A9: INVERSIONES | B9: 7.9614068e+10 | C9: 96.6 | D9: 97.44 | K9: Caucion Byma | R9: 45740
A10: TITULOS PUBLICOS | B10: 1097044698 | C10: 1.33 | D10: 1.34 | K10: Plazo Fijo | L10: =SUMIFS(F:F,A:A,$K$10,B:B,L7) -> 0 | M10: =SUMIFS(G:G,B:B,$K$10,C:C,M7) -> 0 | N10: =SUMIFS(H:H,C:C,$K$10,D:D,N7) -> 0 | R10: 45749
A11: FUTUROS | B11: -8017217500 | C11: -9.73 | D11: -9.81 | K11: Vto. Cheques | L11: =SUMIF($B$101:$B$2996,L7,$D$101:$D$2996) -> 1.7197252e+09 | M11: =SUMIF($B$101:$B$2996,M7,$D$101:$D$2996) -> 1.5761027e+09 | N11: =SUMIF($B$101:$B$2996,N7,$D$101:$D$2996) -> 2.3416412e+09 | P11: =SUMIF($B$99:$B$1878,P7,$D$99:$D$1878) -> 0 | Q11: =SUMIF($B$99:$B$1878,Q7,$D$99:$D$1878) -> 0 | R11: =SUMIF($B$99:$B$1878,R7,$D$99:$D$1878) -> 0 | S11: =SUMIF($B$99:$B$1878,S7,$D$99:$D$1878) -> 0 | T11: =SUMIF($B$99:$B$1878,T7,$D$99:$D$1878) -> 0
A12: DISPONIBILIDADES | B12: 22697507 | C12: 0.03 | D12: 0.03 | K12: Vto. Pagarés/FCE Dollar Linked | L12: =+SUMIF($B$3000:$B$3040,L7,$F$3000:$F$3040) -> 0 | M12: =+SUMIF($B$3000:$B$3040,M7,$F$3000:$F$3040) -> 0 | N12: =+SUMIF($B$3000:$B$3040,N7,$F$3000:$F$3040) -> 0 | R12: 45778
A13: EN PESOS | B13: 22697815 | C13: 0.03 | D13: 0.03 | J13: 0.1914 | K13: FCI IEB Ahorro - Clase E | L13: =SUMIF(A:A,K13,E:E)*(1+(J13/365)*1) -> 2.1241133e+09 | R13: 45779
A14: EN DOLARES | B14: -307.92 | C14: 0 | D14: 0 | K14: COMAFI $ Nº 24148/3 | L14: =+B13 -> 22697815 | R14: 45802
A15: CREDITOS | B15: 2.7818804e+09 | C15: 3.38 | D15: 3.4 | K15: Ctte Momentum | L15: 19578500 | R15: 45824
A16: PASIVO | B16: -7.1025901e+08 | K16: Cheques pendientes | R16: 45828
A17: PROVISIONES | B17: -1.7881313e+08 | K17: Compra/Venta Bonos | R17: 45847
A18: PROV. HONORARIOS SOC. DEPOSITARIA | B18: -10375743 | K18: TOTAL | L18: =SUM(L8:L17) -> 5.8872526e+09 | R18: 45884
A19: PROV. HONORARIOS SOCIEDAD GERENTE | B19: -1.5312489e+08 | K19: Neg. Cheques / Pagare | R19: 45886
A20: PROV. GASTOS SOCIEDAD DEPOSITARIA | B20: -15312489 | K20: Coloca caucion MAV | R20: 45942
A21: DEUDAS EN PESOS | B21: -5.2622709e+08 | K21: Compra/Venta de Bonos | R21: 45982
A22: RESCATES | B22: -84000000 | J22: EGRESOS EN EL DIA Clase B | K22: Suscripciones | R22: 45985
A23: PREVISIÓN INCOBRABLES | B23: -4.4018937e+08 | K23: Rescates | L23: =SUMIF(A:A,K23,B:B) -> -84000000 | R23: 45999
A24: Valor Patrimonial del Fondo | B24: 8.1708387e+10 | K24: Pase | R24: 46016
A25: Liquidez Efectiva (2) | B25: 2.273132e+09 | D25: 2.78 | K25: Rentas y Amortizaciones
A26: Liquidez Corriente (3) | B26: 2.0943189e+09 | D26: 2.56 | K26: Pago de honorarios ACDI
K27: Caja cierre | L27: =SUM(L18:L26) -> 5.8032526e+09 | M27: =SUM(M8:M26) -> 1.5761027e+09 | N27: =SUM(N8:N26) -> 2.3416412e+09
A41: Inversiones
A42: TITULO PUBLICO en Pesos
A43: Denominación | B43: IsinCode | C43: Cantidad | D43: Cierre | E43: Total | F43: % (1) | G43: Costo | H43: Var | I43: Vencimiento
A44: Lecap S30N6 | B44: AR0451031345 | C44: 500000000 | D44: 1.2745 | E44: 637261975 | F44: 0.78 | G44: 0 | I44: 30/11/2026
A45: TMG28 - Bono del Tesoro Nacional | B45: AR0175438917 | C45: 600000000 | D45: 1.1025 | E45: 661501302 | F45: 0.81 | G45: 0 | I45: 31/01/2028
C46: 1100000000 | E46: 1298763277 | F46: 1.59
A48: OBLIGACIONES NEGOCIABLES en Pesos
A49: Denominación | B49: IsinCode | C49: Cantidad | D49: Cierre | E49: Total | F49: % (1) | G49: Costo | H49: Var | I49: Vencimiento
A50: LR8AO - ON Laboratorios Richmond Serie 8 Clase A | B50: AR0266435707 | C50: 300000000 | D50: 1.1273 | E50: 338192253 | F50: 0.41 | G50: 0 | I50: 31/07/2028
A51: MTC3O - ON Mastellone Clase 3 | B51: AR0494875476 | C51: 250000000 | D51: 1.016 | E51: 253988325 | F51: 0.31 | G51: 1 | H51: 1.6 | I51: 22/06/2027
C52: 550000000 | E52: 592180578 | F52: 0.72
A54: FIDEICOMISOS FINANCIEROS en Pesos
A55: Denominación | B55: IsinCode | C55: Cantidad | D55: Cierre | E55: Total | F55: % (1) | G55: Costo | H55: Var | I55: Vencimiento
A56: CQ08A - VD FF CENTROCARD CREDITOS 8 CL.A $ | B56: AR0253965559 | C56: 250000000 | D56: 0.6332 | E56: 158308610 | F56: 0.19 | G56: 0.9784 | H56: -35.28 | I56: 26/05/2027 | K56: Activos Pyme | L56: 6.6921612e+10
A57: FF AMFAyS S49 Clase A | B57: AR0711423134 | C57: 100000000 | D57: 0.0699 | E57: 6985208 | F57: 0.01 | G57: 0.9846 | H57: -92.91 | I57: 31/12/2026 | K57: % Pyme | L57: =L56/B24 -> 0.8190299
A58: GE05A - VDF Grancoop 5 Clase A | B58: AR0985951141 | C58: 300000000 | D58: 0.9195 | E58: 275854038 | F58: 0.34 | G58: 0.9961 | H58: -7.69 | I58: 22/11/2027
A59: MY50B - VD FF AMFAYS S.50 CL.B $ | B59: AR0695284973 | C59: 101962042 | D59: 1.4678 | E59: 1.4965989e+08 | F59: 0.18 | G59: 0.924 | H59: 58.85 | I59: 13/01/2027 | K59: T+1 Ayer
A60: MY50C - VD FF AMFAYS S.50 CL.C $ | B60: AR0890638411 | C60: 382357659 | D60: 1.2979 | E60: 4.9625705e+08 | F60: 0.61 | G60: 0.85 | H60: 52.69 | I60: 13/04/2027 | K60: T+0 Hoy | L60: =+W68 -> 3.9780119e+08
A61: MY51B - VD FF AMFAYS Serie 51 Clase B | B61: AR0207834935 | C61: 75584213 | D61: 1.1736 | E61: 88707666 | F61: 0.11 | G61: 0.8718 | H61: 34.62 | I61: 15/03/2027 | K61: Conciliación Derivacion | L61: =+L60+L59+L19 -> 3.9780119e+08
A62: MY51C - VD FF AMFAYS Serie 51 Clase C | B62: AR0601005553 | C62: 176363163 | D62: 1.1056 | E62: 1.949906e+08 | F62: 0.24 | G62: 0.8446 | H62: 30.9 | I62: 15/11/2027
A63: MY52B - FF AMFAYS 52 CL.B $ | B63: AR0013738833 | C63: 63635566 | D63: 1.0105 | E63: 64305453 | F63: 0.08 | G63: 0.9054 | H63: 11.61 | I63: 15/12/2027
A64: MY52C - FF AMFAYS 52 CL.C $ | B64: AR0959603397 | C64: 148482986 | D64: 0.9274 | E64: 1.3770906e+08 | F64: 0.17 | G64: 0.7853 | H64: 18.1 | I64: 15/02/2028
C65: 1598385629 | E65: 1.5727776e+09 | F65: 1.92 | K65: PN ACTUAL | L65: =VLOOKUP("Valor Patrimonial del Fondo",A:B,2,0)+L22 -> 8.1708387e+10 | U65: Operación cheques
K66: Límite | L66: $ | M66: % | N66: Diferencia | U66: Concertación | V66: Liquidación | W66: Suma de Neto
A67: FUTUROS en Pesos | K67: 5% MM | L67: =+$L$65*M67 -> 4.0854193e+09 | M67: 0.05 | N67: =+L67-L27 -> -1.7178333e+09 | O67: =+L67-L13 -> 1.9613061e+09 | U67: 46303 | V67: 46303 | W67: 4.8518872e+08
A68: Denominación | B68: IsinCode | C68: Cantidad | D68: Cierre | E68: Total | F68: % (1) | G68: Costo | H68: Var | I68: Vencimiento | K68: 20% CAUCION | L68: =+$L$65*M68 -> 1.6341677e+10 | M68: 0.2 | N68: =+L68-(L8+L9) -> 1.434054e+10 | U68: 46304 | V68: 46304 | W68: 3.9780119e+08
A69: Fut Rofex DLR012027 | C69: -120000 | D69: 1624 | E69: -194880000 | F69: -0.24 | G69: 0 | I69: 29/01/2027 | K69: 20% Librador | L69: =+$L$65*M69 -> 1.6341677e+10 | M69: 0.2 | N69: =L69-M72 -> 1.2873837e+10
A70: Fut Rofex DLR042027 | C70: -1800000 | D70: 1715 | E70: -3087000000 | F70: -3.78 | G70: 0 | I70: 30/04/2027 | K70: % Pymes | L70: =+$L$65*M70 -> 6.128129e+10 | M70: 0.75 | N70: =+L56-L70 -> 5.6403219e+09
A71: Fut Rofex DLR102026 | C71: -1357000 | D71: 1538 | E71: -2087066000 | F71: -2.55 | G71: 0 | I71: 30/10/2026
A72: Fut Rofex DLR112026 | C72: -750000 | D72: 1567.5 | E72: -1175625000 | F72: -1.44 | G72: 0 | I72: 30/11/2026 | K72: Máximo librador | L72: {=_xlfn.LET(_xlpm.lib,_xlfn.UNIQUE('Reporte de Cheques'!$A$4:$A$4982),_xlpm.tot,SUMIFS('Reporte de Cheques'!$J$4:$J$4982,'Reporte de Cheques'!$A$4:$A$4982,_xlpm.lib),_xlfn.XLOOKUP(MAX(_xlpm.tot),_xlpm.tot,_xlpm.lib))} -> A M F A Y S ASOCIACION MUTUAL | M72: {=MAX(SUMIFS('Reporte de Cheques'!$J$4:$J$4982,'Reporte de Cheques'!$A$4:$A$4982,_xlfn.UNIQUE('Reporte de Cheques'!$A$4:$A$4982)))} -> 3.4678401e+09
A73: Fut Rofex DLR122026 | C73: -923000 | D73: 1595.5 | E73: -1472646500 | F73: -1.8 | G73: 0 | I73: 31/12/2026
C74: -4950000 | E74: -8017217500 | F74: -9.81 | K74: Pagarés Dólar Link que vencen hoy
K75: Librador | L75: Vencimiento | M75: Nominal (USD) | N75: Importe Actual ($)
A76: MONEY MARKET en Pesos | K76: {=_xlfn._xlws.FILTER(_xlfn.CHOOSECOLS('Reporte de Cheques'!A4:V2249,1,3,7,10,21),('Reporte de Cheques'!B4:B2249="Dolar Link")*('Reporte de Cheques'!C4:C2249=TODAY()),"Sin vencimientos hoy")} -> Sin vencimientos hoy
A77: Denominación | B77: IsinCode | C77: Cantidad | D77: Cierre | E77: Total | F77: % (1) | G77: Costo | H77: Var | I77: Vencimiento
A78: FCI IEB Ahorro - Clase E | C78: 1.6021353e+08 | D78: 13.2511 | E78: 2123000000 | F78: 2.6 | G78: 13.2432 | H78: 0.06
C79: 1.6021353e+08 | E79: 2123000000 | F79: 2.6
A81: PAGARE en Pesos
A82: Denominación | B82: IsinCode | C82: Cantidad | D82: Cierre | E82: Total | F82: % (1) | G82: Costo | H82: Var | I82: Vencimiento
A83: #MAV181160012 | C83: 300000000 | D83: 1.0471 | E83: 3.1414326e+08 | F83: 0.38 | G83: 0.9841 | H83: 6.41 | I83: 19/11/2026
A84: #MAV250370017 | C84: 100000000 | D84: 0.9802 | E84: 98015915 | F84: 0.12 | G84: 0.9793 | H84: 0.09 | I84: 30/03/2027
C85: 400000000 | E85: 4.1215917e+08 | F85: 0.5
A87: TITULO PROVINCIAL en Pesos
A88: Denominación | B88: IsinCode | C88: Cantidad | D88: Cierre | E88: Total | F88: % (1) | G88: Costo | H88: Var | I88: Vencimiento
A89: PBA27 - Letra de la Provincia de Buenos Aires Vto 30/04/27 | B89: AR0647160248 | C89: 400000000 | D89: 1.0889 | E89: 435543396 | F89: 0.53 | G89: 1 | H89: 8.89 | I89: 30/04/2027
C90: 400000000 | E90: 435543396 | F90: 0.53
A93: Aperturas, Pases y Cauciones en Pesos
A94: Tipo | B94: Vencimiento | C94: Concertación | D94: Plazo | E94: Tasa | F94: Total | G94: % (1)
A95: CAUCION | B95: 30/10/2026 | C95: 29/10/2026 | D95: 1 | E95: 20.764578 | F95: 2000000000 | G95: 2.45
A96: PASE | B96: 04/11/2026 | C96: 05/10/2026 | D96: 30 | E96: 37.500944 | F96: 6.0495817e+08 | G96: 0.74
D97: 2.16 | E97: 31.555256 | F97: 2.6049582e+09 | G97: 3.19
A100: Cheques de Pago Diferido en Pesos
A101: Descripción | B101: Vencimiento | C101: Compra | D101: Nominal | E101: Precio | F101: Actual | G101: % (1)
A102: *AAR101100035 | B102: 12/11/2026 | C102: 22/04/2026 | D102: 8560000 | E102: 0.98637985 | F102: 8443411.5 | G102: 0.01
A103: *AAR131100017 | B103: 17/11/2026 | C103: 22/04/2026 | D103: 9450000 | E103: 0.98160501 | F103: 9276167.4 | G103: 0.01
A104: *AAR161100027 | B104: 18/11/2026 | C104: 22/04/2026 | D104: 9450000 | E104: 0.98065558 | F104: 9267195.2 | G104: 0.01
A105: *AAR201100017 | B105: 25/11/2026 | C105: 22/04/2026 | D105: 9450000 | E105: 0.97406065 | F105: 9204873.2 | G105: 0.01
A106: *AAR091100027 | B106: 11/11/2026 | C106: 22/04/2026 | D106: 8560000 | E106: 0.98734041 | F106: 8451633.9 | G106: 0.01
A107: *MOV291000063 | B107: 02/11/2026 | C107: 22/04/2026 | D107: 2500000 | E107: 0.9969409 | F107: 2492352.2 | G107: 0
A108: *MAV151101538 | B108: 18/11/2026 | C108: 23/04/2026 | D108: 1500000 | E108: 0.98118281 | F108: 1471774.2 | G108: 0
A109: *NEU101100035 | B109: 12/11/2026 | C109: 30/04/2026 | D109: 17118303 | E109: 0.98899909 | F109: 16929986 | G109: 0.02
A110: *NEU031100019 | B110: 05/11/2026 | C110: 11/05/2026 | D110: 11923077 | E110: 0.99427949 | F110: 11854871 | G110: 0.01
A111: *MAV171101249 | B111: 19/11/2026 | C111: 13/05/2026 | D111: 3750000 | E111: 0.97805412 | F111: 3667703 | G111: 0
A112: *MAV101101561 | B112: 12/11/2026 | C112: 13/05/2026 | D112: 3750000 | E112: 0.98526159 | F112: 3694731 | G112: 0
A113: *MAV121101139 | B113: 16/11/2026 | C113: 13/05/2026 | D113: 3750000 | E113: 0.98113007 | F113: 3679237.8 | G113: 0
... A2996: *MAV290101208 | B2996: 02/02/2027 | C2996: 29/10/2026 | D2996: 20000000 | E2996: 0.92686661 | F2996: 18537332 | G2996: 0.02
F2997: 6.3111941e+10 | G2997: 77.24
A2999: Cheques de Pago Diferido en Dolar 3500
A3000: Descripción | B3000: Vencimiento | C3000: Compra | D3000: Nominal | E3000: Precio | F3000: Actual | G3000: % (1)
A3001: #UMV250180006 | B3001: 27/01/2028 | C3001: 30/12/2025 | D3001: 20856 | E3001: 1368.9452 | F3001: 28550721 | G3001: 0.03
A3002: #UMV250770007 | B3002: 28/07/2027 | C3002: 30/12/2025 | D3002: 20856 | E3002: 1432.8188 | F3002: 29882869 | G3002: 0.04
A3003: #UMV250780006 | B3003: 27/07/2028 | C3003: 30/12/2025 | D3003: 20856 | E3003: 1310.8296 | F3003: 27338661 | G3003: 0.03
A3004: #UMV250170065 | B3004: 27/01/2027 | C3004: 30/12/2025 | D3004: 13904 | E3004: 1502.546 | F3004: 20891400 | G3004: 0.03
...

Sheet Parametros
A1: Min | B1: 0.75 | C1: en Pymes | D1: =+B1*(VLOOKUP($E$1,'GESTION MOMENTUM'!$A$8:$B$32,2,0)) -> 6.128129e+10 | E1: Valor Patrimonial del Fondo | G1: PN actual | H1: P&L | I1: PN reservado
A2: Max | B2: 0.05 | C2: Money Market | D2: =+B2*(VLOOKUP($E$1,'GESTION MOMENTUM'!$A$8:$B$32,2,0)) -> 4.0854193e+09 | G2: =VLOOKUP(E1,'GESTION MOMENTUM'!A8:B32,2,0) -> 8.1708387e+10 | H2: -0.002 | I2: =+G2*(1+H2) -> 8.154497e+10
A3: Max | B3: 0.2 | C3: PFRemuneradasCaucion | D3: =+B3*(VLOOKUP($E$1,'GESTION MOMENTUM'!$A$8:$B$32,2,0)) -> 1.6341677e+10 | G3: Money Market | H3: 0.05 | I3: =+I2*H3 -> 4.0772485e+09
A4: Max | B4: 0.2 | C4: cheques x librador | D4: =+B4*(VLOOKUP($E$1,'GESTION MOMENTUM'!$A$8:$B$32,2,0)) -> 1.6341677e+10
A5: Max | B5: 0.25 | C5: x titulo en Pymes | D5: =+B5*(VLOOKUP($E$1,'GESTION MOMENTUM'!$A$8:$B$32,2,0)) -> 2.0427097e+10
B8: Garantías RFX (MOMENTUM)
B9: Bono | C9: VN | D9: Precio | E9: Aforo | F9: $
B10: TMG28 - Bono del Tesoro Nacional | C10: 600000000 | D10: =+VLOOKUP(B10,'GESTION MOMENTUM'!A:D,4,0) -> 1.1025 | E10: 0.8 | F10: =C10*D10*E10 -> 529200000
B11: Lecap S30N6 | C11: 500000000 | D11: =+VLOOKUP(B11,'GESTION MOMENTUM'!A:D,4,0) -> 1.2745 | E11: 0.8 | F11: =C11*D11*E11 -> 509800000
E13: Garantia | F13: =SUM(F10:F12) -> 1039000000
B15: Garantías | C15: Total $ por contrato | D15: Contratos a shortear | E15: Contratos Shorteados | F15: Garantia Requerida
A16: Fut Rofex DLR102026 | B16: Octubre | C16: 155000 | D16: 0 | E16: =_xlfn.IFNA(-VLOOKUP(A16,'GESTION MOMENTUM'!A:C,3,0)/1000,0) -> 1357 | F16: =+C16*(E16+D16) -> 210335000
A17: Fut Rofex DLR112026 | B17: Noviembre | C17: 160000 | D17: 0 | E17: =_xlfn.IFNA(-VLOOKUP(A17,'GESTION MOMENTUM'!A:C,3,0)/1000,0) -> 750 | F17: =+C17*(E17+D17) -> 120000000
A18: Fut Rofex DLR122026 | B18: Diciembre | C18: 165000 | E18: =_xlfn.IFNA(-VLOOKUP(A18,'GESTION MOMENTUM'!A:C,3,0)/1000,0) -> 923 | F18: =+C18*(E18+D18) -> 152295000
B19: Enero
B20: Febrero
B21: Marzo
A22: Fut Rofex DLR042027 | B22: Abril | C22: 180000 | D22: 0 | E22: =_xlfn.IFNA(-VLOOKUP(A22,'GESTION MOMENTUM'!A:C,3,0)/1000,0) -> 1800 | F22: =+C22*(E22+D22) -> 324000000
F23: =+SUM(F16:F22) -> 806630000
B24: Saldo de Garantias | C24: =F13-F23 -> 232370000

Sheet Cheques pendientes
A1: FONDO | B1: CHPD | C1: VTO | D1: MONEDA | E1: MONTO | F1: MONTO $ | G1: ESTADO | H1: LIBRADOR | I1: DIAS DE MORA
A2: AMOMPY | B2: *MAV030300645 | C2: 45723 | D2: $ | E2: 3406250 | G2: PREVISIONADO | H2: UKUMARI SOCIEDAD ANONIMA. | I2: =+TODAY()-C2 -> 602 | U2: LIBRADORES PENDIENTES
A3: AMOMPY | B3: *MAV100300802 | C3: 45728 | D3: $ | E3: 3406250 | G3: PREVISIONADO | H3: UKUMARI SOCIEDAD ANONIMA. | I3: =+TODAY()-C3 -> 597 | U3: {=+_xlfn.UNIQUE(H2:H78)} -> UKUMARI SOCIEDAD ANONIMA. | V3: =+SUMIF(H:H,U3,E:E) -> 6812500
A4: AMOMPY | B4: *MAV200500842 | C4: 45799 | D4: $ | E4: 129185000 | G4: PENDIENTE | H4: NIRO CONSTRUYE S. A. | I4: =+TODAY()-C4 -> 526 | U4: NIRO CONSTRUYE S. A. | V4: =+SUMIF(H:H,U4,E:E) -> 258370000
A5: AMOMPY | B5: *MAV300500862 | C5: 45811 | D5: $ | E5: 129185000 | G5: PREVISIONADO | H5: NIRO CONSTRUYE S. A. | I5: =+TODAY()-C5 -> 514 | U5: MERCOL RAUL ALBERTO Y MERCOL MAURICIO EDUARDO. | V5: =+SUMIF(H:H,U5,E:E) -> 62500000
A6: AMOMPY | B6: *MAV091000727 | C6: 45943 | D6: $ | E6: 12500000 | G6: PENDIENTE | H6: MERCOL RAUL ALBERTO Y MERCOL MAURICIO EDUARDO. | I6: =+TODAY()-C6 -> 382 | U6: AKAI ENERGY LED SRL | V6: =+SUMIF(H:H,U6,E:E) -> 44963000
A7: AMOMPY | B7: *MAV031100940 | C7: 45966 | D7: $ | E7: 4400000 | G7: PREVISIONADO | H7: AKAI ENERGY LED SRL | I7: =+TODAY()-C7 -> 359 | U7: FRIGORIFICO GENERAL PICO S A | V7: =+SUMIF(H:H,U7,E:E) -> 70000000
A8: AMOMPY | B8: *MAV041100892 | C8: 45968 | D8: $ | E8: 4400000 | G8: PREVISIONADO | H8: AKAI ENERGY LED SRL | I8: =+TODAY()-C8 -> 357 | K8: Valor Patrimonial del Fondo | L8: =+VLOOKUP(K8,'GESTION MOMENTUM'!A:B,2,0) -> 8.1708387e+10 | U8: MIANI CLARA A Y MIANI ADA CLELIA | V8: =+SUMIF(H:H,U8,E:E) -> 3125000
A9: AMOMPY | B9: *MAV051100567 | C9: 45971 | D9: $ | E9: 25000000 | G9: PENDIENTE | H9: MERCOL RAUL ALBERTO Y MERCOL MAURICIO EDUARDO. | I9: =+TODAY()-C9 -> 354 | U9: PORT PLA S.R.L. | V9: =+SUMIF(H:H,U9,E:E) -> 150000000
A10: AMOMPY | B10: *MAV051100722 | C10: 45971 | D10: $ | E10: 4400000 | G10: PREVISIONADO | H10: AKAI ENERGY LED SRL | I10: =+TODAY()-C10 -> 354 | L10: $ | M10: % PN | U10: MASTER DESIGN HOME SRL | V10: =+SUMIF(H:H,U10,E:E) -> 24000000
A11: AMOMPY | B11: *MAV071100935 | C11: 45972 | D11: $ | E11: 4400000 | G11: PREVISIONADO | H11: AKAI ENERGY LED SRL | I11: =+TODAY()-C11 -> 353 | K11: PREVISIÓN INCOBRABLES | L11: =+VLOOKUP(K11,'GESTION MOMENTUM'!A:B,2,0) -> -4.4018937e+08 | M11: =+L11/L8 -> -0.0053873217 | U11: GROCAL S.A. | V11: =+SUMIF(H:H,U11,E:E) -> 15000000
A12: AMOMPY | B12: *MAV111100890 | C12: 45974 | D12: $ | E12: 963000 | G12: PREVISIONADO | H12: AKAI ENERGY LED SRL | I12: =+TODAY()-C12 -> 351 | K12: PREVISIONADO | L12: =+SUMIF(G:G,K12,E:E) -> 391310500 | U12: Paccioli Group Sociedad Anonima | V12: =+SUMIF(H:H,U12,E:E) -> 13958000
A13: AMOMPY | B13: *MAV121100854 | C13: 45975 | D13: $ | E13: 4400000 | G13: PREVISIONADO | H13: AKAI ENERGY LED SRL | I13: =+TODAY()-C13 -> 350 | K13: Prevision a aplicar | L13: =+L11+L12 -> -48878868 | U13: FINEX CABA S. A. | V13: =+SUMIF(H:H,U13,E:E) -> 55300000
A14: AMOMPY | B14: *MAV121100675 | C14: 45975 | D14: $ | E14: 25000000 | G14: PENDIENTE | H14: MERCOL RAUL ALBERTO Y MERCOL MAURICIO EDUARDO. | I14: =+TODAY()-C14 -> 350 | U14: TRADICION VALORES S.A. | V14: =+SUMIF(H:H,U14,E:E) -> 25000000
A15: AMOMPY | B15: *MAV141101053 | C15: 45979 | D15: $ | E15: 4400000 | G15: PREVISIONADO | H15: AKAI ENERGY LED SRL | I15: =+TODAY()-C15 -> 346 | K15: PENDIENTE | L15: =+SUMIF(G:G,K15,E:E)+E2 -> 2332411780 | M15: =+SUMIF(G:G,K15,E:E)/$L$8 -> 0.028503874 | U15: Maradona Wines | V15: =+SUMIF(H:H,U15,E:E) -> 119500000
A16: AMOMPY | B16: *MAV141101054 | C16: 45979 | D16: $ | E16: 4400000 | G16: PREVISIONADO | H16: AKAI ENERGY LED SRL | I16: =+TODAY()-C16 -> 346 | U16: LOPEZ LUCIA SOLEDAD | V16: =+SUMIF(H:H,U16,E:E) -> 995000
A17: AMOMPY | B17: *MAV171100932 | C17: 45980 | D17: $ | E17: 4400000 | G17: PREVISIONADO | H17: AKAI ENERGY LED SRL | I17: =+TODAY()-C17 -> 345 | U17: RABU INVERSIONES SRL | V17: =+SUMIF(H:H,U17,E:E) -> 7194300
A18: AMOMPY | B18: *MAV151101337 | C18: 45980 | D18: $ | E18: 4400000 | G18: PREVISIONADO | H18: AKAI ENERGY LED SRL | I18: =+TODAY()-C18 -> 345 | U18: GROUP DIEZ S.A. | V18: =+SUMIF(H:H,U18,E:E) -> 425000000
A19: AMOMPY | B19: *MAV181100869 | C19: 45981 | D19: $ | E19: 4400000 | G19: PREVISIONADO | H19: AKAI ENERGY LED SRL | I19: =+TODAY()-C19 -> 344 | U19: INVLAC CONSTRUCCIONES S.R.L | V19: =+SUMIF(H:H,U19,E:E) -> 4000000
A20: AMOMPY | B20: *MAV181100773 | C20: 45981 | D20: $ | E20: 20000000 | G20: PREVISIONADO | H20: FRIGORIFICO GENERAL PICO S A | I20: =+TODAY()-C20 -> 344 | K20: LIBRADOR PENDIENTE | L20: $ | M20: % PN | O20: VIGENTE | U20: I-LED ARGENTINA S.A. | V20: =+SUMIF(H:H,U20,E:E) -> 93100000
A21: AMOMPY | B21: *MAV191100661 | C21: 45986 | D21: $ | E21: 20000000 | G21: PREVISIONADO | H21: FRIGORIFICO GENERAL PICO S A | I21: =+TODAY()-C21 -> 339 | K21: {=+_xlfn._xlws.SORT(U3:V34,2,-1)} -> GROUP DIEZ S.A. | L21: 425000000 | M21: =+L21/$L$8 -> 0.0052014244 | O21: =+SUMIF('Reporte de Cheques'!A:A,'Cheques pendientes'!K21,'Reporte de Cheques'!I:I) -> 0 | V21: =+SUMIF(H:H,U21,E:E) -> 0
A22: AMOMPY | B22: *MAV201100887 | C22: 45987 | D22: $ | E22: 10000000 | G22: PREVISIONADO | H22: FRIGORIFICO GENERAL PICO S A | I22: =+TODAY()-C22 -> 338 | K22: NIRO CONSTRUYE S. A. | L22: 258370000 | M22: =+L22/$L$8 -> 0.0031620989 | O22: =+SUMIF('Reporte de Cheques'!A:A,'Cheques pendientes'!K22,'Reporte de Cheques'!I:I) -> 0 | V22: =+SUMIF(H:H,U22,E:E) -> 0
A23: AMOMPY | B23: *MAV211100687 | C23: 45988 | D23: $ | E23: 10000000 | G23: PREVISIONADO | H23: FRIGORIFICO GENERAL PICO S A | I23: =+TODAY()-C23 -> 337 | K23: PORT PLA S.R.L. | L23: 150000000 | M23: =+L23/$L$8 -> 0.0018357969 | O23: =+SUMIF('Reporte de Cheques'!A:A,'Cheques pendientes'!K23,'Reporte de Cheques'!I:I) -> 0 | V23: =+SUMIF(H:H,U23,E:E) -> 0
A24: AMOMPY | B24: *MAV221100992 | C24: 45988 | D24: $ | E24: 10000000 | G24: PREVISIONADO | H24: FRIGORIFICO GENERAL PICO S A | I24: =+TODAY()-C24 -> 337 | K24: Maradona Wines | L24: 119500000 | M24: =+L24/$L$8 -> 0.0014625182 | O24: =+SUMIF('Reporte de Cheques'!A:A,'Cheques pendientes'!K24,'Reporte de Cheques'!I:I) -> 0 | V24: =+SUMIF(H:H,U24,E:E) -> 0
A25: AMOMPY | B25: *MAV271100809 | C25: 45992 | D25: $ | E25: 3125000 | G25: PENDIENTE | H25: MIANI CLARA A Y MIANI ADA CLELIA | I25: =+TODAY()-C25 -> 333 | K25: I-LED ARGENTINA S.A. | L25: 93100000 | M25: =+L25/$L$8 -> 0.0011394179 | O25: =+SUMIF('Reporte de Cheques'!A:A,'Cheques pendientes'!K25,'Reporte de Cheques'!I:I) -> 0 | V25: =+SUMIF(H:H,U25,E:E) -> 0
A26: AMOMPY | B26: *MAV291101201 | C26: 45994 | D26: $ | E26: 25000000 | G26: PENDIENTE | H26: PORT PLA S.R.L. | I26: =+TODAY()-C26 -> 331 | K26: FRIGORIFICO GENERAL PICO S A | L26: 70000000 | M26: =+L26/$L$8 -> 0.0008567052 | O26: =+SUMIF('Reporte de Cheques'!A:A,'Cheques pendientes'!K26,'Reporte de Cheques'!I:I) -> 0 | V26: =+SUMIF(H:H,U26,E:E) -> 0
A27: AMOMPY | B27: *MAV171200694 | C27: 46010 | D27: $ | E27: 6000000 | G27: PREVISIONADO | H27: MASTER DESIGN HOME SRL | I27: =+TODAY()-C27 -> 315 | K27: MERCOL RAUL ALBERTO Y MERCOL MAURICIO EDUARDO. | L27: 62500000 | M27: =+L27/$L$8 -> 0.00076491536 | O27: =+SUMIF('Reporte de Cheques'!A:A,'Cheques pendientes'!K27,'Reporte de Cheques'!I:I) -> 0 | V27: =+SUMIF(H:H,U27,E:E) -> 0
A28: AMOMPY | B28: *MAV291200938 | C28: 46024 | D28: $ | E28: 25000000 | G28: PENDIENTE | H28: PORT PLA S.R.L. | I28: =+TODAY()-C28 -> 301 | K28: FINEX CABA S. A. | L28: 55300000 | M28: =+L28/$L$8 -> 0.00067679711 | O28: =+SUMIF('Reporte de Cheques'!A:A,'Cheques pendientes'!K28,'Reporte de Cheques'!I:I) -> 0 | V28: =+SUMIF(H:H,U28,E:E) -> 0
A29: AMOMPY | B29: *MAV020100774 | C29: 46028 | D29: $ | E29: 10000000 | G29: PENDIENTE | H29: PORT PLA S.R.L. | I29: =+TODAY()-C29 -> 297 | K29: AKAI ENERGY LED SRL | L29: 44963000 | M29: =+L29/$L$8 -> 0.00055028623 | O29: =+SUMIF('Reporte de Cheques'!A:A,'Cheques pendientes'!K29,'Reporte de Cheques'!I:I) -> 0 | V29: =+SUMIF(H:H,U29,E:E) -> 0
A30: AMOMPY | B30: *MAV311200688 | C30: 46028 | D30: $ | E30: 6000000 | G30: PREVISIONADO | H30: MASTER DESIGN HOME SRL | I30: =+TODAY()-C30 -> 297 | K30: TRADICION VALORES S.A. | L30: 25000000 | M30: =+L30/$L$8 -> 0.00030596614 | O30: =+SUMIF('Reporte de Cheques'!A:A,'Cheques pendientes'!K30,'Reporte de Cheques'!I:I) -> 0 | V30: =+SUMIF(H:H,U30,E:E) -> 0
A31: AMOMPY | B31: *MAV050100914 | C31: 46029 | D31: $ | E31: 10000000 | G31: PENDIENTE | H31: PORT PLA S.R.L. | I31: =+TODAY()-C31 -> 296 | K31: MASTER DESIGN HOME SRL | L31: 24000000 | M31: =+L31/$L$8 -> 0.0002937275 | O31: =+SUMIF('Reporte de Cheques'!A:A,'Cheques pendientes'!K31,'Reporte de Cheques'!I:I) -> 0 | V31: =+SUMIF(H:H,U31,E:E) -> 0
A32: AMOMPY | B32: *MAV090100782 | C32: 46035 | D32: $ | E32: 10000000 | G32: PENDIENTE | H32: PORT PLA S.R.L. | I32: =+TODAY()-C32 -> 290 | K32: GROCAL S.A. | L32: 15000000 | M32: =+L32/$L$8 -> 0.00018357969 | O32: =+SUMIF('Reporte de Cheques'!A:A,'Cheques pendientes'!K32,'Reporte de Cheques'!I:I) -> 0 | V32: =+SUMIF(H:H,U32,E:E) -> 0
A33: AMOMPY | B33: *MAV120100963 | C33: 46036 | D33: $ | E33: 10000000 | G33: PENDIENTE | H33: PORT PLA S.R.L. | I33: =+TODAY()-C33 -> 289 | K33: Paccioli Group Sociedad Anonima | L33: 13958000 | M33: =+L33/$L$8 -> 0.00017082702 | O33: =+SUMIF('Reporte de Cheques'!A:A,'Cheques pendientes'!K33,'Reporte de Cheques'!I:I) -> 0 | V33: =+SUMIF(H:H,U33,E:E) -> 0
A34: AMOMPY | B34: *MAV120101031 | C34: 46036 | D34: $ | E34: 5000000 | G34: PENDIENTE | H34: GROCAL S.A. | I34: =+TODAY()-C34 -> 289 | K34: RABU INVERSIONES SRL | L34: 7194300 | M34: =+L34/$L$8 -> 8.8048489e-05 | O34: =+SUMIF('Reporte de Cheques'!A:A,'Cheques pendientes'!K34,'Reporte de Cheques'!I:I) -> 0 | V34: =+SUMIF(H:H,U34,E:E) -> 0
A35: AMOMPY | B35: *MAV140100871 | C35: 46038 | D35: $ | E35: 5000000 | G35: PENDIENTE | H35: GROCAL S.A. | I35: =+TODAY()-C35 -> 287 | K35: UKUMARI SOCIEDAD ANONIMA. | L35: 6812500 | M35: =+L35/$L$8 -> 8.3375774e-05 | O35: =+SUMIF('Reporte de Cheques'!A:A,'Cheques pendientes'!K35,'Reporte de Cheques'!I:I) -> 0
A36: AMOMPY | B36: *MAV160100849 | C36: 46042 | D36: $ | E36: 10000000 | G36: PENDIENTE | H36: PORT PLA S.R.L. | I36: =+TODAY()-C36 -> 283 | K36: INVLAC CONSTRUCCIONES S.R.L | L36: 4000000 | M36: =+L36/$L$8 -> 4.8954583e-05 | O36: =+SUMIF('Reporte de Cheques'!A:A,'Cheques pendientes'!K36,'Reporte de Cheques'!I:I) -> 0
A37: AMOMPY | B37: *MAV160100806 | C37: 46042 | D37: $ | E37: 4000000 | G37: PREVISIONADO | H37: MASTER DESIGN HOME SRL | I37: =+TODAY()-C37 -> 283 | K37: MIANI CLARA A Y MIANI ADA CLELIA | L37: 3125000 | M37: =+L37/$L$8 -> 3.8245768e-05 | O37: =+SUMIF('Reporte de Cheques'!A:A,'Cheques pendientes'!K37,'Reporte de Cheques'!I:I) -> 0
A38: AMOMPY | B38: *MAV190100896 | C38: 46043 | D38: $ | E38: 10000000 | G38: PENDIENTE | H38: PORT PLA S.R.L. | I38: =+TODAY()-C38 -> 282 | K38: LOPEZ LUCIA SOLEDAD | L38: 995000 | M38: =+L38/$L$8 -> 1.2177453e-05 | O38: =+SUMIF('Reporte de Cheques'!A:A,'Cheques pendientes'!K38,'Reporte de Cheques'!I:I) -> 0
A39: AMOMPY | B39: *MAV200101319 | C39: 46044 | D39: $ | E39: 1395800 | G39: PENDIENTE | H39: Paccioli Group Sociedad Anonima | I39: =+TODAY()-C39 -> 281 | K39: 0 | L39: 0 | M39: =+L39/$L$8 -> 0 | O39: =+SUMIF('Reporte de Cheques'!A:A,'Cheques pendientes'!K39,'Reporte de Cheques'!I:I) -> 0
A40: AMOMPY | B40: *MAV200101320 | C40: 46044 | D40: $ | E40: 1395800 | G40: PENDIENTE | H40: Paccioli Group Sociedad Anonima | I40: =+TODAY()-C40 -> 281 | K40: 0 | L40: 0 | M40: =+L40/$L$8 -> 0 | O40: =+SUMIF('Reporte de Cheques'!A:A,'Cheques pendientes'!K40,'Reporte de Cheques'!I:I) -> 0
A41: AMOMPY | B41: *MAV200101321 | C41: 46044 | D41: $ | E41: 1395800 | G41: PENDIENTE | H41: Paccioli Group Sociedad Anonima | I41: =+TODAY()-C41 -> 281 | K41: 0 | L41: 0 | M41: =+L41/$L$8 -> 0 | O41: =+SUMIF('Reporte de Cheques'!A:A,'Cheques pendientes'!K41,'Reporte de Cheques'!I:I) -> 0
A42: AMOMPY | B42: *MAV200101322 | C42: 46044 | D42: $ | E42: 1395800 | G42: PENDIENTE | H42: Paccioli Group Sociedad Anonima | I42: =+TODAY()-C42 -> 281 | K42: 0 | L42: 0 | M42: =+L42/$L$8 -> 0 | O42: =+SUMIF('Reporte de Cheques'!A:A,'Cheques pendientes'!K42,'Reporte de Cheques'!I:I) -> 0
A43: AMOMPY | B43: *MAV210100855 | C43: 46045 | D43: $ | E43: 1395800 | G43: PENDIENTE | H43: Paccioli Group Sociedad Anonima | I43: =+TODAY()-C43 -> 280 | K43: 0 | L43: 0 | M43: =+L43/$L$8 -> 0 | O43: =+SUMIF('Reporte de Cheques'!A:A,'Cheques pendientes'!K43,'Reporte de Cheques'!I:I) -> 0
A44: AMOMPY | B44: *MAV210100764 | C44: 46045 | D44: $ | E44: 4000000 | G44: PREVISIONADO | H44: MASTER DESIGN HOME SRL | I44: =+TODAY()-C44 -> 280 | K44: 0 | L44: 0 | M44: =+L44/$L$8 -> 0 | O44: =+SUMIF('Reporte de Cheques'!A:A,'Cheques pendientes'!K44,'Reporte de Cheques'!I:I) -> 0
A45: AMOMPY | B45: *MAV210100850 | C45: 46045 | D45: $ | E45: 15900000 | G45: PENDIENTE | H45: FINEX CABA S. A. | I45: =+TODAY()-C45 -> 280 | K45: 0 | L45: 0 | M45: =+L45/$L$8 -> 0 | O45: =+SUMIF('Reporte de Cheques'!A:A,'Cheques pendientes'!K45,'Reporte de Cheques'!I:I) -> 0
A46: AMOMPY | B46: *MAV210100774 | C46: 46045 | D46: $ | E46: 5000000 | G46: PENDIENTE | H46: GROCAL S.A. | I46: =+TODAY()-C46 -> 280 | K46: 0 | L46: 0 | M46: =+L46/$L$8 -> 0 | O46: =+SUMIF('Reporte de Cheques'!A:A,'Cheques pendientes'!K46,'Reporte de Cheques'!I:I) -> 0
A47: AMOMPY | B47: *MAV220100909 | C47: 46048 | D47: $ | E47: 1395800 | G47: PENDIENTE | H47: Paccioli Group Sociedad Anonima | I47: =+TODAY()-C47 -> 277 | K47: 0 | L47: 0 | M47: =+L47/$L$8 -> 0 | O47: =+SUMIF('Reporte de Cheques'!A:A,'Cheques pendientes'!K47,'Reporte de Cheques'!I:I) -> 0
A48: AMOMPY | B48: *MAV230100842 | C48: 46049 | D48: $ | E48: 10000000 | G48: PENDIENTE | H48: PORT PLA S.R.L. | I48: =+TODAY()-C48 -> 276 | K48: 0 | L48: 0 | M48: =+L48/$L$8 -> 0 | O48: =+SUMIF('Reporte de Cheques'!A:A,'Cheques pendientes'!K48,'Reporte de Cheques'!I:I) -> 0
A49: AMOMPY | B49: *MAV230100905 | C49: 46049 | D49: $ | E49: 1395800 | G49: PENDIENTE | H49: Paccioli Group Sociedad Anonima | I49: =+TODAY()-C49 -> 276 | K49: 0 | L49: 0 | M49: =+L49/$L$8 -> 0 | O49: =+SUMIF('Reporte de Cheques'!A:A,'Cheques pendientes'!K49,'Reporte de Cheques'!I:I) -> 0
A50: AMOMPY | B50: *MAV230100906 | C50: 46049 | D50: $ | E50: 1395800 | G50: PENDIENTE | H50: Paccioli Group Sociedad Anonima | I50: =+TODAY()-C50 -> 276 | K50: 0 | L50: 0 | M50: =+L50/$L$8 -> 0 | O50: =+SUMIF('Reporte de Cheques'!A:A,'Cheques pendientes'!K50,'Reporte de Cheques'!I:I) -> 0
... A52: AMOMPY | B52: *MAV230100908 | C52: 46049 | D52: $ | E52: 1395800 | G52: PENDIENTE | H52: Paccioli Group Sociedad Anonima | I52: =+TODAY()-C52 -> 276 | K52: 0 | L52: 0 | M52: =+L52/$L$8 -> 0 | O52: =+SUMIF('Reporte de Cheques'!A:A,'Cheques pendientes'!K52,'Reporte de Cheques'!I:I) -> 0
A53: AMOMPY | B53: *MAV260100839 | C53: 46050 | D53: $ | E53: 6250000 | G53: PENDIENTE | H53: TRADICION VALORES S.A. | I53: =+TODAY()-C53 -> 275
A54: AMOMPY | B54: *MAV260100805 | C54: 46050 | D54: $ | E54: 4000000 | G54: PREVISIONADO | H54: MASTER DESIGN HOME SRL | I54: =+TODAY()-C54 -> 275
A55: AMOMPY | B55: *MAV240101107 | C55: 46050 | D55: $ | E55: 22000000 | G55: PREVISIONADO | H55: Maradona Wines | I55: =+TODAY()-C55 -> 275
A56: AMOMPY | B56: *MAV270100949 | C56: 46051 | D56: $ | E56: 10000000 | G56: PENDIENTE | H56: PORT PLA S.R.L. | I56: =+TODAY()-C56 -> 274
A57: AMOMPY | B57: *MAV280100704 | C57: 46052 | D57: $ | E57: 6250000 | G57: PENDIENTE | H57: TRADICION VALORES S.A. | I57: =+TODAY()-C57 -> 273
A58: AMOMPY | B58: *MAV300100888 | C58: 46056 | D58: $ | E58: 6250000 | G58: PENDIENTE | H58: TRADICION VALORES S.A. | I58: =+TODAY()-C58 -> 269
A59: AMOMPY | B59: *MAV300100901 | C59: 46056 | D59: $ | E59: 995000 | G59: PENDIENTE | H59: LOPEZ LUCIA SOLEDAD | I59: =+TODAY()-C59 -> 269
A60: AMOMPY | B60: *MAV300100900 | C60: 46056 | D60: $ | E60: 2398100 | G60: PENDIENTE | H60: RABU INVERSIONES SRL | I60: =+TODAY()-C60 -> 269
A61: AMOMPY | B61: *MAV300100917 | C61: 46056 | D61: $ | E61: 10000000 | G61: PENDIENTE | H61: PORT PLA S.R.L. | I61: =+TODAY()-C61 -> 269
A62: AMOMPY | B62: *MAV310101295 | C62: 46057 | D62: $ | E62: 6250000 | G62: PENDIENTE | H62: TRADICION VALORES S.A. | I62: =+TODAY()-C62 -> 268
A63: AMOMPY | B63: *MAV020200696 | C63: 46057 | D63: $ | E63: 2398100 | G63: PENDIENTE | H63: RABU INVERSIONES SRL | I63: =+TODAY()-C63 -> 268
A64: AMOMPY | B64: *MAV020200731 | C64: 46057 | D64: $ | E64: 10000000 | G64: PENDIENTE | H64: PORT PLA S.R.L. | I64: =+TODAY()-C64 -> 268
... A106: AMOMPY | B106: #MAV281060018 | C106: 46324 | D106: $ | E106: 851000000 | G106: PENDIENTE | H106: LA MANTOVANA DE SERVICIOS GENERALES SA | I106: =+TODAY()-C106 -> 1

Sheet Concentración
A4: Suma de %
A5: Sociedad de Garantía Recíproca / Librador | B5: Total
A6: A M F A Y S ASOCIACION MUTUAL | B6: 0.042441666
A7: SES SA | B7: 0.040831459
A8: SIGMA AGRO S.A. | B8: 0.036845088
A9: FIDEICOMISO DORREGO Y LIBERTADOR | B9: 0.032352861
A10: AUTOPISTAS URBANAS SA | B10: 0.029617112
A11: COM & LOG SA | B11: 0.02820532
A12: AESA ASEO Y ECOLOGIA SA | B12: 0.024601958
A13: ESPECIALIDADES AGROPECUARIAS S.A. | B13: 0.022141538
A14: KOMPASS SRL | B14: 0.021048406
A15: SUPERLIGA PROFESIONAL DEL FUTBOL ARGENTINO ASOCIACION CIVIL | B15: 0.01933571
A16: WTS DEL SUR SRL | B16: 0.017023679
A17: TEXTUM SA | B17: 0.014744776
... A545: Total general | B545: 0.8935522

Sheet Reporte de Cheques
A1: Reporte de Cheques de Pago Diferido | W1: Valor Patrimonial del Fondo
A2: Cheque de Pago Diferido y Pagaré | B2: Moneda | C2: Cheque de Pago Diferido y Pagaré | D2: Fecha | E2: Precio | F2: Tipo de Cambio (Cheque/Fondo) | G2: Moneda Cheque | H2: Moneda Cheque | I2: Moneda Fondo | J2: Moneda Fondo | K2: Compra | L2: Fondo | M2: Compra | N2: Compra | O2: Compra | P2: Compra | Q2: Vendido | R2: Venta | S2: Venta | T2: Venta | U2: Cheque de Pago Diferido y Pagaré | V2: Cheque de Pago Diferido y Pagaré | W2: =+VLOOKUP(W1,'GESTION MOMENTUM'!A:B,2,0) -> 8.1708387e+10
A3: Sociedad de Garantía Recíproca / Librador | B3: Descripción | C3: Fecha de Vencimiento | D3: Fecha | E3: Precio | F3: Tipo de Cambio (Cheque/Fondo) | G3: Importe Nominal | H3: Importe Actual | I3: Importe Nominal | J3: Importe Actual | K3: Nro. de Operación | L3: Nombre | M3: Agente | N3: Fecha Concertación | O3: Fecha Liquidación | P3: Tasa de Descuento | Q3: Vendido | R3: Nro. de Operación | S3: Fecha Concertación | T3: Fecha Liquidación | U3: Abreviatura | V3: Código CAFCI | W3: %
A4: TREND SGR | B4: Pesos | C4: 46324 | D4: 29/10/2026 | E4: 1 | G4: 15000000 | H4: 15000000 | I4: 15000000 | J4: 15000000 | K4: 69911131 | L4: AMOMPY | M4: Momentum Capital Investment S.A. | N4: 23/09/2026 | O4: 23/09/2026 | P4: 25 | Q4: No | U4: *TRD271000035 | V4: *TRD271000035 | W4: =+J4/$W$2 -> 0.00018357969
A5: Vinculos S.G.R. | B5: Pesos | C5: 46324 | D5: 29/10/2026 | E5: 1 | G5: 3000000 | H5: 3000000 | I5: 3000000 | J5: 3000000 | K5: 3792078 | L5: AMOMPY | M5: Momentum Capital Investment S.A. | N5: 18/08/2026 | O5: 18/08/2026 | P5: 30 | Q5: No | U5: *AFB271000007 | V5: *AFB271000007 | W5: =+J5/$W$2 -> 3.6715937e-05
A6: Vinculos S.G.R. | B6: Pesos | C6: 46324 | D6: 29/10/2026 | E6: 1 | G6: 31628756 | H6: 31628756 | I6: 31628756 | J6: 31628756 | K6: 22295 | L6: AMOMPY | M6: Momentum Capital Investment S.A. | N6: 15/09/2026 | O6: 15/09/2026 | P6: 30 | Q6: No | U6: *AFB271000013 | V6: *AFB271000013 | W6: =+J6/$W$2 -> 0.00038709314
A7: PAMPA VIDA S.R.L. | B7: Pesos | C7: 46324 | D7: 29/10/2026 | E7: 1 | G7: 3625698.8 | H7: 3625698.8 | I7: 3625698.8 | J7: 3625698.8 | K7: 3346 | L7: AMOMPY | M7: Momentum Capital Investment S.A. | N7: 28/08/2026 | O7: 28/08/2026 | P7: 36 | Q7: No | U7: *MAV271001495 | V7: *MAV271001495 | W7: =+J7/$W$2 -> 4.4373643e-05
A8: PAMPA VIDA S.R.L. | B8: Pesos | C8: 46324 | D8: 29/10/2026 | E8: 1 | G8: 2502550.4 | H8: 2502550.4 | I8: 2502550.4 | J8: 2502550.4 | K8: 3140 | L8: AMOMPY | M8: Momentum Capital Investment S.A. | N8: 23/07/2026 | O8: 23/07/2026 | P8: 33 | Q8: No | U8: *MAV271001362 | V8: *MAV271001362 | W8: =+J8/$W$2 -> 3.0627827e-05
A9: PAMPA VIDA S.R.L. | B9: Pesos | C9: 46324 | D9: 29/10/2026 | E9: 1 | G9: 2502550.4 | H9: 2502550.4 | I9: 2502550.4 | J9: 2502550.4 | K9: 3130 | L9: AMOMPY | M9: Momentum Capital Investment S.A. | N9: 23/07/2026 | O9: 23/07/2026 | P9: 33 | Q9: No | U9: *MAV271001363 | V9: *MAV271001363 | W9: =+J9/$W$2 -> 3.0627827e-05
A10: PAMPA VIDA S.R.L. | B10: Pesos | C10: 46324 | D10: 29/10/2026 | E10: 1 | G10: 1020845.7 | H10: 1020845.7 | I10: 1020845.7 | J10: 1020845.7 | K10: 2906 | L10: AMOMPY | M10: Momentum Capital Investment S.A. | N10: 15/07/2026 | O10: 15/07/2026 | P10: 34 | Q10: No | U10: *MAV271001341 | V10: *MAV271001341 | W10: =+J10/$W$2 -> 1.2493768e-05
A11: PAMPA VIDA S.R.L. | B11: Pesos | C11: 46324 | D11: 29/10/2026 | E11: 1 | G11: 990902.64 | H11: 990902.64 | I11: 990902.64 | J11: 990902.64 | K11: 2956 | L11: AMOMPY | M11: Momentum Capital Investment S.A. | N11: 15/07/2026 | O11: 15/07/2026 | P11: 34 | Q11: No | U11: *MAV271001342 | V11: *MAV271001342 | W11: =+J11/$W$2 -> 1.2127306e-05
A12: Movil SGR | B12: Pesos | C12: 46324 | D12: 29/10/2026 | E12: 1 | G12: 20000000 | H12: 20000000 | I12: 20000000 | J12: 20000000 | K12: 22803 | L12: AMOMPY | M12: Momentum Capital Investment S.A. | N12: 28/09/2026 | O12: 28/09/2026 | P12: 26 | Q12: No | U12: *MOV271000087 | V12: *MOV271000087 | W12: =+J12/$W$2 -> 0.00024477292
A13: Movil SGR | B13: Pesos | C13: 46324 | D13: 29/10/2026 | E13: 1 | G13: 2500000 | H13: 2500000 | I13: 2500000 | J13: 2500000 | K13: 90031823 | L13: AMOMPY | M13: Momentum Capital Investment S.A. | N13: 22/04/2026 | O13: 22/04/2026 | P13: 28 | Q13: No | U13: *MOV271000069 | V13: *MOV271000069 | W13: =+J13/$W$2 -> 3.0596614e-05
A14: TREND SGR | B14: Pesos | C14: 46324 | D14: 29/10/2026 | E14: 1 | G14: 1572269.7 | H14: 1572269.7 | I14: 1572269.7 | J14: 1572269.7 | K14: 22513 | L14: AMOMPY | M14: Momentum Capital Investment S.A. | N14: 25/09/2026 | O14: 25/09/2026 | P14: 26 | Q14: No | U14: *TRD271000036 | V14: *TRD271000036 | W14: =+J14/$W$2 -> 1.9242452e-05
A15: ELI SA | B15: Pesos | C15: 46324 | D15: 29/10/2026 | E15: 1 | G15: 6535955.2 | H15: 6535955.2 | I15: 6535955.2 | J15: 6535955.2 | K15: 30000338 | L15: AMOMPY | M15: Momentum Capital Investment S.A. | N15: 04/09/2026 | O15: 04/09/2026 | P15: 32 | Q15: No | U15: *MAV271001542 | V15: *MAV271001542 | W15: =+J15/$W$2 -> 7.999124e-05
... A274: METALFOR SA | B274: Pesos | C274: 46330 | D274: 29/10/2026 | E274: 0.99590724 | G274: 12000000 | H274: 11950887 | I274: 12000000 | J274: 11950887 | K274: 34562 | L274: AMOMPY | M274: Momentum Capital Investment S.A. | N274: 31/07/2026 | O274: 31/07/2026 | P274: 25 | Q274: No | U274: *MAV011101206 | V274: *MAV011101206 | W274: =+J274/$W$2 -> 0.00014626267
A275: ALLIANCE ONE TOBACCO ARGENTINA | B275: Dolar 3500 | C275: 46330 | D275: 29/10/2026 | E275: 0.99868666 | F275: 1 US3 = 1539,5930209017 $ | G275: 500000 | H275: 499343.33 | I275: 7.6979651e+08 | J275: 7.6878551e+08 | K275: 152502 | L275: AMOMPY | M275: Momentum Capital Investment S.A. | N275: 04/06/2026 | O275: 04/06/2026 | P275: 8 | Q275: No | U275: #UMV021160025 | V275: #UMV021160025 | W275: =+J275/$W$2 -> 0.0094088935
A276: TEXTUM SA | B276: Pesos | C276: 46330 | D276: 29/10/2026 | E276: 0.99444203 | G276: 10000000 | H276: 9944420.3 | I276: 10000000 | J276: 9944420.3 | K276: 14284512 | L276: AMOMPY | M276: Momentum Capital Investment S.A. | N276: 24/08/2026 | O276: 24/08/2026 | P276: 34 | Q276: No | U276: *MAV021100898 | V276: *MAV021100898 | W276: =+J276/$W$2 -> 0.00012170624
A277: TEXTUM SA | B277: Pesos | C277: 46330 | D277: 29/10/2026 | E277: 0.99476729 | G277: 11000000 | H277: 10942440 | I277: 11000000 | J277: 10942440 | K277: 14651796 | L277: AMOMPY | M277: Momentum Capital Investment S.A. | N277: 01/10/2026 | O277: 01/10/2026 | P277: 32 | Q277: No | U277: *MAV311001979 | V277: *MAV311001979 | W277: =+J277/$W$2 -> 0.00013392065
A278: GHEZZI CARLOS ALBERTO | B278: Pesos | C278: 46330 | D278: 29/10/2026 | E278: 0.9952556 | G278: 2289494 | H278: 2278631.7 | I278: 2289494 | J278: 2278631.7 | K278: 11273460 | L278: AMOMPY | M278: Momentum Capital Investment S.A. | N278: 23/10/2026 | O278: 23/10/2026 | P278: 29 | Q278: No | U278: *MAV011101481 | V278: *MAV011101481 | W278: =+J278/$W$2 -> 2.7887366e-05
A279: SALTAPOR S.R.L. | B279: Pesos | C279: 46330 | D279: 29/10/2026 | E279: 0.99476727 | G279: 2749536.5 | H279: 2735148.9 | I279: 2749536.5 | J279: 2735148.9 | K279: 74760911 | L279: AMOMPY | M279: Momentum Capital Investment S.A. | N279: 04/09/2026 | O279: 04/09/2026 | P279: 32 | Q279: No | U279: *MAV021100999 | V279: *MAV021100999 | W279: =+J279/$W$2 -> 3.3474518e-05
A280: Union S.G.R. | B280: Pesos | C280: 46330 | D280: 29/10/2026 | E280: 0.99558128 | G280: 33170000 | H280: 33023431 | I280: 33170000 | J280: 33023431 | K280: 32240 | L280: AMOMPY | M280: Momentum Capital Investment S.A. | N280: 17/09/2026 | O280: 17/09/2026 | P280: 27 | Q280: No | U280: *NIO021100025 | V280: *NIO021100025 | W280: =+J280/$W$2 -> 0.00040416208
A281: NOVA FUSION SRL | B281: Pesos | C281: 46330 | D281: 29/10/2026 | E281: 0.99509276 | G281: 161938.32 | H281: 161143.65 | I281: 161938.32 | J281: 161143.65 | K281: 70489487 | L281: AMOMPY | M281: Momentum Capital Investment S.A. | N281: 19/10/2026 | O281: 19/10/2026 | P281: 30 | Q281: No | U281: *MAV311002169 | V281: *MAV311002169 | W281: =+J281/$W$2 -> 1.97218e-06
A282: PREMECOL SRL | B282: Pesos | C282: 46330 | D282: 29/10/2026 | E282: 0.99476732 | G282: 5000000 | H282: 4973836.6 | I282: 5000000 | J282: 4973836.6 | K282: 40981968 | L282: AMOMPY | M282: Momentum Capital Investment S.A. | N282: 19/10/2026 | O282: 19/10/2026 | P282: 32 | Q282: No | U282: *MAV311002171 | V282: *MAV311002171 | W282: =+J282/$W$2 -> 6.0873024e-05
A283: BSP LARTI SA | B283: Dolar 3500 | C283: 46330 | D283: 29/10/2026 | E283: 0.9985227 | F283: 1 US3 = 1539,5930209017 $ | G283: 100000 | H283: 99852.27 | I283: 1.539593e+08 | J283: 1.5373186e+08 | K283: 155821 | L283: AMOMPY | M283: Momentum Capital Investment S.A. | N283: 02/07/2026 | O283: 02/07/2026 | P283: 9 | Q283: No | U283: #UMV021160028 | V283: #UMV021160028 | W283: =+J283/$W$2 -> 0.0018814698
A284: COOPERATIVA DE TABACALEROS DE JUJUY LTDA | B284: Dolar 3500 | C284: 46330 | D284: 29/10/2026 | E284: 0.9986866 | F284: 1 US3 = 1539,5930209017 $ | G284: 188100 | H284: 187852.95 | I284: 2.8959745e+08 | J284: 2.8921709e+08 | K284: 160722 | L284: AMOMPY | M284: Momentum Capital Investment S.A. | N284: 12/08/2026 | O284: 12/08/2026 | P284: 8 | Q284: No | U284: #UMV021160035 | V284: #UMV021160035 | W284: =+J284/$W$2 -> 0.0035396255
A285: COOPERATIVA DE TABACALEROS DE JUJUY LTDA | B285: Dolar 3500 | C285: 46330 | D285: 29/10/2026 | E285: 0.9983589 | F285: 1 US3 = 1539,5930209017 $ | G285: 100000 | H285: 99835.89 | I285: 1.539593e+08 | J285: 1.5370664e+08 | K285: 165199 | L285: AMOMPY | M285: Momentum Capital Investment S.A. | N285: 15/09/2026 | O285: 15/09/2026 | P285: 10 | Q285: No | U285: #UMV021160051 | V285: #UMV021160051 | W285: =+J285/$W$2 -> 0.0018811611
A286: SURSEM SOCIEDAD ANONIMA | B286: Pesos | C286: 46330 | D286: 29/10/2026 | E286: 0.99460467 | G286: 363101.32 | H286: 361142.27 | I286: 363101.32 | J286: 361142.27 | K286: 7241 | L286: AMOMPY | M286: Momentum Capital Investment S.A. | N286: 09/10/2026 | O286: 09/10/2026 | P286: 33 | Q286: No | U286: *MAV021101384 | V286: *MAV021101384 | W286: =+J286/$W$2 -> 4.4198923e-06
A287: ESPECIALIDADES AGROPECUARIAS S.A. | B287: Pesos | C287: 46330 | D287: 29/10/2026 | E287: 0.99509273 | G287: 5000000 | H287: 4975463.7 | I287: 5000000 | J287: 4975463.7 | K287: 1347 | L287: AMOMPY | M287: Momentum Capital Investment S.A. | N287: 01/10/2026 | O287: 01/10/2026 | P287: 30 | Q287: No | U287: *MAV021101248 | V287: *MAV021101248 | W287: =+J287/$W$2 -> 6.0892937e-05
A288: ESPECIALIDADES AGROPECUARIAS S.A. | B288: Pesos | C288: 46330 | D288: 29/10/2026 | E288: 0.99509275 | G288: 5000000 | H288: 4975463.7 | I288: 5000000 | J288: 4975463.7 | K288: 1350 | L288: AMOMPY | M288: Momentum Capital Investment S.A. | N288: 02/10/2026 | O288: 02/10/2026 | P288: 30 | Q288: No | U288: *MAV021101283 | V288: *MAV021101283 | W288: =+J288/$W$2 -> 6.0892938e-05
A289: ESPECIALIDADES AGROPECUARIAS S.A. | B289: Pesos | C289: 46330 | D289: 29/10/2026 | E289: 0.99509272 | G289: 4000000 | H289: 3980370.9 | I289: 4000000 | J289: 3980370.9 | K289: 1289 | L289: AMOMPY | M289: Momentum Capital Investment S.A. | N289: 23/09/2026 | O289: 23/09/2026 | P289: 30 | Q289: No | U289: *MAV021101170 | V289: *MAV021101170 | W289: =+J289/$W$2 -> 4.8714349e-05
A290: ESPECIALIDADES AGROPECUARIAS S.A. | B290: Pesos | C290: 46330 | D290: 29/10/2026 | E290: 0.9950927 | G290: 5000000 | H290: 4975463.5 | I290: 5000000 | J290: 4975463.5 | K290: 1307 | L290: AMOMPY | M290: Momentum Capital Investment S.A. | N290: 29/09/2026 | O290: 29/09/2026 | P290: 30 | Q290: No | U290: *MAV021101220 | V290: *MAV021101220 | W290: =+J290/$W$2 -> 6.0892935e-05
A291: GOMEZ ROCO Y CIA SRL | B291: Pesos | C291: 46330 | D291: 29/10/2026 | E291: 0.9947673 | G291: 22929530 | H291: 22809546 | I291: 22929530 | J291: 22809546 | K291: 82628359 | L291: AMOMPY | M291: Momentum Capital Investment S.A. | N291: 05/10/2026 | O291: 02/10/2026 | P291: 32 | Q291: No | U291: *MAV011101364 | V291: *MAV011101364 | W291: =+J291/$W$2 -> 0.00027915796
A292: LW GROUP SRL | B292: Pesos | C292: 46330 | D292: 29/10/2026 | E292: 0.99460462 | G292: 2000000 | H292: 1989209.2 | I292: 2000000 | J292: 1989209.2 | K292: 42 | L292: AMOMPY | M292: Momentum Capital Investment S.A. | N292: 13/08/2026 | O292: 13/08/2026 | P292: 33 | Q292: No | U292: *MAV311001718 | V292: *MAV311001718 | W292: =+J292/$W$2 -> 2.4345227e-05
A293: BROADBANDTECH SA | B293: Pesos | C293: 46330 | D293: 29/10/2026 | E293: 0.99476729 | G293: 20000000 | H293: 19895346 | I293: 20000000 | J293: 19895346 | K293: 724 | L293: AMOMPY | M293: Momentum Capital Investment S.A. | N293: 21/09/2026 | O293: 21/09/2026 | P293: 32 | Q293: No | U293: *MAV021101140 | V293: *MAV021101140 | W293: =+J293/$W$2 -> 0.00024349209
A294: PINTURAS SAN AGUSTIN SRL | B294: Pesos | C294: 46330 | D294: 29/10/2026 | E294: 0.99476731 | G294: 6000000 | H294: 5968603.8 | I294: 6000000 | J294: 5968603.8 | K294: 70158555 | L294: AMOMPY | M294: Momentum Capital Investment S.A. | N294: 02/10/2026 | O294: 02/10/2026 | P294: 32 | Q294: No | U294: *MAV311002021 | V294: *MAV311002021 | W294: =+J294/$W$2 -> 7.3047628e-05
A295: RUBBO GUSTAVO ALEJANDRO MARIO | B295: Pesos | C295: 46330 | D295: 29/10/2026 | E295: 0.9947673 | G295: 1000000 | H295: 994767.3 | I295: 1000000 | J295: 994767.3 | K295: 70161997 | L295: AMOMPY | M295: Momentum Capital Investment S.A. | N295: 02/10/2026 | O295: 02/10/2026 | P295: 32 | Q295: No | U295: *MAV311002020 | V295: *MAV311002020 | W295: =+J295/$W$2 -> 1.2174605e-05
A296: NELIO RAUL PIGNATTA Y CIA SA | B296: Pesos | C296: 46330 | D296: 29/10/2026 | E296: 0.9947673 | G296: 18485149 | H296: 18388422 | I296: 18485149 | J296: 18388422 | K296: 4478 | L296: AMOMPY | M296: Momentum Capital Investment S.A. | N296: 05/10/2026 | O296: 05/10/2026 | P296: 32 | Q296: No | U296: *MAV311002023 | V296: *MAV311002023 | W296: =+J296/$W$2 -> 0.00022504939
A297: DE DOMINGO FRANCISCO JORGE ESTEBAN | B297: Pesos | C297: 46330 | D297: 29/10/2026 | E297: 0.99476729 | G297: 363375.5 | H297: 361474.06 | I297: 363375.5 | J297: 361474.06 | K297: 304 | L297: AMOMPY | M297: Momentum Capital Investment S.A. | N297: 06/10/2026 | O297: 06/10/2026 | P297: 32 | Q297: No | U297: *MAV011101362 | V297: *MAV011101362 | W297: =+J297/$W$2 -> 4.423953e-06
... A311: DE LAS MISIONES S.A. | B311: Pesos | C311: 46330 | D311: 29/10/2026 | E311: 0.9950927 | G311: 2700000 | H311: 2686750.3 | I311: 2700000 | J311: 2686750.3 | K311: 6910 | L311: AMOMPY | M311: Momentum Capital Investment S.A. | N311: 11/09/2026 | O311: 11/09/2026 | P311: 30 | Q311: No | U311: *MAV311001868 | V311: *MAV311001868 | W311: =+J311/$W$2 -> 3.2882185e-05
A312: DEMAGRO SRL | B312: Dolar 3500 | C312: 46330 | D312: 29/10/2026 | E312: 0.9986868 | F312: 1 US3 = 1539,5930209017 $ | G312: 50000 | H312: 49934.34 | I312: 76979651 | J312: 76878561 | K312: 158025 | L312: AMOMPY | M312: Momentum Capital Investment S.A. | N312: 23/07/2026 | O312: 23/07/2026 | P312: 8 | Q312: No | U312: #UMV011160007 | V312: #UMV011160007 | W312: =+J312/$W$2 -> 0.00094088948
A313: QUILMES | B313: Pesos | C313: 46330 | D313: 29/10/2026 | E313: 0.99590723 | G313: 695186.79 | H313: 692341.55 | I313: 695186.79 | J313: 692341.55 | K313: 40014794 | L313: AMOMPY | M313: Momentum Capital Investment S.A. | N313: 31/08/2026 | O313: 31/08/2026 | P313: 25 | Q313: No | U313: *MAV021100935 | V313: *MAV021100935 | W313: =+J313/$W$2 -> 8.473323e-06
A314: GRUPO PETBA SA. | B314: Pesos | C314: 46330 | D314: 29/10/2026 | E314: 0.99395459 | G314: 25000000 | H314: 24848865 | I314: 25000000 | J314: 24848865 | K314: 2593 | L314: AMOMPY | M314: Momentum Capital Investment S.A. | N314: 07/08/2026 | O314: 07/08/2026 | P314: 37 | Q314: No | U314: *MAV021100857 | V314: *MAV021100857 | W314: =+J314/$W$2 -> 0.00030411645
A315: ESPECIALIDADES AGROPECUARIAS S.A. | B315: Pesos | C315: 46330 | D315: 29/10/2026 | E315: 0.99509271 | G315: 5000000 | H315: 4975463.5 | I315: 5000000 | J315: 4975463.5 | K315: 1199 | L315: AMOMPY | M315: Momentum Capital Investment S.A. | N315: 08/09/2026 | O315: 08/09/2026 | P315: 30 | Q315: No | U315: *MAV021101040 | V315: *MAV021101040 | W315: =+J315/$W$2 -> 6.0892936e-05
A316: ESPECIALIDADES AGROPECUARIAS S.A. | B316: Pesos | C316: 46330 | D316: 29/10/2026 | E316: 0.99509272 | G316: 5000000 | H316: 4975463.6 | I316: 5000000 | J316: 4975463.6 | K316: 1243 | L316: AMOMPY | M316: Momentum Capital Investment S.A. | N316: 17/09/2026 | O316: 17/09/2026 | P316: 30 | Q316: No | U316: *MAV021101117 | V316: *MAV021101117 | W316: =+J316/$W$2 -> 6.0892937e-05
A317: ESPECIALIDADES AGROPECUARIAS S.A. | B317: Pesos | C317: 46330 | D317: 29/10/2026 | E317: 0.99476726 | G317: 3000000 | H317: 2984301.8 | I317: 3000000 | J317: 2984301.8 | K317: 1048 | L317: AMOMPY | M317: Momentum Capital Investment S.A. | N317: 25/08/2026 | O317: 25/08/2026 | P317: 32 | Q317: No | U317: *MAV021100906 | V317: *MAV021100906 | W317: =+J317/$W$2 -> 3.6523812e-05
A318: ESPECIALIDADES AGROPECUARIAS S.A. | B318: Pesos | C318: 46330 | D318: 29/10/2026 | E318: 0.99460463 | G318: 2500000 | H318: 2486511.6 | I318: 2500000 | J318: 2486511.6 | K318: 1014 | L318: AMOMPY | M318: Momentum Capital Investment S.A. | N318: 19/08/2026 | O318: 19/08/2026 | P318: 33 | Q318: No | U318: *MAV021100886 | V318: *MAV021100886 | W318: =+J318/$W$2 -> 3.0431534e-05
A319: KOMPASS SRL | B319: Pesos | C319: 46330 | D319: 29/10/2026 | E319: 0.99476732 | G319: 50000000 | H319: 49738366 | I319: 50000000 | J319: 49738366 | K319: 21553 | L319: AMOMPY | M319: Momentum Capital Investment S.A. | N319: 19/10/2026 | O319: 19/10/2026 | P319: 32 | Q319: No | U319: *MAV311002172 | V319: *MAV311002172 | W319: =+J319/$W$2 -> 0.00060873025
A320: TREND SGR | B320: Pesos | C320: 46331 | D320: 29/10/2026 | E320: 0.99522837 | G320: 15000000 | H320: 14928425 | I320: 15000000 | J320: 14928425 | K320: 69911195 | L320: AMOMPY | M320: Momentum Capital Investment S.A. | N320: 23/09/2026 | O320: 23/09/2026 | P320: 25 | Q320: No | U320: *TRD031100028 | V320: *TRD031100028 | W320: =+J320/$W$2 -> 0.00018270371
A321: Vinculos S.G.R. | B321: Pesos | C321: 46331 | D321: 29/10/2026 | E321: 0.99427949 | G321: 5568708.9 | H321: 5536853 | I321: 5568708.9 | J321: 5536853 | K321: 23042 | L321: AMOMPY | M321: Momentum Capital Investment S.A. | N321: 15/09/2026 | O321: 15/09/2026 | P321: 30 | Q321: No | U321: *AFB031100008 | V321: *AFB031100008 | W321: =+J321/$W$2 -> 6.7763583e-05
A322: Vinculos S.G.R. | B322: Pesos | C322: 46331 | D322: 29/10/2026 | E322: 0.99484862 | G322: 2500000 | H322: 2487121.6 | I322: 2500000 | J322: 2487121.6 | K322: 69814628 | L322: AMOMPY | M322: Momentum Capital Investment S.A. | N322: 18/09/2026 | O322: 18/09/2026 | P322: 27 | Q322: No | U322: *AFB031100009 | V322: *AFB031100009 | W322: =+J322/$W$2 -> 3.0439e-05
A323: PAMPA VIDA S.R.L. | B323: Pesos | C323: 46331 | D323: 29/10/2026 | E323: 0.99314324 | G323: 3625698.8 | H323: 3600838.2 | I323: 3625698.8 | J323: 3600838.2 | K323: 3350 | L323: AMOMPY | M323: Momentum Capital Investment S.A. | N323: 28/08/2026 | O323: 28/08/2026 | P323: 36 | Q323: No | U323: *MAV031101392 | V323: *MAV031101392 | W323: =+J323/$W$2 -> 4.4069383e-05
A324: PAMPA VIDA S.R.L. | B324: Pesos | C324: 46331 | D324: 29/10/2026 | E324: 0.99333246 | G324: 3256800.5 | H324: 3235085.6 | I324: 3256800.5 | J324: 3235085.6 | K324: 3578 | L324: AMOMPY | M324: Momentum Capital Investment S.A. | N324: 17/09/2026 | O324: 17/09/2026 | P324: 35 | Q324: No | U324: *MAV031101518 | V324: *MAV031101518 | W324: =+J324/$W$2 -> 3.9593067e-05
... A682: AUTOPISTAS URBANAS SA | B682: Pesos | C682: 46342 | D682: 29/10/2026 | E682: 0.98494262 | G682: 1.6385601e+09 | H682: 1.6138876e+09 | I682: 1.6385601e+09 | J682: 1.6138876e+09 | K682: 90 | L682: AMOMPY | M682: Momentum Capital Investment S.A. | N682: 23/10/2026 | O682: 23/10/2026 | P682: 31 | Q682: No | U682: %AUU131100001 | V682: %AUU131100001 | W682: =+J682/$W$2 -> 0.019751799
A683: MONDELEZ ARG SA | B683: Dolar Link | C683: 46342 | D683: 29/10/2026 | E683: 0.9897501 | F683: 1 BNA = 1560,0000998400 $ | G683: 136308.7 | H683: 134911.55 | I683: 2.1264159e+08 | J683: 2.1046203e+08 | K683: 60 | L683: AMOMPY | M683: Momentum Capital Investment S.A. | N683: 16/10/2026 | O683: 16/10/2026 | P683: 21 | Q683: No | U683: %UON131100001 | V683: %UON131100001 | W683: =+J683/$W$2 -> 0.0025757702
A684: TARJETA NARANJA SA | B684: Pesos | C684: 46342 | D684: 29/10/2026 | E684: 0.98782145 | G684: 3915102.3 | H684: 3867422 | I684: 3915102.3 | J684: 3867422 | K684: 681630 | L684: AMOMPY | M684: Momentum Capital Investment S.A. | N684: 18/09/2026 | O684: 18/09/2026 | P684: 25 | Q684: No | U684: *MAV121101549 | V684: *MAV121101549 | W684: =+J684/$W$2 -> 4.7332008e-05
A685: TARJETA NARANJA SA | B685: Pesos | C685: 46342 | D685: 29/10/2026 | E685: 0.98782145 | G685: 973870.43 | H685: 962010.1 | I685: 973870.43 | J685: 962010.1 | K685: 681511 | L685: AMOMPY | M685: Momentum Capital Investment S.A. | N685: 18/09/2026 | O685: 18/09/2026 | P685: 25 | Q685: No | U685: *MAV121101550 | V685: *MAV121101550 | W685: =+J685/$W$2 -> 1.1773701e-05
A686: TARJETA NARANJA SA | B686: Pesos | C686: 46342 | D686: 29/10/2026 | E686: 0.98782144 | G686: 1029426 | H686: 1016889.1 | I686: 1029426 | J686: 1016889.1 | K686: 681498 | L686: AMOMPY | M686: Momentum Capital Investment S.A. | N686: 18/09/2026 | O686: 18/09/2026 | P686: 25 | Q686: No | U686: *MAV121101551 | V686: *MAV121101551 | W686: =+J686/$W$2 -> 1.2445346e-05
A687: TARJETA NARANJA SA | B687: Pesos | C687: 46342 | D687: 29/10/2026 | E687: 0.98782143 | G687: 1351574.4 | H687: 1335114.2 | I687: 1351574.4 | J687: 1335114.2 | K687: 681634 | L687: AMOMPY | M687: Momentum Capital Investment S.A. | N687: 18/09/2026 | O687: 18/09/2026 | P687: 25 | Q687: No | U687: *MAV121101552 | V687: *MAV121101552 | W687: =+J687/$W$2 -> 1.6339989e-05
A688: TARJETA NARANJA SA | B688: Pesos | C688: 46342 | D688: 29/10/2026 | E688: 0.98782135 | G688: 188938.02 | H688: 186637.01 | I688: 188938.02 | J688: 186637.01 | K688: 681548 | L688: AMOMPY | M688: Momentum Capital Investment S.A. | N688: 18/09/2026 | O688: 18/09/2026 | P688: 25 | Q688: No | U688: *MAV121101553 | V688: *MAV121101553 | W688: =+J688/$W$2 -> 2.2841843e-06
A689: TARJETA NARANJA SA | B689: Pesos | C689: 46342 | D689: 29/10/2026 | E689: 0.98782143 | G689: 1351574.4 | H689: 1335114.2 | I689: 1351574.4 | J689: 1335114.2 | K689: 681632 | L689: AMOMPY | M689: Momentum Capital Investment S.A. | N689: 18/09/2026 | O689: 18/09/2026 | P689: 25 | Q689: No | U689: *MAV121101554 | V689: *MAV121101554 | W689: =+J689/$W$2 -> 1.6339989e-05
A690: VELVET COMFORT & DESIGN S.R.L. | B690: Pesos | C690: 46342 | D690: 29/10/2026 | E690: 0.98542135 | G690: 2006000 | H690: 1976755.2 | I690: 2006000 | J690: 1976755.2 | K690: 70555885 | L690: AMOMPY | M690: Momentum Capital Investment S.A. | N690: 21/10/2026 | O690: 21/10/2026 | P690: 30 | Q690: No | U690: *MAV121101885 | V690: *MAV121101885 | W690: =+J690/$W$2 -> 2.4192807e-05
A691: SIBIU PRODUCCIONES S.A.S. | B691: Pesos | C691: 46342 | D691: 29/10/2026 | E691: 0.98398662 | G691: 686128.26 | H691: 675141.03 | I691: 686128.26 | J691: 675141.03 | K691: 19384 | L691: AMOMPY | M691: Momentum Capital Investment S.A. | N691: 15/09/2026 | O691: 15/09/2026 | P691: 33 | Q691: No | U691: *MAV121101505 | V691: *MAV121101505 | W691: =+J691/$W$2 -> 8.2628119e-06
A692: GOBIERNO DE LA CUIDAD DE BUENOS AIRES | B692: Pesos | C692: 46342 | D692: 29/10/2026 | E692: 0.98542126 | G692: 19275534 | H692: 18994521 | I692: 19275534 | J692: 18994521 | K692: 40800772 | L692: AMOMPY | M692: Momentum Capital Investment S.A. | N692: 23/10/2026 | O692: 23/10/2026 | P692: 30 | Q692: No | U692: *MAV121101909 | V692: *MAV121101909 | W692: =+J692/$W$2 -> 0.00023246721
A693: GOBIERNO DE LA CUIDAD DE BUENOS AIRES | B693: Pesos | C693: 46342 | D693: 29/10/2026 | E693: 0.98542126 | G693: 20775705 | H693: 20472821 | I693: 20775705 | J693: 20472821 | K693: 40298602 | L693: AMOMPY | M693: Momentum Capital Investment S.A. | N693: 23/10/2026 | O693: 23/10/2026 | P693: 30 | Q693: No | U693: *MAV121101910 | V693: *MAV121101910 | W693: =+J693/$W$2 -> 0.0002505596
A694: CELULOSA CAMPANA SA | B694: Pesos | C694: 46342 | D694: 29/10/2026 | E694: 0.98446437 | G694: 11829798 | H694: 11646014 | I694: 11829798 | J694: 11646014 | K694: 30897 | L694: AMOMPY | M694: Momentum Capital Investment S.A. | N694: 31/07/2026 | O694: 31/07/2026 | P694: 32 | Q694: No | U694: *MAV121101212 | V694: *MAV121101212 | W694: =+J694/$W$2 -> 0.00014253144
A695: CELULOSA CAMPANA SA | B695: Pesos | C695: 46342 | D695: 29/10/2026 | E695: 0.98446437 | G695: 11229494 | H695: 11055037 | I695: 11229494 | J695: 11055037 | K695: 30920 | L695: AMOMPY | M695: Momentum Capital Investment S.A. | N695: 31/07/2026 | O695: 31/07/2026 | P695: 32 | Q695: No | U695: *MAV121101210 | V695: *MAV121101210 | W695: =+J695/$W$2 -> 0.00013529868
... A742: CEIBO CREDITOS S.A. | B742: Pesos | C742: 46343 | D742: 29/10/2026 | E742: 0.9846238 | G742: 50000000 | H742: 49231190 | I742: 50000000 | J742: 49231190 | K742: 16836871 | L742: AMOMPY | M742: Momentum Capital Investment S.A. | N742: 14/10/2026 | O742: 14/10/2026 | P742: 30 | Q742: No | U742: *MAV131101704 | V742: *MAV131101704 | W742: =+J742/$W$2 -> 0.00060252309
A743: PUNTO PACK SRL | B743: Dolar 3500 | C743: 46343 | D743: 29/10/2026 | E743: 0.99585409 | F743: 1 US3 = 1539,5930209017 $ | G743: 18230 | H743: 18154.42 | I743: 28066781 | J743: 27950418 | K743: 146446 | L743: AMOMPY | M743: Momentum Capital Investment S.A. | N743: 17/04/2026 | O743: 17/04/2026 | P743: 8 | Q743: No | U743: #UMV131160016 | V743: #UMV131160016 | W743: =+J743/$W$2 -> 0.00034207527
A744: TEXTUM SA | B744: Pesos | C744: 46343 | D744: 29/10/2026 | E744: 0.98260922 | G744: 10000000 | H744: 9826092.2 | I744: 10000000 | J744: 9826092.2 | K744: 14284515 | L744: AMOMPY | M744: Momentum Capital Investment S.A. | N744: 24/08/2026 | O744: 24/08/2026 | P744: 34 | Q744: No | U744: *MAV131101195 | V744: *MAV131101195 | W744: =+J744/$W$2 -> 0.00012025806
A745: LAROCCA NEUMATICOS S A | B745: Pesos | C745: 46343 | D745: 29/10/2026 | E745: 0.98361539 | G745: 50000000 | H745: 49180770 | I745: 50000000 | J745: 49180770 | K745: 5360 | L745: AMOMPY | M745: Momentum Capital Investment S.A. | N745: 16/09/2026 | O745: 16/09/2026 | P745: 32 | Q745: No | U745: *MAV131101362 | V745: *MAV131101362 | W745: =+J745/$W$2 -> 0.00060190602
A746: S.E.S. S.A. - CONSTRUERE INGENIERIA S.A. | B746: Pesos | C746: 46343 | D746: 29/10/2026 | E746: 0.97960283 | G746: 197500000 | H746: 1.9347156e+08 | I746: 197500000 | J746: 1.9347156e+08 | K746: 70408191 | L746: AMOMPY | M746: Momentum Capital Investment S.A. | N746: 05/10/2026 | O746: 05/10/2026 | P746: 40 | Q746: No | U746: *MAV131101550 | V746: *MAV131101550 | W746: =+J746/$W$2 -> 0.0023678299
A747: BILOROOM | B747: Pesos | C747: 46343 | D747: 29/10/2026 | E747: 0.9831121 | G747: 2500000 | H747: 2457780.2 | I747: 2500000 | J747: 2457780.2 | K747: 98 | L747: AMOMPY | M747: Momentum Capital Investment S.A. | N747: 22/09/2026 | O747: 22/09/2026 | P747: 33 | Q747: No | U747: *MAV131101407 | V747: *MAV131101407 | W747: =+J747/$W$2 -> 3.0079902e-05
A748: ESPECIALIDADES AGROPECUARIAS S.A. | B748: Pesos | C748: 46343 | D748: 29/10/2026 | E748: 0.9846238 | G748: 3500000 | H748: 3446183.3 | I748: 3500000 | J748: 3446183.3 | K748: 1387 | L748: AMOMPY | M748: Momentum Capital Investment S.A. | N748: 14/10/2026 | O748: 14/10/2026 | P748: 30 | Q748: No | U748: *MAV131101678 | V748: *MAV131101678 | W748: =+J748/$W$2 -> 4.2176617e-05
A749: ESPECIALIDADES AGROPECUARIAS S.A. | B749: Pesos | C749: 46343 | D749: 29/10/2026 | E749: 0.98462385 | G749: 7500000 | H749: 7384678.8 | I749: 7500000 | J749: 7384678.8 | K749: 1388 | L749: AMOMPY | M749: Momentum Capital Investment S.A. | N749: 15/10/2026 | O749: 15/10/2026 | P749: 30 | Q749: No | U749: *MAV131101722 | V749: *MAV131101722 | W749: =+J749/$W$2 -> 9.0378468e-05
A750: ESPECIALIDADES AGROPECUARIAS S.A. | B750: Pesos | C750: 46343 | D750: 29/10/2026 | E750: 0.98462375 | G750: 6500000 | H750: 6400054.4 | I750: 6500000 | J750: 6400054.4 | K750: 1383 | L750: AMOMPY | M750: Momentum Capital Investment S.A. | N750: 13/10/2026 | O750: 13/10/2026 | P750: 30 | Q750: No | U750: *MAV131101629 | V750: *MAV131101629 | W750: =+J750/$W$2 -> 7.8327998e-05
A751: ESPECIALIDADES AGROPECUARIAS S.A. | B751: Pesos | C751: 46343 | D751: 29/10/2026 | E751: 0.9846237 | G751: 5000000 | H751: 4923118.5 | I751: 5000000 | J751: 4923118.5 | K751: 1349 | L751: AMOMPY | M751: Momentum Capital Investment S.A. | N751: 01/10/2026 | O751: 01/10/2026 | P751: 30 | Q751: No | U751: *MAV131101499 | V751: *MAV131101499 | W751: =+J751/$W$2 -> 6.0252303e-05
A752: ESPECIALIDADES AGROPECUARIAS S.A. | B752: Pesos | C752: 46343 | D752: 29/10/2026 | E752: 0.98462378 | G752: 4250000 | H752: 4184651.1 | I752: 4250000 | J752: 4184651.1 | K752: 1331 | L752: AMOMPY | M752: Momentum Capital Investment S.A. | N752: 30/09/2026 | O752: 30/09/2026 | P752: 30 | Q752: No | U752: *MAV131101487 | V752: *MAV131101487 | W752: =+J752/$W$2 -> 5.1214462e-05
A753: COOPERATIVA DE VIVIENDA CREDITO Y CONSUMO PARA EL DESARROLLO LIMITADA | B753: Pesos | C753: 46343 | D753: 29/10/2026 | E753: 0.98060294 | G753: 45200000 | H753: 44323253 | I753: 45200000 | J753: 44323253 | K753: 163278 | L753: AMOMPY | M753: Momentum Capital Investment S.A. | N753: 04/09/2026 | O753: 04/09/2026 | P753: 38 | Q753: No | U753: #MAV161160038 | V753: #MAV161160038 | W753: =+J753/$W$2 -> 0.00054245659
A754: COOPERATIVA DE VIVIENDA CREDITO Y CONSUMO PARA EL DESARROLLO LIMITADA | B754: Pesos | C754: 46343 | D754: 29/10/2026 | E754: 0.98060294 | G754: 25000000 | H754: 24515073 | I754: 25000000 | J754: 24515073 | K754: 163279 | L754: AMOMPY | M754: Momentum Capital Investment S.A. | N754: 04/09/2026 | O754: 04/09/2026 | P754: 38 | Q754: No | U754: #MAV161160039 | V754: #MAV161160039 | W754: =+J754/$W$2 -> 0.0003000313
A755: BAIRES QUIMICA SA | B755: Pesos | C755: 46343 | D755: 29/10/2026 | E755: 0.98361543 | G755: 1858362 | H755: 1827913.5 | I755: 1858362 | J755: 1827913.5 | K755: 1484 | L755: AMOMPY | M755: Momentum Capital Investment S.A. | N755: 05/10/2026 | O755: 05/10/2026 | P755: 32 | Q755: No | U755: *MAV131101523 | V755: *MAV131101523 | W755: =+J755/$W$2 -> 2.2371186e-05
... A1390: LAROCCA NEUMATICOS S A | B1390: Pesos | C1390: 46359 | D1390: 29/10/2026 | E1390: 0.97022866 | G1390: 50000000 | H1390: 48511433 | I1390: 50000000 | J1390: 48511433 | K1390: 5292 | L1390: AMOMPY | M1390: Momentum Capital Investment S.A. | N1390: 08/09/2026 | O1390: 08/09/2026 | P1390: 32 | Q1390: No | U1390: *MAV011201533 | V1390: *MAV011201533 | W1390: =+J1390/$W$2 -> 0.00059371424
A1391: BSP LARTI SA | B1391: Dolar 3500 | C1391: 46359 | D1391: 29/10/2026 | E1391: 0.9914437 | F1391: 1 US3 = 1539,5930209017 $ | G1391: 100000 | H1391: 99144.37 | I1391: 1.539593e+08 | J1391: 1.5264198e+08 | K1391: 159253 | L1391: AMOMPY | M1391: Momentum Capital Investment S.A. | N1391: 03/08/2026 | O1391: 03/08/2026 | P1391: 9 | Q1391: No | U1391: #UMV011260046 | V1391: #UMV011260046 | W1391: =+J1391/$W$2 -> 0.0018681311
A1392: ESPECIALIDADES AGROPECUARIAS S.A. | B1392: Pesos | C1392: 46359 | D1392: 29/10/2026 | E1392: 0.97203744 | G1392: 10000000 | H1392: 9720374.4 | I1392: 10000000 | J1392: 9720374.4 | K1392: 1434 | L1392: AMOMPY | M1392: Momentum Capital Investment S.A. | N1392: 26/10/2026 | O1392: 26/10/2026 | P1392: 30 | Q1392: No | U1392: *MAV011201828 | V1392: *MAV011201828 | W1392: =+J1392/$W$2 -> 0.00011896422
A1393: ESPECIALIDADES AGROPECUARIAS S.A. | B1393: Pesos | C1393: 46359 | D1393: 29/10/2026 | E1393: 0.97203752 | G1393: 9000000 | H1393: 8748337.6 | I1393: 9000000 | J1393: 8748337.6 | K1393: 1437 | L1393: AMOMPY | M1393: Momentum Capital Investment S.A. | N1393: 27/10/2026 | O1393: 27/10/2026 | P1393: 30 | Q1393: No | U1393: *MAV011201851 | V1393: *MAV011201851 | W1393: =+J1393/$W$2 -> 0.00010706781
A1394: ESPECIALIDADES AGROPECUARIAS S.A. | B1394: Pesos | C1394: 46359 | D1394: 29/10/2026 | E1394: 0.97203732 | G1394: 10000000 | H1394: 9720373.2 | I1394: 10000000 | J1394: 9720373.2 | K1394: 1442 | L1394: AMOMPY | M1394: Momentum Capital Investment S.A. | N1394: 28/10/2026 | O1394: 28/10/2026 | P1394: 30 | Q1394: No | U1394: *MAV011201876 | V1394: *MAV011201876 | W1394: =+J1394/$W$2 -> 0.0001189642
A1395: ESPECIALIDADES AGROPECUARIAS S.A. | B1395: Dolar 3500 | C1395: 46359 | D1395: 29/10/2026 | E1395: 0.99238716 | F1395: 1 US3 = 1539,5930209017 $ | G1395: 450000 | H1395: 446574.22 | I1395: 6.9281686e+08 | J1395: 6.8754255e+08 | K1395: 165877 | L1395: AMOMPY | M1395: Momentum Capital Investment S.A. | N1395: 21/09/2026 | O1395: 21/09/2026 | P1395: 8 | Q1395: No | U1395: #UMV011260065 | V1395: #UMV011260065 | W1395: =+J1395/$W$2 -> 0.0084145897
A1396: SERVICIOS DE PRODUCCIONES ARTISTICAS SRL | B1396: Pesos | C1396: 46359 | D1396: 29/10/2026 | E1396: 0.9720374 | G1396: 75000000 | H1396: 72902805 | I1396: 75000000 | J1396: 72902805 | K1396: 343 | L1396: AMOMPY | M1396: Momentum Capital Investment S.A. | N1396: 01/10/2026 | O1396: 01/10/2026 | P1396: 30 | Q1396: No | U1396: *MAV011201651 | V1396: *MAV011201651 | W1396: =+J1396/$W$2 -> 0.00089223161
A1397: ARINCO SA | B1397: Pesos | C1397: 46359 | D1397: 29/10/2026 | E1397: 0.97022876 | G1397: 5106355 | H1397: 4954332.5 | I1397: 5106355 | J1397: 4954332.5 | K1397: 10405 | L1397: AMOMPY | M1397: Momentum Capital Investment S.A. | N1397: 05/10/2026 | O1397: 05/10/2026 | P1397: 32 | Q1397: No | U1397: *MAV011201670 | V1397: *MAV011201670 | W1397: =+J1397/$W$2 -> 6.063432e-05
A1398: DE DOMINGO FRANCISCO JORGE ESTEBAN | B1398: Pesos | C1398: 46359 | D1398: 29/10/2026 | E1398: 0.97022862 | G1398: 363375.5 | H1398: 352557.31 | I1398: 363375.5 | J1398: 352557.31 | K1398: 305 | L1398: AMOMPY | M1398: Momentum Capital Investment S.A. | N1398: 06/10/2026 | O1398: 06/10/2026 | P1398: 32 | Q1398: No | U1398: *MAV011201671 | V1398: *MAV011201671 | W1398: =+J1398/$W$2 -> 4.314824e-06
A1399: CAMPO CUATRO SA | B1399: Pesos | C1399: 46359 | D1399: 29/10/2026 | E1399: 0.96932685 | G1399: 2616499.5 | H1399: 2536243.2 | I1399: 2616499.5 | J1399: 2536243.2 | K1399: 10858294 | L1399: AMOMPY | M1399: Momentum Capital Investment S.A. | N1399: 14/10/2026 | O1399: 14/10/2026 | P1399: 33 | Q1399: No | U1399: *MAV011201733 | V1399: *MAV011201733 | W1399: =+J1399/$W$2 -> 3.1040182e-05
A1400: MILLS S.G.R. | B1400: Pesos | C1400: 46359 | D1400: 29/10/2026 | E1400: 0.97113212 | G1400: 6000000 | H1400: 5826792.7 | I1400: 6000000 | J1400: 5826792.7 | K1400: 12299307 | L1400: AMOMPY | M1400: Momentum Capital Investment S.A. | N1400: 07/09/2026 | O1400: 07/09/2026 | P1400: 31 | Q1400: No | U1400: *MIL011200029 | V1400: *MIL011200029 | W1400: =+J1400/$W$2 -> 7.1312052e-05
A1401: POTENCIAR SGR | B1401: Pesos | C1401: 46359 | D1401: 29/10/2026 | E1401: 0.975675 | G1401: 7000000 | H1401: 6829725 | I1401: 7000000 | J1401: 6829725 | K1401: 1741 | L1401: AMOMPY | M1401: Momentum Capital Investment S.A. | N1401: 01/09/2026 | O1401: 01/09/2026 | P1401: 26 | Q1401: No | U1401: *POT011200055 | V1401: *POT011200055 | W1401: =+J1401/$W$2 -> 8.3586585e-05
A1402: DEMAGRO SRL | B1402: Dolar 3500 | C1402: 46359 | D1402: 29/10/2026 | E1402: 0.9923872 | F1402: 1 US3 = 1539,5930209017 $ | G1402: 50000 | H1402: 49619.36 | I1402: 76979651 | J1402: 76393620 | K1402: 158027 | L1402: AMOMPY | M1402: Momentum Capital Investment S.A. | N1402: 23/07/2026 | O1402: 23/07/2026 | P1402: 8 | Q1402: No | U1402: #UMV011260045 | V1402: #UMV011260045 | W1402: =+J1402/$W$2 -> 0.00093495446
A1403: QUILMES | B1403: Pesos | C1403: 46359 | D1403: 29/10/2026 | E1403: 0.97567495 | G1403: 1633163.6 | H1403: 1593436.8 | I1403: 1633163.6 | J1403: 1593436.8 | K1403: 40015662 | L1403: AMOMPY | M1403: Momentum Capital Investment S.A. | N1403: 25/09/2026 | O1403: 25/09/2026 | P1403: 26 | Q1403: No | U1403: *MAV011201603 | V1403: *MAV011201603 | W1403: =+J1403/$W$2 -> 1.9501508e-05
A1404: ESPECIALIDADES AGROPECUARIAS S.A. | B1404: Dolar 3500 | C1404: 46359 | D1404: 29/10/2026 | E1404: 0.99238713 | F1404: 1 US3 = 1539,5930209017 $ | G1404: 150000 | H1404: 148858.07 | I1404: 2.3093895e+08 | J1404: 2.2918085e+08 | K1404: 164929 | L1404: AMOMPY | M1404: Momentum Capital Investment S.A. | N1404: 14/09/2026 | O1404: 14/09/2026 | P1404: 8 | Q1404: No | U1404: #UMV011260064 | V1404: #UMV011260064 | W1404: =+J1404/$W$2 -> 0.0028048632
A1405: SERVICIOS L&A SRL | B1405: Pesos | C1405: 46359 | D1405: 29/10/2026 | E1405: 0.97022873 | G1405: 75000000 | H1405: 72767154 | I1405: 75000000 | J1405: 72767154 | K1405: 586 | L1405: AMOMPY | M1405: Momentum Capital Investment S.A. | N1405: 22/10/2026 | O1405: 22/10/2026 | P1405: 32 | Q1405: No | U1405: *MAV011201819 | V1405: *MAV011201819 | W1405: =+J1405/$W$2 -> 0.00089057143
A1406: PAMPA VIDA S.R.L. | B1406: Pesos | C1406: 46360 | D1406: 29/10/2026 | E1406: 0.96571076 | G1406: 2874176.5 | H1406: 2775623.1 | I1406: 2874176.5 | J1406: 2775623.1 | K1406: 3437 | L1406: AMOMPY | M1406: Momentum Capital Investment S.A. | N1406: 10/09/2026 | O1406: 10/09/2026 | P1406: 36 | Q1406: No | U1406: *MAV021201317 | V1406: *MAV021201317 | W1406: =+J1406/$W$2 -> 3.3969868e-05
A1407: PAMPA VIDA S.R.L. | B1407: Pesos | C1407: 46360 | D1407: 29/10/2026 | E1407: 0.96571076 | G1407: 3841101.3 | H1407: 3709392.8 | I1407: 3841101.3 | J1407: 3709392.8 | K1407: 3367 | L1407: AMOMPY | M1407: Momentum Capital Investment S.A. | N1407: 10/09/2026 | O1407: 10/09/2026 | P1407: 36 | Q1407: No | U1407: *MAV021201318 | V1407: *MAV021201318 | W1407: =+J1407/$W$2 -> 4.5397945e-05
A1408: PAMPA VIDA S.R.L. | B1408: Pesos | C1408: 46360 | D1408: 29/10/2026 | E1408: 0.96571075 | G1408: 3105640.3 | H1408: 2999150.2 | I1408: 3105640.3 | J1408: 2999150.2 | K1408: 3389 | L1408: AMOMPY | M1408: Momentum Capital Investment S.A. | N1408: 10/09/2026 | O1408: 10/09/2026 | P1408: 36 | Q1408: No | U1408: *MAV021201319 | V1408: *MAV021201319 | W1408: =+J1408/$W$2 -> 3.6705537e-05
...

Sheet Posicion cuotapartista
A1: Posición de Cuotapartista
A2: Fondo | B2: Cuotapartista | C2: Tipo de Valor Cuotaparte | D2: Cuotapartes | E2: Inversión | F2: Moneda | G2: Fondo | H2: Tipo de Inversor | I2: Fondo | J2: Porcentaje
A3: Nombre | B3: Nombre | F3: Símbolo | G3: Fecha Valor Cuotaparte | I3: Valor Cuotaparte
A4: AMOMPY | B4: ZOFINGEN SECURITIES S.A. (ACDI) | C4: C | D4: 1.7003547e+09 | E4: 3.1799166e+09 | F4: $ | G4: 29/10/2026 | H4: Agentes de Colocación y Distribución Integral de FCIs | I4: 1.870149 | J4: 5.0185449
A5: AMOMPY | B5: BANCO DE LA CIUDAD DE BUENOS AIRES | C5: C | D5: 1.8078341e+09 | E5: 3380919138 | F5: $ | G5: 29/10/2026 | H5: Agentes de Colocación y Distribución Integral de FCIs | I5: 1.870149 | J5: 5.3357672
A6: AMOMPY | B6: MOMENTUM CAPITAL INVESTMENT S.A. (ACDI) | C6: C | D6: 2.8082279e+10 | E6: 5.2518046e+10 | F6: $ | G6: 29/10/2026 | H6: Agentes de Colocación y Distribución Integral de FCIs | I6: 1.870149 | J6: 82.88399
A7: AMOMPY | B7: ALYCBUR S.A. (ACDI) | C7: C | D7: 3.1629211e+08 | E7: 5.9151337e+08 | F7: $ | G7: 29/10/2026 | H7: Agentes de Colocación y Distribución Integral de FCIs | I7: 1.870149 | J7: 0.9335265
A8: AMOMPY | B8: BANCO DE SAN JUAN SA ( ACDI ) | C8: C | D8: 1.683916e+09 | E8: 3.1491738e+09 | F8: $ | G8: 29/10/2026 | H8: Agentes de Colocación y Distribución Integral de FCIs | I8: 1.870149 | J8: 4.9700267
A9: AMOMPY | B9: BANCO DE SANTA CRUZ SA (ACDI) | C9: C | D9: 2.9075177e+08 | E9: 5.4374913e+08 | F9: $ | G9: 29/10/2026 | H9: Agentes de Colocación y Distribución Integral de FCIs | I9: 1.870149 | J9: 0.85814497
A10: AMOMPY | B10: MOMENTUM CAPITAL INVESTMENT S.A. (ACDI) | C10: A | D10: 4.2098672e+09 | E10: 6.5219389e+09 | F10: $ | G10: 29/10/2026 | H10: Agentes de Colocación y Distribución Integral de FCIs | I10: 1.549203 | J10: 93.866975
A11: AMOMPY | B11: ALYCBUR S.A. (ACDI) | C11: A | D11: 2.7506183e+08 | E11: 4.2612661e+08 | F11: $ | G11: 29/10/2026 | H11: Agentes de Colocación y Distribución Integral de FCIs | I11: 1.549203 | J11: 6.1330252
A12: AMOMPY | B12: MOMENTUM CAPITAL INVESTMENT S.A. (ACDI) | C12: B | D12: 5.9702873e+09 | E12: 1.1083008e+10 | F12: $ | G12: 29/10/2026 | H12: Agentes de Colocación y Distribución Integral de FCIs | I12: 1.856361 | J12: 97.245008
A13: AMOMPY | B13: ALYCBUR S.A. (ACDI) | C13: B | D13: 1.6914077e+08 | E13: 3.1398634e+08 | F13: $ | G13: 29/10/2026 | H13: Agentes de Colocación y Distribución Integral de FCIs | I13: 1.856361 | J13: 2.7549924
D14: 4.4505785e+10 | E14: 8.1708379e+10
