Workbook

Sheet GESTION MOMENTUM
A1: FONDOS COMUNES DE INVERSION
A2: 6/7/2026
A3: 09:52:13
A4: Informe de Gestión al 3/7/2026
A5: FCI ABIERTO MOMENTUM PYMES | K5: COMAFI $ Nº 24148/3
A6: Todos los importes están expresados en Pesos | K6: BANCO DEL SOL
C7: (4) | D7: (1) | L7: 46209 | M7: =WORKDAY(L7,1,$R:$R) -> 46210 | N7: =WORKDAY(M7,1,$R:$R) -> 46211 | R7: 45719 | S7: Lista de feriados 2025
A8: ACTIVO | B8: 4.9215866e+10 | C8: 100 | K8: Caucion MAV | L8: 3.504411e+09 | R8: 45720
A9: INVERSIONES | B9: 4.7433111e+10 | C9: 96.38 | D9: 97.03 | K9: Vto Pase | R9: 45740
A10: TITULOS PUBLICOS | B10: 295167942 | C10: 0.6 | D10: 0.6 | K10: Plazo Fijo | L10: =SUMIFS(F:F,A:A,$K$10,B:B,L7) -> 0 | M10: =SUMIFS(G:G,B:B,$K$10,C:C,M7) -> 0 | N10: =SUMIFS(H:H,C:C,$K$10,D:D,N7) -> 0 | R10: 45749
A11: FUTUROS | B11: -1224725000 | C11: -2.49 | D11: -2.51 | K11: Vto. Cheques | L11: =SUMIF($B$95:$B$1441,L7,$D$95:$D$1441) -> 73381630 | M11: =SUMIF($B$95:$B$1441,M7,$D$95:$D$1441) -> 1034833880 | N11: =SUMIF($B$95:$B$1441,N7,$D$95:$D$1441) -> 3.4646107e+08 | R11: 45765
A12: DISPONIBILIDADES | B12: 2914404.2 | C12: 0.01 | D12: 0.01 | K12: Vto. Pagarés Dollar Linked | L12: =+SUMIF($B$1446:$B$1472,L7,$F$1446:$F$1472) -> 0 | M12: =+SUMIF($B$1428:$B$1454,M7,$F$1428:$F$1454) -> 0 | N12: =+SUMIF($B$1428:$B$1454,N7,$F$1428:$F$1454) -> 0 | R12: 45778
A13: EN PESOS | B13: 2914463.7 | C13: 0.01 | D13: 0.01 | K13: FCI IEB Ahorro - Clase E | L13: =SUMIF(A:A,K13,E:E) -> 3179000000 | R13: 45779
A14: EN DOLARES | B14: -59.54 | C14: 0 | D14: 0 | K14: COMAFI $ Nº 24148/3 | L14: =+B13 -> 2914463.7 | R14: 45802
A15: CREDITOS | B15: 1.7798403e+09 | C15: 3.62 | D15: 3.64 | K15: Ctte Momentum | L15: 5100000 | R15: 45824
A16: PASIVO | B16: -3.3047503e+08 | K16: Cheques pendientes | R16: 45828
A17: PROVISIONES | B17: -11501078 | K17: Compra/Venta Bonos | R17: 45847
A18: PROV. HONORARIOS SOC. DEPOSITARIA | B18: -667357.16 | K18: TOTAL | L18: =SUM(L8:L17) -> 6764807090 | R18: 45884
A19: PROV. HONORARIOS SOCIEDAD GERENTE | B19: -9848836.8 | K19: Neg. Cheques / Pagare | L19: =-607698546.5 -> -6.0769855e+08 | R19: 45886
A20: PROV. GASTOS SOCIEDAD DEPOSITARIA | B20: -984883.69 | K20: Coloca caucion MAV | R20: 45942
A21: DEUDAS EN PESOS | B21: -2.9410995e+08 | K21: Compra/Venta de Bonos | R21: 45982
A22: RESCATES | B22: -8056027 | J22: EGRESOS EN EL DIA Clase B | K22: Suscripciones | R22: 45985
A23: PREVISIÓN INCOBRABLES | B23: -2.4492492e+08 | K23: Rescates | L23: =SUMIF(A:A,K23,B:B) -> -8056027 | R23: 45999
A24: Valor Patrimonial del Fondo | B24: 4.8885391e+10 | K24: Pase | R24: 46016
A25: Liquidez Efectiva (2) | B25: 1463780795 | D25: 2.99 | K25: Rentas y Amortizaciones
A26: Liquidez Corriente (3) | B26: 1.4522797e+09 | D26: 2.97 | K26: Pago Gastos Banco Comafi
K27: Caja cierre | L27: =SUM(L18:L26) -> 6149052516 | M27: =SUM(M8:M26) -> 1034833880 | N27: =SUM(N8:N26) -> 3.4646107e+08
K31: Activos Pyme | L31: 3.3186984e+10
K32: % Pyme | L32: =L31/B24 -> 0.67887325
K40: PN ACTUAL | L40: =VLOOKUP("Valor Patrimonial del Fondo",A:B,2,0)+L22+L23 -> 48877334847
A41: Inversiones | K41: 5% MM | L41: =+L40*0.05 -> 2443866742
A42: TITULO PUBLICO en Pesos | K42: 20% CAUCION | L42: =+L40*0.2 -> 9775466969
A43: Denominación | B43: IsinCode | C43: Cantidad | D43: Cierre | E43: Total | F43: % (1) | G43: Costo | H43: Var | I43: Vencimiento
A44: Lecap S30N6 | B44: AR0451031345 | C44: 200000000 | D44: 1.1909 | E44: 238183006 | F44: 0.49 | G44: 0 | I44: 30/11/2026
C45: 200000000 | E45: 238183006 | F45: 0.49
A47: OBLIGACIONES NEGOCIABLES en Pesos
A48: Denominación | B48: IsinCode | C48: Cantidad | D48: Cierre | E48: Total | F48: % (1) | G48: Costo | H48: Var | I48: Vencimiento
A49: LR7AO - ON Laboratorios Richmond Serie 7 Cl A Vto 10/12/26 | B49: AR0905777444 | C49: 300000000 | D49: 1.0379 | E49: 311382795 | F49: 0.64 | G49: 1 | H49: 3.79 | I49: 10/12/2026
A50: MTC3O - ON Mastellone Clase 3 | B50: AR0494875476 | C50: 250000000 | D50: 0.9973 | E50: 249320315 | F50: 0.51 | G50: 1 | H50: -0.27 | I50: 22/06/2027
A51: VBC3O - ON BANCO DE VALORES CL.3 24/10/26 $ | B51: AR0531585807 | C51: 300000000 | D51: 1.0476 | E51: 314281872 | F51: 0.64 | G51: 1 | H51: 4.76 | I51: 24/10/2026
C52: 850000000 | E52: 874984982 | F52: 1.79
A54: FIDEICOMISOS FINANCIEROS en Pesos
A55: Denominación | B55: IsinCode | C55: Cantidad | D55: Cierre | E55: Total | F55: % (1) | G55: Costo | H55: Var | I55: Vencimiento
A56: CQ08A - VD FF CENTROCARD CREDITOS 8 CL.A $ | B56: AR0253965559 | C56: 250000000 | D56: 1.001 | E56: 250253945 | F56: 0.51 | G56: 0.9784 | H56: 2.31 | I56: 26/05/2027
A57: FF AMFAyS S49 Clase A | B57: AR0711423134 | C57: 100000000 | D57: 0.2654 | E57: 26540514 | F57: 0.05 | G57: 0.9846 | H57: -73.04 | I57: 31/12/2026
A58: MY50B - VD FF AMFAYS S.50 CL.B $ | B58: AR0695284973 | C58: 101962042 | D58: 1.3755 | E58: 1.402475e+08 | F58: 0.29 | G58: 0.924 | H58: 48.86 | I58: 13/01/2027
A59: MY50C - VD FF AMFAYS S.50 CL.C $ | B59: AR0890638411 | C59: 382357659 | D59: 1.1508 | E59: 4.4002556e+08 | F59: 0.9 | G59: 0.85 | H59: 35.39 | I59: 13/04/2027
A60: MY51B - VD FF AMFAYS Serie 51 Clase B | B60: AR0207834935 | C60: 75584213 | D60: 1.063 | E60: 80343269 | F60: 0.16 | G60: 0.8718 | H60: 21.93 | I60: 15/03/2027
A61: MY51C - VD FF AMFAYS Serie 51 Clase C | B61: AR0601005553 | C61: 176363163 | D61: 1.0057 | E61: 1.7737085e+08 | F61: 0.36 | G61: 0.8446 | H61: 19.08 | I61: 15/11/2027
A62: MY52B - FF AMFAYS 52 CL.B $ | B62: AR0013738833 | C62: 63635566 | D62: 0.9177 | E62: 58398971 | F62: 0.12 | G62: 0.9054 | H62: 1.36 | I62: 15/12/2027
A63: MY52C - FF AMFAYS 52 CL.C $ | B63: AR0959603397 | C63: 148482986 | D63: 0.8645 | E63: 1.283684e+08 | F63: 0.26 | G63: 0.7853 | H63: 10.09 | I63: 15/02/2028
A64: VD FF SECUBONO 245 CL.A $ | B64: AR0822887474 | C64: 306275000 | D64: 0.0622 | E64: 19037843 | F64: 0.04 | G64: 1.0324 | H64: -93.98 | I64: 28/08/2026
C65: 1604660629 | E65: 1.3205869e+09 | F65: 2.7
A67: FUTUROS en Pesos
A68: Denominación | B68: IsinCode | C68: Cantidad | D68: Cierre | E68: Total | F68: % (1) | G68: Costo | H68: Var | I68: Vencimiento
A69: Fut Rofex DLR072026 | C69: -225000 | D69: 1504.5 | E69: -338512500 | F69: -0.69 | G69: -651.5822 | H69: -330.9 | I69: 31/07/2026
A70: Fut Rofex DLR082026 | C70: -475000 | D70: 1531.5 | E70: -727462500 | F70: -1.49 | G70: 0 | I70: 31/08/2026
A71: Fut Rofex DLR092026 | C71: -575000 | D71: 1558 | E71: -895850000 | F71: -1.83 | G71: 0 | I71: 30/09/2026
A72: Fut Rofex DLR102026 | C72: -100000 | D72: 1587.5 | E72: -158750000 | F72: -0.32 | G72: 0 | I72: 30/10/2026
C73: -1375000 | E73: -2120575000 | F73: -4.34
A75: MONEY MARKET en Pesos
A76: Denominación | B76: IsinCode | C76: Cantidad | D76: Cierre | E76: Total | F76: % (1) | G76: Costo | H76: Var | I76: Vencimiento
A77: FCI IEB Ahorro - Clase E | C77: 2.5519999e+08 | D77: 12.4569 | E77: 3179000000 | F77: 6.5 | G77: 12.4569 | H77: 0
C78: 2.5519999e+08 | E78: 3179000000 | F78: 6.5
A80: TITULO PROVINCIAL en Pesos
A81: Denominación | B81: IsinCode | C81: Cantidad | D81: Cierre | E81: Total | F81: % (1) | G81: Costo | H81: Var | I81: Vencimiento
A82: CO2D7 - Título provincia de Córdoba 05/12/27 | B82: AR0569903542 | C82: 300000000 | D82: 0.9839 | E82: 295167942 | F82: 0.6 | G82: 0 | I82: 05/12/2027
C83: 300000000 | E83: 295167942 | F83: 0.6
A86: Aperturas, Pases y Cauciones en Pesos
A87: Tipo | B87: Vencimiento | C87: Concertación | D87: Plazo | E87: Tasa | F87: Total | G87: % (1)
A88: CAUCION | B88: 06/07/2026 | C88: 03/07/2026 | D88: 3 | E88: 15.333461 | F88: 3500000000 | G88: 7.16
A89: PASE | B89: 03/08/2026 | C89: 03/07/2026 | D89: 31 | E89: 38.499976 | F89: 612000000 | G89: 1.25
D90: 7.17 | E90: 30.246433 | F90: 4112000000 | G90: 8.41
A93: Cheques de Pago Diferido en Pesos
A94: Descripción | B94: Vencimiento | C94: Compra | D94: Nominal | E94: Precio | F94: Actual | G94: % (1)
A95: *MAV170700987 | B95: 21/07/2026 | C95: 11/08/2025 | D95: 10000000 | E95: 0.97781828 | F95: 9778182.8 | G95: 0.02
A96: *MAV140801099 | B96: 19/08/2026 | C96: 03/09/2025 | D96: 10000000 | E96: 0.90872879 | F96: 9087287.8 | G96: 0.02
A97: *MAV280800986 | B97: 01/09/2026 | C97: 03/09/2025 | D97: 10000000 | E97: 0.88635265 | F97: 8863526.5 | G97: 0.02
A98: *MAV310701190 | B98: 04/08/2026 | C98: 03/09/2025 | D98: 10000000 | E98: 0.93599345 | F98: 9359934.5 | G98: 0.02
A99: *ACI280700201 | B99: 30/07/2026 | C99: 29/01/2026 | D99: 6530318 | E99: 0.97899847 | F99: 6393171.4 | G99: 0.01
A100: *MAV150701442 | B100: 17/07/2026 | C100: 13/02/2026 | D100: 45000000 | E100: 0.98451748 | F100: 44303287 | G100: 0.09
A101: *MAV290701035 | B101: 31/07/2026 | C101: 13/02/2026 | D101: 40000000 | E101: 0.96950708 | F101: 38780283 | G101: 0.08
A102: *MAV120801367 | B102: 14/08/2026 | C102: 13/02/2026 | D102: 3000000 | E102: 0.95285336 | F102: 2858560.1 | G102: 0.01
A103: *MAV130700768 | B103: 15/07/2026 | C103: 13/02/2026 | D103: 3000000 | E103: 0.9860601 | F103: 2958180.3 | G103: 0.01
A104: *MAV130800916 | B104: 18/08/2026 | C104: 13/02/2026 | D104: 3500000 | E104: 0.94859401 | F104: 3320079 | G104: 0.01
A105: *MAV140701247 | B105: 16/07/2026 | C105: 13/02/2026 | D105: 3500000 | E105: 0.98491595 | F105: 3447205.8 | G105: 0.01
A106: *MAV140801103 | B106: 19/08/2026 | C106: 13/02/2026 | D106: 3500000 | E106: 0.94753519 | F106: 3316373.2 | G106: 0.01
... A1441: *MAV200801501 | B1441: 24/08/2026 | C1441: 03/07/2026 | D1441: 175000000 | E1441: 0.95509757 | F1441: 1.6714207e+08 | G1441: 0.34
F1442: 3.642176e+10 | G1442: 74.5
A1444: Cheques de Pago Diferido en Dolar 3500
A1445: Descripción | B1445: Vencimiento | C1445: Compra | D1445: Nominal | E1445: Precio | F1445: Actual | G1445: % (1)
A1446: #UMV250180006 | B1446: 27/01/2028 | C1446: 30/12/2025 | D1446: 20856 | E1446: 1286.6054 | F1446: 26833443 | G1446: 0.05
A1447: #UMV250770007 | B1447: 28/07/2027 | C1447: 30/12/2025 | D1447: 20856 | E1447: 1344.8848 | F1447: 28048918 | G1447: 0.06
A1448: #UMV250780006 | B1448: 27/07/2028 | C1448: 30/12/2025 | D1448: 20856 | E1448: 1233.4507 | F1448: 25724848 | G1448: 0.05
A1449: #UMV250170065 | B1449: 27/01/2027 | C1449: 30/12/2025 | D1449: 13904 | E1449: 1408.3303 | F1449: 19581425 | G1449: 0.04
A1450: #UMV030860027 | B1450: 05/08/2026 | C1450: 30/03/2026 | D1450: 50000 | E1450: 1477.8967 | F1450: 73894833 | G1450: 0.15
A1451: #UMV030860028 | B1451: 05/08/2026 | C1451: 01/04/2026 | D1451: 50000 | E1451: 1476.5709 | F1451: 73828546 | G1451: 0.15
A1452: #UMV131160016 | B1452: 17/11/2026 | C1452: 17/04/2026 | D1452: 18230 | E1452: 1445.1891 | F1452: 26345797 | G1452: 0.05
A1453: #UMV141060033 | B1453: 16/10/2026 | C1453: 17/04/2026 | D1453: 18230 | E1453: 1455.0972 | F1453: 26526422 | G1453: 0.05
A1454: #UMV131260004 | B1454: 16/12/2026 | C1454: 17/04/2026 | D1454: 18230 | E1454: 1436.3253 | F1454: 26184211 | G1454: 0.05
...

Sheet Parametros
A1: Min | B1: 0.75 | C1: en Pymes | D1: =+B1*(VLOOKUP($E$1,'GESTION MOMENTUM'!$A$8:$B$32,2,0)) -> 36664043156 | E1: Valor Patrimonial del Fondo | G1: PN actual | H1: P&L | I1: PN reservado
A2: Max | B2: 0.05 | C2: Money Market | D2: =+B2*(VLOOKUP($E$1,'GESTION MOMENTUM'!$A$8:$B$32,2,0)) -> 2444269544 | G2: =VLOOKUP(E1,'GESTION MOMENTUM'!A8:B32,2,0) -> 48885390874 | H2: -0.002 | I2: =+G2*(1+H2) -> 48787620093
A3: Max | B3: 0.2 | C3: PFRemuneradasCaucion | D3: =+B3*(VLOOKUP($E$1,'GESTION MOMENTUM'!$A$8:$B$32,2,0)) -> 9777078175 | G3: Money Market | H3: 0.05 | I3: =+I2*H3 -> 2439381005
A4: Max | B4: 0.2 | C4: cheques x librador | D4: =+B4*(VLOOKUP($E$1,'GESTION MOMENTUM'!$A$8:$B$32,2,0)) -> 9777078175
A5: Max | B5: 0.25 | C5: x titulo en Pymes | D5: =+B5*(VLOOKUP($E$1,'GESTION MOMENTUM'!$A$8:$B$32,2,0)) -> 12221347719
B8: Garantías RFX (MOMENTUM)
B9: Bono | C9: VN | D9: Precio | E9: Aforo | F9: $
B10: Lecap S30N6 | C10: 200000000 | D10: =+VLOOKUP(B10,'GESTION MOMENTUM'!A:D,4,0) -> 1.1909 | E10: 0.85 | F10: =C10*D10*E10 -> 202453000
B11: CO2D7 - Título provincia de Córdoba 05/12/27 | C11: 300000000 | D11: =+VLOOKUP(B11,'GESTION MOMENTUM'!A:D,4,0) -> 0.9839 | E11: 0.6 | F11: =C11*D11*E11 -> 177102000
E13: Garantia | F13: =SUM(F10:F12) -> 379555000
B15: Garantías | C15: Total $ por contrato | D15: Contratos a shortear | E15: Contratos Shorteados | F15: Garantia Requerida
A16: Fut Rofex DLR052026 | B16: Mayo | C16: 150000 | D16: 0 | E16: =IFNA(-VLOOKUP(A16,'GESTION MOMENTUM'!A:C,3,0)/1000,0) -> 0 | F16: =+C16*(E16+D16) -> 0
A17: Fut Rofex DLR062026 | B17: Junio | C17: 155000 | D17: 0 | E17: =IFNA(-VLOOKUP(A17,'GESTION MOMENTUM'!A:C,3,0)/1000,0) -> 0 | F17: =+C17*(E17+D17) -> 0
A18: Fut Rofex DLR072026 | B18: Julio | C18: 160000 | D18: 0 | E18: =IFNA(-VLOOKUP(A18,'GESTION MOMENTUM'!A:C,3,0)/1000,0) -> 225 | F18: =+C18*(E18+D18) -> 36000000
A19: Fut Rofex DLR082026 | B19: Agosto | C19: 165000 | D19: 0 | E19: =IFNA(-VLOOKUP(A19,'GESTION MOMENTUM'!A:C,3,0)/1000,0) -> 475 | F19: =+C19*(E19+D19) -> 78375000
A20: Fut Rofex DLR092026 | B20: Septiembre | C20: 170000 | D20: 0 | E20: =IFNA(-VLOOKUP(A20,'GESTION MOMENTUM'!A:C,3,0)/1000,0) -> 575 | F20: =+C20*(E20+D20) -> 97750000
C21: 175000 | D21: 0 | E21: =IFNA(-VLOOKUP(A21,'GESTION MOMENTUM'!A:C,3,0)/1000,0) -> 0 | F21: =+C21*(E21+D21) -> 0
F22: =+SUM(F16:F21) -> 212125000
B23: Saldo de Garantias | C23: =F13-F22 -> 167430000

Sheet Cheques pendientes
A1: FONDO | B1: CHPD | C1: VTO | D1: MONEDA | E1: MONTO | F1: MONTO $ | G1: ESTADO | H1: LIBRADOR | I1: DIAS DE MORA
A2: AMOMPY | B2: *MAV030300645 | C2: 45723 | D2: $ | E2: 3406250 | G2: PREVISIONADO | H2: UKUMARI SOCIEDAD ANONIMA. | I2: =+TODAY()-C2 -> 486 | U2: LIBRADORES PENDIENTES
A3: AMOMPY | B3: *MAV100300802 | C3: 45728 | D3: $ | E3: 3406250 | G3: PREVISIONADO | H3: UKUMARI SOCIEDAD ANONIMA. | I3: =+TODAY()-C3 -> 481 | U3: {=+UNIQUE(H2:H91)} -> UKUMARI SOCIEDAD ANONIMA. | V3: =+SUMIF(H:H,U3,E:E) -> 6812500
A4: AMOMPY | B4: *MAV200500842 | C4: 45799 | D4: $ | E4: 129185000 | G4: PENDIENTE | H4: NIRO CONSTRUYE S. A. | I4: =+TODAY()-C4 -> 410 | U4: NIRO CONSTRUYE S. A. | V4: =+SUMIF(H:H,U4,E:E) -> 258370000
A5: AMOMPY | B5: *MAV300500862 | C5: 45811 | D5: $ | E5: 129185000 | G5: PENDIENTE | H5: NIRO CONSTRUYE S. A. | I5: =+TODAY()-C5 -> 398 | U5: MERCOL RAUL ALBERTO Y MERCOL MAURICIO EDUARDO. | V5: =+SUMIF(H:H,U5,E:E) -> 62500000
A6: AMOMPY | B6: *MAV091000727 | C6: 45943 | D6: $ | E6: 12500000 | G6: PENDIENTE | H6: MERCOL RAUL ALBERTO Y MERCOL MAURICIO EDUARDO. | I6: =+TODAY()-C6 -> 266 | U6: F G SANITARIOS S R L | V6: =+SUMIF(H:H,U6,E:E) -> 35000000
A7: AMOMPY | B7: *MAV151000873 | C7: 45947 | D7: $ | E7: 5000000 | G7: PREVISIONADO | H7: F G SANITARIOS S R L | I7: =+TODAY()-C7 -> 262 | U7: AKAI ENERGY LED SRL | V7: =+SUMIF(H:H,U7,E:E) -> 44963000
A8: AMOMPY | B8: *MAV201001014 | C8: 45952 | D8: $ | E8: 5000000 | G8: PREVISIONADO | H8: F G SANITARIOS S R L | I8: =+TODAY()-C8 -> 257 | K8: Valor Patrimonial del Fondo | L8: =+VLOOKUP(K8,'GESTION MOMENTUM'!A:B,2,0) -> 48885390874 | U8: FRIGORIFICO GENERAL PICO S A | V8: =+SUMIF(H:H,U8,E:E) -> 70000000
A9: AMOMPY | B9: *MAV231000788 | C9: 45957 | D9: $ | E9: 5000000 | G9: PREVISIONADO | H9: F G SANITARIOS S R L | I9: =+TODAY()-C9 -> 252 | U9: MIANI CLARA A Y MIANI ADA CLELIA | V9: =+SUMIF(H:H,U9,E:E) -> 3125000
A10: AMOMPY | B10: *MAV271000879 | C10: 45959 | D10: $ | E10: 5000000 | G10: PREVISIONADO | H10: F G SANITARIOS S R L | I10: =+TODAY()-C10 -> 250 | L10: $ | M10: % PN | U10: PORT PLA S.R.L. | V10: =+SUMIF(H:H,U10,E:E) -> 150000000
A11: AMOMPY | B11: *MAV301000860 | C11: 45964 | D11: $ | E11: 5000000 | G11: PREVISIONADO | H11: F G SANITARIOS S R L | I11: =+TODAY()-C11 -> 245 | K11: PREVISIÓN INCOBRABLES | L11: =+VLOOKUP(K11,'GESTION MOMENTUM'!A:B,2,0) -> -2.4492492e+08 | M11: =+L11/L8 -> -0.0050101863 | U11: CONEXION SALUD SRL | V11: =+SUMIF(H:H,U11,E:E) -> 27000000
A12: AMOMPY | B12: *MAV031100816 | C12: 45966 | D12: $ | E12: 5000000 | G12: PREVISIONADO | H12: F G SANITARIOS S R L | I12: =+TODAY()-C12 -> 243 | K12: PREVISIONADO | L12: =+SUMIF(G:G,K12,E:E) -> 187612500 | U12: MASTER DESIGN HOME SRL | V12: =+SUMIF(H:H,U12,E:E) -> 24000000
A13: AMOMPY | B13: *MAV031100940 | C13: 45966 | D13: $ | E13: 4400000 | G13: PENDIENTE | H13: AKAI ENERGY LED SRL | I13: =+TODAY()-C13 -> 243 | K13: Prevision a aplicar | L13: =+L11+L12 -> -57312416 | U13: BUNYAR S.R.L. | V13: =+SUMIF(H:H,U13,E:E) -> 24800000
A14: AMOMPY | B14: *MAV041100892 | C14: 45968 | D14: $ | E14: 4400000 | G14: PENDIENTE | H14: AKAI ENERGY LED SRL | I14: =+TODAY()-C14 -> 241 | U14: GROCAL S.A. | V14: =+SUMIF(H:H,U14,E:E) -> 15000000
A15: AMOMPY | B15: *MAV051100567 | C15: 45971 | D15: $ | E15: 25000000 | G15: PENDIENTE | H15: MERCOL RAUL ALBERTO Y MERCOL MAURICIO EDUARDO. | I15: =+TODAY()-C15 -> 238 | K15: PENDIENTE | L15: =+SUMIF(G:G,K15,E:E)+E2 -> 1564111550 | M15: =+SUMIF(G:G,K15,E:E)/$L$8 -> 0.031925802 | U15: Paccioli Group Sociedad Anonima | V15: =+SUMIF(H:H,U15,E:E) -> 13958000
A16: AMOMPY | B16: *MAV051100722 | C16: 45971 | D16: $ | E16: 4400000 | G16: PENDIENTE | H16: AKAI ENERGY LED SRL | I16: =+TODAY()-C16 -> 238 | U16: FINEX CABA S. A. | V16: =+SUMIF(H:H,U16,E:E) -> 55300000
A17: AMOMPY | B17: *MAV071100935 | C17: 45972 | D17: $ | E17: 4400000 | G17: PENDIENTE | H17: AKAI ENERGY LED SRL | I17: =+TODAY()-C17 -> 237 | U17: TRADICION VALORES S.A. | V17: =+SUMIF(H:H,U17,E:E) -> 25000000
A18: AMOMPY | B18: *MAV061100646 | C18: 45972 | D18: $ | E18: 5000000 | G18: PREVISIONADO | H18: F G SANITARIOS S R L | I18: =+TODAY()-C18 -> 237 | U18: Maradona Wines | V18: =+SUMIF(H:H,U18,E:E) -> 119500000
A19: AMOMPY | B19: *MAV111100890 | C19: 45974 | D19: $ | E19: 963000 | G19: PENDIENTE | H19: AKAI ENERGY LED SRL | I19: =+TODAY()-C19 -> 235 | U19: LOPEZ LUCIA SOLEDAD | V19: =+SUMIF(H:H,U19,E:E) -> 995000
A20: AMOMPY | B20: *MAV121100854 | C20: 45975 | D20: $ | E20: 4400000 | G20: PENDIENTE | H20: AKAI ENERGY LED SRL | I20: =+TODAY()-C20 -> 234 | K20: LIBRADOR PENDIENTE | L20: $ | M20: % PN | O20: VIGENTE | U20: RABU INVERSIONES SRL | V20: =+SUMIF(H:H,U20,E:E) -> 7194300
A21: AMOMPY | B21: *MAV121100675 | C21: 45975 | D21: $ | E21: 25000000 | G21: PENDIENTE | H21: MERCOL RAUL ALBERTO Y MERCOL MAURICIO EDUARDO. | I21: =+TODAY()-C21 -> 234 | K21: {=+_xlws.SORT(U3:V34,2,-1)} -> #NAME? | M21: =+L21/$L$8 -> 0 | O21: =+SUMIF('Reporte de Cheques'!A:A,'Cheques pendientes'!K21,'Reporte de Cheques'!I:I) -> 0 | U21: GROUP DIEZ S.A. | V21: =+SUMIF(H:H,U21,E:E) -> 425000000
A22: AMOMPY | B22: *MAV141101053 | C22: 45979 | D22: $ | E22: 4400000 | G22: PENDIENTE | H22: AKAI ENERGY LED SRL | I22: =+TODAY()-C22 -> 230 | M22: =+L22/$L$8 -> 0 | O22: =+SUMIF('Reporte de Cheques'!A:A,'Cheques pendientes'!K22,'Reporte de Cheques'!I:I) -> 0 | U22: INVLAC CONSTRUCCIONES S.R.L | V22: =+SUMIF(H:H,U22,E:E) -> 4000000
A23: AMOMPY | B23: *MAV141101054 | C23: 45979 | D23: $ | E23: 4400000 | G23: PENDIENTE | H23: AKAI ENERGY LED SRL | I23: =+TODAY()-C23 -> 230 | M23: =+L23/$L$8 -> 0 | O23: =+SUMIF('Reporte de Cheques'!A:A,'Cheques pendientes'!K23,'Reporte de Cheques'!I:I) -> 0 | U23: I-LED ARGENTINA S.A. | V23: =+SUMIF(H:H,U23,E:E) -> 21800000
A24: AMOMPY | B24: *MAV171100932 | C24: 45980 | D24: $ | E24: 4400000 | G24: PENDIENTE | H24: AKAI ENERGY LED SRL | I24: =+TODAY()-C24 -> 229 | M24: =+L24/$L$8 -> 0 | O24: =+SUMIF('Reporte de Cheques'!A:A,'Cheques pendientes'!K24,'Reporte de Cheques'!I:I) -> 0 | U24: INTANSIA S.R.L | V24: =+SUMIF(H:H,U24,E:E) -> 40000000
A25: AMOMPY | B25: *MAV151101337 | C25: 45980 | D25: $ | E25: 4400000 | G25: PENDIENTE | H25: AKAI ENERGY LED SRL | I25: =+TODAY()-C25 -> 229 | M25: =+L25/$L$8 -> 0 | O25: =+SUMIF('Reporte de Cheques'!A:A,'Cheques pendientes'!K25,'Reporte de Cheques'!I:I) -> 0 | U25: ASOCIACION ATLETICA ARGENTINOS JUNIORS | V25: =+SUMIF(H:H,U25,E:E) -> 300000000
A26: AMOMPY | B26: *MAV181100869 | C26: 45981 | D26: $ | E26: 4400000 | G26: PENDIENTE | H26: AKAI ENERGY LED SRL | I26: =+TODAY()-C26 -> 228 | M26: =+L26/$L$8 -> 0 | O26: =+SUMIF('Reporte de Cheques'!A:A,'Cheques pendientes'!K26,'Reporte de Cheques'!I:I) -> 0 | V26: =+SUMIF(H:H,U26,E:E) -> 0
A27: AMOMPY | B27: *MAV181100773 | C27: 45981 | D27: $ | E27: 20000000 | G27: PREVISIONADO | H27: FRIGORIFICO GENERAL PICO S A | I27: =+TODAY()-C27 -> 228 | M27: =+L27/$L$8 -> 0 | O27: =+SUMIF('Reporte de Cheques'!A:A,'Cheques pendientes'!K27,'Reporte de Cheques'!I:I) -> 0 | V27: =+SUMIF(H:H,U27,E:E) -> 0
A28: AMOMPY | B28: *MAV191100661 | C28: 45986 | D28: $ | E28: 20000000 | G28: PREVISIONADO | H28: FRIGORIFICO GENERAL PICO S A | I28: =+TODAY()-C28 -> 223 | M28: =+L28/$L$8 -> 0 | O28: =+SUMIF('Reporte de Cheques'!A:A,'Cheques pendientes'!K28,'Reporte de Cheques'!I:I) -> 0 | V28: =+SUMIF(H:H,U28,E:E) -> 0
A29: AMOMPY | B29: *MAV201100887 | C29: 45987 | D29: $ | E29: 10000000 | G29: PREVISIONADO | H29: FRIGORIFICO GENERAL PICO S A | I29: =+TODAY()-C29 -> 222 | M29: =+L29/$L$8 -> 0 | O29: =+SUMIF('Reporte de Cheques'!A:A,'Cheques pendientes'!K29,'Reporte de Cheques'!I:I) -> 0 | V29: =+SUMIF(H:H,U29,E:E) -> 0
A30: AMOMPY | B30: *MAV211100687 | C30: 45988 | D30: $ | E30: 10000000 | G30: PREVISIONADO | H30: FRIGORIFICO GENERAL PICO S A | I30: =+TODAY()-C30 -> 221 | M30: =+L30/$L$8 -> 0 | O30: =+SUMIF('Reporte de Cheques'!A:A,'Cheques pendientes'!K30,'Reporte de Cheques'!I:I) -> 0 | V30: =+SUMIF(H:H,U30,E:E) -> 0
A31: AMOMPY | B31: *MAV221100992 | C31: 45988 | D31: $ | E31: 10000000 | G31: PREVISIONADO | H31: FRIGORIFICO GENERAL PICO S A | I31: =+TODAY()-C31 -> 221 | M31: =+L31/$L$8 -> 0 | O31: =+SUMIF('Reporte de Cheques'!A:A,'Cheques pendientes'!K31,'Reporte de Cheques'!I:I) -> 0 | V31: =+SUMIF(H:H,U31,E:E) -> 0
A32: AMOMPY | B32: *MAV271100809 | C32: 45992 | D32: $ | E32: 3125000 | G32: PENDIENTE | H32: MIANI CLARA A Y MIANI ADA CLELIA | I32: =+TODAY()-C32 -> 217 | M32: =+L32/$L$8 -> 0 | O32: =+SUMIF('Reporte de Cheques'!A:A,'Cheques pendientes'!K32,'Reporte de Cheques'!I:I) -> 0 | V32: =+SUMIF(H:H,U32,E:E) -> 0
A33: AMOMPY | B33: *MAV291101201 | C33: 45994 | D33: $ | E33: 25000000 | G33: PENDIENTE | H33: PORT PLA S.R.L. | I33: =+TODAY()-C33 -> 215 | M33: =+L33/$L$8 -> 0 | O33: =+SUMIF('Reporte de Cheques'!A:A,'Cheques pendientes'!K33,'Reporte de Cheques'!I:I) -> 0 | V33: =+SUMIF(H:H,U33,E:E) -> 0
A34: AMOMPY | B34: *MAV151201389 | C34: 46008 | D34: $ | E34: 27000000 | G34: PREVISIONADO | H34: CONEXION SALUD SRL | I34: =+TODAY()-C34 -> 201 | M34: =+L34/$L$8 -> 0 | O34: =+SUMIF('Reporte de Cheques'!A:A,'Cheques pendientes'!K34,'Reporte de Cheques'!I:I) -> 0 | V34: =+SUMIF(H:H,U34,E:E) -> 0
A35: AMOMPY | B35: *MAV171200694 | C35: 46010 | D35: $ | E35: 6000000 | G35: PREVISIONADO | H35: MASTER DESIGN HOME SRL | I35: =+TODAY()-C35 -> 199 | M35: =+L35/$L$8 -> 0 | O35: =+SUMIF('Reporte de Cheques'!A:A,'Cheques pendientes'!K35,'Reporte de Cheques'!I:I) -> 0
A36: AMOMPY | B36: *MAV181201122 | C36: 46013 | D36: $ | E36: 24800000 | G36: PREVISIONADO | H36: BUNYAR S.R.L. | I36: =+TODAY()-C36 -> 196 | M36: =+L36/$L$8 -> 0 | O36: =+SUMIF('Reporte de Cheques'!A:A,'Cheques pendientes'!K36,'Reporte de Cheques'!I:I) -> 0
A37: AMOMPY | B37: *MAV291200938 | C37: 46024 | D37: $ | E37: 25000000 | G37: PENDIENTE | H37: PORT PLA S.R.L. | I37: =+TODAY()-C37 -> 185 | M37: =+L37/$L$8 -> 0 | O37: =+SUMIF('Reporte de Cheques'!A:A,'Cheques pendientes'!K37,'Reporte de Cheques'!I:I) -> 0
A38: AMOMPY | B38: *MAV020100774 | C38: 46028 | D38: $ | E38: 10000000 | G38: PENDIENTE | H38: PORT PLA S.R.L. | I38: =+TODAY()-C38 -> 181 | M38: =+L38/$L$8 -> 0 | O38: =+SUMIF('Reporte de Cheques'!A:A,'Cheques pendientes'!K38,'Reporte de Cheques'!I:I) -> 0
A39: AMOMPY | B39: *MAV311200688 | C39: 46028 | D39: $ | E39: 6000000 | G39: PREVISIONADO | H39: MASTER DESIGN HOME SRL | I39: =+TODAY()-C39 -> 181 | M39: =+L39/$L$8 -> 0 | O39: =+SUMIF('Reporte de Cheques'!A:A,'Cheques pendientes'!K39,'Reporte de Cheques'!I:I) -> 0
A40: AMOMPY | B40: *MAV050100914 | C40: 46029 | D40: $ | E40: 10000000 | G40: PENDIENTE | H40: PORT PLA S.R.L. | I40: =+TODAY()-C40 -> 180 | M40: =+L40/$L$8 -> 0 | O40: =+SUMIF('Reporte de Cheques'!A:A,'Cheques pendientes'!K40,'Reporte de Cheques'!I:I) -> 0
A41: AMOMPY | B41: *MAV090100782 | C41: 46035 | D41: $ | E41: 10000000 | G41: PENDIENTE | H41: PORT PLA S.R.L. | I41: =+TODAY()-C41 -> 174 | M41: =+L41/$L$8 -> 0 | O41: =+SUMIF('Reporte de Cheques'!A:A,'Cheques pendientes'!K41,'Reporte de Cheques'!I:I) -> 0
A42: AMOMPY | B42: *MAV120100963 | C42: 46036 | D42: $ | E42: 10000000 | G42: PENDIENTE | H42: PORT PLA S.R.L. | I42: =+TODAY()-C42 -> 173 | M42: =+L42/$L$8 -> 0 | O42: =+SUMIF('Reporte de Cheques'!A:A,'Cheques pendientes'!K42,'Reporte de Cheques'!I:I) -> 0
A43: AMOMPY | B43: *MAV120101031 | C43: 46036 | D43: $ | E43: 5000000 | G43: PENDIENTE | H43: GROCAL S.A. | I43: =+TODAY()-C43 -> 173 | M43: =+L43/$L$8 -> 0 | O43: =+SUMIF('Reporte de Cheques'!A:A,'Cheques pendientes'!K43,'Reporte de Cheques'!I:I) -> 0
A44: AMOMPY | B44: *MAV140100871 | C44: 46038 | D44: $ | E44: 5000000 | G44: PENDIENTE | H44: GROCAL S.A. | I44: =+TODAY()-C44 -> 171 | M44: =+L44/$L$8 -> 0 | O44: =+SUMIF('Reporte de Cheques'!A:A,'Cheques pendientes'!K44,'Reporte de Cheques'!I:I) -> 0
A45: AMOMPY | B45: *MAV160100849 | C45: 46042 | D45: $ | E45: 10000000 | G45: PENDIENTE | H45: PORT PLA S.R.L. | I45: =+TODAY()-C45 -> 167 | M45: =+L45/$L$8 -> 0 | O45: =+SUMIF('Reporte de Cheques'!A:A,'Cheques pendientes'!K45,'Reporte de Cheques'!I:I) -> 0
A46: AMOMPY | B46: *MAV160100806 | C46: 46042 | D46: $ | E46: 4000000 | G46: PREVISIONADO | H46: MASTER DESIGN HOME SRL | I46: =+TODAY()-C46 -> 167 | M46: =+L46/$L$8 -> 0 | O46: =+SUMIF('Reporte de Cheques'!A:A,'Cheques pendientes'!K46,'Reporte de Cheques'!I:I) -> 0
... A52: AMOMPY | B52: *MAV210100855 | C52: 46045 | D52: $ | E52: 1395800 | G52: PENDIENTE | H52: Paccioli Group Sociedad Anonima | I52: =+TODAY()-C52 -> 164 | M52: =+L52/$L$8 -> 0 | O52: =+SUMIF('Reporte de Cheques'!A:A,'Cheques pendientes'!K52,'Reporte de Cheques'!I:I) -> 0
A53: AMOMPY | B53: *MAV210100764 | C53: 46045 | D53: $ | E53: 4000000 | G53: PREVISIONADO | H53: MASTER DESIGN HOME SRL | I53: =+TODAY()-C53 -> 164
A54: AMOMPY | B54: *MAV210100850 | C54: 46045 | D54: $ | E54: 15900000 | G54: PENDIENTE | H54: FINEX CABA S. A. | I54: =+TODAY()-C54 -> 164
A55: AMOMPY | B55: *MAV210100774 | C55: 46045 | D55: $ | E55: 5000000 | G55: PENDIENTE | H55: GROCAL S.A. | I55: =+TODAY()-C55 -> 164
A56: AMOMPY | B56: *MAV220100909 | C56: 46048 | D56: $ | E56: 1395800 | G56: PENDIENTE | H56: Paccioli Group Sociedad Anonima | I56: =+TODAY()-C56 -> 161
A57: AMOMPY | B57: *MAV230100842 | C57: 46049 | D57: $ | E57: 10000000 | G57: PENDIENTE | H57: PORT PLA S.R.L. | I57: =+TODAY()-C57 -> 160
A58: AMOMPY | B58: *MAV230100905 | C58: 46049 | D58: $ | E58: 1395800 | G58: PENDIENTE | H58: Paccioli Group Sociedad Anonima | I58: =+TODAY()-C58 -> 160
A59: AMOMPY | B59: *MAV230100906 | C59: 46049 | D59: $ | E59: 1395800 | G59: PENDIENTE | H59: Paccioli Group Sociedad Anonima | I59: =+TODAY()-C59 -> 160
A60: AMOMPY | B60: *MAV230100907 | C60: 46049 | D60: $ | E60: 1395800 | G60: PENDIENTE | H60: Paccioli Group Sociedad Anonima | I60: =+TODAY()-C60 -> 160
A61: AMOMPY | B61: *MAV230100908 | C61: 46049 | D61: $ | E61: 1395800 | G61: PENDIENTE | H61: Paccioli Group Sociedad Anonima | I61: =+TODAY()-C61 -> 160
A62: AMOMPY | B62: *MAV260100839 | C62: 46050 | D62: $ | E62: 6250000 | G62: PENDIENTE | H62: TRADICION VALORES S.A. | I62: =+TODAY()-C62 -> 159
A63: AMOMPY | B63: *MAV260100805 | C63: 46050 | D63: $ | E63: 4000000 | G63: PREVISIONADO | H63: MASTER DESIGN HOME SRL | I63: =+TODAY()-C63 -> 159
A64: AMOMPY | B64: *MAV240101107 | C64: 46050 | D64: $ | E64: 22000000 | G64: PENDIENTE | H64: Maradona Wines | I64: =+TODAY()-C64 -> 159
... A96: AMOMPY | B96: *MIL010700023 | C96: 46206 | D96: $ | E96: 10000000 | G96: PENDIENTE | H96: MILLS S.G.R. | I96: =+TODAY()-C96 -> 3
E97: {=SUM(E2:E96-E63,E53,E46,E39,E35,E3,E2)} -> 1395130300

Sheet Concentración

Sheet Reporte de Cheques
A1: Reporte de Cheques de Pago Diferido | W1: Valor Patrimonial del Fondo
A2: Cheque de Pago Diferido y Pagaré | B2: Moneda | C2: Cheque de Pago Diferido y Pagaré | D2: Fecha | E2: Precio | F2: Tipo de Cambio (Cheque/Fondo) | G2: Moneda Cheque | H2: Moneda Cheque | I2: Moneda Fondo | J2: Moneda Fondo | K2: Compra | L2: Fondo | M2: Compra | N2: Compra | O2: Compra | P2: Compra | Q2: Vendido | R2: Venta | S2: Venta | T2: Venta | U2: Cheque de Pago Diferido y Pagaré | V2: Cheque de Pago Diferido y Pagaré | W2: =+VLOOKUP(W1,'GESTION MOMENTUM'!A:B,2,0) -> 48885390874
A3: Sociedad de Garantía Recíproca / Librador | B3: Descripción | C3: Fecha de Vencimiento | D3: Fecha | E3: Precio | F3: Tipo de Cambio (Cheque/Fondo) | G3: Importe Nominal | H3: Importe Actual | I3: Importe Nominal | J3: Importe Actual | K3: Nro. de Operación | L3: Nombre | M3: Agente | N3: Fecha Concertación | O3: Fecha Liquidación | P3: Tasa de Descuento | Q3: Vendido | R3: Nro. de Operación | S3: Fecha Concertación | T3: Fecha Liquidación | U3: Abreviatura | V3: Código CAFCI | W3: %
A4: ACINDAR PYMES SGR | B4: Pesos | C4: 46206 | D4: 03/07/2026 | E4: 1 | G4: 2500000 | H4: 2500000 | I4: 2500000 | J4: 2500000 | K4: 6119 | L4: AMOMPY | M4: Momentum Capital Investment S.A. | N4: 29/05/2026 | O4: 29/05/2026 | P4: 20 | Q4: =SUMPRODUCT(P4:P1392,I4:I1392)/SUM(I4:I1392) -> 31.870304 | U4: *ACI010700324 | V4: *ACI010700324 | W4: =+J4/$W$2 -> 5.1140023e-05
A5: LOGICA CONSULTING GROUP SAU | B5: Pesos | C5: 46206 | D5: 03/07/2026 | E5: 1 | G5: 4298084.2 | H5: 4298084.2 | I5: 4298084.2 | J5: 4298084.2 | K5: 533 | L5: AMOMPY | M5: Momentum Capital Investment S.A. | N5: 22/04/2026 | O5: 22/04/2026 | P5: 38 | Q5: No | U5: *MAV010701115 | V5: *MAV010701115 | W5: =+J5/$W$2 -> 8.7921649e-05
A6: DESDE EL MAR S.A. | B6: Pesos | C6: 46206 | D6: 03/07/2026 | E6: 1 | G6: 2000000 | H6: 2000000 | I6: 2000000 | J6: 2000000 | K6: 7744 | L6: AMOMPY | M6: Momentum Capital Investment S.A. | N6: 08/05/2026 | O6: 08/05/2026 | P6: 35 | Q6: No | U6: *MAV010701183 | V6: *MAV010701183 | W6: =+J6/$W$2 -> 4.0912018e-05
A7: EL TREBOL SRL | B7: Pesos | C7: 46206 | D7: 03/07/2026 | E7: 1 | G7: 9676723.3 | H7: 9676723.3 | I7: 9676723.3 | J7: 9676723.3 | K7: 263806 | L7: AMOMPY | M7: Momentum Capital Investment S.A. | N7: 27/05/2026 | O7: 27/05/2026 | P7: 33 | Q7: No | U7: *MAV010701315 | V7: *MAV010701315 | W7: =+J7/$W$2 -> 0.00019794714
A8: COOPERATIVA DE VIVIENDA CREDITO Y CONSUMO PARA EL DESARROLLO LIMITADA | B8: Pesos | C8: 46206 | D8: 03/07/2026 | E8: 1 | G8: 15000000 | H8: 15000000 | I8: 15000000 | J8: 15000000 | K8: 70219532 | L8: AMOMPY | M8: Momentum Capital Investment S.A. | N8: 05/05/2026 | O8: 05/05/2026 | P8: 31 | Q8: No | U8: *MAV010701150 | V8: *MAV010701150 | W8: =+J8/$W$2 -> 0.00030684014
A9: COOPERATIVA DE VIVIENDA CREDITO Y CONSUMO PARA EL DESARROLLO LIMITADA | B9: Pesos | C9: 46206 | D9: 03/07/2026 | E9: 1 | G9: 25000000 | H9: 25000000 | I9: 25000000 | J9: 25000000 | K9: 70219533 | L9: AMOMPY | M9: Momentum Capital Investment S.A. | N9: 07/05/2026 | O9: 07/05/2026 | P9: 31 | Q9: No | U9: *MAV010701178 | V9: *MAV010701178 | W9: =+J9/$W$2 -> 0.00051140023
A10: JUARROS JOSE LUIS | B10: Pesos | C10: 46206 | D10: 03/07/2026 | E10: 1 | G10: 6238663.2 | H10: 6238663.2 | I10: 6238663.2 | J10: 6238663.2 | K10: 9266641 | L10: AMOMPY | M10: Momentum Capital Investment S.A. | N10: 16/04/2026 | O10: 16/04/2026 | P10: 35 | Q10: No | U10: *MAV010701098 | V10: *MAV010701098 | W10: =+J10/$W$2 -> 0.00012761815
A11: VITALCAN S.A. | B11: Pesos | C11: 46206 | D11: 03/07/2026 | E11: 1 | G11: 100000000 | H11: 100000000 | I11: 100000000 | J11: 100000000 | K11: 7353 | L11: AMOMPY | M11: Momentum Capital Investment S.A. | N11: 31/03/2026 | O11: 31/03/2026 | P11: 37 | Q11: No | U11: *MAV010701052 | V11: *MAV010701052 | W11: =+J11/$W$2 -> 0.0020456009
A12: DEMAGRO SRL | B12: Pesos | C12: 46206 | D12: 03/07/2026 | E12: 1 | G12: 22500000 | H12: 22500000 | I12: 22500000 | J12: 22500000 | K12: 65800963 | L12: AMOMPY | M12: Momentum Capital Investment S.A. | N12: 26/03/2026 | O12: 26/03/2026 | P12: 38 | Q12: No | U12: *MAV010701039 | V12: *MAV010701039 | W12: =+J12/$W$2 -> 0.0004602602
A13: BiBank S.A. | B13: Pesos | C13: 46206 | D13: 03/07/2026 | E13: 1 | G13: 500000000 | H13: 500000000 | I13: 500000000 | J13: 500000000 | K13: 147165 | L13: AMOMPY | M13: Momentum Capital Investment S.A. | N13: 23/04/2026 | O13: 23/04/2026 | P13: 28 | Q13: No | U13: #INT020760001 | V13: #INT020760001 | W13: =+J13/$W$2 -> 0.010228005
Q14: No | U14: #UMV010760032 | V14: #UMV010760032 | W14: =+J14/$W$2 -> 0
A15: MILLS S.G.R. | B15: Pesos | C15: 46206 | D15: 03/07/2026 | E15: 1 | G15: 10000000 | H15: 10000000 | I15: 10000000 | J15: 10000000 | K15: 32529 | L15: AMOMPY | M15: Momentum Capital Investment S.A. | N15: 27/04/2026 | O15: 27/04/2026 | P15: 27 | Q15: No | U15: *MIL010700023 | V15: *MIL010700023 | W15: =+J15/$W$2 -> 0.00020456009
A16: ALLIANCE ONE TOBACCO ARGENTINA | B16: Pesos | C16: 46206 | D16: 03/07/2026 | E16: 1 | G16: 1000000000 | H16: 1000000000 | I16: 1000000000 | J16: 1000000000 | K16: 147160 | L16: AMOMPY | M16: Momentum Capital Investment S.A. | N16: 23/04/2026 | O16: 23/04/2026 | P16: 30 | Q16: No | U16: #MAV020760016 | V16: #MAV020760016 | W16: =+J16/$W$2 -> 0.020456009
A17: QUILMES | B17: Pesos | C17: 46206 | D17: 03/07/2026 | E17: 1 | G17: 8168237.9 | H17: 8168237.9 | I17: 8168237.9 | J17: 8168237.9 | K17: 40012237 | L17: AMOMPY | M17: Momentum Capital Investment S.A. | N17: 22/05/2026 | O17: 22/05/2026 | P17: 21 | Q17: No | U17: *MAV010701292 | V17: *MAV010701292 | W17: =+J17/$W$2 -> 0.00016708955
A18: INTEGRA PYMES SGR | B18: Pesos | C18: 46206 | D18: 03/07/2026 | E18: 1 | G18: 5000000 | H18: 5000000 | I18: 5000000 | J18: 5000000 | K18: 16779597 | L18: AMOMPY | M18: Momentum Capital Investment S.A. | N18: 30/04/2026 | O18: 30/04/2026 | P18: 29 | Q18: No | U18: *INP010700054 | V18: *INP010700054 | W18: =+J18/$W$2 -> 0.00010228005
A19: AVAL AR SGR | B19: Pesos | C19: 46206 | D19: 03/07/2026 | E19: 1 | G19: 15000000 | H19: 15000000 | I19: 15000000 | J19: 15000000 | K19: 801 | L19: AMOMPY | M19: Momentum Capital Investment S.A. | N19: 31/03/2026 | O19: 31/03/2026 | P19: 29 | Q19: No | U19: *AAR010700018 | V19: *AAR010700018 | W19: =+J19/$W$2 -> 0.00030684014
A20: AVAL AR SGR | B20: Pesos | C20: 46206 | D20: 03/07/2026 | E20: 1 | G20: 12500000 | H20: 12500000 | I20: 12500000 | J20: 12500000 | K20: 28996520 | L20: AMOMPY | M20: Momentum Capital Investment S.A. | N20: 31/03/2026 | O20: 31/03/2026 | P20: 29 | Q20: No | U20: *AAR010700017 | V20: *AAR010700017 | W20: =+J20/$W$2 -> 0.00025570011
A21: DESDE EL MAR S.A. | B21: Pesos | C21: 46209 | D21: 03/07/2026 | E21: 0.99713156 | G21: 2000000 | H21: 1994263.1 | I21: 2000000 | J21: 1994263.1 | K21: 7745 | L21: AMOMPY | M21: Momentum Capital Investment S.A. | N21: 08/05/2026 | O21: 08/05/2026 | P21: 35 | Q21: No | U21: *MAV020700893 | V21: *MAV020700893 | W21: =+J21/$W$2 -> 4.0794664e-05
A22: COOPERATIVA DE VIVIENDA CREDITO Y CONSUMO PARA EL DESARROLLO LIMITADA | B22: Pesos | C22: 46209 | D22: 03/07/2026 | E22: 0.99745853 | G22: 42000000 | H22: 41893258 | I22: 42000000 | J22: 41893258 | K22: 148257 | L22: AMOMPY | M22: Momentum Capital Investment S.A. | N22: 05/05/2026 | O22: 05/05/2026 | P22: 31 | Q22: No | U22: #MAV030760052 | V22: #MAV030760052 | W22: =+J22/$W$2 -> 0.00085696887
A23: CAMPO AVAL SGR | B23: Pesos | C23: 46209 | D23: 03/07/2026 | E23: 0.99786757 | G23: 10000000 | H23: 9978675.7 | I23: 10000000 | J23: 9978675.7 | K23: 1742541 | L23: AMOMPY | M23: Momentum Capital Investment S.A. | N23: 21/04/2026 | O23: 21/04/2026 | P23: 26 | Q23: No | U23: *CMP020700021 | V23: *CMP020700021 | W23: =+J23/$W$2 -> 0.00020412388
A24: BUROMAHTIK SA | B24: Pesos | C24: 46209 | D24: 03/07/2026 | E24: 0.99704984 | G24: 3000000 | H24: 2991149.5 | I24: 3000000 | J24: 2991149.5 | K24: 40743051 | L24: AMOMPY | M24: Momentum Capital Investment S.A. | N24: 26/05/2026 | O24: 26/05/2026 | P24: 36 | Q24: No | U24: *MAV020700980 | V24: *MAV020700980 | W24: =+J24/$W$2 -> 6.1186982e-05
A25: AVAL AR SGR | B25: Pesos | C25: 46209 | D25: 03/07/2026 | E25: 0.99762211 | G25: 15000000 | H25: 14964332 | I25: 15000000 | J25: 14964332 | K25: 802 | L25: AMOMPY | M25: Momentum Capital Investment S.A. | N25: 31/03/2026 | O25: 31/03/2026 | P25: 29 | Q25: No | U25: *AAR020700017 | V25: *AAR020700017 | W25: =+J25/$W$2 -> 0.0003061105
A26: TPS CONSTRUCTORA SA | B26: Pesos | C26: 46209 | D26: 03/07/2026 | E26: 0.99754035 | G26: 1381630.2 | H26: 1378231.9 | I26: 1381630.2 | J26: 1378231.9 | K26: 70386150 | L26: AMOMPY | M26: Momentum Capital Investment S.A. | N26: 17/06/2026 | O26: 17/06/2026 | P26: 30 | Q26: No | U26: *MAV020701143 | V26: *MAV020701143 | W26: =+J26/$W$2 -> 2.8193124e-05
... A545: MILLS S.G.R. | B545: Pesos | C545: 46239 | D545: 03/07/2026 | E545: 0.97617089 | G545: 5800000 | H545: 5661791.2 | I545: 5800000 | J545: 5661791.2 | K545: 121 | L545: AMOMPY | M545: Momentum Capital Investment S.A. | N545: 25/06/2026 | O545: 25/06/2026 | P545: 27 | Q545: No | U545: *MIL020800026 | V545: *MIL020800026 | W545: =+J545/$W$2 -> 0.00011581765
A546: BSP LARTI SA | Q546: No | U546: #UMV030860028 | V546: #UMV030860028 | W546: =+J546/$W$2 -> 0
A547: BSP LARTI SA | Q547: No | U547: #UMV030860027 | V547: #UMV030860027 | W547: =+J547/$W$2 -> 0
A548: COOPERATIVA DE TABACALEROS DE JUJUY LTDA | Q548: No | U548: #UMV030860029 | V548: #UMV030860029 | W548: =+J548/$W$2 -> 0
A549: COOPERATIVA DE TABACALEROS DE JUJUY LTDA | Q549: No | U549: #UMV030860035 | V549: #UMV030860035 | W549: =+J549/$W$2 -> 0
A550: MILLS S.G.R. | B550: Pesos | C550: 46239 | D550: 03/07/2026 | E550: 0.97445074 | G550: 4166666.7 | H550: 4060211.4 | I550: 4166666.7 | J550: 4060211.4 | K550: 13567710 | L550: AMOMPY | M550: Momentum Capital Investment S.A. | N550: 30/04/2026 | O550: 30/04/2026 | P550: 29 | Q550: No | U550: *MIL020800023 | V550: *MIL020800023 | W550: =+J550/$W$2 -> 8.3055721e-05
A551: BUROMAHTIK SA | B551: Pesos | C551: 46239 | D551: 03/07/2026 | E551: 0.96932685 | G551: 2000000 | H551: 1938653.7 | I551: 2000000 | J551: 1938653.7 | K551: 40751276 | L551: AMOMPY | M551: Momentum Capital Investment S.A. | N551: 02/06/2026 | O551: 02/06/2026 | P551: 35 | Q551: No | U551: *MAV030800905 | V551: *MAV030800905 | W551: =+J551/$W$2 -> 3.9657118e-05
A552: LAGAVULIN S.A. | B552: Pesos | C552: 46239 | D552: 03/07/2026 | E552: 0.97102888 | G552: 50000000 | H552: 48551444 | I552: 50000000 | J552: 48551444 | K552: 136 | L552: AMOMPY | M552: Momentum Capital Investment S.A. | N552: 13/05/2026 | O552: 13/05/2026 | P552: 33 | Q552: No | U552: *MAV030800838 | V552: *MAV030800838 | W552: =+J552/$W$2 -> 0.00099316878
A553: METALFOR SA | B553: Pesos | C553: 46239 | D553: 03/07/2026 | E553: 0.96847805 | G553: 16800000 | H553: 16270431 | I553: 16800000 | J553: 16270431 | K553: 32600 | L553: AMOMPY | M553: Momentum Capital Investment S.A. | N553: 29/04/2026 | O553: 29/04/2026 | P553: 36 | Q553: No | U553: *MAV030800746 | V553: *MAV030800746 | W553: =+J553/$W$2 -> 0.00033282809
A554: QUILMES | B554: Pesos | C554: 46239 | D554: 03/07/2026 | E554: 0.9813675 | G554: 8756337 | H554: 8593184.5 | I554: 8756337 | J554: 8593184.5 | K554: 40012226 | L554: AMOMPY | M554: Momentum Capital Investment S.A. | N554: 22/05/2026 | O554: 22/05/2026 | P554: 21 | Q554: No | U554: *MAV030800874 | V554: *MAV030800874 | W554: =+J554/$W$2 -> 0.00017578226
A555: QUILMES | B555: Pesos | C555: 46239 | D555: 03/07/2026 | E555: 0.97876223 | G555: 1484637.5 | H555: 1453107.1 | I555: 1484637.5 | J555: 1453107.1 | K555: 40012463 | L555: AMOMPY | M555: Momentum Capital Investment S.A. | N555: 29/05/2026 | O555: 29/05/2026 | P555: 24 | Q555: No | U555: *MAV030800891 | V555: *MAV030800891 | W555: =+J555/$W$2 -> 2.9724771e-05
A556: INTEGRA PYMES SGR | B556: Pesos | C556: 46239 | D556: 03/07/2026 | E556: 0.97359304 | G556: 15000000 | H556: 14603896 | I556: 15000000 | J556: 14603896 | K556: 90000127 | L556: AMOMPY | M556: Momentum Capital Investment S.A. | N556: 05/05/2026 | O556: 05/05/2026 | P556: 30 | Q556: No | U556: *INP030800027 | V556: *INP030800027 | W556: =+J556/$W$2 -> 0.00029873742
A557: SIGMA AGRO S.A. | B557: Pesos | C557: 46239 | D557: 03/07/2026 | E557: 0.97445081 | G557: 100000000 | H557: 97445081 | I557: 100000000 | J557: 97445081 | K557: 90003818 | L557: AMOMPY | M557: Momentum Capital Investment S.A. | N557: 03/06/2026 | O557: 03/06/2026 | P557: 29 | Q557: No | U557: *MAV030800921 | V557: *MAV030800921 | W557: =+J557/$W$2 -> 0.0019933375
A558: GRUB SA | B558: Pesos | C558: 46239 | D558: 03/07/2026 | E558: 0.98398667 | G558: 346128566 | H558: 3.405859e+08 | I558: 346128566 | J558: 3.405859e+08 | K558: 152123 | L558: AMOMPY | M558: Momentum Capital Investment S.A. | N558: 02/06/2026 | O558: 02/06/2026 | P558: 18 | Q558: No | U558: #MAV040860041 | V558: #MAV040860041 | W558: =+J558/$W$2 -> 0.0069670282
A559: SANDYPACK SRL | B559: Pesos | C559: 46239 | D559: 03/07/2026 | E559: 0.971882 | G559: 1000000 | H559: 971882 | I559: 1000000 | J559: 971882 | K559: 66487550 | L559: AMOMPY | M559: Momentum Capital Investment S.A. | N559: 04/06/2026 | O559: 04/06/2026 | P559: 32 | Q559: No | U559: *MAV010801165 | V559: *MAV010801165 | W559: =+J559/$W$2 -> 1.9880827e-05
A560: LINEA PUNTO CERO SRL | B560: Pesos | C560: 46239 | D560: 03/07/2026 | E560: 0.971882 | G560: 5000000 | H560: 4859410 | I560: 5000000 | J560: 4859410 | K560: 551 | L560: AMOMPY | M560: Momentum Capital Investment S.A. | N560: 04/06/2026 | O560: 04/06/2026 | P560: 32 | Q560: No | U560: *MAV010801167 | V560: *MAV010801167 | W560: =+J560/$W$2 -> 9.9404135e-05
A561: IGAR SRL | B561: Pesos | C561: 46239 | D561: 03/07/2026 | E561: 0.97188198 | G561: 2046492.4 | H561: 1988949.1 | I561: 2046492.4 | J561: 1988949.1 | K561: 12864393 | L561: AMOMPY | M561: Momentum Capital Investment S.A. | N561: 04/06/2026 | O561: 04/06/2026 | P561: 32 | Q561: No | U561: *MAV030800940 | V561: *MAV030800940 | W561: =+J561/$W$2 -> 4.068596e-05
... A964: DE LAS MISIONES S.A. | B964: Pesos | C964: 46268 | D964: 03/07/2026 | E964: 0.95151213 | G964: 2700000 | H964: 2569082.8 | I964: 2700000 | J964: 2569082.8 | K964: 6275 | L964: AMOMPY | M964: Momentum Capital Investment S.A. | N964: 17/06/2026 | O964: 17/06/2026 | P964: 30 | Q964: No | U964: *MAV010901263 | V964: *MAV010901263 | W964: =+J964/$W$2 -> 5.255318e-05
A965: DEMAGRO SRL | U965: #UMV010960019 | V965: #UMV010960019 | W965: =+J965/$W$2 -> 0
A966: BSP LARTI SA | U966: #UMV010960024 | V966: #UMV010960024 | W966: =+J966/$W$2 -> 0
A967: COOPERATIVA DE TABACALEROS DE JUJUY LTDA | U967: #UMV010960009 | V967: #UMV010960009 | W967: =+J967/$W$2 -> 0
A968: COOPERATIVA DE TABACALEROS DE JUJUY LTDA | U968: #UMV010960013 | V968: #UMV010960013 | W968: =+J968/$W$2 -> 0
A969: TALLERES METALURGICOS CRUCIANELLI SA | B969: Pesos | C969: 46268 | D969: 03/07/2026 | E969: 0.9469206 | G969: 12500000 | H969: 11836508 | I969: 12500000 | J969: 11836508 | K969: 1357 | L969: AMOMPY | M969: Momentum Capital Investment S.A. | N969: 21/05/2026 | O969: 21/05/2026 | P969: 33 | Q969: No | U969: *MAV010901169 | V969: *MAV010901169 | W969: =+J969/$W$2 -> 0.00024212771
A970: QUILMES | B970: Pesos | C970: 46268 | D970: 03/07/2026 | E970: 0.96634994 | G970: 248941.88 | H970: 240564.97 | I970: 248941.88 | J970: 240564.97 | K970: 40013131 | L970: AMOMPY | M970: Momentum Capital Investment S.A. | N970: 24/06/2026 | O970: 24/06/2026 | P970: 20.5 | Q970: No | U970: *MAV010901282 | V970: *MAV010901282 | W970: =+J970/$W$2 -> 4.9209992e-06
A971: QUILMES | B971: Pesos | C971: 46268 | D971: 03/07/2026 | E971: 0.96634993 | G971: 1236587.7 | H971: 1194976.5 | I971: 1236587.7 | J971: 1194976.5 | K971: 40013042 | L971: AMOMPY | M971: Momentum Capital Investment S.A. | N971: 24/06/2026 | O971: 24/06/2026 | P971: 20.5 | Q971: No | U971: *MAV010901283 | V971: *MAV010901283 | W971: =+J971/$W$2 -> 2.4444449e-05
A972: LINAL SA | B972: Pesos | C972: 46268 | D972: 03/07/2026 | E972: 0.94692057 | G972: 25000000 | H972: 23673014 | I972: 25000000 | J972: 23673014 | K972: 40 | L972: AMOMPY | M972: Momentum Capital Investment S.A. | N972: 03/07/2026 | O972: 03/07/2026 | P972: 33 | Q972: No | U972: *MAV010901339 | V972: *MAV010901339 | W972: =+J972/$W$2 -> 0.00048425539
A973: CELULOSA CAMPANA SA | B973: Pesos | C973: 46269 | D973: 03/07/2026 | E973: 0.94611069 | G973: 16005576 | H973: 15143046 | I973: 16005576 | J973: 15143046 | K973: 30713 | L973: AMOMPY | M973: Momentum Capital Investment S.A. | N973: 27/05/2026 | O973: 27/05/2026 | P973: 33 | Q973: No | U973: *MAV020901169 | V973: *MAV020901169 | W973: =+J973/$W$2 -> 0.00030976629
A974: CASSAB HNOS S.R.L. | B974: Pesos | C974: 46269 | D974: 03/07/2026 | E974: 0.93541783 | G974: 15166667 | H974: 14187171 | I974: 15166667 | J974: 14187171 | K974: 90020551 | L974: AMOMPY | M974: Momentum Capital Investment S.A. | N974: 12/05/2026 | O974: 12/05/2026 | P974: 40 | Q974: No | U974: *MAV020901153 | V974: *MAV020901153 | W974: =+J974/$W$2 -> 0.00029021289
A975: LOS INCAS DESARROLLOS | B975: Pesos | C975: 46269 | D975: 03/07/2026 | E975: 0.94149831 | G975: 6000000 | H975: 5648989.9 | I975: 6000000 | J975: 5648989.9 | K975: 160 | L975: AMOMPY | M975: Momentum Capital Investment S.A. | N975: 11/06/2026 | O975: 11/06/2026 | P975: 36 | Q975: No | U975: *MAV020901218 | V975: *MAV020901218 | W975: =+J975/$W$2 -> 0.00011555579
A976: HARJUICE SRL | B976: Pesos | C976: 46269 | D976: 03/07/2026 | E976: 0.94149826 | G976: 2067824.4 | H976: 1946853 | I976: 2067824.4 | J976: 1946853 | K976: 2202 | L976: AMOMPY | M976: Momentum Capital Investment S.A. | N976: 27/05/2026 | O976: 27/05/2026 | P976: 36 | Q976: No | U976: *MAV020901170 | V976: *MAV020901170 | W976: =+J976/$W$2 -> 3.9824843e-05
A977: COOPERATIVA DE VIVIENDA CREDITO Y CONSUMO PARA EL DESARROLLO LIMITADA | B977: Pesos | C977: 46269 | D977: 03/07/2026 | E977: 0.93844824 | G977: 42000000 | H977: 39414826 | I977: 42000000 | J977: 39414826 | K977: 155473 | L977: AMOMPY | M977: Momentum Capital Investment S.A. | N977: 02/07/2026 | O977: 02/07/2026 | P977: 38 | Q977: No | U977: #MAV030960028 | V977: #MAV030960028 | W977: =+J977/$W$2 -> 0.00080627004
A978: MILLS S.G.R. | B978: Pesos | C978: 46269 | D978: 03/07/2026 | E978: 0.95233128 | G978: 10000000 | H978: 9523312.8 | I978: 10000000 | J978: 9523312.8 | K978: 66613066 | L978: AMOMPY | M978: Momentum Capital Investment S.A. | N978: 30/04/2026 | O978: 30/04/2026 | P978: 29 | Q978: No | U978: *MIL020900026 | V978: *MIL020900026 | W978: =+J978/$W$2 -> 0.00019480897
A979: Neuquén Pymes S.G.R. | B979: Pesos | C979: 46269 | D979: 03/07/2026 | E979: 0.95705086 | G979: 10000000 | H979: 9570508.6 | I979: 10000000 | J979: 9570508.6 | K979: 9825610 | L979: AMOMPY | M979: Momentum Capital Investment S.A. | N979: 22/06/2026 | O979: 22/06/2026 | P979: 26 | Q979: No | U979: *NEU020900019 | V979: *NEU020900019 | W979: =+J979/$W$2 -> 0.00019577441
A980: TALLERES METALURGICOS CRUCIANELLI SA | B980: Pesos | C980: 46269 | D980: 03/07/2026 | E980: 0.94303073 | G980: 16600000 | H980: 15654310 | I980: 16600000 | J980: 15654310 | K980: 29088027 | L980: AMOMPY | M980: Momentum Capital Investment S.A. | N980: 14/04/2026 | O980: 14/04/2026 | P980: 35 | Q980: No | U980: *MAV020901140 | V980: *MAV020901140 | W980: =+J980/$W$2 -> 0.00032022471
... A1234: APEXAR TECHNOLOGIES SA | B1234: Pesos | C1234: 46300 | D1234: 03/07/2026 | E1234: 0.90660708 | G1234: 7203888 | H1234: 6531095.9 | I1234: 7203888 | J1234: 6531095.9 | K1234: 66329827 | L1234: AMOMPY | M1234: Momentum Capital Investment S.A. | N1234: 17/04/2026 | O1234: 17/04/2026 | P1234: 40 | Q1234: No | U1234: *MAV011000998 | V1234: *MAV011000998 | W1234: =+J1234/$W$2 -> 0.00013360016
A1235: COOPERATIVA DE TABACALEROS DE JUJUY LTDA | V1235: #UMV011060013 | W1235: =+J1235/$W$2 -> 0
A1236: COOPERATIVA DE TABACALEROS DE JUJUY LTDA | V1236: #UMV011060014 | W1236: =+J1236/$W$2 -> 0
A1237: VITALCAN S.A. | B1237: Pesos | C1237: 46301 | D1237: 03/07/2026 | E1237: 0.91432887 | G1237: 100000000 | H1237: 91432887 | I1237: 100000000 | J1237: 91432887 | K1237: 8439 | L1237: AMOMPY | M1237: Momentum Capital Investment S.A. | N1237: 02/07/2026 | O1237: 02/07/2026 | P1237: 36 | Q1237: No | U1237: *MAV021000989 | V1237: *MAV021000989 | W1237: =+J1237/$W$2 -> 0.001870352
A1238: TALLERES METALURGICOS CRUCIANELLI SA | B1238: Pesos | C1238: 46301 | D1238: 03/07/2026 | E1238: 0.92090328 | G1238: 12500000 | H1238: 11511291 | I1238: 12500000 | J1238: 11511291 | K1238: 1362 | L1238: AMOMPY | M1238: Momentum Capital Investment S.A. | N1238: 21/05/2026 | O1238: 21/05/2026 | P1238: 33 | Q1238: No | U1238: *MAV021000917 | V1238: *MAV021000917 | W1238: =+J1238/$W$2 -> 0.00023547507
A1239: Movil SGR | B1239: Pesos | C1239: 46301 | D1239: 03/07/2026 | E1239: 0.93207358 | G1239: 2500000 | H1239: 2330184 | I1239: 2500000 | J1239: 2330184 | K1239: 90031811 | L1239: AMOMPY | M1239: Momentum Capital Investment S.A. | N1239: 22/04/2026 | O1239: 22/04/2026 | P1239: 28 | Q1239: No | U1239: *MOV021000044 | V1239: *MOV021000044 | W1239: =+J1239/$W$2 -> 4.7666264e-05
A1240: Movil SGR | B1240: Pesos | C1240: 46301 | D1240: 03/07/2026 | E1240: 0.93207368 | G1240: 25000000 | H1240: 23301842 | I1240: 25000000 | J1240: 23301842 | K1240: 360569 | L1240: AMOMPY | M1240: Momentum Capital Investment S.A. | N1240: 21/04/2026 | O1240: 21/04/2026 | P1240: 28 | Q1240: No | U1240: *MOV021000043 | V1240: *MOV021000043 | W1240: =+J1240/$W$2 -> 0.00047666269
A1241: METALFOR SA | B1241: Pesos | C1241: 46301 | D1241: 03/07/2026 | E1241: 0.94584092 | G1241: 13000000 | H1241: 12295932 | I1241: 13000000 | J1241: 12295932 | K1241: 34113 | L1241: AMOMPY | M1241: Momentum Capital Investment S.A. | N1241: 30/06/2026 | O1241: 30/06/2026 | P1241: 22 | Q1241: No | U1241: *MAV021000966 | V1241: *MAV021000966 | W1241: =+J1241/$W$2 -> 0.0002515257
A1242: CELULOSA CAMPANA SA | B1242: Pesos | C1242: 46302 | D1242: 03/07/2026 | E1242: 0.92236956 | G1242: 14479900 | H1242: 13355819 | I1242: 14479900 | J1242: 13355819 | K1242: 9933008 | L1242: AMOMPY | M1242: Momentum Capital Investment S.A. | N1242: 12/06/2026 | O1242: 12/06/2026 | P1242: 32 | Q1242: No | U1242: *MAV051000919 | V1242: *MAV051000919 | W1242: =+J1242/$W$2 -> 0.00027320675
A1243: APEXAR TECHNOLOGIES SA | B1243: Pesos | C1243: 46302 | D1243: 03/07/2026 | E1243: 0.90480923 | G1243: 7203888 | H1243: 6518144.4 | I1243: 7203888 | J1243: 6518144.4 | K1243: 66329877 | L1243: AMOMPY | M1243: Momentum Capital Investment S.A. | N1243: 17/04/2026 | O1243: 17/04/2026 | P1243: 40 | Q1243: No | U1243: *MAV051000897 | V1243: *MAV051000897 | W1243: =+J1243/$W$2 -> 0.00013333522
A1244: APEXAR TECHNOLOGIES SA | B1244: Pesos | C1244: 46302 | D1244: 03/07/2026 | E1244: 0.90480923 | G1244: 7900000 | H1244: 7147992.9 | I1244: 7900000 | J1244: 7147992.9 | K1244: 877 | L1244: AMOMPY | M1244: Momentum Capital Investment S.A. | N1244: 17/04/2026 | O1244: 17/04/2026 | P1244: 40 | Q1244: No | U1244: *MAV051000898 | V1244: *MAV051000898 | W1244: =+J1244/$W$2 -> 0.00014621941
A1245: INDUSTRIAS ERCA S A | B1245: Pesos | C1245: 46302 | D1245: 03/07/2026 | E1245: 0.92013733 | G1245: 25000000 | H1245: 23003433 | I1245: 25000000 | J1245: 23003433 | K1245: 1233892 | L1245: AMOMPY | M1245: Momentum Capital Investment S.A. | N1245: 01/06/2026 | O1245: 01/06/2026 | P1245: 33 | Q1245: No | U1245: *MAV031001149 | V1245: *MAV031001149 | W1245: =+J1245/$W$2 -> 0.00047055844
A1246: Movil SGR | B1246: Pesos | C1246: 46302 | D1246: 03/07/2026 | E1246: 0.93140772 | G1246: 2500000 | H1246: 2328519.3 | I1246: 2500000 | J1246: 2328519.3 | K1246: 90031812 | L1246: AMOMPY | M1246: Momentum Capital Investment S.A. | N1246: 22/04/2026 | O1246: 22/04/2026 | P1246: 28 | Q1246: No | U1246: *MOV051000047 | V1246: *MOV051000047 | W1246: =+J1246/$W$2 -> 4.7632212e-05
A1247: CELULOSA CAMPANA SA | B1247: Pesos | C1247: 46303 | D1247: 03/07/2026 | E1247: 0.92162423 | G1247: 14479900 | H1247: 13345026 | I1247: 14479900 | J1247: 13345026 | K1247: 9933007 | L1247: AMOMPY | M1247: Momentum Capital Investment S.A. | N1247: 12/06/2026 | O1247: 12/06/2026 | P1247: 32 | Q1247: No | U1247: *MAV061001220 | V1247: *MAV061001220 | W1247: =+J1247/$W$2 -> 0.00027298598
A1248: REGCEN S.R.L. | B1248: Pesos | C1248: 46303 | D1248: 03/07/2026 | E1248: 0.90608951 | G1248: 3750000 | H1248: 3397835.7 | I1248: 3750000 | J1248: 3397835.7 | K1248: 66919994 | L1248: AMOMPY | M1248: Momentum Capital Investment S.A. | N1248: 13/05/2026 | O1248: 13/05/2026 | P1248: 39 | Q1248: No | U1248: *MAV061001207 | V1248: *MAV061001207 | W1248: =+J1248/$W$2 -> 6.9506157e-05
... A1278: REGCEN S.R.L. | B1278: Pesos | C1278: 46311 | D1278: 03/07/2026 | E1278: 0.89912556 | G1278: 3750000 | H1278: 3371720.9 | I1278: 3750000 | J1278: 3371720.9 | K1278: 66920206 | L1278: AMOMPY | M1278: Momentum Capital Investment S.A. | N1278: 13/05/2026 | O1278: 13/05/2026 | P1278: 39 | Q1278: No | U1278: *MAV141001310 | V1278: *MAV141001310 | W1278: =+J1278/$W$2 -> 6.8971953e-05
A1279: PUNTO PACK SRL | U1279: #UMV141060033 | V1279: #UMV141060033 | W1279: =+J1279/$W$2 -> 0
A1280: TRANSPORTE ZAVIOLA | B1280: Pesos | C1280: 46311 | D1280: 03/07/2026 | E1280: 0.9132993 | G1280: 7190687 | H1280: 6567249.4 | I1280: 7190687 | J1280: 6567249.4 | K1280: 90001573 | L1280: AMOMPY | M1280: Momentum Capital Investment S.A. | N1280: 02/06/2026 | O1280: 02/06/2026 | P1280: 33 | Q1280: No | U1280: *MAV141001327 | V1280: *MAV141001327 | W1280: =+J1280/$W$2 -> 0.00013433971
A1281: REGCEN S.R.L. | B1281: Pesos | C1281: 46314 | D1281: 03/07/2026 | E1281: 0.89654165 | G1281: 3750000 | H1281: 3362031.2 | I1281: 3750000 | J1281: 3362031.2 | K1281: 66917997 | L1281: AMOMPY | M1281: Momentum Capital Investment S.A. | N1281: 13/05/2026 | O1281: 13/05/2026 | P1281: 39 | Q1281: No | U1281: *MAV151001351 | V1281: *MAV151001351 | W1281: =+J1281/$W$2 -> 6.8773741e-05
A1282: LW GROUP SRL | B1282: Pesos | C1282: 46314 | D1282: 03/07/2026 | E1282: 0.90615707 | G1282: 1500000 | H1282: 1359235.6 | I1282: 1500000 | J1282: 1359235.6 | K1282: 4 | L1282: AMOMPY | M1282: Momentum Capital Investment S.A. | N1282: 23/04/2026 | O1282: 23/04/2026 | P1282: 35 | Q1282: No | U1282: *MAV151001338 | V1282: *MAV151001338 | W1282: =+J1282/$W$2 -> 2.7804536e-05
A1283: ESPECIALIDADES AGROPECUARIAS S.A. | B1283: Pesos | C1283: 46314 | D1283: 03/07/2026 | E1283: 0.9184702 | G1283: 10000000 | H1283: 9184702 | I1283: 10000000 | J1283: 9184702 | K1283: 726 | L1283: AMOMPY | M1283: Momentum Capital Investment S.A. | N1283: 30/06/2026 | O1283: 30/06/2026 | P1283: 30 | Q1283: No | U1283: *MAV151001396 | V1283: *MAV151001396 | W1283: =+J1283/$W$2 -> 0.00018788235
A1284: AVAL FEDERAL S.G.R. | B1284: Pesos | C1284: 46314 | D1284: 03/07/2026 | E1284: 0.92348962 | G1284: 212000000 | H1284: 1.957798e+08 | I1284: 212000000 | J1284: 1.957798e+08 | K1284: 39 | L1284: AMOMPY | M1284: Momentum Capital Investment S.A. | N1284: 03/07/2026 | O1284: 03/07/2026 | P1284: 28 | Q1284: No | U1284: *FED151000042 | V1284: *FED151000042 | W1284: =+J1284/$W$2 -> 0.0040048734
A1285: I-LED ARGENTINA S.A. | B1285: Pesos | C1285: 46314 | D1285: 03/07/2026 | E1285: 0.91598074 | G1285: 16500000 | H1285: 15113682 | I1285: 16500000 | J1285: 15113682 | K1285: 28676 | L1285: AMOMPY | M1285: Momentum Capital Investment S.A. | N1285: 27/04/2026 | O1285: 27/04/2026 | P1285: 31 | Q1285: No | U1285: *MAV151001343 | V1285: *MAV151001343 | W1285: =+J1285/$W$2 -> 0.00030916562
A1286: Movil SGR | B1286: Pesos | C1286: 46314 | D1286: 03/07/2026 | E1286: 0.92348964 | G1286: 2500000 | H1286: 2308724.1 | I1286: 2500000 | J1286: 2308724.1 | K1286: 90031816 | L1286: AMOMPY | M1286: Momentum Capital Investment S.A. | N1286: 22/04/2026 | O1286: 22/04/2026 | P1286: 28 | Q1286: No | U1286: *MOV151000067 | V1286: *MOV151000067 | W1286: =+J1286/$W$2 -> 4.7227281e-05
A1287: CONSTRUCCIONES S&C SAS | B1287: Pesos | C1287: 46315 | D1287: 03/07/2026 | E1287: 0.8980858 | G1287: 6899161.8 | H1287: 6196039.2 | I1287: 6899161.8 | J1287: 6196039.2 | K1287: 65964607 | L1287: AMOMPY | M1287: Momentum Capital Investment S.A. | N1287: 22/04/2026 | O1287: 22/04/2026 | P1287: 38 | Q1287: No | U1287: *MAV161001047 | V1287: *MAV161001047 | W1287: =+J1287/$W$2 -> 0.00012674623
A1288: INDUSTRIAS ERCA S A | B1288: Pesos | C1288: 46315 | D1288: 03/07/2026 | E1288: 0.91029255 | G1288: 45000000 | H1288: 40963165 | I1288: 45000000 | J1288: 40963165 | K1288: 67764210 | L1288: AMOMPY | M1288: Momentum Capital Investment S.A. | N1288: 18/06/2026 | O1288: 18/06/2026 | P1288: 33 | Q1288: No | U1288: *MAV161001066 | V1288: *MAV161001066 | W1288: =+J1288/$W$2 -> 0.00083794287
A1289: Movil SGR | B1289: Pesos | C1289: 46315 | D1289: 03/07/2026 | E1289: 0.92283582 | G1289: 2500000 | H1289: 2307089.6 | I1289: 2500000 | J1289: 2307089.6 | K1289: 90031817 | L1289: AMOMPY | M1289: Momentum Capital Investment S.A. | N1289: 22/04/2026 | O1289: 22/04/2026 | P1289: 28 | Q1289: No | U1289: *MOV161000058 | V1289: *MOV161000058 | W1289: =+J1289/$W$2 -> 4.7193845e-05
A1290: Movil SGR | B1290: Pesos | C1290: 46315 | D1290: 03/07/2026 | E1290: 0.92283578 | G1290: 25000000 | H1290: 23070895 | I1290: 25000000 | J1290: 23070895 | K1290: 360572 | L1290: AMOMPY | M1290: Momentum Capital Investment S.A. | N1290: 21/04/2026 | O1290: 21/04/2026 | P1290: 28 | Q1290: No | U1290: *MOV161000057 | V1290: *MOV161000057 | W1290: =+J1290/$W$2 -> 0.00047193843
A1291: INTEGRA PYMES SGR | B1291: Pesos | C1291: 46315 | D1291: 03/07/2026 | E1291: 0.91777732 | G1291: 2000000 | H1291: 1835554.6 | I1291: 2000000 | J1291: 1835554.6 | K1291: 13442187 | L1291: AMOMPY | M1291: Momentum Capital Investment S.A. | N1291: 29/05/2026 | O1291: 29/05/2026 | P1291: 30 | Q1291: No | U1291: *INP161000050 | V1291: *INP161000050 | W1291: =+J1291/$W$2 -> 3.7548122e-05
... A1327: LA MANTOVANA DE SERVICIOS GENERALES SA | B1327: Pesos | C1327: 46330 | D1327: 03/07/2026 | E1327: 0.89919203 | G1327: 933333333 | H1327: 8.3924589e+08 | I1327: 933333333 | J1327: 8.3924589e+08 | K1327: 154531 | L1327: AMOMPY | M1327: Momentum Capital Investment S.A. | N1327: 23/06/2026 | O1327: 23/06/2026 | P1327: 33 | Q1327: No | U1327: #MAV031160008 | V1327: #MAV031160008 | W1327: =+J1327/$W$2 -> 0.017167622
A1328: ALLIANCE ONE TOBACCO ARGENTINA | U1328: #UMV021160025 | V1328: #UMV021160025 | W1328: =+J1328/$W$2 -> 0
A1329: BSP LARTI SA | U1329: #UMV021160028 | V1329: #UMV021160028 | W1329: =+J1329/$W$2 -> 0
A1330: MOBEL SOCIEDAD ANONIMA | B1330: Pesos | C1330: 46330 | D1330: 03/07/2026 | E1330: 0.89102632 | G1330: 20408241 | H1330: 18184280 | I1330: 20408241 | J1330: 18184280 | K1330: 67998060 | L1330: AMOMPY | M1330: Momentum Capital Investment S.A. | N1330: 30/06/2026 | O1330: 30/06/2026 | P1330: 36 | Q1330: No | U1330: *MAV311001562 | V1330: *MAV311001562 | W1330: =+J1330/$W$2 -> 0.0003719778
A1331: METALURGICA DEL CENTRO SRL | B1331: Pesos | C1331: 46330 | D1331: 03/07/2026 | E1331: 0.90750889 | G1331: 10900000 | H1331: 9891846.9 | I1331: 10900000 | J1331: 9891846.9 | K1331: 237 | L1331: AMOMPY | M1331: Momentum Capital Investment S.A. | N1331: 02/07/2026 | O1331: 02/07/2026 | P1331: 30 | Q1331: No | U1331: *MAV011101200 | V1331: *MAV011101200 | W1331: =+J1331/$W$2 -> 0.00020234771
A1332: LOS GROBO SGR | B1332: Pesos | C1332: 46331 | D1332: 03/07/2026 | E1332: 0.91536061 | G1332: 15000000 | H1332: 13730409 | I1332: 15000000 | J1332: 13730409 | K1332: 236 | L1332: AMOMPY | M1332: Momentum Capital Investment S.A. | N1332: 02/07/2026 | O1332: 02/07/2026 | P1332: 27 | Q1332: No | U1332: *PRO031100021 | V1332: *PRO031100021 | W1332: =+J1332/$W$2 -> 0.00028086937
A1333: REGCEN S.R.L. | B1333: Pesos | C1333: 46331 | D1333: 03/07/2026 | E1333: 0.88217539 | G1333: 3750000 | H1333: 3308157.7 | I1333: 3750000 | J1333: 3308157.7 | K1333: 66918287 | L1333: AMOMPY | M1333: Momentum Capital Investment S.A. | N1333: 13/05/2026 | O1333: 13/05/2026 | P1333: 39 | Q1333: No | U1333: *MAV031101211 | V1333: *MAV031101211 | W1333: =+J1333/$W$2 -> 6.7671705e-05
A1334: Neuquén Pymes S.G.R. | B1334: Pesos | C1334: 46331 | D1334: 03/07/2026 | E1334: 0.90683234 | G1334: 11923077 | H1334: 10812232 | I1334: 11923077 | J1334: 10812232 | K1334: 90021990 | L1334: AMOMPY | M1334: Momentum Capital Investment S.A. | N1334: 11/05/2026 | O1334: 11/05/2026 | P1334: 30 | Q1334: No | U1334: *NEU031100019 | V1334: *NEU031100019 | W1334: =+J1334/$W$2 -> 0.00022117511
A1335: REGCEN S.R.L. | B1335: Pesos | C1335: 46336 | D1335: 03/07/2026 | E1335: 0.87803713 | G1335: 3750000 | H1335: 3292639.2 | I1335: 3750000 | J1335: 3292639.2 | K1335: 66918815 | L1335: AMOMPY | M1335: Momentum Capital Investment S.A. | N1335: 13/05/2026 | O1335: 13/05/2026 | P1335: 39 | Q1335: No | U1335: *MAV051100975 | V1335: *MAV051100975 | W1335: =+J1335/$W$2 -> 6.7354258e-05
A1336: DANBURY S. A | B1336: Pesos | C1336: 46336 | D1336: 03/07/2026 | E1336: 0.89482739 | G1336: 933333333 | H1336: 8.3517223e+08 | I1336: 933333333 | J1336: 8.3517223e+08 | K1336: 154563 | L1336: AMOMPY | M1336: Momentum Capital Investment S.A. | N1336: 24/06/2026 | O1336: 24/06/2026 | P1336: 33 | Q1336: No | U1336: #MAV061160016 | V1336: #MAV061160016 | W1336: =+J1336/$W$2 -> 0.017084291
A1337: LOS GROBO SGR | B1337: Pesos | C1337: 46337 | D1337: 03/07/2026 | E1337: 0.90572977 | G1337: 35000000 | H1337: 31700542 | I1337: 35000000 | J1337: 31700542 | K1337: 65 | L1337: AMOMPY | M1337: Momentum Capital Investment S.A. | N1337: 29/05/2026 | O1337: 29/05/2026 | P1337: 29 | Q1337: No | U1337: *PRO061100023 | V1337: *PRO061100023 | W1337: =+J1337/$W$2 -> 0.00064846657
...

Sheet Posicion cuotapartista
A1: Posición de Cuotapartista
A2: Fondo | B2: Cuotapartista | C2: Tipo de Valor Cuotaparte | D2: Cuotapartes | E2: Inversión | F2: Moneda | G2: Fondo | H2: Tipo de Inversor | I2: Fondo | J2: Porcentaje
A3: Nombre | B3: Nombre | F3: Símbolo | G3: Fecha Valor Cuotaparte | I3: Valor Cuotaparte
A4: AMOMPY | B4: MOMENTUM CAPITAL INVESTMENT S.A. (ACDI) | C4: C | D4: 1.7869429e+10 | E4: 3.0799302e+10 | F4: $ | G4: 03/07/2026 | H4: Agentes de Colocación y Distribución Integral de FCIs | I4: 1.723575 | J4: 84.290188
A5: AMOMPY | B5: BANCO DE SAN JUAN SA | C5: C | D5: 5.8150354e+08 | E5: 1.002265e+09 | F5: $ | G5: 03/07/2026 | H5: Agentes de Colocación y Distribución Integral de FCIs | I5: 1.723575 | J5: 2.7429551
A6: AMOMPY | B6: ZOFINGEN SECURITIES S.A. (ACDI) | C6: C | D6: 3.3408168e+08 | E6: 5.7581483e+08 | F6: $ | G6: 03/07/2026 | H6: Agentes de Colocación y Distribución Integral de FCIs | I6: 1.723575 | J6: 1.575865
A7: AMOMPY | B7: MOMENTUM CAPITAL INVESTMENT S.A. (ACDI) | C7: B | D7: 3.2641096e+09 | E7: 5.5844639e+09 | F7: $ | G7: 03/07/2026 | H7: Agentes de Colocación y Distribución Integral de FCIs | I7: 1.710869 | J7: 95.073451
A8: AMOMPY | B8: BANCO DE LA CIUDAD DE BUENOS AIRES | C8: C | D8: 1.8078341e+09 | E8: 3.1159377e+09 | F8: $ | G8: 03/07/2026 | H8: Agentes de Colocación y Distribución Integral de FCIs | I8: 1.723575 | J8: 8.5275626
A9: AMOMPY | B9: MOMENTUM CAPITAL INVESTMENT S.A. (ACDI) | C9: A | D9: 4.0849927e+09 | E9: 5.8324831e+09 | F9: $ | G9: 03/07/2026 | H9: Agentes de Colocación y Distribución Integral de FCIs | I9: 1.427783 | J9: 90.119519
A10: AMOMPY | B10: ALYCBUR S.A. (ACDI) | C10: B | D10: 1.6914077e+08 | E10: 2.8937771e+08 | F10: $ | G10: 03/07/2026 | H10: Agentes de Colocación y Distribución Integral de FCIs | I10: 1.710869 | J10: 4.9265494
A11: AMOMPY | B11: ALYCBUR S.A. (ACDI) | C11: A | D11: 4.4786848e+08 | E11: 6.3945901e+08 | F11: $ | G11: 03/07/2026 | H11: Agentes de Colocación y Distribución Integral de FCIs | I11: 1.427783 | J11: 9.8804809
A12: AMOMPY | B12: BANCO DE SANTA CRUZ SA | C12: C | D12: 2.9075177e+08 | E12: 5.0113248e+08 | F12: $ | G12: 03/07/2026 | H12: Agentes de Colocación y Distribución Integral de FCIs | I12: 1.723575 | J12: 1.3714776
A13: AMOMPY | B13: ALYCBUR S.A. (ACDI) | C13: C | D13: 3.1629211e+08 | E13: 5.4515317e+08 | F13: $ | G13: 03/07/2026 | H13: Agentes de Colocación y Distribución Integral de FCIs | I13: 1.723575 | J13: 1.4919515
D14: 2.9166004e+10 | E14: 4.8885388e+10
