Workbook

Sheet GESTION MOMENTUM
A1: FONDOS COMUNES DE INVERSION
A2: 15/5/2026
A3: 10:22:06
A4: Informe de Gestión al 14/5/2026
A5: FCI ABIERTO MOMENTUM PYMES | K5: COMAFI $ Nº 24148/3
A6: Todos los importes están expresados en Pesos | K6: BANCO DEL SOL
C7: (4) | D7: (1) | L7: 46157 | M7: =WORKDAY(L7,1,$R:$R) -> 46160 | N7: =WORKDAY(M7,1,$R:$R) -> 46161 | R7: 45719 | S7: Lista de feriados 2025
A8: ACTIVO | B8: 3.8267482e+10 | C8: 100 | K8: Caucion MAV | R8: 45720
A9: INVERSIONES | B9: 3.6016156e+10 | C9: 94.12 | D9: 94.92 | K9: Vto Pase | R9: 45740
A10: TITULOS PUBLICOS | B10: 5.6938407e+08 | C10: 1.49 | D10: 1.5 | K10: Plazo Fijo | L10: =SUMIFS(F:F,A:A,$K$10,B:B,L7) -> 0 | M10: =SUMIFS(G:G,B:B,$K$10,C:C,M7) -> 0 | N10: =SUMIFS(H:H,C:C,$K$10,D:D,N7) -> 0 | R10: 45749
A11: FUTUROS | B11: -1054249000 | C11: -2.75 | D11: -2.78 | K11: Vto. Cheques | L11: =SUMIF($B$91:$B$1225,L7,$D$91:$D$1225) -> 2.8318299e+08 | M11: =SUMIF($B$91:$B$1225,M7,$D$91:$D$1225) -> 2.2010609e+08 | N11: =SUMIF($B$91:$B$1225,N7,$D$91:$D$1225) -> 2.7483551e+08 | R11: 45765
A12: DISPONIBILIDADES | B12: 1973761.5 | C12: 0.01 | D12: 0.01 | K12: Vto. Pagarés Dollar Linked | L12: =+SUMIF($B$1230:$B$1250,L7,$F$1230:$F$1250) -> 0 | M12: =+SUMIF($B$1230:$B$1250,M7,$F$1230:$F$1250) -> 0 | N12: =+SUMIF($B$1230:$B$1250,N7,$F$1230:$F$1250) -> 0 | R12: 45778
A13: EN PESOS | B13: 1973719.7 | C13: 0.01 | D13: 0.01 | K13: FCI IEB Ahorro - Clase E | L13: =SUMIF($A:$A,K13,$E:$E) -> 1670000000 | R13: 45779
A14: EN DOLARES | B14: 41.8 | C14: 0 | D14: 0 | K14: COMAFI $ Nº 24148/3 | L14: =+B13 -> 1973719.7 | R14: 45802
A15: CREDITOS | B15: 2.2493527e+09 | C15: 5.88 | D15: 5.93 | K15: Ctte Momentum | L15: 2626000 | R15: 45824
A16: PASIVO | B16: -3.255195e+08 | K16: Cheques pendientes | R16: 45828
A17: PROVISIONES | B17: -41621110 | K17: Compra/Venta Bonos | R17: 45847
A18: PROV. HONORARIOS SOC. DEPOSITARIA | B18: -2415090.8 | K18: TOTAL | L18: =SUM(L8:L17) -> 1.9577827e+09 | R18: 45884
A19: PROV. HONORARIOS SOCIEDAD GERENTE | B19: -35641836 | K19: Neg. Cheques / Pagare | L19: =-32380754.09 -> -32380754 | R19: 45886
A20: PROV. GASTOS SOCIEDAD DEPOSITARIA | B20: -3564183.6 | K20: Coloca caucion MAV | R20: 45942
A21: DEUDAS EN PESOS | B21: -2.7185579e+08 | K21: Compra/Venta de Bonos | R21: 45982
A22: RESCATES | B22: -50000000 | J22: EGRESOS EN EL DIA Clase B | K22: Suscripciones | R22: 45985
A23: PREVISIÓN INCOBRABLES | B23: -1.6900272e+08 | K23: Rescates | L23: =SUMIF(A:A,K23,B:B) -> -50000000 | R23: 45999
A24: Valor Patrimonial del Fondo | B24: 3.7941963e+10 | K24: Pase | R24: 46016
A25: Liquidez Efectiva (2) | B25: 1.9674281e+09 | D25: 5.19 | K25: Rentas y Amortizaciones
A26: Liquidez Corriente (3) | B26: 1.925807e+09 | D26: 5.08 | K26: Pago Gastos SG y SD
K27: Caja cierre | L27: =SUM(L18:L26) -> 1.875402e+09 | M27: =SUM(M8:M26) -> 2.2010609e+08 | N27: =SUM(N8:N26) -> 2.7483551e+08
K31: Activos Pyme | L31: 2.6702326e+10
K32: % Pyme | L32: =L31/B24 -> 0.70376766
K40: PN ACTUAL | L40: =VLOOKUP("Valor Patrimonial del Fondo",A:B,2,0)+L22+L23 -> 3.7891963e+10
A41: Inversiones | K41: 5% MM | L41: =+L40*0.05 -> 1.8945981e+09
A42: TITULO PUBLICO en Pesos | K42: 20% CAUCION | L42: =+L40*0.2 -> 7.5783925e+09
A43: Denominación | B43: IsinCode | C43: Cantidad | D43: Cierre | E43: Total | F43: % (1) | G43: Costo | H43: Var | I43: Vencimiento
A44: Lecap S30N6 | B44: AR0451031345 | C44: 200000000 | D44: 1.1518 | E44: 230366940 | F44: 0.61 | G44: 0 | I44: 30/11/2026
A45: S29Y6 - Lecap S29Y6 | B45: AR0716680340 | C45: 197919126 | D45: 1.3098 | E45: 2.5923868e+08 | F45: 0.68 | G45: 0 | I45: 29/05/2026
C46: 397919126 | E46: 4.8960562e+08 | F46: 1.29
A48: OBLIGACIONES NEGOCIABLES en Pesos
A49: Denominación | B49: IsinCode | C49: Cantidad | D49: Cierre | E49: Total | F49: % (1) | G49: Costo | H49: Var | I49: Vencimiento
A50: LR7AO - ON Laboratorios Richmond Serie 7 Cl A Vto 10/12/26 | B50: AR0905777444 | C50: 300000000 | D50: 1.0732 | E50: 321969276 | F50: 0.85 | G50: 1 | H50: 7.32 | I50: 10/12/2026
A51: VBC3O - ON BANCO DE VALORES CL.3 24/10/26 $ | B51: AR0531585807 | C51: 300000000 | D51: 1.013 | E51: 303895314 | F51: 0.8 | G51: 1 | H51: 1.3 | I51: 24/10/2026
C52: 600000000 | E52: 625864590 | F52: 1.65
A54: FIDEICOMISOS FINANCIEROS en Pesos
A55: Denominación | B55: IsinCode | C55: Cantidad | D55: Cierre | E55: Total | F55: % (1) | G55: Costo | H55: Var | I55: Vencimiento
A56: FF AMFAyS S49 Clase A | B56: AR0711423134 | C56: 100000000 | D56: 0.4052 | E56: 40524917 | F56: 0.11 | G56: 0.9846 | H56: -58.84 | I56: 31/12/2026
A57: MY50B - VD FF AMFAYS S.50 CL.B $ | B57: AR0695284973 | C57: 101962042 | D57: 1.3171 | E57: 1.3429384e+08 | F57: 0.35 | G57: 0.924 | H57: 42.54 | I57: 13/01/2027
A58: MY50C - VD FF AMFAYS S.50 CL.C $ | B58: AR0890638411 | C58: 382357659 | D58: 1.0846 | E58: 4.1469711e+08 | F58: 1.09 | G58: 0.85 | H58: 27.6 | I58: 13/04/2027
A59: MY51B - VD FF AMFAYS Serie 51 Clase B | B59: AR0207834935 | C59: 75584213 | D59: 1.0518 | E59: 79498954 | F59: 0.21 | G59: 0.8718 | H59: 20.65 | I59: 15/03/2027
A60: MY51C - VD FF AMFAYS Serie 51 Clase C | B60: AR0601005553 | C60: 176363163 | D60: 0.9644 | E60: 1.7008436e+08 | F60: 0.45 | G60: 0.8446 | H60: 14.18 | I60: 15/11/2027
A61: VD FF SECUBONO 245 CL.A $ | B61: AR0822887474 | C61: 306275000 | D61: 0.4454 | E61: 1.3640375e+08 | F61: 0.36 | G61: 1.0324 | H61: -56.86 | I61: 28/08/2026
C62: 1142542077 | E62: 9.7550293e+08 | F62: 2.57
A64: FUTUROS en Pesos
A65: Denominación | B65: IsinCode | C65: Cantidad | D65: Cierre | E65: Total | F65: % (1) | G65: Costo | H65: Var | I65: Vencimiento
A66: Fut Rofex DLR052026 | C66: -40000 | D66: 1401.5 | E66: -56060000 | F66: -0.15 | G66: 0 | I66: 30/05/2026
A67: Fut Rofex DLR062026 | C67: -314000 | D67: 1426.5 | E67: -447921000 | F67: -1.18 | G67: 0 | I67: 30/06/2026
A68: Fut Rofex DLR072026 | C68: -276000 | D68: 1455.5 | E68: -401718000 | F68: -1.06 | G68: 0 | I68: 31/07/2026
A69: Fut Rofex DLR082026 | C69: -100000 | D69: 1485.5 | E69: -148550000 | F69: -0.39 | G69: 0 | I69: 31/08/2026
C70: -730000 | E70: -1054249000 | F70: -2.78
A72: MONEY MARKET en Pesos
A73: Denominación | B73: IsinCode | C73: Cantidad | D73: Cierre | E73: Total | F73: % (1) | G73: Costo | H73: Var | I73: Vencimiento
A74: FCI IEB Ahorro - Clase E | C74: 1.37341e+08 | D74: 12.1595 | E74: 1670000000 | F74: 4.4 | G74: 12.1595 | H74: 0
C75: 1.37341e+08 | E75: 1670000000 | F75: 4.4
A77: TITULO PROVINCIAL en Pesos
A78: Denominación | B78: IsinCode | C78: Cantidad | D78: Cierre | E78: Total | F78: % (1) | G78: Costo | H78: Var | I78: Vencimiento
A79: CO2D7 - Título provincia de Córdoba 05/12/27 | B79: AR0569903542 | C79: 300000000 | D79: 1.0338 | E79: 310145394 | F79: 0.82 | G79: 0 | I79: 05/12/2027
C80: 300000000 | E80: 310145394 | F80: 0.82
A83: Aperturas, Pases y Cauciones en Pesos
A84: Tipo | B84: Vencimiento | C84: Concertación | D84: Plazo | E84: Tasa | F84: Total | G84: % (1)
A85: PASE | B85: 03/06/2026 | C85: 04/05/2026 | D85: 30 | E85: 37.876424 | F85: 5.8626977e+08 | G85: 1.55
D86: 20 | E86: 37.876424 | F86: 5.8626977e+08 | G86: 1.55
A89: Cheques de Pago Diferido en Pesos
A90: Descripción | B90: Vencimiento | C90: Compra | D90: Nominal | E90: Precio | F90: Actual | G90: % (1)
A91: *MAV150501075 | B91: 19/05/2026 | C91: 07/08/2025 | D91: 10000000 | E91: 0.9937381 | F91: 9937381 | G91: 0.03
A92: *MAV170700987 | B92: 21/07/2026 | C92: 11/08/2025 | D92: 10000000 | E92: 0.92106597 | F92: 9210659.7 | G92: 0.02
A93: *MAV120601248 | B93: 17/06/2026 | C93: 11/08/2025 | D93: 10000000 | E93: 0.95891131 | F93: 9589113.1 | G93: 0.03
A94: *MAV260600989 | B94: 30/06/2026 | C94: 11/08/2025 | D94: 10000000 | E94: 0.94407949 | F94: 9440794.9 | G94: 0.02
A95: *MAV290500940 | B95: 02/06/2026 | C95: 11/08/2025 | D95: 10000000 | E95: 0.97661477 | F95: 9766147.7 | G95: 0.03
A96: *MAV140801099 | B96: 19/08/2026 | C96: 03/09/2025 | D96: 10000000 | E96: 0.82830302 | F96: 8283030.2 | G96: 0.02
A97: *MAV280800986 | B97: 01/09/2026 | C97: 03/09/2025 | D97: 10000000 | E97: 0.80967178 | F97: 8096717.8 | G97: 0.02
A98: *MAV310701190 | B98: 04/08/2026 | C98: 03/09/2025 | D98: 10000000 | E98: 0.85089522 | F98: 8508952.2 | G98: 0.02
A99: *MAV270501010 | B99: 29/05/2026 | C99: 12/12/2025 | D99: 9000000 | E99: 0.98382753 | F99: 8854447.8 | G99: 0.02
A100: *MAV030600839 | B100: 05/06/2026 | C100: 09/01/2026 | D100: 34135701 | E100: 0.97876224 | F100: 33410735 | G100: 0.09
A101: *MAV030600840 | B101: 05/06/2026 | C101: 09/01/2026 | D101: 40810396 | E101: 0.97876224 | F101: 39943674 | G101: 0.11
A102: *MAV030600842 | B102: 05/06/2026 | C102: 09/01/2026 | D102: 41096651 | E102: 0.97876224 | F102: 40223850 | G102: 0.11
... A1225: *MAV180601215 | B1225: 22/06/2026 | C1225: 14/05/2026 | D1225: 150000000 | E1225: 0.96693874 | F1225: 1.4504081e+08 | G1225: 0.38
F1226: 3.0384609e+10 | G1226: 80.74
A1228: Cheques de Pago Diferido en Dolar 3500
A1229: Descripción | B1229: Vencimiento | C1229: Compra | D1229: Nominal | E1229: Precio | F1229: Actual | G1229: % (1)
A1230: #UMV250180006 | B1230: 27/01/2028 | C1230: 30/12/2025 | D1230: 20856 | E1230: 1190.0979 | F1230: 24820684 | G1230: 0.07
A1231: #UMV250770007 | B1231: 28/07/2027 | C1231: 30/12/2025 | D1231: 20856 | E1231: 1243.3489 | F1231: 25931285 | G1231: 0.07
A1232: #UMV250780006 | B1232: 27/07/2028 | C1232: 30/12/2025 | D1232: 20856 | E1232: 1141.4828 | F1232: 23806759 | G1232: 0.06
A1233: #UMV250170065 | B1233: 27/01/2027 | C1233: 30/12/2025 | D1233: 13904 | E1233: 1301.2555 | F1233: 18092654 | G1233: 0.05
A1234: #UMV010660043 | B1234: 03/06/2026 | C1234: 20/01/2026 | D1234: 40000 | E1234: 1385.6394 | F1234: 55425581 | G1234: 0.15
A1235: #UMV010760032 | B1235: 03/07/2026 | C1235: 05/03/2026 | D1235: 50000 | E1235: 1374.4046 | F1235: 68720235 | G1235: 0.18
A1236: #UMV010760033 | B1236: 03/07/2026 | C1236: 12/03/2026 | D1236: 50000 | E1236: 1374.4049 | F1236: 68720249 | G1236: 0.18
A1237: #UMV030860027 | B1237: 05/08/2026 | C1237: 30/03/2026 | D1237: 50000 | E1237: 1368.3399 | F1237: 68416998 | G1237: 0.18
A1238: #UMV010760034 | B1238: 03/07/2026 | C1238: 01/04/2026 | D1238: 50000 | E1238: 1376.2646 | F1238: 68813234 | G1238: 0.18
A1239: #UMV030860028 | B1239: 05/08/2026 | C1239: 01/04/2026 | D1239: 50000 | E1239: 1365.2906 | F1239: 68264537 | G1239: 0.18
A1240: #UMV131160016 | B1240: 17/11/2026 | C1240: 17/04/2026 | D1240: 18230 | E1240: 1338.3755 | F1240: 24398590 | G1240: 0.06
A1241: #UMV141060033 | B1241: 16/10/2026 | C1241: 17/04/2026 | D1241: 18230 | E1241: 1347.4541 | F1241: 24564092 | G1241: 0.06
... A1250: #UMV010960009 | B1250: 03/09/2026 | C1250: 23/04/2026 | D1250: 100000 | E1250: 1363.9358 | F1250: 1.3639358e+08 | G1250: 0.36
...

Sheet Parametros
A1: Min | B1: 0.75 | C1: en Pymes | D1: =+B1*(VLOOKUP($E$1,'GESTION MOMENTUM'!$A$8:$B$32,2,0)) -> 2.8456472e+10 | E1: Valor Patrimonial del Fondo | G1: PN actual | H1: P&L | I1: PN reservado
A2: Max | B2: 0.05 | C2: Money Market | D2: =+B2*(VLOOKUP($E$1,'GESTION MOMENTUM'!$A$8:$B$32,2,0)) -> 1.8970981e+09 | G2: =VLOOKUP(E1,'GESTION MOMENTUM'!A8:B32,2,0) -> 3.7941963e+10 | H2: -0.002 | I2: =+G2*(1+H2) -> 3.7866079e+10
A3: Max | B3: 0.2 | C3: PFRemuneradasCaucion | D3: =+B3*(VLOOKUP($E$1,'GESTION MOMENTUM'!$A$8:$B$32,2,0)) -> 7.5883925e+09 | G3: Money Market | H3: 0.05 | I3: =+I2*H3 -> 1.8933039e+09
A4: Max | B4: 0.2 | C4: cheques x librador | D4: =+B4*(VLOOKUP($E$1,'GESTION MOMENTUM'!$A$8:$B$32,2,0)) -> 7.5883925e+09
A5: Max | B5: 0.25 | C5: x titulo en Pymes | D5: =+B5*(VLOOKUP($E$1,'GESTION MOMENTUM'!$A$8:$B$32,2,0)) -> 9.4854907e+09
B8: Garantías RFX (MOMENTUM)
B9: Bono | C9: VN | D9: Precio | E9: Aforo | F9: $
B10: Lecap S30N6 | C10: 200000000 | D10: =+VLOOKUP(B10,'GESTION MOMENTUM'!A:D,4,0) -> 1.1518 | E10: 0.8 | F10: =C10*D10*E10 -> 184288000
B11: CO2D7 - Título provincia de Córdoba 05/12/27 | C11: 300000000 | D11: =+VLOOKUP(B11,'GESTION MOMENTUM'!A:D,4,0) -> 1.0338 | E11: 0.6 | F11: =C11*D11*E11 -> 186084000
E13: Garantia | F13: =SUM(F10:F12) -> 370372000
B15: Garantías | C15: Total $ por contrato | D15: Contratos a shortear | E15: Contratos Shorteados | F15: Garantia Requerida
A16: Fut Rofex DLR042026 | B16: Abril | C16: 150000 | D16: 0 | E16: =_xlfn.IFNA(-VLOOKUP(A16,'GESTION MOMENTUM'!A:C,3,0)/1000,0) -> 0 | F16: =+C16*(E16+D16) -> 0
A17: Fut Rofex DLR052026 | B17: Mayo | C17: 155000 | D17: 0 | E17: =_xlfn.IFNA(-VLOOKUP(A17,'GESTION MOMENTUM'!A:C,3,0)/1000,0) -> 40 | F17: =+C17*(E17+D17) -> 6200000
A18: Fut Rofex DLR062026 | B18: Junio | C18: 160000 | D18: 0 | E18: =_xlfn.IFNA(-VLOOKUP(A18,'GESTION MOMENTUM'!A:C,3,0)/1000,0) -> 314 | F18: =+C18*(E18+D18) -> 50240000
A19: Fut Rofex DLR072026 | B19: Julio | C19: 165000 | D19: 0 | E19: =_xlfn.IFNA(-VLOOKUP(A19,'GESTION MOMENTUM'!A:C,3,0)/1000,0) -> 276 | F19: =+C19*(E19+D19) -> 45540000
C20: 170000 | D20: 0 | E20: =_xlfn.IFNA(-VLOOKUP(A20,'GESTION MOMENTUM'!A:C,3,0)/1000,0) -> 0 | F20: =+C20*(E20+D20) -> 0
C21: 175000 | D21: 0 | E21: =_xlfn.IFNA(-VLOOKUP(A21,'GESTION MOMENTUM'!A:C,3,0)/1000,0) -> 0 | F21: =+C21*(E21+D21) -> 0
F22: =+SUM(F16:F21) -> 101980000
B23: Saldo de Garantias | C23: =+F13-F22 -> 268392000

Sheet Cheques pendientes
A1: FONDO | B1: CHPD | C1: VTO | D1: MONEDA | E1: MONTO | F1: MONTO $ | G1: ESTADO | H1: LIBRADOR | I1: DIAS DE MORA
A2: AMOMPY | B2: *MAV030300645 | C2: 45723 | D2: $ | E2: 3406250 | G2: PREVISIONADO | H2: UKUMARI SOCIEDAD ANONIMA. | I2: =+TODAY()-C2 -> 434 | U2: LIBRADORES PENDIENTES
A3: AMOMPY | B3: *MAV100300802 | C3: 45728 | D3: $ | E3: 3406250 | G3: PREVISIONADO | H3: UKUMARI SOCIEDAD ANONIMA. | I3: =+TODAY()-C3 -> 429 | U3: {=+_xlfn.UNIQUE(H2:H108)} -> UKUMARI SOCIEDAD ANONIMA. | V3: =+SUMIF(H:H,U3,E:E) -> 6812500
A4: AMOMPY | B4: *MAV250400806 | C4: 45776 | D4: $ | E4: 20000000 | G4: PENDIENTE | H4: FRIGORIFICO H V S A | I4: =+TODAY()-C4 -> 381 | U4: FRIGORIFICO H V S A | V4: =+SUMIF(H:H,U4,E:E) -> 215445000
A5: AMOMPY | B5: *MAV260400819 | C5: 45777 | D5: $ | E5: 20000000 | G5: PENDIENTE | H5: FRIGORIFICO H V S A | I5: =+TODAY()-C5 -> 380 | U5: NIRO CONSTRUYE S. A. | V5: =+SUMIF(H:H,U5,E:E) -> 258370000
A6: AMOMPY | B6: *MAV270400527 | C6: 45777 | D6: $ | E6: 20000000 | G6: PENDIENTE | H6: FRIGORIFICO H V S A | I6: =+TODAY()-C6 -> 380 | U6: EL GUAYMALLEN SA | V6: =+SUMIF(H:H,U6,E:E) -> 113700000
A7: AMOMPY | B7: *MAV280400632 | C7: 45777 | D7: $ | E7: 20000000 | G7: PENDIENTE | H7: FRIGORIFICO H V S A | I7: =+TODAY()-C7 -> 380 | U7: MERCOL RAUL ALBERTO Y MERCOL MAURICIO EDUARDO. | V7: =+SUMIF(H:H,U7,E:E) -> 62500000
A8: AMOMPY | B8: *MAV200500842 | C8: 45799 | D8: $ | E8: 129185000 | G8: PENDIENTE | H8: NIRO CONSTRUYE S. A. | I8: =+TODAY()-C8 -> 358 | K8: Valor Patrimonial del Fondo | L8: =+VLOOKUP(K8,'GESTION MOMENTUM'!A:B,2,0) -> 3.7941963e+10 | U8: F G SANITARIOS S R L | V8: =+SUMIF(H:H,U8,E:E) -> 35000000
A9: AMOMPY | B9: *MAV300500862 | C9: 45811 | D9: $ | E9: 129185000 | G9: PENDIENTE | H9: NIRO CONSTRUYE S. A. | I9: =+TODAY()-C9 -> 346 | U9: AKAI ENERGY LED SRL | V9: =+SUMIF(H:H,U9,E:E) -> 44963000
A10: AMOMPY | B10: *MAV150701156 | C10: 45855 | D10: $ | E10: 22500000 | G10: PENDIENTE | H10: FRIGORIFICO H V S A | I10: =+TODAY()-C10 -> 302 | L10: $ | M10: % PN | U10: COOPERATIVA TAMBERA LAS CAÑITAS LIMITADA | V10: =+SUMIF(H:H,U10,E:E) -> 190000000
A11: AMOMPY | B11: *MAV150701157 | C11: 45855 | D11: $ | E11: 22510000 | G11: PENDIENTE | H11: FRIGORIFICO H V S A | I11: =+TODAY()-C11 -> 302 | K11: PREVISIÓN INCOBRABLES | L11: =+VLOOKUP(K11,'GESTION MOMENTUM'!A:B,2,0) -> -1.6900272e+08 | M11: =+L11/L8 -> -0.0044542429 | U11: FRIGORIFICO GENERAL PICO S A | V11: =+SUMIF(H:H,U11,E:E) -> 70000000
A12: AMOMPY | B12: *MAV160700725 | C12: 45856 | D12: $ | E12: 22482000 | G12: PENDIENTE | H12: FRIGORIFICO H V S A | I12: =+TODAY()-C12 -> 301 | K12: PREVISIONADO | L12: =+SUMIF(G:G,K12,E:E) -> 144512500 | U12: MIANI CLARA A Y MIANI ADA CLELIA | V12: =+SUMIF(H:H,U12,E:E) -> 3125000
A13: AMOMPY | B13: *MAV210700860 | C13: 45861 | D13: $ | E13: 22646000 | G13: PENDIENTE | H13: FRIGORIFICO H V S A | I13: =+TODAY()-C13 -> 296 | K13: Prevision a aplicar | L13: =+L11+L12 -> -24490216 | U13: PORT PLA S.R.L. | V13: =+SUMIF(H:H,U13,E:E) -> 150000000
A14: AMOMPY | B14: *MAV220700935 | C14: 45862 | D14: $ | E14: 22690000 | G14: PENDIENTE | H14: FRIGORIFICO H V S A | I14: =+TODAY()-C14 -> 295 | U14: SOUTHAMERICAN TRENDY S.A. | V14: =+SUMIF(H:H,U14,E:E) -> 332000000
A15: AMOMPY | B15: *MAV230700673 | C15: 45863 | D15: $ | E15: 22617000 | G15: PENDIENTE | H15: FRIGORIFICO H V S A | I15: =+TODAY()-C15 -> 294 | K15: PENDIENTE | L15: =+SUMIF(G:G,K15,E:E)+E2 -> 2087556550 | M15: =+SUMIF(G:G,K15,E:E)/$L$8 -> 0.054929955 | U15: CONEXION SALUD SRL | V15: =+SUMIF(H:H,U15,E:E) -> 27000000
A16: AMOMPY | B16: *MAV091000728 | C16: 45943 | D16: $ | E16: 20000000 | G16: PREVISIONADO | H16: EL GUAYMALLEN SA | I16: =+TODAY()-C16 -> 214 | U16: MASTER DESIGN HOME SRL | V16: =+SUMIF(H:H,U16,E:E) -> 24000000
A17: AMOMPY | B17: *MAV091000727 | C17: 45943 | D17: $ | E17: 12500000 | G17: PENDIENTE | H17: MERCOL RAUL ALBERTO Y MERCOL MAURICIO EDUARDO. | I17: =+TODAY()-C17 -> 214 | U17: BUNYAR S.R.L. | V17: =+SUMIF(H:H,U17,E:E) -> 24800000
A18: AMOMPY | B18: *MAV151000873 | C18: 45947 | D18: $ | E18: 5000000 | G18: PENDIENTE | H18: F G SANITARIOS S R L | I18: =+TODAY()-C18 -> 210 | U18: GROCAL S.A. | V18: =+SUMIF(H:H,U18,E:E) -> 15000000
A19: AMOMPY | B19: *MAV201001014 | C19: 45952 | D19: $ | E19: 5000000 | G19: PENDIENTE | H19: F G SANITARIOS S R L | I19: =+TODAY()-C19 -> 205 | U19: Paccioli Group Sociedad Anonima | V19: =+SUMIF(H:H,U19,E:E) -> 13958000
A20: AMOMPY | B20: *MAV221000795 | C20: 45954 | D20: $ | E20: 18700000 | G20: PREVISIONADO | H20: EL GUAYMALLEN SA | I20: =+TODAY()-C20 -> 203 | K20: LIBRADOR PENDIENTE | L20: $ | M20: % PN | O20: VIGENTE | U20: FINEX CABA S. A. | V20: =+SUMIF(H:H,U20,E:E) -> 55300000
A21: AMOMPY | B21: *MAV231000788 | C21: 45957 | D21: $ | E21: 5000000 | G21: PENDIENTE | H21: F G SANITARIOS S R L | I21: =+TODAY()-C21 -> 200 | K21: {=+_xlfn._xlws.SORT(U3:V34,2,-1)} -> SOUTHAMERICAN TRENDY S.A. | L21: 332000000 | M21: =+L21/$L$8 -> 0.0087502063 | O21: =+SUMIF('Reporte de Cheques'!A:A,'Cheques pendientes'!K21,'Reporte de Cheques'!I:I) -> 0 | U21: TRADICION VALORES S.A. | V21: =+SUMIF(H:H,U21,E:E) -> 25000000
A22: AMOMPY | B22: *MAV271000879 | C22: 45959 | D22: $ | E22: 5000000 | G22: PENDIENTE | H22: F G SANITARIOS S R L | I22: =+TODAY()-C22 -> 198 | K22: NIRO CONSTRUYE S. A. | L22: 258370000 | M22: =+L22/$L$8 -> 0.0068096108 | O22: =+SUMIF('Reporte de Cheques'!A:A,'Cheques pendientes'!K22,'Reporte de Cheques'!I:I) -> 0 | U22: Maradona Wines | V22: =+SUMIF(H:H,U22,E:E) -> 119500000
A23: AMOMPY | B23: *MAV301000860 | C23: 45964 | D23: $ | E23: 5000000 | G23: PENDIENTE | H23: F G SANITARIOS S R L | I23: =+TODAY()-C23 -> 193 | K23: FRIGORIFICO H V S A | L23: 215445000 | M23: =+L23/$L$8 -> 0.0056782777 | O23: =+SUMIF('Reporte de Cheques'!A:A,'Cheques pendientes'!K23,'Reporte de Cheques'!I:I) -> 0 | U23: LOPEZ LUCIA SOLEDAD | V23: =+SUMIF(H:H,U23,E:E) -> 995000
A24: AMOMPY | B24: *MAV031100816 | C24: 45966 | D24: $ | E24: 5000000 | G24: PENDIENTE | H24: F G SANITARIOS S R L | I24: =+TODAY()-C24 -> 191 | K24: COOPERATIVA TAMBERA LAS CAÑITAS LIMITADA | L24: 190000000 | M24: =+L24/$L$8 -> 0.0050076482 | O24: =+SUMIF('Reporte de Cheques'!A:A,'Cheques pendientes'!K24,'Reporte de Cheques'!I:I) -> 0 | U24: RABU INVERSIONES SRL | V24: =+SUMIF(H:H,U24,E:E) -> 7194300
A25: AMOMPY | B25: *MAV031100940 | C25: 45966 | D25: $ | E25: 4400000 | G25: PENDIENTE | H25: AKAI ENERGY LED SRL | I25: =+TODAY()-C25 -> 191 | K25: PORT PLA S.R.L. | L25: 150000000 | M25: =+L25/$L$8 -> 0.0039534065 | O25: =+SUMIF('Reporte de Cheques'!A:A,'Cheques pendientes'!K25,'Reporte de Cheques'!I:I) -> 0 | U25: INC SOCIEDAD ANONIMA | V25: =+SUMIF(H:H,U25,E:E) -> 0
A26: AMOMPY | B26: *MAV041100892 | C26: 45968 | D26: $ | E26: 4400000 | G26: PENDIENTE | H26: AKAI ENERGY LED SRL | I26: =+TODAY()-C26 -> 189 | K26: Maradona Wines | L26: 119500000 | M26: =+L26/$L$8 -> 0.0031495471 | O26: =+SUMIF('Reporte de Cheques'!A:A,'Cheques pendientes'!K26,'Reporte de Cheques'!I:I) -> 0 | V26: =+SUMIF(H:H,U26,E:E) -> 0
A27: AMOMPY | B27: *MAV051100567 | C27: 45971 | D27: $ | E27: 25000000 | G27: PENDIENTE | H27: MERCOL RAUL ALBERTO Y MERCOL MAURICIO EDUARDO. | I27: =+TODAY()-C27 -> 186 | K27: EL GUAYMALLEN SA | L27: 113700000 | M27: =+L27/$L$8 -> 0.0029966821 | O27: =+SUMIF('Reporte de Cheques'!A:A,'Cheques pendientes'!K27,'Reporte de Cheques'!I:I) -> 0 | V27: =+SUMIF(H:H,U27,E:E) -> 0
A28: AMOMPY | B28: *MAV051100566 | C28: 45971 | D28: $ | E28: 37500000 | G28: PREVISIONADO | H28: EL GUAYMALLEN SA | I28: =+TODAY()-C28 -> 186 | K28: FRIGORIFICO GENERAL PICO S A | L28: 70000000 | M28: =+L28/$L$8 -> 0.001844923 | O28: =+SUMIF('Reporte de Cheques'!A:A,'Cheques pendientes'!K28,'Reporte de Cheques'!I:I) -> 0 | V28: =+SUMIF(H:H,U28,E:E) -> 0
A29: AMOMPY | B29: *MAV051100722 | C29: 45971 | D29: $ | E29: 4400000 | G29: PENDIENTE | H29: AKAI ENERGY LED SRL | I29: =+TODAY()-C29 -> 186 | K29: MERCOL RAUL ALBERTO Y MERCOL MAURICIO EDUARDO. | L29: 62500000 | M29: =+L29/$L$8 -> 0.0016472527 | O29: =+SUMIF('Reporte de Cheques'!A:A,'Cheques pendientes'!K29,'Reporte de Cheques'!I:I) -> 0 | V29: =+SUMIF(H:H,U29,E:E) -> 0
A30: AMOMPY | B30: *MAV071100935 | C30: 45972 | D30: $ | E30: 4400000 | G30: PENDIENTE | H30: AKAI ENERGY LED SRL | I30: =+TODAY()-C30 -> 185 | K30: FINEX CABA S. A. | L30: 55300000 | M30: =+L30/$L$8 -> 0.0014574892 | O30: =+SUMIF('Reporte de Cheques'!A:A,'Cheques pendientes'!K30,'Reporte de Cheques'!I:I) -> 0 | V30: =+SUMIF(H:H,U30,E:E) -> 0
A31: AMOMPY | B31: *MAV061100646 | C31: 45972 | D31: $ | E31: 5000000 | G31: PENDIENTE | H31: F G SANITARIOS S R L | I31: =+TODAY()-C31 -> 185 | K31: AKAI ENERGY LED SRL | L31: 44963000 | M31: =+L31/$L$8 -> 0.0011850468 | O31: =+SUMIF('Reporte de Cheques'!A:A,'Cheques pendientes'!K31,'Reporte de Cheques'!I:I) -> 0 | V31: =+SUMIF(H:H,U31,E:E) -> 0
A32: AMOMPY | B32: *MAV111100862 | C32: 45974 | D32: $ | E32: 10000000 | G32: PENDIENTE | H32: COOPERATIVA TAMBERA LAS CAÑITAS LIMITADA | I32: =+TODAY()-C32 -> 183 | K32: F G SANITARIOS S R L | L32: 35000000 | M32: =+L32/$L$8 -> 0.00092246151 | O32: =+SUMIF('Reporte de Cheques'!A:A,'Cheques pendientes'!K32,'Reporte de Cheques'!I:I) -> 0 | V32: =+SUMIF(H:H,U32,E:E) -> 0
A33: AMOMPY | B33: *MAV111100857 | C33: 45974 | D33: $ | E33: 10000000 | G33: PENDIENTE | H33: COOPERATIVA TAMBERA LAS CAÑITAS LIMITADA | I33: =+TODAY()-C33 -> 183 | K33: CONEXION SALUD SRL | L33: 27000000 | M33: =+L33/$L$8 -> 0.00071161316 | O33: =+SUMIF('Reporte de Cheques'!A:A,'Cheques pendientes'!K33,'Reporte de Cheques'!I:I) -> 0 | V33: =+SUMIF(H:H,U33,E:E) -> 0
A34: AMOMPY | B34: *MAV111100890 | C34: 45974 | D34: $ | E34: 963000 | G34: PENDIENTE | H34: AKAI ENERGY LED SRL | I34: =+TODAY()-C34 -> 183 | K34: TRADICION VALORES S.A. | L34: 25000000 | M34: =+L34/$L$8 -> 0.00065890108 | O34: =+SUMIF('Reporte de Cheques'!A:A,'Cheques pendientes'!K34,'Reporte de Cheques'!I:I) -> 0 | V34: =+SUMIF(H:H,U34,E:E) -> 0
A35: AMOMPY | B35: *MAV111100854 | C35: 45974 | D35: $ | E35: 10000000 | G35: PENDIENTE | H35: COOPERATIVA TAMBERA LAS CAÑITAS LIMITADA | I35: =+TODAY()-C35 -> 183 | K35: BUNYAR S.R.L. | L35: 24800000 | M35: =+L35/$L$8 -> 0.00065362987 | O35: =+SUMIF('Reporte de Cheques'!A:A,'Cheques pendientes'!K35,'Reporte de Cheques'!I:I) -> 0
A36: AMOMPY | B36: *MAV111100855 | C36: 45974 | D36: $ | E36: 10000000 | G36: PENDIENTE | H36: COOPERATIVA TAMBERA LAS CAÑITAS LIMITADA | I36: =+TODAY()-C36 -> 183 | K36: MASTER DESIGN HOME SRL | L36: 24000000 | M36: =+L36/$L$8 -> 0.00063254503 | O36: =+SUMIF('Reporte de Cheques'!A:A,'Cheques pendientes'!K36,'Reporte de Cheques'!I:I) -> 0
A37: AMOMPY | B37: *MAV111100856 | C37: 45974 | D37: $ | E37: 10000000 | G37: PENDIENTE | H37: COOPERATIVA TAMBERA LAS CAÑITAS LIMITADA | I37: =+TODAY()-C37 -> 183 | K37: GROCAL S.A. | L37: 15000000 | M37: =+L37/$L$8 -> 0.00039534065 | O37: =+SUMIF('Reporte de Cheques'!A:A,'Cheques pendientes'!K37,'Reporte de Cheques'!I:I) -> 0
A38: AMOMPY | B38: *MAV111100858 | C38: 45974 | D38: $ | E38: 10000000 | G38: PENDIENTE | H38: COOPERATIVA TAMBERA LAS CAÑITAS LIMITADA | I38: =+TODAY()-C38 -> 183 | K38: Paccioli Group Sociedad Anonima | L38: 13958000 | M38: =+L38/$L$8 -> 0.00036787765 | O38: =+SUMIF('Reporte de Cheques'!A:A,'Cheques pendientes'!K38,'Reporte de Cheques'!I:I) -> 0
A39: AMOMPY | B39: *MAV111100859 | C39: 45974 | D39: $ | E39: 10000000 | G39: PENDIENTE | H39: COOPERATIVA TAMBERA LAS CAÑITAS LIMITADA | I39: =+TODAY()-C39 -> 183 | K39: RABU INVERSIONES SRL | L39: 7194300 | M39: =+L39/$L$8 -> 0.00018961328 | O39: =+SUMIF('Reporte de Cheques'!A:A,'Cheques pendientes'!K39,'Reporte de Cheques'!I:I) -> 0
A40: AMOMPY | B40: *MAV111100860 | C40: 45974 | D40: $ | E40: 10000000 | G40: PENDIENTE | H40: COOPERATIVA TAMBERA LAS CAÑITAS LIMITADA | I40: =+TODAY()-C40 -> 183 | K40: UKUMARI SOCIEDAD ANONIMA. | L40: 6812500 | M40: =+L40/$L$8 -> 0.00017955054 | O40: =+SUMIF('Reporte de Cheques'!A:A,'Cheques pendientes'!K40,'Reporte de Cheques'!I:I) -> 0
A41: AMOMPY | B41: *MAV111100861 | C41: 45974 | D41: $ | E41: 10000000 | G41: PENDIENTE | H41: COOPERATIVA TAMBERA LAS CAÑITAS LIMITADA | I41: =+TODAY()-C41 -> 183 | K41: MIANI CLARA A Y MIANI ADA CLELIA | L41: 3125000 | M41: =+L41/$L$8 -> 8.2362635e-05 | O41: =+SUMIF('Reporte de Cheques'!A:A,'Cheques pendientes'!K41,'Reporte de Cheques'!I:I) -> 0
A42: AMOMPY | B42: *MAV121100854 | C42: 45975 | D42: $ | E42: 4400000 | G42: PENDIENTE | H42: AKAI ENERGY LED SRL | I42: =+TODAY()-C42 -> 182 | K42: LOPEZ LUCIA SOLEDAD | L42: 995000 | M42: =+L42/$L$8 -> 2.6224263e-05 | O42: =+SUMIF('Reporte de Cheques'!A:A,'Cheques pendientes'!K42,'Reporte de Cheques'!I:I) -> 0
A43: AMOMPY | B43: *MAV121100675 | C43: 45975 | D43: $ | E43: 25000000 | G43: PENDIENTE | H43: MERCOL RAUL ALBERTO Y MERCOL MAURICIO EDUARDO. | I43: =+TODAY()-C43 -> 182 | K43: INC SOCIEDAD ANONIMA | L43: 0 | M43: =+L43/$L$8 -> 0 | O43: =+SUMIF('Reporte de Cheques'!A:A,'Cheques pendientes'!K43,'Reporte de Cheques'!I:I) -> 5.4789531e+08
A44: AMOMPY | B44: *MAV121100674 | C44: 45975 | D44: $ | E44: 37500000 | G44: PREVISIONADO | H44: EL GUAYMALLEN SA | I44: =+TODAY()-C44 -> 182 | K44: 0 | L44: 0 | M44: =+L44/$L$8 -> 0 | O44: =+SUMIF('Reporte de Cheques'!A:A,'Cheques pendientes'!K44,'Reporte de Cheques'!I:I) -> 0
A45: AMOMPY | B45: *MAV141101053 | C45: 45979 | D45: $ | E45: 4400000 | G45: PENDIENTE | H45: AKAI ENERGY LED SRL | I45: =+TODAY()-C45 -> 178 | K45: 0 | L45: 0 | M45: =+L45/$L$8 -> 0 | O45: =+SUMIF('Reporte de Cheques'!A:A,'Cheques pendientes'!K45,'Reporte de Cheques'!I:I) -> 0
A46: AMOMPY | B46: *MAV141101054 | C46: 45979 | D46: $ | E46: 4400000 | G46: PENDIENTE | H46: AKAI ENERGY LED SRL | I46: =+TODAY()-C46 -> 178 | K46: 0 | L46: 0 | M46: =+L46/$L$8 -> 0 | O46: =+SUMIF('Reporte de Cheques'!A:A,'Cheques pendientes'!K46,'Reporte de Cheques'!I:I) -> 0
A47: AMOMPY | B47: *MAV171100932 | C47: 45980 | D47: $ | E47: 4400000 | G47: PENDIENTE | H47: AKAI ENERGY LED SRL | I47: =+TODAY()-C47 -> 177 | K47: 0 | L47: 0 | M47: =+L47/$L$8 -> 0 | O47: =+SUMIF('Reporte de Cheques'!A:A,'Cheques pendientes'!K47,'Reporte de Cheques'!I:I) -> 0
A48: AMOMPY | B48: *MAV151101337 | C48: 45980 | D48: $ | E48: 4400000 | G48: PENDIENTE | H48: AKAI ENERGY LED SRL | I48: =+TODAY()-C48 -> 177 | K48: 0 | L48: 0 | M48: =+L48/$L$8 -> 0 | O48: =+SUMIF('Reporte de Cheques'!A:A,'Cheques pendientes'!K48,'Reporte de Cheques'!I:I) -> 0
A49: AMOMPY | B49: *MAV181100717 | C49: 45981 | D49: $ | E49: 10000000 | G49: PENDIENTE | H49: COOPERATIVA TAMBERA LAS CAÑITAS LIMITADA | I49: =+TODAY()-C49 -> 176 | K49: 0 | L49: 0 | M49: =+L49/$L$8 -> 0 | O49: =+SUMIF('Reporte de Cheques'!A:A,'Cheques pendientes'!K49,'Reporte de Cheques'!I:I) -> 0
A50: AMOMPY | B50: *MAV181100718 | C50: 45981 | D50: $ | E50: 10000000 | G50: PENDIENTE | H50: COOPERATIVA TAMBERA LAS CAÑITAS LIMITADA | I50: =+TODAY()-C50 -> 176 | K50: 0 | L50: 0 | M50: =+L50/$L$8 -> 0 | O50: =+SUMIF('Reporte de Cheques'!A:A,'Cheques pendientes'!K50,'Reporte de Cheques'!I:I) -> 0
A51: AMOMPY | B51: *MAV181100719 | C51: 45981 | D51: $ | E51: 10000000 | G51: PENDIENTE | H51: COOPERATIVA TAMBERA LAS CAÑITAS LIMITADA | I51: =+TODAY()-C51 -> 176 | K51: 0 | L51: 0 | M51: =+L51/$L$8 -> 0 | O51: =+SUMIF('Reporte de Cheques'!A:A,'Cheques pendientes'!K51,'Reporte de Cheques'!I:I) -> 0
A52: AMOMPY | B52: *MAV181100720 | C52: 45981 | D52: $ | E52: 10000000 | G52: PENDIENTE | H52: COOPERATIVA TAMBERA LAS CAÑITAS LIMITADA | I52: =+TODAY()-C52 -> 176 | K52: 0 | L52: 0 | M52: =+L52/$L$8 -> 0 | O52: =+SUMIF('Reporte de Cheques'!A:A,'Cheques pendientes'!K52,'Reporte de Cheques'!I:I) -> 0
A53: AMOMPY | B53: *MAV181100722 | C53: 45981 | D53: $ | E53: 10000000 | G53: PENDIENTE | H53: COOPERATIVA TAMBERA LAS CAÑITAS LIMITADA | I53: =+TODAY()-C53 -> 176
A54: AMOMPY | B54: *MAV181100723 | C54: 45981 | D54: $ | E54: 10000000 | G54: PENDIENTE | H54: COOPERATIVA TAMBERA LAS CAÑITAS LIMITADA | I54: =+TODAY()-C54 -> 176
A55: AMOMPY | B55: *MAV181100724 | C55: 45981 | D55: $ | E55: 10000000 | G55: PENDIENTE | H55: COOPERATIVA TAMBERA LAS CAÑITAS LIMITADA | I55: =+TODAY()-C55 -> 176
A56: AMOMPY | B56: *MAV181100725 | C56: 45981 | D56: $ | E56: 10000000 | G56: PENDIENTE | H56: COOPERATIVA TAMBERA LAS CAÑITAS LIMITADA | I56: =+TODAY()-C56 -> 176
A57: AMOMPY | B57: *MAV181100869 | C57: 45981 | D57: $ | E57: 4400000 | G57: PENDIENTE | H57: AKAI ENERGY LED SRL | I57: =+TODAY()-C57 -> 176
A58: AMOMPY | B58: *MAV181100716 | C58: 45981 | D58: $ | E58: 10000000 | G58: PENDIENTE | H58: COOPERATIVA TAMBERA LAS CAÑITAS LIMITADA | I58: =+TODAY()-C58 -> 176
A59: AMOMPY | B59: *MAV181100773 | C59: 45981 | D59: $ | E59: 20000000 | G59: PENDIENTE | H59: FRIGORIFICO GENERAL PICO S A | I59: =+TODAY()-C59 -> 176
A60: AMOMPY | B60: *MAV181100721 | C60: 45981 | D60: $ | E60: 10000000 | G60: PENDIENTE | H60: COOPERATIVA TAMBERA LAS CAÑITAS LIMITADA | I60: =+TODAY()-C60 -> 176
A61: AMOMPY | B61: *MAV191100661 | C61: 45986 | D61: $ | E61: 20000000 | G61: PENDIENTE | H61: FRIGORIFICO GENERAL PICO S A | I61: =+TODAY()-C61 -> 171
A62: AMOMPY | B62: *MAV201100887 | C62: 45987 | D62: $ | E62: 10000000 | G62: PENDIENTE | H62: FRIGORIFICO GENERAL PICO S A | I62: =+TODAY()-C62 -> 170
A63: AMOMPY | B63: *MAV211100687 | C63: 45988 | D63: $ | E63: 10000000 | G63: PENDIENTE | H63: FRIGORIFICO GENERAL PICO S A | I63: =+TODAY()-C63 -> 169
A64: AMOMPY | B64: *MAV221100992 | C64: 45988 | D64: $ | E64: 10000000 | G64: PENDIENTE | H64: FRIGORIFICO GENERAL PICO S A | I64: =+TODAY()-C64 -> 169
... A119: AMOMPY | B119: *MAV100501303 | C119: 46155 | D119: $ | E119: 5000000 | G119: PENDIENTE | H119: SAN MARCOS TRADING S.A. | I119: =+TODAY()-C119 -> 2

Sheet Concentración
A4: Suma de %
A5: Sociedad de Garantía Recíproca / Librador | B5: Total
A6: CREDICUOTAS CONSUMO SA | B6: 0.050864354
A7: MILLS S.G.R. | B7: 0.044706974
A8: EMOVA MOVILIDAD S.A. | B8: 0.044297684
A9: COOPERATIVA DE VIVIENDA CREDITO Y CONSUMO PARA EL DESARROLLO LIMITADA | B9: 0.043772089
A10: SES SA | B10: 0.038838027
A11: EMPRESA DIST SUR S.A. EDESUR S.A. | B11: 0.03824526
A12: TRANS BOX SRL | B12: 0.031761609
A13: ALLIANCE ONE TOBACCO ARGENTINA | B13: 0.025315676
A14: TARJETA NARANJA SA | B14: 0.025043459
A15: INTEGRA PYMES SGR | B15: 0.023718967
A16: ASOCIACION ATLETICA ARGENTINOS JUNIORS | B16: 0.022789711
A17: Casa Hutton SA | B17: 0.019833211
... A160: Total general | B160: 0.83383783

Sheet Reporte de Cheques
A1: Reporte de Cheques de Pago Diferido | W1: Valor Patrimonial del Fondo
A2: Cheque de Pago Diferido y Pagaré | B2: Moneda | C2: Cheque de Pago Diferido y Pagaré | D2: Fecha | E2: Precio | F2: Tipo de Cambio (Cheque/Fondo) | G2: Moneda Cheque | H2: Moneda Cheque | I2: Moneda Fondo | J2: Moneda Fondo | K2: Compra | L2: Fondo | M2: Compra | N2: Compra | O2: Compra | P2: Compra | Q2: Vendido | R2: Venta | S2: Venta | T2: Venta | U2: Cheque de Pago Diferido y Pagaré | V2: Cheque de Pago Diferido y Pagaré | W2: =+VLOOKUP(W1,'GESTION MOMENTUM'!A:B,2,0) -> 3.7941963e+10
A3: Sociedad de Garantía Recíproca / Librador | B3: Descripción | C3: Fecha de Vencimiento | D3: Fecha | E3: Precio | F3: Tipo de Cambio (Cheque/Fondo) | G3: Importe Nominal | H3: Importe Actual | I3: Importe Nominal | J3: Importe Actual | K3: Nro. de Operación | L3: Nombre | M3: Agente | N3: Fecha Concertación | O3: Fecha Liquidación | P3: Tasa de Descuento | Q3: Vendido | R3: Nro. de Operación | S3: Fecha Concertación | T3: Fecha Liquidación | U3: Abreviatura | V3: Código CAFCI | W3: %
A4: TEXTUM SA | B4: Pesos | C4: 46156 | D4: 14/05/2026 | E4: 1 | G4: 10000000 | H4: 10000000 | I4: 10000000 | J4: 10000000 | K4: 13445369 | L4: AMOMPY | M4: Momentum Capital Investment S.A. | N4: 17/04/2026 | O4: 17/04/2026 | P4: 38 | Q4: No | U4: *MAV120501729 | V4: *MAV120501729 | W4: =+J4/$W$2 -> 0.00026356043
A5: EDITAR SRL | B5: Pesos | C5: 46156 | D5: 14/05/2026 | E5: 1 | G5: 2601958.1 | H5: 2601958.1 | I5: 2601958.1 | J5: 2601958.1 | K5: 123113 | L5: AMOMPY | M5: Momentum Capital Investment S.A. | N5: 17/03/2026 | O5: 17/03/2026 | P5: 43 | Q5: No | U5: *MAV120501493 | V5: *MAV120501493 | W5: =+J5/$W$2 -> 6.857732e-05
A6: TECNOGRAF SA | B6: Pesos | C6: 46156 | D6: 14/05/2026 | E6: 1 | G6: 2778395.1 | H6: 2778395.1 | I6: 2778395.1 | J6: 2778395.1 | K6: 65732098 | L6: AMOMPY | M6: Momentum Capital Investment S.A. | N6: 27/03/2026 | O6: 27/03/2026 | P6: 41 | Q6: No | U6: *MAV120501553 | V6: *MAV120501553 | W6: =+J6/$W$2 -> 7.32275e-05
A7: BROADBANDTECH SA | B7: Pesos | C7: 46156 | D7: 14/05/2026 | E7: 1 | G7: 10000000 | H7: 10000000 | I7: 10000000 | J7: 10000000 | K7: 161 | L7: AMOMPY | M7: Momentum Capital Investment S.A. | N7: 31/03/2026 | O7: 31/03/2026 | P7: 38 | Q7: No | U7: *MAV120501577 | V7: *MAV120501577 | W7: =+J7/$W$2 -> 0.00026356043
A8: PLANTIUM S.A. | B8: Pesos | C8: 46156 | D8: 14/05/2026 | E8: 1 | G8: 5000000 | H8: 5000000 | I8: 5000000 | J8: 5000000 | K8: 60524088 | L8: AMOMPY | M8: Momentum Capital Investment S.A. | N8: 19/03/2026 | O8: 19/03/2026 | P8: 38 | Q8: No | U8: *MAV120501511 | V8: *MAV120501511 | W8: =+J8/$W$2 -> 0.00013178022
A9: PAMPA VIDA S.R.L. | B9: Pesos | C9: 46156 | D9: 14/05/2026 | E9: 1 | G9: 5000000 | H9: 5000000 | I9: 5000000 | J9: 5000000 | K9: 2254 | L9: AMOMPY | M9: Momentum Capital Investment S.A. | N9: 05/03/2026 | O9: 05/03/2026 | P9: 40 | Q9: No | U9: *MAV120501386 | V9: *MAV120501386 | W9: =+J9/$W$2 -> 0.00013178022
A10: MINIGRAF SRL | B10: Pesos | C10: 46156 | D10: 14/05/2026 | E10: 1 | G10: 2714500 | H10: 2714500 | I10: 2714500 | J10: 2714500 | K10: 8838125 | L10: AMOMPY | M10: Momentum Capital Investment S.A. | N10: 17/03/2026 | O10: 17/03/2026 | P10: 43 | Q10: No | U10: *MAV120501494 | V10: *MAV120501494 | W10: =+J10/$W$2 -> 7.1543479e-05
A11: BiBank S.A. | B11: Pesos | C11: 46156 | D11: 14/05/2026 | E11: 1 | G11: 10000000 | H11: 10000000 | I11: 10000000 | J11: 10000000 | K11: 90033755 | L11: AMOMPY | M11: Momentum Capital Investment S.A. | N11: 28/01/2026 | O11: 28/01/2026 | P11: 37 | Q11: No | U11: *BIF120500002 | V11: *BIF120500002 | W11: =+J11/$W$2 -> 0.00026356043
A12: Casa Hutton SA | B12: Pesos | C12: 46156 | D12: 14/05/2026 | E12: 1 | G12: 20000000 | H12: 20000000 | I12: 20000000 | J12: 20000000 | K12: 13237773 | L12: AMOMPY | M12: Momentum Capital Investment S.A. | N12: 03/03/2026 | O12: 03/03/2026 | P12: 43 | Q12: No | U12: *MAV120501374 | V12: *MAV120501374 | W12: =+J12/$W$2 -> 0.00052712086
A13: Movil SGR | B13: Pesos | C13: 46156 | D13: 14/05/2026 | E13: 1 | G13: 1221790.3 | H13: 1221790.3 | I13: 1221790.3 | J13: 1221790.3 | K13: 5719 | L13: AMOMPY | M13: Momentum Capital Investment S.A. | N13: 17/04/2026 | O13: 17/04/2026 | P13: 25 | Q13: No | U13: *MOV120500068 | V13: *MOV120500068 | W13: =+J13/$W$2 -> 3.2201557e-05
A14: Movil SGR | B14: Pesos | C14: 46156 | D14: 14/05/2026 | E14: 1 | G14: 2048050 | H14: 2048050 | I14: 2048050 | J14: 2048050 | K14: 2286 | L14: AMOMPY | M14: Momentum Capital Investment S.A. | N14: 17/04/2026 | O14: 17/04/2026 | P14: 25 | Q14: No | U14: *MOV120500069 | V14: *MOV120500069 | W14: =+J14/$W$2 -> 5.3978494e-05
A15: SA IMP Y EXP DE LA PATAGONIA | B15: Pesos | C15: 46156 | D15: 14/05/2026 | E15: 1 | G15: 86320024 | H15: 86320024 | I15: 86320024 | J15: 86320024 | K15: 304510 | L15: AMOMPY | M15: Momentum Capital Investment S.A. | N15: 17/03/2026 | O15: 17/03/2026 | P15: 43 | Q15: No | U15: *MAV120501495 | V15: *MAV120501495 | W15: =+J15/$W$2 -> 0.0022750543
... A225: I-LED ARGENTINA S.A. | B225: Pesos | C225: 46176 | D225: 14/05/2026 | E225: 0.97960288 | G225: 5450000 | H225: 5338835.7 | I225: 5450000 | J225: 5338835.7 | K225: 28512 | L225: AMOMPY | M225: Momentum Capital Investment S.A. | N225: 08/04/2026 | O225: 08/04/2026 | P225: 38 | Q225: No | U225: *MAV300501529 | V225: *MAV300501529 | W225: =+J225/$W$2 -> 0.00014071058
A226: DEMAGRO SRL | B226: Dolar 3500 | C226: 46176 | D226: 14/05/2026 | E226: 0.99455018 | F226: 1 US3 = 1393,2322905547 $ | G226: 40000 | H226: 39782.01 | I226: 55729292 | J226: 55425581 | K226: 137080 | L226: AMOMPY | M226: Momentum Capital Investment S.A. | N226: 20/01/2026 | O226: 20/01/2026 | P226: 10 | Q226: No | U226: #UMV010660043 | V226: #UMV010660043 | W226: =+J226/$W$2 -> 0.001460799
A227: DANBURY S. A | B227: Pesos | C227: 46176 | D227: 14/05/2026 | E227: 0.97855241 | G227: 39425781 | H227: 38580193 | I227: 39425781 | J227: 38580193 | K227: 66111089 | L227: AMOMPY | M227: Momentum Capital Investment S.A. | N227: 09/04/2026 | O227: 09/04/2026 | P227: 40 | Q227: No | U227: *MAV310501403 | V227: *MAV310501403 | W227: =+J227/$W$2 -> 0.0010168212
A228: DANBURY S. A | B228: Pesos | C228: 46176 | D228: 14/05/2026 | E228: 0.97855241 | G228: 6273580.8 | H228: 6139027.6 | I228: 6273580.8 | J228: 6139027.6 | K228: 66111090 | L228: AMOMPY | M228: Momentum Capital Investment S.A. | N228: 09/04/2026 | O228: 09/04/2026 | P228: 40 | Q228: No | U228: *MAV310501404 | V228: *MAV310501404 | W228: =+J228/$W$2 -> 0.00016180048
A229: AVAL FEDERAL S.G.R. | B229: Pesos | C229: 46176 | D229: 14/05/2026 | E229: 0.98435827 | G229: 30000000 | H229: 29530748 | I229: 30000000 | J229: 29530748 | K229: 90041865 | L229: AMOMPY | M229: Momentum Capital Investment S.A. | N229: 20/04/2026 | O229: 20/04/2026 | P229: 29 | Q229: No | U229: *FED310500139 | V229: *FED310500139 | W229: =+J229/$W$2 -> 0.00077831366
A230: INTEGRA PYMES SGR | B230: Pesos | C230: 46176 | D230: 14/05/2026 | E230: 0.98542127 | G230: 15200000 | H230: 14978403 | I230: 15200000 | J230: 14978403 | K230: 2597 | L230: AMOMPY | M230: Momentum Capital Investment S.A. | N230: 30/04/2026 | O230: 30/04/2026 | P230: 27 | Q230: No | U230: *INP010600019 | V230: *INP010600019 | W230: =+J230/$W$2 -> 0.00039477144
A231: DROGUERIA GARZON SA | B231: Pesos | C231: 46176 | D231: 14/05/2026 | E231: 0.97750404 | G231: 6582395.2 | H231: 6434317.9 | I231: 6582395.2 | J231: 6434317.9 | K231: 5077 | L231: AMOMPY | M231: Momentum Capital Investment S.A. | N231: 17/04/2026 | O231: 17/04/2026 | P231: 42 | Q231: No | U231: *MAV010600936 | V231: *MAV010600936 | W231: =+J231/$W$2 -> 0.00016958316
A232: QUILMES | B232: Pesos | C232: 46176 | D232: 14/05/2026 | E232: 0.98595356 | G232: 7166689.8 | H232: 7066023.3 | I232: 7166689.8 | J232: 7066023.3 | K232: 40011392 | L232: AMOMPY | M232: Momentum Capital Investment S.A. | N232: 10/04/2026 | O232: 10/04/2026 | P232: 26 | Q232: No | U232: *MAV010600896 | V232: *MAV010600896 | W232: =+J232/$W$2 -> 0.00018623241
A233: CUYO AVAL SGR | B233: Pesos | C233: 46176 | D233: 14/05/2026 | E233: 0.98488951 | G233: 8000000 | H233: 7879116.1 | I233: 8000000 | J233: 7879116.1 | K233: 6034637 | L233: AMOMPY | M233: Momentum Capital Investment S.A. | N233: 04/05/2026 | O233: 04/05/2026 | P233: 28 | Q233: No | U233: *CUY010600023 | V233: *CUY010600023 | W233: =+J233/$W$2 -> 0.00020766232
A234: Movil SGR | B234: Pesos | C234: 46176 | D234: 14/05/2026 | E234: 0.9864865 | G234: 696309 | H234: 686899.43 | I234: 696309 | J234: 686899.43 | K234: 18103474 | L234: AMOMPY | M234: Momentum Capital Investment S.A. | N234: 17/04/2026 | O234: 17/04/2026 | P234: 25 | Q234: No | U234: *MOV310500086 | V234: *MOV310500086 | W234: =+J234/$W$2 -> 1.8103951e-05
A235: DOS MATES SA | B235: Pesos | C235: 46176 | D235: 14/05/2026 | E235: 0.98276798 | G235: 45748280 | H235: 44959944 | I235: 45748280 | J235: 44959944 | K235: 7723 | L235: AMOMPY | M235: Momentum Capital Investment S.A. | N235: 13/05/2026 | O235: 13/05/2026 | P235: 32 | Q235: No | U235: *MAV010601240 | V235: *MAV010601240 | W235: =+J235/$W$2 -> 0.0011849662
A236: DOS MATES SA | B236: Pesos | C236: 46176 | D236: 14/05/2026 | E236: 0.98276798 | G236: 45748280 | H236: 44959944 | I236: 45748280 | J236: 44959944 | K236: 8911 | L236: AMOMPY | M236: Momentum Capital Investment S.A. | N236: 13/05/2026 | O236: 13/05/2026 | P236: 32 | Q236: No | U236: *MAV010601241 | V236: *MAV010601241 | W236: =+J236/$W$2 -> 0.0011849662
A237: CELULOSA CAMPANA SA | B237: Pesos | C237: 46176 | D237: 14/05/2026 | E237: 0.97802796 | G237: 10918372 | H237: 10678473 | I237: 10918372 | J237: 10678473 | K237: 30447 | L237: AMOMPY | M237: Momentum Capital Investment S.A. | N237: 01/04/2026 | O237: 01/04/2026 | P237: 41 | Q237: No | U237: *MAV010600842 | V237: *MAV010600842 | W237: =+J237/$W$2 -> 0.00028144229
A238: CELULOSA CAMPANA SA | B238: Pesos | C238: 46176 | D238: 14/05/2026 | E238: 0.97802796 | G238: 11171160 | H238: 10925706 | I238: 11171160 | J238: 10925706 | K238: 30370 | L238: AMOMPY | M238: Momentum Capital Investment S.A. | N238: 01/04/2026 | O238: 01/04/2026 | P238: 41 | Q238: No | U238: *MAV010600843 | V238: *MAV010600843 | W238: =+J238/$W$2 -> 0.00028795839
... A598: DEMAGRO SRL | B598: Pesos | C598: 46206 | D598: 14/05/2026 | E598: 0.95052099 | G598: 22500000 | H598: 21386722 | I598: 22500000 | J598: 21386722 | K598: 65800963 | L598: AMOMPY | M598: Momentum Capital Investment S.A. | N598: 26/03/2026 | O598: 26/03/2026 | P598: 38 | Q598: No | U598: *MAV010701039 | V598: *MAV010701039 | W598: =+J598/$W$2 -> 0.00056366937
A599: DEMAGRO SRL | B599: Dolar 3500 | C599: 46206 | D599: 14/05/2026 | E599: 0.98648655 | F599: 1 US3 = 1393,2322905547 $ | G599: 50000 | H599: 49324.33 | I599: 69661615 | J599: 68720249 | K599: 142720 | L599: AMOMPY | M599: Momentum Capital Investment S.A. | N599: 12/03/2026 | O599: 12/03/2026 | P599: 10 | Q599: No | U599: #UMV010760033 | V599: #UMV010760033 | W599: =+J599/$W$2 -> 0.0018111938
A600: BSP LARTI SA | B600: Dolar 3500 | C600: 46206 | D600: 14/05/2026 | E600: 0.98648635 | F600: 1 US3 = 1393,2322905547 $ | G600: 50000 | H600: 49324.32 | I600: 69661615 | J600: 68720235 | K600: 141980 | L600: AMOMPY | M600: Momentum Capital Investment S.A. | N600: 05/03/2026 | O600: 05/03/2026 | P600: 10 | Q600: No | U600: #UMV010760032 | V600: #UMV010760032 | W600: =+J600/$W$2 -> 0.0018111935
A601: BSP LARTI SA | B601: Dolar 3500 | C601: 46206 | D601: 14/05/2026 | E601: 0.98782135 | F601: 1 US3 = 1393,2322905547 $ | G601: 50000 | H601: 49391.07 | I601: 69661615 | J601: 68813234 | K601: 144915 | L601: AMOMPY | M601: Momentum Capital Investment S.A. | N601: 01/04/2026 | O601: 01/04/2026 | P601: 9 | Q601: No | U601: #UMV010760034 | V601: #UMV010760034 | W601: =+J601/$W$2 -> 0.0018136445
A602: AVAL AR SGR | B602: Pesos | C602: 46206 | D602: 14/05/2026 | E602: 0.96179187 | G602: 15000000 | H602: 14426878 | I602: 15000000 | J602: 14426878 | K602: 801 | L602: AMOMPY | M602: Momentum Capital Investment S.A. | N602: 31/03/2026 | O602: 31/03/2026 | P602: 29 | Q602: No | U602: *AAR010700018 | V602: *AAR010700018 | W602: =+J602/$W$2 -> 0.00038023542
A603: AVAL AR SGR | B603: Pesos | C603: 46206 | D603: 14/05/2026 | E603: 0.96179187 | G603: 12500000 | H603: 12022398 | I603: 12500000 | J603: 12022398 | K603: 28996520 | L603: AMOMPY | M603: Momentum Capital Investment S.A. | N603: 31/03/2026 | O603: 31/03/2026 | P603: 29 | Q603: No | U603: *AAR010700017 | V603: *AAR010700017 | W603: =+J603/$W$2 -> 0.00031686285
A604: VITALCAN S.A. | B604: Pesos | C604: 46206 | D604: 14/05/2026 | E604: 0.95176015 | G604: 100000000 | H604: 95176015 | I604: 100000000 | J604: 95176015 | K604: 7353 | L604: AMOMPY | M604: Momentum Capital Investment S.A. | N604: 31/03/2026 | O604: 31/03/2026 | P604: 37 | Q604: No | U604: *MAV010701052 | V604: *MAV010701052 | W604: =+J604/$W$2 -> 0.0025084631
A605: INTEGRA PYMES SGR | B605: Pesos | C605: 46206 | D605: 14/05/2026 | E605: 0.96179193 | G605: 5000000 | H605: 4808959.6 | I605: 5000000 | J605: 4808959.6 | K605: 16779597 | L605: AMOMPY | M605: Momentum Capital Investment S.A. | N605: 30/04/2026 | O605: 30/04/2026 | P605: 29 | Q605: No | U605: *INP010700054 | V605: *INP010700054 | W605: =+J605/$W$2 -> 0.00012674515
A606: BiBank S.A. | B606: Pesos | C606: 46206 | D606: 14/05/2026 | E606: 0.96306079 | G606: 500000000 | H606: 4.8153039e+08 | I606: 500000000 | J606: 4.8153039e+08 | K606: 147165 | L606: AMOMPY | M606: Momentum Capital Investment S.A. | N606: 23/04/2026 | O606: 23/04/2026 | P606: 28 | Q606: No | U606: #INT020760001 | V606: #INT020760001 | W606: =+J606/$W$2 -> 0.012691236
A607: MILLS S.G.R. | B607: Pesos | C607: 46206 | D607: 14/05/2026 | E607: 0.96433301 | G607: 10000000 | H607: 9643330.1 | I607: 10000000 | J607: 9643330.1 | K607: 32529 | L607: AMOMPY | M607: Momentum Capital Investment S.A. | N607: 27/04/2026 | O607: 27/04/2026 | P607: 27 | Q607: No | U607: *MIL010700023 | V607: *MIL010700023 | W607: =+J607/$W$2 -> 0.00025416002
A608: METALFOR SA | B608: Pesos | C608: 46206 | D608: 14/05/2026 | E608: 0.95300267 | G608: 16500000 | H608: 15724544 | I608: 16500000 | J608: 15724544 | K608: 32225 | L608: AMOMPY | M608: Momentum Capital Investment S.A. | N608: 22/04/2026 | O608: 22/04/2026 | P608: 36 | Q608: No | U608: *MAV010701100 | V608: *MAV010701100 | W608: =+J608/$W$2 -> 0.00041443676
A609: ALLIANCE ONE TOBACCO ARGENTINA | B609: Pesos | C609: 46206 | D609: 14/05/2026 | E609: 0.96052642 | G609: 1000000000 | H609: 9.6052642e+08 | I609: 1000000000 | J609: 9.6052642e+08 | K609: 147160 | L609: AMOMPY | M609: Momentum Capital Investment S.A. | N609: 23/04/2026 | O609: 23/04/2026 | P609: 30 | Q609: No | U609: #MAV020760016 | V609: #MAV020760016 | W609: =+J609/$W$2 -> 0.025315676
A610: DESDE EL MAR S.A. | B610: Pesos | C610: 46209 | D610: 14/05/2026 | E610: 0.95163627 | G610: 2000000 | H610: 1903272.5 | I610: 2000000 | J610: 1903272.5 | K610: 7745 | L610: AMOMPY | M610: Momentum Capital Investment S.A. | N610: 08/05/2026 | O610: 08/05/2026 | P610: 35 | Q610: No | U610: *MAV020700893 | V610: *MAV020700893 | W610: =+J610/$W$2 -> 5.0162733e-05
A611: COOPERATIVA DE VIVIENDA CREDITO Y CONSUMO PARA EL DESARROLLO LIMITADA | B611: Pesos | C611: 46209 | D611: 14/05/2026 | E611: 0.95692526 | G611: 42000000 | H611: 40190861 | I611: 42000000 | J611: 40190861 | K611: 148257 | L611: AMOMPY | M611: Momentum Capital Investment S.A. | N611: 05/05/2026 | O611: 05/05/2026 | P611: 31 | Q611: No | U611: #MAV030760052 | V611: #MAV030760052 | W611: =+J611/$W$2 -> 0.0010592721
A612: CAMPO AVAL SGR | B612: Pesos | C612: 46209 | D612: 14/05/2026 | E612: 0.96362007 | G612: 10000000 | H612: 9636200.7 | I612: 10000000 | J612: 9636200.7 | K612: 1742541 | L612: AMOMPY | M612: Momentum Capital Investment S.A. | N612: 21/04/2026 | O612: 21/04/2026 | P612: 26 | Q612: No | U612: *CMP020700021 | V612: *CMP020700021 | W612: =+J612/$W$2 -> 0.00025397212
A613: AVAL AR SGR | B613: Pesos | C613: 46209 | D613: 14/05/2026 | E613: 0.95959204 | G613: 15000000 | H613: 14393881 | I613: 15000000 | J613: 14393881 | K613: 802 | L613: AMOMPY | M613: Momentum Capital Investment S.A. | N613: 31/03/2026 | O613: 31/03/2026 | P613: 29 | Q613: No | U613: *AAR020700017 | V613: *AAR020700017 | W613: =+J613/$W$2 -> 0.00037936574
... A866: GEOPOLIS SA | B866: Pesos | C866: 46239 | D866: 14/05/2026 | E866: 0.9204622 | G866: 2398145.2 | H866: 2207402 | I866: 2398145.2 | J866: 2207402 | K866: 13270644 | L866: AMOMPY | M866: Momentum Capital Investment S.A. | N866: 24/04/2026 | O866: 24/04/2026 | P866: 38 | Q866: No | U866: *MAV030800739 | V866: *MAV030800739 | W866: =+J866/$W$2 -> 5.8178383e-05
A867: BSP LARTI SA | B867: Dolar 3500 | C867: 46239 | D867: 14/05/2026 | E867: 0.97994473 | F867: 1 US3 = 1393,2322905547 $ | G867: 50000 | H867: 48997.24 | I867: 69661615 | J867: 68264537 | K867: 144917 | L867: AMOMPY | M867: Momentum Capital Investment S.A. | N867: 01/04/2026 | O867: 01/04/2026 | P867: 9 | Q867: No | U867: #UMV030860028 | V867: #UMV030860028 | W867: =+J867/$W$2 -> 0.0017991831
A868: BSP LARTI SA | B868: Dolar 3500 | C868: 46239 | D868: 14/05/2026 | E868: 0.98213337 | F868: 1 US3 = 1393,2322905547 $ | G868: 50000 | H868: 49106.67 | I868: 69661615 | J868: 68416998 | K868: 144506 | L868: AMOMPY | M868: Momentum Capital Investment S.A. | N868: 30/03/2026 | O868: 30/03/2026 | P868: 8 | Q868: No | U868: #UMV030860027 | V868: #UMV030860027 | W868: =+J868/$W$2 -> 0.0018032014
A869: COOPERATIVA DE TABACALEROS DE JUJUY LTDA | B869: Dolar 3500 | C869: 46239 | D869: 14/05/2026 | E869: 0.98433168 | F869: 1 US3 = 1393,2322905547 $ | G869: 100000 | H869: 98433.17 | I869: 1.3932323e+08 | J869: 1.3714027e+08 | K869: 147169 | L869: AMOMPY | M869: Momentum Capital Investment S.A. | N869: 23/04/2026 | O869: 23/04/2026 | P869: 7 | Q869: No | U869: #UMV030860029 | V869: #UMV030860029 | W869: =+J869/$W$2 -> 0.0036144749
A870: AVAL FEDERAL S.G.R. | B870: Pesos | C870: 46239 | D870: 14/05/2026 | E870: 0.93613764 | G870: 8500000 | H870: 7957170 | I870: 8500000 | J870: 7957170 | K870: 1070 | L870: AMOMPY | M870: Momentum Capital Investment S.A. | N870: 17/04/2026 | O870: 17/04/2026 | P870: 30 | Q870: No | U870: *FED030800023 | V870: *FED030800023 | W870: =+J870/$W$2 -> 0.00020971951
A871: AVAL FEDERAL S.G.R. | B871: Pesos | C871: 46239 | D871: 14/05/2026 | E871: 0.93613764 | G871: 10000000 | H871: 9361376.4 | I871: 10000000 | J871: 9361376.4 | K871: 40621855 | L871: AMOMPY | M871: Momentum Capital Investment S.A. | N871: 17/04/2026 | O871: 17/04/2026 | P871: 30 | Q871: No | U871: *FED030800024 | V871: *FED030800024 | W871: =+J871/$W$2 -> 0.00024672884
A872: LAGAVULIN S.A. | B872: Pesos | C872: 46239 | D872: 14/05/2026 | E872: 0.93019728 | G872: 50000000 | H872: 46509864 | I872: 50000000 | J872: 46509864 | K872: 136 | L872: AMOMPY | M872: Momentum Capital Investment S.A. | N872: 13/05/2026 | O872: 13/05/2026 | P872: 33 | Q872: No | U872: *MAV030800838 | V872: *MAV030800838 | W872: =+J872/$W$2 -> 0.001225816
A873: INTEGRA PYMES SGR | B873: Pesos | C873: 46239 | D873: 14/05/2026 | E873: 0.93613766 | G873: 15000000 | H873: 14042065 | I873: 15000000 | J873: 14042065 | K873: 90000127 | L873: AMOMPY | M873: Momentum Capital Investment S.A. | N873: 05/05/2026 | O873: 05/05/2026 | P873: 30 | Q873: No | U873: *INP030800027 | V873: *INP030800027 | W873: =+J873/$W$2 -> 0.00037009327
A874: MILLS S.G.R. | B874: Pesos | C874: 46239 | D874: 14/05/2026 | E874: 0.93813462 | G874: 4166666.7 | H874: 3908894.2 | I874: 4166666.7 | J874: 3908894.2 | K874: 13567710 | L874: AMOMPY | M874: Momentum Capital Investment S.A. | N874: 30/04/2026 | O874: 30/04/2026 | P874: 29 | Q874: No | U874: *MIL020800023 | V874: *MIL020800023 | W874: =+J874/$W$2 -> 0.00010302298
A875: MILLS S.G.R. | B875: Pesos | C875: 46239 | D875: 14/05/2026 | E875: 0.93813469 | G875: 12500000 | H875: 11726684 | I875: 12500000 | J875: 11726684 | K875: 4955 | L875: AMOMPY | M875: Momentum Capital Investment S.A. | N875: 24/04/2026 | O875: 24/04/2026 | P875: 29 | Q875: No | U875: *MIL010800019 | V875: *MIL010800019 | W875: =+J875/$W$2 -> 0.00030906898
A876: LOS GROBO SGR | B876: Pesos | C876: 46239 | D876: 14/05/2026 | E876: 0.94215432 | G876: 6060681.8 | H876: 5710097.5 | I876: 6060681.8 | J876: 5710097.5 | K876: 66717853 | L876: AMOMPY | M876: Momentum Capital Investment S.A. | N876: 06/05/2026 | O876: 06/05/2026 | P876: 27 | Q876: No | U876: *PRO030800006 | V876: *PRO030800006 | W876: =+J876/$W$2 -> 0.00015049558
A877: CUYO AVAL SGR | B877: Pesos | C877: 46239 | D877: 14/05/2026 | E877: 0.94014023 | G877: 6500000 | H877: 6110911.5 | I877: 6500000 | J877: 6110911.5 | K877: 29175491 | L877: AMOMPY | M877: Momentum Capital Investment S.A. | N877: 04/05/2026 | O877: 04/05/2026 | P877: 28 | Q877: No | U877: *CUY030800022 | V877: *CUY030800022 | W877: =+J877/$W$2 -> 0.00016105945
A878: METALFOR SA | B878: Pesos | C878: 46239 | D878: 14/05/2026 | E878: 0.92433148 | G878: 16800000 | H878: 15528769 | I878: 16800000 | J878: 15528769 | K878: 32600 | L878: AMOMPY | M878: Momentum Capital Investment S.A. | N878: 29/04/2026 | O878: 29/04/2026 | P878: 36 | Q878: No | U878: *MAV030800746 | V878: *MAV030800746 | W878: =+J878/$W$2 -> 0.0004092769
A879: AVAL FEDERAL S.G.R. | B879: Pesos | C879: 46240 | D879: 14/05/2026 | E879: 0.93541785 | G879: 8500000 | H879: 7951051.7 | I879: 8500000 | J879: 7951051.7 | K879: 1075 | L879: AMOMPY | M879: Momentum Capital Investment S.A. | N879: 17/04/2026 | O879: 17/04/2026 | P879: 30 | Q879: No | U879: *FED040800020 | V879: *FED040800020 | W879: =+J879/$W$2 -> 0.00020955826
A880: AVAL FEDERAL S.G.R. | B880: Pesos | C880: 46240 | D880: 14/05/2026 | E880: 0.93541785 | G880: 10000000 | H880: 9354178.5 | I880: 10000000 | J880: 9354178.5 | K880: 40621856 | L880: AMOMPY | M880: Momentum Capital Investment S.A. | N880: 17/04/2026 | O880: 17/04/2026 | P880: 30 | Q880: No | U880: *FED040800021 | V880: *FED040800021 | W880: =+J880/$W$2 -> 0.00024653913
A881: TREND SGR | B881: Pesos | C881: 46240 | D881: 14/05/2026 | E881: 0.93946276 | G881: 25000000 | H881: 23486569 | I881: 25000000 | J881: 23486569 | K881: 896 | L881: AMOMPY | M881: Momentum Capital Investment S.A. | N881: 22/04/2026 | O881: 22/04/2026 | P881: 28 | Q881: No | U881: *TRD040800019 | V881: *TRD040800019 | W881: =+J881/$W$2 -> 0.00061901303
... A1035: ACERIAS 4 C SA | B1035: Pesos | C1035: 46268 | D1035: 14/05/2026 | E1035: 0.89067854 | G1035: 9972890.6 | H1035: 8882639.6 | I1035: 9972890.6 | J1035: 8882639.6 | K1035: 1179208 | L1035: AMOMPY | M1035: Momentum Capital Investment S.A. | N1035: 16/04/2026 | O1035: 16/04/2026 | P1035: 40 | Q1035: No | U1035: *MAV010901130 | V1035: *MAV010901130 | W1035: =+J1035/$W$2 -> 0.00023411123
A1036: COOPERATIVA DE TABACALEROS DE JUJUY LTDA | B1036: Dolar 3500 | C1036: 46268 | D1036: 14/05/2026 | E1036: 0.97897227 | F1036: 1 US3 = 1393,2322905547 $ | G1036: 100000 | H1036: 97897.23 | I1036: 1.3932323e+08 | J1036: 1.3639358e+08 | K1036: 147170 | L1036: AMOMPY | M1036: Momentum Capital Investment S.A. | N1036: 23/04/2026 | O1036: 23/04/2026 | P1036: 7 | Q1036: No | U1036: #UMV010960009 | V1036: #UMV010960009 | W1036: =+J1036/$W$2 -> 0.0035947951
A1037: CASSAB HNOS S.R.L. | B1037: Pesos | C1037: 46269 | D1037: 14/05/2026 | E1037: 0.88981 | G1037: 15166667 | H1037: 13495452 | I1037: 15166667 | J1037: 13495452 | K1037: 90020551 | L1037: AMOMPY | M1037: Momentum Capital Investment S.A. | N1037: 12/05/2026 | O1037: 12/05/2026 | P1037: 40 | Q1037: No | U1037: *MAV020901153 | V1037: *MAV020901153 | W1037: =+J1037/$W$2 -> 0.00035568671
A1038: INTEGRA PYMES SGR | B1038: Pesos | C1038: 46269 | D1038: 14/05/2026 | E1038: 0.91501634 | G1038: 5000000 | H1038: 4575081.7 | I1038: 5000000 | J1038: 4575081.7 | K1038: 58 | L1038: AMOMPY | M1038: Momentum Capital Investment S.A. | N1038: 30/04/2026 | O1038: 30/04/2026 | P1038: 30 | Q1038: No | U1038: *INP020900036 | V1038: *INP020900036 | W1038: =+J1038/$W$2 -> 0.00012058105
A1039: MILLS S.G.R. | B1039: Pesos | C1039: 46269 | D1039: 14/05/2026 | E1039: 0.91761575 | G1039: 10000000 | H1039: 9176157.5 | I1039: 10000000 | J1039: 9176157.5 | K1039: 66613066 | L1039: AMOMPY | M1039: Momentum Capital Investment S.A. | N1039: 30/04/2026 | O1039: 30/04/2026 | P1039: 29 | Q1039: No | U1039: *MIL020900026 | V1039: *MIL020900026 | W1039: =+J1039/$W$2 -> 0.0002418472
A1040: TALLERES METALURGICOS CRUCIANELLI SA | B1040: Pesos | C1040: 46269 | D1040: 14/05/2026 | E1040: 0.90223724 | G1040: 16600000 | H1040: 14977138 | I1040: 16600000 | J1040: 14977138 | K1040: 29088027 | L1040: AMOMPY | M1040: Momentum Capital Investment S.A. | N1040: 14/04/2026 | O1040: 14/04/2026 | P1040: 35 | Q1040: No | U1040: *MAV020901140 | V1040: *MAV020901140 | W1040: =+J1040/$W$2 -> 0.0003947381
A1041: LOGICA CONSULTING GROUP SAU | B1041: Pesos | C1041: 46272 | D1041: 14/05/2026 | E1041: 0.89224621 | G1041: 4957711.8 | H1041: 4423499.5 | I1041: 4957711.8 | J1041: 4423499.5 | K1041: 598 | L1041: AMOMPY | M1041: Momentum Capital Investment S.A. | N1041: 24/04/2026 | O1041: 24/04/2026 | P1041: 38 | Q1041: No | U1041: *MAV030900796 | V1041: *MAV030900796 | W1041: =+J1041/$W$2 -> 0.00011658594
A1042: CONSTRUCCIONES S&C SAS | B1042: Pesos | C1042: 46273 | D1042: 14/05/2026 | E1042: 0.8914182 | G1042: 7162509.2 | H1042: 6384791 | I1042: 7162509.2 | J1042: 6384791 | K1042: 65964541 | L1042: AMOMPY | M1042: Momentum Capital Investment S.A. | N1042: 22/04/2026 | O1042: 22/04/2026 | P1042: 38 | Q1042: No | U1042: *MAV040900869 | V1042: *MAV040900869 | W1042: =+J1042/$W$2 -> 0.00016827783
A1043: CASSAB HNOS S.R.L. | B1043: Pesos | C1043: 46273 | D1043: 14/05/2026 | E1043: 0.88635272 | G1043: 12166667 | H1043: 10783958 | I1043: 12166667 | J1043: 10783958 | K1043: 90020552 | L1043: AMOMPY | M1043: Momentum Capital Investment S.A. | N1043: 12/05/2026 | O1043: 12/05/2026 | P1043: 40 | Q1043: No | U1043: *MAV040900876 | V1043: *MAV040900876 | W1043: =+J1043/$W$2 -> 0.00028422247
A1044: INTEGRA PYMES SGR | B1044: Pesos | C1044: 46273 | D1044: 14/05/2026 | E1044: 0.91494751 | G1044: 11923077 | H1044: 10908990 | I1044: 11923077 | J1044: 10908990 | K1044: 90021986 | L1044: AMOMPY | M1044: Momentum Capital Investment S.A. | N1044: 30/04/2026 | O1044: 30/04/2026 | P1044: 29 | Q1044: No | U1044: *NEU040900012 | V1044: *NEU040900012 | W1044: =+J1044/$W$2 -> 0.0002875178
A1045: MILLS S.G.R. | B1045: Pesos | C1045: 46273 | D1045: 14/05/2026 | E1045: 0.91227204 | G1045: 60000000 | H1045: 54736323 | I1045: 60000000 | J1045: 54736323 | K1045: 61 | L1045: AMOMPY | M1045: Momentum Capital Investment S.A. | N1045: 05/05/2026 | O1045: 05/05/2026 | P1045: 30 | Q1045: No | U1045: *MIL040900020 | V1045: *MIL040900020 | W1045: =+J1045/$W$2 -> 0.0014426329
A1046: MILLS S.G.R. | B1046: Pesos | C1046: 46273 | D1046: 14/05/2026 | E1046: 0.91494751 | G1046: 10000000 | H1046: 9149475.1 | I1046: 10000000 | J1046: 9149475.1 | K1046: 66613291 | L1046: AMOMPY | M1046: Momentum Capital Investment S.A. | N1046: 30/04/2026 | O1046: 30/04/2026 | P1046: 29 | Q1046: No | U1046: *MIL040900019 | V1046: *MIL040900019 | W1046: =+J1046/$W$2 -> 0.00024114396
A1047: CONAVAL SGR | B1047: Pesos | C1047: 46273 | D1047: 14/05/2026 | E1047: 0.91227204 | G1047: 24000000 | H1047: 21894529 | I1047: 24000000 | J1047: 21894529 | K1047: 718980 | L1047: AMOMPY | M1047: Momentum Capital Investment S.A. | N1047: 17/04/2026 | O1047: 17/04/2026 | P1047: 30 | Q1047: No | U1047: *CVA040900007 | V1047: *CVA040900007 | W1047: =+J1047/$W$2 -> 0.00057705315
A1048: Movil SGR | B1048: Pesos | C1048: 46273 | D1048: 14/05/2026 | E1048: 0.9176389 | G1048: 10000000 | H1048: 9176389 | I1048: 10000000 | J1048: 9176389 | K1048: 360562 | L1048: AMOMPY | M1048: Momentum Capital Investment S.A. | N1048: 21/04/2026 | O1048: 21/04/2026 | P1048: 28 | Q1048: No | U1048: *MOV040900048 | V1048: *MOV040900048 | W1048: =+J1048/$W$2 -> 0.0002418533
... A1122: Movil SGR | B1122: Pesos | C1122: 46310 | D1122: 14/05/2026 | E1122: 0.8943449 | G1122: 25000000 | H1122: 22358622 | I1122: 25000000 | J1122: 22358622 | K1122: 360571 | L1122: AMOMPY | M1122: Momentum Capital Investment S.A. | N1122: 21/04/2026 | O1122: 21/04/2026 | P1122: 28 | Q1122: No | U1122: *MOV131000082 | V1122: *MOV131000082 | W1122: =+J1122/$W$2 -> 0.00058928482
A1123: PUNTO PACK SRL | B1123: Dolar 3500 | C1123: 46311 | D1123: 14/05/2026 | E1123: 0.96714244 | F1123: 1 US3 = 1393,2322905547 $ | G1123: 18230 | H1123: 17631.01 | I1123: 25398625 | J1123: 24564092 | K1123: 146445 | L1123: AMOMPY | M1123: Momentum Capital Investment S.A. | N1123: 17/04/2026 | O1123: 17/04/2026 | P1123: 8 | Q1123: No | U1123: #UMV141060033 | V1123: #UMV141060033 | W1123: =+J1123/$W$2 -> 0.00064741228
A1124: REGCEN S.R.L. | B1124: Pesos | C1124: 46311 | D1124: 14/05/2026 | E1124: 0.85791522 | G1124: 3750000 | H1124: 3217182.1 | I1124: 3750000 | J1124: 3217182.1 | K1124: 66920206 | L1124: AMOMPY | M1124: Momentum Capital Investment S.A. | N1124: 13/05/2026 | O1124: 13/05/2026 | P1124: 39 | Q1124: No | U1124: *MAV141001310 | V1124: *MAV141001310 | W1124: =+J1124/$W$2 -> 8.4792189e-05
A1125: REGCEN S.R.L. | B1125: Pesos | C1125: 46314 | D1125: 14/05/2026 | E1125: 0.85556245 | G1125: 3750000 | H1125: 3208359.2 | I1125: 3750000 | J1125: 3208359.2 | K1125: 66917997 | L1125: AMOMPY | M1125: Momentum Capital Investment S.A. | N1125: 13/05/2026 | O1125: 13/05/2026 | P1125: 39 | Q1125: No | U1125: *MAV151001351 | V1125: *MAV151001351 | W1125: =+J1125/$W$2 -> 8.4559653e-05
A1126: LW GROUP SRL | B1126: Pesos | C1126: 46314 | D1126: 14/05/2026 | E1126: 0.86842754 | G1126: 1500000 | H1126: 1302641.3 | I1126: 1500000 | J1126: 1302641.3 | K1126: 4 | L1126: AMOMPY | M1126: Momentum Capital Investment S.A. | N1126: 23/04/2026 | O1126: 23/04/2026 | P1126: 35 | Q1126: No | U1126: *MAV151001338 | V1126: *MAV151001338 | W1126: =+J1126/$W$2 -> 3.433247e-05
A1127: I-LED ARGENTINA S.A. | B1127: Pesos | C1127: 46314 | D1127: 14/05/2026 | E1127: 0.88168512 | G1127: 16500000 | H1127: 14547804 | I1127: 16500000 | J1127: 14547804 | K1127: 28676 | L1127: AMOMPY | M1127: Momentum Capital Investment S.A. | N1127: 27/04/2026 | O1127: 27/04/2026 | P1127: 31 | Q1127: No | U1127: *MAV151001343 | V1127: *MAV151001343 | W1127: =+J1127/$W$2 -> 0.00038342256
A1128: Movil SGR | B1128: Pesos | C1128: 46314 | D1128: 14/05/2026 | E1128: 0.89189731 | G1128: 2500000 | H1128: 2229743.3 | I1128: 2500000 | J1128: 2229743.3 | K1128: 90031816 | L1128: AMOMPY | M1128: Momentum Capital Investment S.A. | N1128: 22/04/2026 | O1128: 22/04/2026 | P1128: 28 | Q1128: No | U1128: *MOV151000067 | V1128: *MOV151000067 | W1128: =+J1128/$W$2 -> 5.876721e-05
A1129: CONSTRUCCIONES S&C SAS | B1129: Pesos | C1129: 46315 | D1129: 14/05/2026 | E1129: 0.85797575 | G1129: 6899161.8 | H1129: 5919313.5 | I1129: 6899161.8 | J1129: 5919313.5 | K1129: 65964607 | L1129: AMOMPY | M1129: Momentum Capital Investment S.A. | N1129: 22/04/2026 | O1129: 22/04/2026 | P1129: 38 | Q1129: No | U1129: *MAV161001047 | V1129: *MAV161001047 | W1129: =+J1129/$W$2 -> 0.00015600968
A1130: Movil SGR | B1130: Pesos | C1130: 46315 | D1130: 14/05/2026 | E1130: 0.89128744 | G1130: 2500000 | H1130: 2228218.6 | I1130: 2500000 | J1130: 2228218.6 | K1130: 90031817 | L1130: AMOMPY | M1130: Momentum Capital Investment S.A. | N1130: 22/04/2026 | O1130: 22/04/2026 | P1130: 28 | Q1130: No | U1130: *MOV161000058 | V1130: *MOV161000058 | W1130: =+J1130/$W$2 -> 5.8727025e-05
A1131: Movil SGR | B1131: Pesos | C1131: 46315 | D1131: 14/05/2026 | E1131: 0.89128739 | G1131: 25000000 | H1131: 22282185 | I1131: 25000000 | J1131: 22282185 | K1131: 360572 | L1131: AMOMPY | M1131: Momentum Capital Investment S.A. | N1131: 21/04/2026 | O1131: 21/04/2026 | P1131: 28 | Q1131: No | U1131: *MOV161000057 | V1131: *MOV161000057 | W1131: =+J1131/$W$2 -> 0.00058727022
A1132: BILOMAT | B1132: Pesos | C1132: 46316 | D1132: 14/05/2026 | E1132: 0.85720999 | G1132: 7133529.1 | H1132: 6114932.5 | I1132: 7133529.1 | J1132: 6114932.5 | K1132: 90000170 | L1132: AMOMPY | M1132: Momentum Capital Investment S.A. | N1132: 22/04/2026 | O1132: 22/04/2026 | P1132: 38 | Q1132: No | U1132: *MAV171001314 | V1132: *MAV171001314 | W1132: =+J1132/$W$2 -> 0.00016116542
A1133: Movil SGR | B1133: Pesos | C1133: 46316 | D1133: 14/05/2026 | E1133: 0.89067855 | G1133: 25000000 | H1133: 22266964 | I1133: 25000000 | J1133: 22266964 | K1133: 360573 | L1133: AMOMPY | M1133: Momentum Capital Investment S.A. | N1133: 21/04/2026 | O1133: 21/04/2026 | P1133: 28 | Q1133: No | U1133: *MOV181000045 | V1133: *MOV181000045 | W1133: =+J1133/$W$2 -> 0.00058686905
A1134: Neuquén Pymes S.G.R. | B1134: Pesos | C1134: 46316 | D1134: 14/05/2026 | E1134: 0.88377732 | G1134: 11923077 | H1134: 10537345 | I1134: 11923077 | J1134: 10537345 | K1134: 90021989 | L1134: AMOMPY | M1134: Momentum Capital Investment S.A. | N1134: 11/05/2026 | O1134: 11/05/2026 | P1134: 30 | Q1134: No | U1134: *NEU191000011 | V1134: *NEU191000011 | W1134: =+J1134/$W$2 -> 0.00027772272
A1135: REGCEN S.R.L. | B1135: Pesos | C1135: 46317 | D1135: 14/05/2026 | E1135: 0.85322255 | G1135: 3750000 | H1135: 3199584.6 | I1135: 3750000 | J1135: 3199584.6 | K1135: 66918105 | L1135: AMOMPY | M1135: Momentum Capital Investment S.A. | N1135: 13/05/2026 | O1135: 13/05/2026 | P1135: 39 | Q1135: No | U1135: *MAV201001458 | V1135: *MAV201001458 | W1135: =+J1135/$W$2 -> 8.4328388e-05
... A1156: REGCEN S.R.L. | B1156: Pesos | C1156: 46342 | D1156: 14/05/2026 | E1156: 0.83420965 | G1156: 3750000 | H1156: 3128286.2 | I1156: 3750000 | J1156: 3128286.2 | K1156: 66918897 | L1156: AMOMPY | M1156: Momentum Capital Investment S.A. | N1156: 13/05/2026 | O1156: 13/05/2026 | P1156: 39 | Q1156: No | U1156: *MAV121101139 | V1156: *MAV121101139 | W1156: =+J1156/$W$2 -> 8.2449246e-05
A1157: PUNTO PACK SRL | B1157: Dolar 3500 | C1157: 46343 | D1157: 14/05/2026 | E1157: 0.96062625 | F1157: 1 US3 = 1393,2322905547 $ | G1157: 18230 | H1157: 17512.22 | I1157: 25398625 | J1157: 24398590 | K1157: 146446 | L1157: AMOMPY | M1157: Momentum Capital Investment S.A. | N1157: 17/04/2026 | O1157: 17/04/2026 | P1157: 8 | Q1157: No | U1157: #UMV131160016 | V1157: #UMV131160016 | W1157: =+J1157/$W$2 -> 0.0006430503
A1158: AVAL AR SGR | B1158: Pesos | C1158: 46343 | D1158: 14/05/2026 | E1158: 0.84428219 | G1158: 9450000 | H1158: 7978466.7 | I1158: 9450000 | J1158: 7978466.7 | K1158: 66335143 | L1158: AMOMPY | M1158: Momentum Capital Investment S.A. | N1158: 22/04/2026 | O1158: 22/04/2026 | P1158: 36 | Q1158: No | U1158: *AAR131100017 | V1158: *AAR131100017 | W1158: =+J1158/$W$2 -> 0.00021028081
A1159: LW GROUP SRL | B1159: Pesos | C1159: 46344 | D1159: 14/05/2026 | E1159: 0.84726107 | G1159: 1500000 | H1159: 1270891.6 | I1159: 1500000 | J1159: 1270891.6 | K1159: 5 | L1159: AMOMPY | M1159: Momentum Capital Investment S.A. | N1159: 23/04/2026 | O1159: 23/04/2026 | P1159: 35 | Q1159: No | U1159: *MAV151101538 | V1159: *MAV151101538 | W1159: =+J1159/$W$2 -> 3.3495674e-05
A1160: AVAL AR SGR | B1160: Pesos | C1160: 46344 | D1160: 14/05/2026 | E1160: 0.84357966 | G1160: 9450000 | H1160: 7971827.8 | I1160: 9450000 | J1160: 7971827.8 | K1160: 66335193 | L1160: AMOMPY | M1160: Momentum Capital Investment S.A. | N1160: 22/04/2026 | O1160: 22/04/2026 | P1160: 36 | Q1160: No | U1160: *AAR161100027 | V1160: *AAR161100027 | W1160: =+J1160/$W$2 -> 0.00021010584
A1161: REGCEN S.R.L. | B1161: Pesos | C1161: 46345 | D1161: 14/05/2026 | E1161: 0.83198494 | G1161: 3750000 | H1161: 3119943.5 | I1161: 3750000 | J1161: 3119943.5 | K1161: 66918963 | L1161: AMOMPY | M1161: Momentum Capital Investment S.A. | N1161: 13/05/2026 | O1161: 13/05/2026 | P1161: 39 | Q1161: No | U1161: *MAV171101249 | V1161: *MAV171101249 | W1161: =+J1161/$W$2 -> 8.2229365e-05
A1162: AVAL AR SGR | B1162: Pesos | C1162: 46351 | D1162: 14/05/2026 | E1162: 0.83869498 | G1162: 9450000 | H1162: 7925667.5 | I1162: 9450000 | J1162: 7925667.5 | K1162: 66335232 | L1162: AMOMPY | M1162: Momentum Capital Investment S.A. | N1162: 22/04/2026 | O1162: 22/04/2026 | P1162: 36 | Q1162: No | U1162: *AAR201100017 | V1162: *AAR201100017 | W1162: =+J1162/$W$2 -> 0.00020888923
A1163: PUNTO PACK SRL | B1163: Dolar 3500 | C1163: 46372 | D1163: 14/05/2026 | E1163: 0.95479768 | F1163: 1 US3 = 1393,2322905547 $ | G1163: 18230 | H1163: 17405.96 | I1163: 25398625 | J1163: 24250546 | K1163: 146447 | L1163: AMOMPY | M1163: Momentum Capital Investment S.A. | N1163: 17/04/2026 | O1163: 17/04/2026 | P1163: 8 | Q1163: No | U1163: #UMV131260004 | V1163: #UMV131260004 | W1163: =+J1163/$W$2 -> 0.00063914842
A1164: PUNTO PACK SRL | B1164: Dolar 3500 | C1164: 46401 | D1164: 14/05/2026 | E1164: 0.94903829 | F1164: 1 US3 = 1393,2322905547 $ | G1164: 18230 | H1164: 17300.97 | I1164: 25398625 | J1164: 24104270 | K1164: 146448 | L1164: AMOMPY | M1164: Momentum Capital Investment S.A. | N1164: 17/04/2026 | O1164: 17/04/2026 | P1164: 8 | Q1164: No | U1164: #UMV120170009 | V1164: #UMV120170009 | W1164: =+J1164/$W$2 -> 0.00063529318
A1165: THE CRAZY COW S.R.L. | B1165: Dolar 3500 | C1165: 46414 | D1165: 14/05/2026 | E1165: 0.93398317 | F1165: 1 US3 = 1393,2322905547 $ | G1165: 13904 | H1165: 12986.1 | I1165: 19371502 | J1165: 18092654 | K1165: 134916 | L1165: AMOMPY | M1165: Momentum Capital Investment S.A. | N1165: 30/12/2025 | O1165: 30/12/2025 | P1165: 10 | Q1165: No | U1165: #UMV250170065 | V1165: #UMV250170065 | W1165: =+J1165/$W$2 -> 0.00047685076
A1166: PUNTO PACK SRL | B1166: Dolar 3500 | C1166: 46433 | D1166: 14/05/2026 | E1166: 0.94276306 | F1166: 1 US3 = 1393,2322905547 $ | G1166: 18230 | H1166: 17186.57 | I1166: 25398625 | J1166: 23944884 | K1166: 146450 | L1166: AMOMPY | M1166: Momentum Capital Investment S.A. | N1166: 17/04/2026 | O1166: 17/04/2026 | P1166: 8 | Q1166: No | U1166: #UMV110270012 | V1166: #UMV110270012 | W1166: =+J1166/$W$2 -> 0.0006310924
...

Sheet Posicion cuotapartista
A1: Posición de Cuotapartista
A2: Fondo | B2: Cuotapartista | C2: Tipo de Valor Cuotaparte | D2: Cuotapartes | E2: Inversión | F2: Moneda | G2: Fondo | H2: Tipo de Inversor | I2: Fondo | J2: Porcentaje
A3: Nombre | B3: Nombre | F3: Símbolo | G3: Fecha Valor Cuotaparte | I3: Valor Cuotaparte
A4: AMOMPY | B4: ZOFINGEN SECURITIES S.A. (ACDI) | C4: C | D4: 3.3408168e+08 | E4: 5.561765e+08 | F4: $ | G4: 14/05/2026 | H4: Agentes de Colocación y Distribución Integral de FCIs | I4: 1.664792 | J4: 1.9677984
A5: AMOMPY | B5: BANCO DE LA CIUDAD DE BUENOS AIRES | C5: C | D5: 9.1589296e+08 | E5: 1.5247713e+09 | F5: $ | G5: 14/05/2026 | H5: Agentes de Colocación y Distribución Integral de FCIs | I5: 1.664792 | J5: 5.3947667
A6: AMOMPY | B6: MOMENTUM CAPITAL INVESTMENT S.A. (ACDI) | C6: C | D6: 1.5387704e+10 | E6: 2.5617327e+10 | F6: $ | G6: 14/05/2026 | H6: Agentes de Colocación y Distribución Integral de FCIs | I6: 1.664792 | J6: 90.636219
A7: AMOMPY | B7: ALYCBUR S.A. (ACDI) | C7: C | D7: 3.3975516e+08 | E7: 5.6562167e+08 | F7: $ | G7: 14/05/2026 | H7: Agentes de Colocación y Distribución Integral de FCIs | I7: 1.664792 | J7: 2.0012162
A8: AMOMPY | B8: MOMENTUM CAPITAL INVESTMENT S.A. (ACDI) | C8: A | D8: 3.1958101e+09 | E8: 4.4072969e+09 | F8: $ | G8: 14/05/2026 | H8: Agentes de Colocación y Distribución Integral de FCIs | I8: 1.379086 | J8: 87.708343
A9: AMOMPY | B9: ALYCBUR S.A. (ACDI) | C9: A | D9: 4.4786848e+08 | E9: 6.1764916e+08 | F9: $ | G9: 14/05/2026 | H9: Agentes de Colocación y Distribución Integral de FCIs | I9: 1.379086 | J9: 12.291657
A10: AMOMPY | B10: MOMENTUM CAPITAL INVESTMENT S.A. (ACDI) | C10: B | D10: 2.6466364e+09 | E10: 4.3736116e+09 | F10: $ | G10: 14/05/2026 | H10: Agentes de Colocación y Distribución Integral de FCIs | I10: 1.652517 | J10: 93.993105
A11: AMOMPY | B11: ALYCBUR S.A. (ACDI) | C11: B | D11: 1.6914077e+08 | E11: 2.79508e+08 | F11: $ | G11: 14/05/2026 | H11: Agentes de Colocación y Distribución Integral de FCIs | I11: 1.652517 | J11: 6.0068948
D12: 2.343689e+10 | E12: 3.7941962e+10
