Workbook

Sheet GESTION MOMENTUM
A1: FONDOS COMUNES DE INVERSION
A2: 30/9/2026
A3: 10:05:46
A4: Informe de Gestión al 29/9/2026 | K4: MOMENTUM
A5: FCI ABIERTO MOMENTUM PYMES | K5: COMAFI $ Nº 24148/3
A6: Todos los importes están expresados en Pesos | K6: BANCO DEL SOL
C7: (4) | D7: (1) | L7: 46295 | M7: =WORKDAY(L7,1,$R:$R) -> 46296 | N7: =WORKDAY(M7,1,$R:$R) -> 46297 | R7: 45719 | S7: Lista de feriados 2025
A8: ACTIVO | B8: 7.580616e+10 | C8: 100 | K8: Caucion MAV | R8: 45720
A9: INVERSIONES | B9: 7.428339e+10 | C9: 97.99 | D9: 98.76 | K9: Caucion BYMA | R9: 45740
A10: TITULOS PUBLICOS | B10: 1070087272 | C10: 1.41 | D10: 1.42 | K10: Plazo Fijo | L10: =SUMIFS(F:F,A:A,$K$10,B:B,L7) -> 0 | M10: =SUMIFS(G:G,B:B,$K$10,C:C,M7) -> 0 | N10: =SUMIFS(H:H,C:C,$K$10,D:D,N7) -> 0 | R10: 45749
A11: FUTUROS | B11: -3336875500 | C11: -4.4 | D11: -4.44 | K11: Vto. Cheques | L11: =SUMIF($B$100:$B$2570,L7,$D$100:$D$2570) -> 4.8333775e+08 | M11: =SUMIF($B$100:$B$2570,M7,$D$100:$D$2570) -> 3.1391167e+09 | N11: =SUMIF($B$100:$B$2570,N7,$D$100:$D$2570) -> 2.8883542e+09 | P11: =SUMIF($B$99:$B$1908,P7,$D$99:$D$1908) -> 0 | Q11: =SUMIF($B$99:$B$1908,Q7,$D$99:$D$1908) -> 0 | R11: =SUMIF($B$99:$B$1908,R7,$D$99:$D$1908) -> 0 | S11: =SUMIF($B$99:$B$1908,S7,$D$99:$D$1908) -> 0 | T11: =SUMIF($B$99:$B$1908,T7,$D$99:$D$1908) -> 0
A12: DISPONIBILIDADES | B12: 2029277.5 | C12: 0 | D12: 0 | K12: Vto. Pagarés/FCE Dollar Linked | L12: =+SUMIF($B$2574:$B$2618,L7,$F$2574:$F$2618) -> 0 | M12: =+SUMIF($B$2574:$B$2618,M7,$F$2574:$F$2618) -> 0 | N12: =+SUMIF($B$2574:$B$2618,N7,$F$2574:$F$2618) -> 0 | R12: 45778
A13: EN PESOS | B13: 2029338.5 | C13: 0 | D13: 0 | J13: 0.19 | K13: FCI IEB Ahorro - Clase E | L13: =SUMIF(A:A,K13,E:E)*(1+(J13/365*1)) -> 1.6538605e+09 | R13: 45779
A14: EN DOLARES | B14: -60.96 | C14: 0 | D14: 0 | K14: COMAFI $ Nº 24148/3 | L14: =+B13 -> 2029338.5 | R14: 45802
A15: CREDITOS | B15: 1.5207402e+09 | C15: 2.01 | D15: 2.02 | K15: Ctte Momentum | L15: 10853000 | R15: 45824
A16: PASIVO | B16: -5.8747368e+08 | K16: Cheques pendientes | R16: 45828
A17: PROVISIONES | B17: -1.5901604e+08 | K17: Compra/Venta Bonos | R17: 45847
A18: PROV. HONORARIOS SOC. DEPOSITARIA | B18: -9227004.7 | K18: TOTAL | L18: =SUM(L8:L17) -> 2.1500806e+09 | R18: 45884
A19: PROV. HONORARIOS SOCIEDAD GERENTE | B19: -1.3617185e+08 | K19: Neg. Cheques / Pagare | L19: =-1158252548.65 -> -1.1582525e+09 | R19: 45886
A20: PROV. GASTOS SOCIEDAD DEPOSITARIA | B20: -13617185 | K20: Coloca caucion MAV | R20: 45942
A21: DEUDAS EN PESOS | B21: -4.2423421e+08 | K21: Compra/Venta de Bonos | R21: 45982
A22: RESCATES | B22: -51000000 | J22: EGRESOS EN EL DIA Clase B | K22: Suscripciones | R22: 45985
A23: PREVISIÓN INCOBRABLES | B23: -3.7322904e+08 | K23: Rescates | L23: =SUMIF(A:A,K23,B:B) -> -51000000 | R23: 45999
A24: Valor Patrimonial del Fondo | B24: 7.5218686e+10 | K24: Pase | R24: 46016
A25: Liquidez Efectiva (2) | B25: 1.0943118e+09 | D25: 1.45 | K25: Rentas y Amortizaciones
A26: Liquidez Corriente (3) | B26: 9.3529577e+08 | D26: 1.24 | K26: Pago ACDI
K27: Caja cierre | L27: =SUM(L18:L26) -> 9.4082801e+08 | M27: =SUM(M8:M26) -> 3.1391167e+09 | N27: =SUM(N8:N26) -> 2.8883542e+09
A41: Inversiones
A42: TITULO PUBLICO en Pesos
A43: Denominación | B43: IsinCode | C43: Cantidad | D43: Cierre | E43: Total | F43: % (1) | G43: Costo | H43: Var | I43: Vencimiento
A44: Lecap S30N6 | B44: AR0451031345 | C44: 200000000 | D44: 1.2483 | E44: 249656648 | F44: 0.33 | G44: 0 | I44: 30/11/2026
A45: TMG28 - Bono del Tesoro Nacional | B45: AR0175438917 | C45: 600000000 | D45: 1.0768 | E45: 646075548 | F45: 0.86 | G45: 0 | I45: 31/01/2028
C46: 800000000 | E46: 895732196 | F46: 1.19
A48: OBLIGACIONES NEGOCIABLES en Pesos
A49: Denominación | B49: IsinCode | C49: Cantidad | D49: Cierre | E49: Total | F49: % (1) | G49: Costo | H49: Var | I49: Vencimiento
A50: LR8AO - ON Laboratorios Richmond Serie 8 Clase A | B50: AR0266435707 | C50: 300000000 | D50: 1.1029 | E50: 330862383 | F50: 0.44 | G50: 0 | I50: 31/07/2028
A51: MTC3O - ON Mastellone Clase 3 | B51: AR0494875476 | C51: 250000000 | D51: 0.9993 | E51: 249820885 | F51: 0.33 | G51: 1 | H51: -0.07 | I51: 22/06/2027
A52: VBC3O - ON BANCO DE VALORES CL.3 24/10/26 $ | B52: AR0531585807 | C52: 300000000 | D52: 1.1129 | E52: 333868215 | F52: 0.44 | G52: 1 | H52: 11.29 | I52: 24/10/2026
C53: 850000000 | E53: 914551483 | F53: 1.22
A55: FIDEICOMISOS FINANCIEROS en Pesos
A56: Denominación | B56: IsinCode | C56: Cantidad | D56: Cierre | E56: Total | F56: % (1) | G56: Costo | H56: Var | I56: Vencimiento | K56: Activos Pyme | L56: 6.2314744e+10
A57: CQ08A - VD FF CENTROCARD CREDITOS 8 CL.A $ | B57: AR0253965559 | C57: 250000000 | D57: 0.7216 | E57: 180409615 | F57: 0.24 | G57: 0.9784 | H57: -26.25 | I57: 26/05/2027 | K57: % Pyme | L57: =L56/B24 -> 0.82844765
A58: FF AMFAyS S49 Clase A | B58: AR0711423134 | C58: 100000000 | D58: 0.1366 | E58: 13660000 | F58: 0.02 | G58: 0.9846 | H58: -86.13 | I58: 31/12/2026
A59: GE05A - VDF Grancoop 5 Clase A | B59: AR0985951141 | C59: 300000000 | D59: 0.9753 | E59: 292575042 | F59: 0.39 | G59: 0.9961 | H59: -2.1 | I59: 22/11/2027 | K59: T+1 Ayer | L59: -1.3244597e+09
A60: MY50B - VD FF AMFAYS S.50 CL.B $ | B60: AR0695284973 | C60: 101962042 | D60: 1.4588 | E60: 1.4874581e+08 | F60: 0.2 | G60: 0.924 | H60: 57.88 | I60: 13/01/2027 | K60: T+0 Hoy | L60: =+W69 -> 1.0507073e+09
A61: MY50C - VD FF AMFAYS S.50 CL.C $ | B61: AR0890638411 | C61: 382357659 | D61: 1.2546 | E61: 4.7969054e+08 | F61: 0.64 | G61: 0.85 | H61: 47.6 | I61: 13/04/2027 | K61: Conciliación T+1 | L61: =+L59+W68 -> 0
A62: MY51B - VD FF AMFAYS Serie 51 Clase B | B62: AR0207834935 | C62: 75584213 | D62: 1.1453 | E62: 86565404 | F62: 0.12 | G62: 0.8718 | H62: 31.37 | I62: 15/03/2027 | K62: Conciliación Derivacion | L62: =+L19+W68+W69 -> 1.2169145e+09
A63: MY51C - VD FF AMFAYS Serie 51 Clase C | B63: AR0601005553 | C63: 176363163 | D63: 1.0643 | E63: 1.8770261e+08 | F63: 0.25 | G63: 0.8446 | H63: 26.01 | I63: 15/11/2027
A64: MY52B - FF AMFAYS 52 CL.B $ | B64: AR0013738833 | C64: 63635566 | D64: 0.9995 | E64: 63604851 | F64: 0.08 | G64: 0.9054 | H64: 10.4 | I64: 15/12/2027
A65: MY52C - FF AMFAYS 52 CL.C $ | B65: AR0959603397 | C65: 148482986 | D65: 0.8895 | E65: 1.3207012e+08 | F65: 0.18 | G65: 0.7853 | H65: 13.26 | I65: 15/02/2028 | K65: PN ACTUAL | L65: =VLOOKUP("Valor Patrimonial del Fondo",A:B,2,0)+L22 -> 7.5218686e+10 | U65: Operaciones
C66: 1598385629 | E66: 1.585024e+09 | F66: 2.11 | K66: Límite | L66: $ | M66: % | N66: Diferencia | U66: Concertación | V66: Liquidación | W66: Suma de Neto
K67: 5% MM | L67: =+$L$65*M67 -> 3.7609343e+09 | M67: 0.05 | N67: =+L67-L13 -> 2.1070738e+09 | U67: 46293 | V67: 46293 | W67: 1.5176062e+09
A68: FUTUROS en Pesos | K68: 20% CAUCION | L68: =+$L$65*M68 -> 1.5043737e+10 | M68: 0.2 | N68: =+L68-(L8+L9) -> 1.5043737e+10 | U68: 46293 | V68: 46294 | W68: 1.3244597e+09
A69: Denominación | B69: IsinCode | C69: Cantidad | D69: Cierre | E69: Total | F69: % (1) | G69: Costo | H69: Var | I69: Vencimiento | K69: 20% Librador | L69: =+$L$65*M69 -> 1.5043737e+10 | M69: 0.2 | N69: =L69-M72 -> 1.1267154e+10 | U69: 46294 | V69: 46294 | W69: 1.0507073e+09
A70: Fut Rofex DLR092026 | C70: -833000 | D70: 1522 | E70: -1267826000 | F70: -1.69 | G70: 0 | I70: 30/09/2026 | K70: % Pymes | L70: =+$L$65*M70 -> 5.6414015e+10 | M70: 0.75 | N70: =+L56-L70 -> 5.900729e+09 | U70: 46294 | V70: 46295 | W70: 1.1582525e+09
A71: Fut Rofex DLR102026 | C71: -539000 | D71: 1548 | E71: -834372000 | F71: -1.11 | G71: 0 | I71: 30/10/2026
A72: Fut Rofex DLR112026 | C72: -750000 | D72: 1576 | E72: -1182000000 | F72: -1.57 | G72: 0 | I72: 30/11/2026 | K72: Máximo librador | L72: {=_xlfn.LET(_xlpm.lib,_xlfn.UNIQUE('Reporte de Cheques'!$A$4:$A$5000),_xlpm.tot,SUMIFS('Reporte de Cheques'!$J$4:$J$5000,'Reporte de Cheques'!$A$4:$A$5000,_xlpm.lib),_xlfn.XLOOKUP(MAX(_xlpm.tot),_xlpm.tot,_xlpm.lib))} -> SES SA | M72: {=MAX(SUMIFS('Reporte de Cheques'!$J$4:$J$5000,'Reporte de Cheques'!$A$4:$A$5000,_xlfn.UNIQUE('Reporte de Cheques'!$A$4:$A$5000)))} -> 3.7765832e+09
A73: Fut Rofex DLR122026 | C73: -823000 | D73: 1604.5 | E73: -1320503500 | F73: -1.76 | G73: 0 | I73: 31/12/2026
C74: -2945000 | E74: -4604701500 | F74: -6.12 | K74: Pagarés Dólar Link que vencen hoy
K75: Librador | L75: Vencimiento | M75: Nominal (USD) | N75: Importe Actual ($)
A76: MONEY MARKET en Pesos | K76: {=_xlfn._xlws.FILTER(_xlfn.CHOOSECOLS('Reporte de Cheques'!A4:V2253,1,3,7,10,21),('Reporte de Cheques'!B4:B2253="Dolar Link")*('Reporte de Cheques'!C4:C2253=TODAY()),"Sin vencimientos hoy")} -> Sin vencimientos hoy
A77: Denominación | B77: IsinCode | C77: Cantidad | D77: Cierre | E77: Total | F77: % (1) | G77: Costo | H77: Var | I77: Vencimiento
A78: FCI IEB Ahorro - Clase E | C78: 1.267419e+08 | D78: 13.0423 | E78: 1653000000 | F78: 2.2 | G78: 13.0423 | H78: 0
C79: 1.267419e+08 | E79: 1653000000 | F79: 2.2
A81: PAGARE en Pesos
A82: Denominación | B82: IsinCode | C82: Cantidad | D82: Cierre | E82: Total | F82: % (1) | G82: Costo | H82: Var | I82: Vencimiento
A83: #MAV181160012 | C83: 300000000 | D83: 1.0283 | E83: 3.0850479e+08 | F83: 0.41 | G83: 0.9841 | H83: 4.5 | I83: 19/11/2026
C84: 300000000 | E84: 3.0850479e+08 | F84: 0.41
A86: TITULO PROVINCIAL en Pesos
A87: Denominación | B87: IsinCode | C87: Cantidad | D87: Cierre | E87: Total | F87: % (1) | G87: Costo | H87: Var | I87: Vencimiento
A88: PBA27 - Letra de la Provincia de Buenos Aires Vto 30/04/27 | B88: AR0647160248 | C88: 400000000 | D88: 1.06 | E88: 424011724 | F88: 0.56 | G88: 1 | H88: 6 | I88: 30/04/2027
C89: 400000000 | E89: 424011724 | F89: 0.56
A92: Aperturas, Pases y Cauciones en Pesos
A93: Tipo | B93: Vencimiento | C93: Concertación | D93: Plazo | E93: Tasa | F93: Total | G93: % (1)
A94: PASE | B94: 05/10/2026 | C94: 02/09/2026 | D94: 33 | E94: 38.498898 | F94: 6.1461883e+08 | G94: 0.82
D95: 6 | E95: 38.498898 | F95: 6.1461883e+08 | G95: 0.82
A98: Cheques de Pago Diferido en Pesos
A99: Descripción | B99: Vencimiento | C99: Compra | D99: Nominal | E99: Precio | F99: Actual | G99: % (1)
A100: *MAV061001203 | B100: 08/10/2026 | C100: 17/04/2026 | D100: 7900000 | E100: 0.99023332 | F100: 7822843.2 | G100: 0.01
A101: *MAV061001204 | B101: 08/10/2026 | C101: 17/04/2026 | D101: 7203888 | E101: 0.99023332 | F101: 7133530 | G101: 0.01
A102: *MAV011000998 | B102: 05/10/2026 | C102: 17/04/2026 | D102: 7203888 | E102: 0.99346761 | F102: 7156829.4 | G102: 0.01
A103: *MAV051000897 | B103: 07/10/2026 | C103: 17/04/2026 | D103: 7203888 | E103: 0.99130908 | F103: 7141279.6 | G103: 0.01
A104: *MAV051000898 | B104: 07/10/2026 | C104: 17/04/2026 | D104: 7900000 | E104: 0.99130908 | F104: 7831341.7 | G104: 0.01
A105: *NEU300900058 | B105: 02/10/2026 | C105: 20/04/2026 | D105: 21387500 | E105: 0.99729501 | F105: 21329647 | G105: 0.03
A106: *MOV021000043 | B106: 06/10/2026 | C106: 21/04/2026 | D106: 25000000 | E106: 0.99465883 | F106: 24866471 | G106: 0.03
A107: *MOV091000054 | B107: 14/10/2026 | C107: 21/04/2026 | D107: 25000000 | E107: 0.98862407 | F107: 24715602 | G107: 0.03
A108: *MOV131000082 | B108: 15/10/2026 | C108: 21/04/2026 | D108: 25000000 | E108: 0.98787486 | F108: 24696872 | G108: 0.03
A109: *MOV161000057 | B109: 20/10/2026 | C109: 21/04/2026 | D109: 25000000 | E109: 0.98414582 | F109: 24603646 | G109: 0.03
A110: *MOV181000045 | B110: 21/10/2026 | C110: 21/04/2026 | D110: 25000000 | E110: 0.98340341 | F110: 24585085 | G110: 0.03
A111: *MOV300900114 | B111: 02/10/2026 | C111: 21/04/2026 | D111: 15000000 | E111: 0.99770391 | F111: 14965559 | G111: 0.02
... A2569: *MAV301002041 | B2569: 03/11/2026 | C2569: 29/09/2026 | D2569: 50000000 | E2569: 0.97022873 | F2569: 48511436 | G2569: 0.06
F2570: 6.3966966e+10 | G2570: 85.04
A2572: Cheques de Pago Diferido en Dolar 3500
A2573: Descripción | B2573: Vencimiento | C2573: Compra | D2573: Nominal | E2573: Precio | F2573: Actual | G2573: % (1)
A2574: #UMV250180006 | B2574: 27/01/2028 | C2574: 30/12/2025 | D2574: 20856 | E2574: 1345.2219 | F2574: 28055948 | G2574: 0.04
A2575: #UMV250770007 | B2575: 28/07/2027 | C2575: 30/12/2025 | D2575: 20856 | E2575: 1407.5106 | F2575: 29355041 | G2575: 0.04
A2576: #UMV250780006 | B2576: 27/07/2028 | C2576: 30/12/2025 | D2576: 20856 | E2576: 1288.51 | F2576: 26873165 | G2576: 0.04
A2577: #UMV250170065 | B2577: 27/01/2027 | C2577: 30/12/2025 | D2577: 13904 | E2577: 1475.4634 | F2577: 20514843 | G2577: 0.03
A2578: #UMV131160016 | B2578: 17/11/2026 | C2578: 17/04/2026 | D2578: 18230 | E2578: 1507.7771 | F2578: 27486776 | G2578: 0.04
A2579: #UMV141060033 | B2579: 16/10/2026 | C2579: 17/04/2026 | D2579: 18230 | E2579: 1518.3128 | F2579: 27678842 | G2579: 0.04
...

Sheet Parametros
A1: Min | B1: 0.75 | C1: en Pymes | D1: =+B1*(VLOOKUP($E$1,'GESTION MOMENTUM'!$A$8:$B$32,2,0)) -> 5.6414015e+10 | E1: Valor Patrimonial del Fondo | G1: PN actual | H1: P&L | I1: PN reservado
A2: Max | B2: 0.05 | C2: Money Market | D2: =+B2*(VLOOKUP($E$1,'GESTION MOMENTUM'!$A$8:$B$32,2,0)) -> 3.7609343e+09 | G2: =VLOOKUP(E1,'GESTION MOMENTUM'!A8:B32,2,0) -> 7.5218686e+10 | H2: -0.002 | I2: =+G2*(1+H2) -> 7.5068249e+10
A3: Max | B3: 0.2 | C3: PFRemuneradasCaucion | D3: =+B3*(VLOOKUP($E$1,'GESTION MOMENTUM'!$A$8:$B$32,2,0)) -> 1.5043737e+10 | G3: Money Market | H3: 0.05 | I3: =+I2*H3 -> 3.7534124e+09
A4: Max | B4: 0.2 | C4: cheques x librador | D4: =+B4*(VLOOKUP($E$1,'GESTION MOMENTUM'!$A$8:$B$32,2,0)) -> 1.5043737e+10
A5: Max | B5: 0.25 | C5: x titulo en Pymes | D5: =+B5*(VLOOKUP($E$1,'GESTION MOMENTUM'!$A$8:$B$32,2,0)) -> 1.8804672e+10
B8: Garantías RFX (MOMENTUM)
B9: Bono | C9: VN | D9: Precio | E9: Aforo | F9: $
B10: TMG28 - Bono del Tesoro Nacional | C10: 600000000 | D10: =+VLOOKUP(B10,'GESTION MOMENTUM'!A:D,4,0) -> 1.0768 | E10: 0.8 | F10: =C10*D10*E10 -> 516864000
F11: =C11*D11*E11 -> 0
E13: Garantia | F13: =SUM(F10:F12) -> 516864000
B15: Garantías | C15: Total $ por contrato | D15: Contratos a shortear | E15: Contratos Shorteados | F15: Garantia Requerida
A16: Fut Rofex DLR072026 | B16: Julio | D16: 0 | E16: =_xlfn.IFNA(-VLOOKUP(A16,'GESTION MOMENTUM'!A:C,3,0)/1000,0) -> 0 | F16: =+C16*(E16+D16) -> 0
A17: Fut Rofex DLR082026 | B17: Agosto | D17: 0 | E17: =_xlfn.IFNA(-VLOOKUP(A17,'GESTION MOMENTUM'!A:C,3,0)/1000,0) -> 0 | F17: =+C17*(E17+D17) -> 0
A18: Fut Rofex DLR092026 | B18: Septiembre | C18: 150000 | D18: 0 | E18: =_xlfn.IFNA(-VLOOKUP(A18,'GESTION MOMENTUM'!A:C,3,0)/1000,0) -> 833 | F18: =+C18*(E18+D18) -> 124950000
A19: Fut Rofex DLR102026 | B19: Octubre | C19: 155000 | D19: 0 | E19: =_xlfn.IFNA(-VLOOKUP(A19,'GESTION MOMENTUM'!A:C,3,0)/1000,0) -> 539 | F19: =+C19*(E19+D19) -> 83545000
A20: Fut Rofex DLR112026 | B20: Noviembre | C20: 160000 | D20: 0 | E20: =_xlfn.IFNA(-VLOOKUP(A20,'GESTION MOMENTUM'!A:C,3,0)/1000,0) -> 750 | F20: =+C20*(E20+D20) -> 120000000
A21: Fut Rofex DLR122026 | B21: Diciembre | C21: 165000 | E21: =_xlfn.IFNA(-VLOOKUP(A21,'GESTION MOMENTUM'!A:C,3,0)/1000,0) -> 823 | F21: =+C21*(E21+D21) -> 135795000
D22: 0 | E22: =_xlfn.IFNA(-VLOOKUP(A22,'GESTION MOMENTUM'!A:C,3,0)/1000,0) -> 0 | F22: =+C22*(E22+D22) -> 0
F23: =+SUM(F16:F22) -> 464290000
B24: Saldo de Garantias | C24: =F13-F23 -> 52574000

Sheet Concentración
A4: Suma de %
A5: Sociedad de Garantía Recíproca / Librador | B5: Total
A6: SES SA | B6: 0.050208046
A7: A M F A Y S ASOCIACION MUTUAL | B7: 0.046387313
A8: SIGMA AGRO S.A. | B8: 0.037209423
A9: TRANS BOX SRL | B9: 0.030399207
A10: COOPERATIVA DE VIVIENDA CREDITO Y CONSUMO PARA EL DESARROLLO LIMITADA | B10: 0.025056317
A11: COM & LOG SA | B11: 0.024566633
A12: ESPECIALIDADES AGROPECUARIAS S.A. | B12: 0.023516318
A13: GOBIERNO DE LA CUIDAD DE BUENOS AIRES | B13: 0.021887263
A14: MILLS S.G.R. | B14: 0.021607265
A15: AUTOPISTAS URBANAS SA | B15: 0.021592468
A16: INTEGRA PYMES SGR | B16: 0.018812364
A17: LA MANTOVANA DE SERVICIOS GENERALES SA | B17: 0.017784024
... A396: Total general | B396: 0.91953139

Sheet Cheques pendientes
A1: FONDO | B1: CHPD | C1: VTO | D1: MONEDA | E1: MONTO | F1: MONTO $ | G1: ESTADO | H1: LIBRADOR | I1: DIAS DE MORA
A2: AMOMPY | B2: *MAV030300645 | C2: 45723 | D2: $ | E2: 3406250 | G2: PREVISIONADO | H2: UKUMARI SOCIEDAD ANONIMA. | I2: =+TODAY()-C2 -> 572 | U2: LIBRADORES PENDIENTES
A3: AMOMPY | B3: *MAV100300802 | C3: 45728 | D3: $ | E3: 3406250 | G3: PREVISIONADO | H3: UKUMARI SOCIEDAD ANONIMA. | I3: =+TODAY()-C3 -> 567 | U3: {=+_xlfn.UNIQUE(H2:H78)} -> UKUMARI SOCIEDAD ANONIMA. | V3: =+SUMIF(H:H,U3,E:E) -> 6812500
A4: AMOMPY | B4: *MAV200500842 | C4: 45799 | D4: $ | E4: 129185000 | G4: PENDIENTE | H4: NIRO CONSTRUYE S. A. | I4: =+TODAY()-C4 -> 496 | U4: NIRO CONSTRUYE S. A. | V4: =+SUMIF(H:H,U4,E:E) -> 258370000
A5: AMOMPY | B5: *MAV300500862 | C5: 45811 | D5: $ | E5: 129185000 | G5: PENDIENTE | H5: NIRO CONSTRUYE S. A. | I5: =+TODAY()-C5 -> 484 | U5: MERCOL RAUL ALBERTO Y MERCOL MAURICIO EDUARDO. | V5: =+SUMIF(H:H,U5,E:E) -> 62500000
A6: AMOMPY | B6: *MAV091000727 | C6: 45943 | D6: $ | E6: 12500000 | G6: PENDIENTE | H6: MERCOL RAUL ALBERTO Y MERCOL MAURICIO EDUARDO. | I6: =+TODAY()-C6 -> 352 | U6: AKAI ENERGY LED SRL | V6: =+SUMIF(H:H,U6,E:E) -> 44963000
A7: AMOMPY | B7: *MAV031100940 | C7: 45966 | D7: $ | E7: 4400000 | G7: PENDIENTE | H7: AKAI ENERGY LED SRL | I7: =+TODAY()-C7 -> 329 | U7: FRIGORIFICO GENERAL PICO S A | V7: =+SUMIF(H:H,U7,E:E) -> 70000000
A8: AMOMPY | B8: *MAV041100892 | C8: 45968 | D8: $ | E8: 4400000 | G8: PENDIENTE | H8: AKAI ENERGY LED SRL | I8: =+TODAY()-C8 -> 327 | K8: Valor Patrimonial del Fondo | L8: =+VLOOKUP(K8,'GESTION MOMENTUM'!A:B,2,0) -> 7.5218686e+10 | U8: MIANI CLARA A Y MIANI ADA CLELIA | V8: =+SUMIF(H:H,U8,E:E) -> 3125000
A9: AMOMPY | B9: *MAV051100567 | C9: 45971 | D9: $ | E9: 25000000 | G9: PENDIENTE | H9: MERCOL RAUL ALBERTO Y MERCOL MAURICIO EDUARDO. | I9: =+TODAY()-C9 -> 324 | U9: PORT PLA S.R.L. | V9: =+SUMIF(H:H,U9,E:E) -> 150000000
A10: AMOMPY | B10: *MAV051100722 | C10: 45971 | D10: $ | E10: 4400000 | G10: PENDIENTE | H10: AKAI ENERGY LED SRL | I10: =+TODAY()-C10 -> 324 | L10: $ | M10: % PN | U10: MASTER DESIGN HOME SRL | V10: =+SUMIF(H:H,U10,E:E) -> 24000000
A11: AMOMPY | B11: *MAV071100935 | C11: 45972 | D11: $ | E11: 4400000 | G11: PENDIENTE | H11: AKAI ENERGY LED SRL | I11: =+TODAY()-C11 -> 323 | K11: PREVISIÓN INCOBRABLES | L11: =+VLOOKUP(K11,'GESTION MOMENTUM'!A:B,2,0) -> -3.7322904e+08 | M11: =+L11/L8 -> -0.0049619191 | U11: GROCAL S.A. | V11: =+SUMIF(H:H,U11,E:E) -> 15000000
A12: AMOMPY | B12: *MAV111100890 | C12: 45974 | D12: $ | E12: 963000 | G12: PENDIENTE | H12: AKAI ENERGY LED SRL | I12: =+TODAY()-C12 -> 321 | K12: PREVISIONADO | L12: =+SUMIF(G:G,K12,E:E) -> 100812500 | U12: Paccioli Group Sociedad Anonima | V12: =+SUMIF(H:H,U12,E:E) -> 13958000
A13: AMOMPY | B13: *MAV121100854 | C13: 45975 | D13: $ | E13: 4400000 | G13: PENDIENTE | H13: AKAI ENERGY LED SRL | I13: =+TODAY()-C13 -> 320 | K13: Prevision a aplicar | L13: =+L11+L12 -> -2.7241654e+08 | U13: FINEX CABA S. A. | V13: =+SUMIF(H:H,U13,E:E) -> 55300000
A14: AMOMPY | B14: *MAV121100675 | C14: 45975 | D14: $ | E14: 25000000 | G14: PENDIENTE | H14: MERCOL RAUL ALBERTO Y MERCOL MAURICIO EDUARDO. | I14: =+TODAY()-C14 -> 320 | U14: TRADICION VALORES S.A. | V14: =+SUMIF(H:H,U14,E:E) -> 25000000
A15: AMOMPY | B15: *MAV141101053 | C15: 45979 | D15: $ | E15: 4400000 | G15: PENDIENTE | H15: AKAI ENERGY LED SRL | I15: =+TODAY()-C15 -> 316 | K15: PENDIENTE | L15: =+SUMIF(G:G,K15,E:E)+E2 -> 1.3370253e+09 | M15: =+SUMIF(G:G,K15,E:E)/$L$8 -> 0.01772989 | U15: Maradona Wines | V15: =+SUMIF(H:H,U15,E:E) -> 119500000
A16: AMOMPY | B16: *MAV141101054 | C16: 45979 | D16: $ | E16: 4400000 | G16: PENDIENTE | H16: AKAI ENERGY LED SRL | I16: =+TODAY()-C16 -> 316 | U16: LOPEZ LUCIA SOLEDAD | V16: =+SUMIF(H:H,U16,E:E) -> 995000
A17: AMOMPY | B17: *MAV171100932 | C17: 45980 | D17: $ | E17: 4400000 | G17: PENDIENTE | H17: AKAI ENERGY LED SRL | I17: =+TODAY()-C17 -> 315 | U17: RABU INVERSIONES SRL | V17: =+SUMIF(H:H,U17,E:E) -> 7194300
A18: AMOMPY | B18: *MAV151101337 | C18: 45980 | D18: $ | E18: 4400000 | G18: PENDIENTE | H18: AKAI ENERGY LED SRL | I18: =+TODAY()-C18 -> 315 | U18: GROUP DIEZ S.A. | V18: =+SUMIF(H:H,U18,E:E) -> 425000000
A19: AMOMPY | B19: *MAV181100869 | C19: 45981 | D19: $ | E19: 4400000 | G19: PENDIENTE | H19: AKAI ENERGY LED SRL | I19: =+TODAY()-C19 -> 314 | U19: INVLAC CONSTRUCCIONES S.R.L | V19: =+SUMIF(H:H,U19,E:E) -> 4000000
A20: AMOMPY | B20: *MAV181100773 | C20: 45981 | D20: $ | E20: 20000000 | G20: PREVISIONADO | H20: FRIGORIFICO GENERAL PICO S A | I20: =+TODAY()-C20 -> 314 | K20: LIBRADOR PENDIENTE | L20: $ | M20: % PN | O20: VIGENTE | U20: I-LED ARGENTINA S.A. | V20: =+SUMIF(H:H,U20,E:E) -> 60100000
A21: AMOMPY | B21: *MAV191100661 | C21: 45986 | D21: $ | E21: 20000000 | G21: PREVISIONADO | H21: FRIGORIFICO GENERAL PICO S A | I21: =+TODAY()-C21 -> 309 | K21: {=+_xlfn._xlws.SORT(U3:V34,2,-1)} -> GROUP DIEZ S.A. | L21: 425000000 | M21: =+L21/$L$8 -> 0.0056501917 | O21: =+SUMIF('Reporte de Cheques'!A:A,'Cheques pendientes'!K21,'Reporte de Cheques'!I:I) -> 0 | V21: =+SUMIF(H:H,U21,E:E) -> 0
A22: AMOMPY | B22: *MAV201100887 | C22: 45987 | D22: $ | E22: 10000000 | G22: PREVISIONADO | H22: FRIGORIFICO GENERAL PICO S A | I22: =+TODAY()-C22 -> 308 | K22: NIRO CONSTRUYE S. A. | L22: 258370000 | M22: =+L22/$L$8 -> 0.0034349177 | O22: =+SUMIF('Reporte de Cheques'!A:A,'Cheques pendientes'!K22,'Reporte de Cheques'!I:I) -> 0 | V22: =+SUMIF(H:H,U22,E:E) -> 0
A23: AMOMPY | B23: *MAV211100687 | C23: 45988 | D23: $ | E23: 10000000 | G23: PREVISIONADO | H23: FRIGORIFICO GENERAL PICO S A | I23: =+TODAY()-C23 -> 307 | K23: PORT PLA S.R.L. | L23: 150000000 | M23: =+L23/$L$8 -> 0.0019941853 | O23: =+SUMIF('Reporte de Cheques'!A:A,'Cheques pendientes'!K23,'Reporte de Cheques'!I:I) -> 0 | V23: =+SUMIF(H:H,U23,E:E) -> 0
A24: AMOMPY | B24: *MAV221100992 | C24: 45988 | D24: $ | E24: 10000000 | G24: PREVISIONADO | H24: FRIGORIFICO GENERAL PICO S A | I24: =+TODAY()-C24 -> 307 | K24: Maradona Wines | L24: 119500000 | M24: =+L24/$L$8 -> 0.001588701 | O24: =+SUMIF('Reporte de Cheques'!A:A,'Cheques pendientes'!K24,'Reporte de Cheques'!I:I) -> 0 | V24: =+SUMIF(H:H,U24,E:E) -> 0
A25: AMOMPY | B25: *MAV271100809 | C25: 45992 | D25: $ | E25: 3125000 | G25: PENDIENTE | H25: MIANI CLARA A Y MIANI ADA CLELIA | I25: =+TODAY()-C25 -> 303 | K25: FRIGORIFICO GENERAL PICO S A | L25: 70000000 | M25: =+L25/$L$8 -> 0.00093061982 | O25: =+SUMIF('Reporte de Cheques'!A:A,'Cheques pendientes'!K25,'Reporte de Cheques'!I:I) -> 0 | V25: =+SUMIF(H:H,U25,E:E) -> 0
A26: AMOMPY | B26: *MAV291101201 | C26: 45994 | D26: $ | E26: 25000000 | G26: PENDIENTE | H26: PORT PLA S.R.L. | I26: =+TODAY()-C26 -> 301 | K26: MERCOL RAUL ALBERTO Y MERCOL MAURICIO EDUARDO. | L26: 62500000 | M26: =+L26/$L$8 -> 0.00083091055 | O26: =+SUMIF('Reporte de Cheques'!A:A,'Cheques pendientes'!K26,'Reporte de Cheques'!I:I) -> 0 | V26: =+SUMIF(H:H,U26,E:E) -> 0
A27: AMOMPY | B27: *MAV171200694 | C27: 46010 | D27: $ | E27: 6000000 | G27: PREVISIONADO | H27: MASTER DESIGN HOME SRL | I27: =+TODAY()-C27 -> 285 | K27: I-LED ARGENTINA S.A. | L27: 60100000 | M27: =+L27/$L$8 -> 0.00079900359 | O27: =+SUMIF('Reporte de Cheques'!A:A,'Cheques pendientes'!K27,'Reporte de Cheques'!I:I) -> 33000000 | V27: =+SUMIF(H:H,U27,E:E) -> 0
A28: AMOMPY | B28: *MAV291200938 | C28: 46024 | D28: $ | E28: 25000000 | G28: PENDIENTE | H28: PORT PLA S.R.L. | I28: =+TODAY()-C28 -> 271 | K28: FINEX CABA S. A. | L28: 55300000 | M28: =+L28/$L$8 -> 0.00073518966 | O28: =+SUMIF('Reporte de Cheques'!A:A,'Cheques pendientes'!K28,'Reporte de Cheques'!I:I) -> 0 | V28: =+SUMIF(H:H,U28,E:E) -> 0
A29: AMOMPY | B29: *MAV020100774 | C29: 46028 | D29: $ | E29: 10000000 | G29: PENDIENTE | H29: PORT PLA S.R.L. | I29: =+TODAY()-C29 -> 267 | K29: AKAI ENERGY LED SRL | L29: 44963000 | M29: =+L29/$L$8 -> 0.0005977637 | O29: =+SUMIF('Reporte de Cheques'!A:A,'Cheques pendientes'!K29,'Reporte de Cheques'!I:I) -> 0 | V29: =+SUMIF(H:H,U29,E:E) -> 0
A30: AMOMPY | B30: *MAV311200688 | C30: 46028 | D30: $ | E30: 6000000 | G30: PREVISIONADO | H30: MASTER DESIGN HOME SRL | I30: =+TODAY()-C30 -> 267 | K30: TRADICION VALORES S.A. | L30: 25000000 | M30: =+L30/$L$8 -> 0.00033236422 | O30: =+SUMIF('Reporte de Cheques'!A:A,'Cheques pendientes'!K30,'Reporte de Cheques'!I:I) -> 0 | V30: =+SUMIF(H:H,U30,E:E) -> 0
A31: AMOMPY | B31: *MAV050100914 | C31: 46029 | D31: $ | E31: 10000000 | G31: PENDIENTE | H31: PORT PLA S.R.L. | I31: =+TODAY()-C31 -> 266 | K31: MASTER DESIGN HOME SRL | L31: 24000000 | M31: =+L31/$L$8 -> 0.00031906965 | O31: =+SUMIF('Reporte de Cheques'!A:A,'Cheques pendientes'!K31,'Reporte de Cheques'!I:I) -> 0 | V31: =+SUMIF(H:H,U31,E:E) -> 0
A32: AMOMPY | B32: *MAV090100782 | C32: 46035 | D32: $ | E32: 10000000 | G32: PENDIENTE | H32: PORT PLA S.R.L. | I32: =+TODAY()-C32 -> 260 | K32: GROCAL S.A. | L32: 15000000 | M32: =+L32/$L$8 -> 0.00019941853 | O32: =+SUMIF('Reporte de Cheques'!A:A,'Cheques pendientes'!K32,'Reporte de Cheques'!I:I) -> 0 | V32: =+SUMIF(H:H,U32,E:E) -> 0
A33: AMOMPY | B33: *MAV120100963 | C33: 46036 | D33: $ | E33: 10000000 | G33: PENDIENTE | H33: PORT PLA S.R.L. | I33: =+TODAY()-C33 -> 259 | K33: Paccioli Group Sociedad Anonima | L33: 13958000 | M33: =+L33/$L$8 -> 0.00018556559 | O33: =+SUMIF('Reporte de Cheques'!A:A,'Cheques pendientes'!K33,'Reporte de Cheques'!I:I) -> 0 | V33: =+SUMIF(H:H,U33,E:E) -> 0
A34: AMOMPY | B34: *MAV120101031 | C34: 46036 | D34: $ | E34: 5000000 | G34: PENDIENTE | H34: GROCAL S.A. | I34: =+TODAY()-C34 -> 259 | K34: RABU INVERSIONES SRL | L34: 7194300 | M34: =+L34/$L$8 -> 9.5645116e-05 | O34: =+SUMIF('Reporte de Cheques'!A:A,'Cheques pendientes'!K34,'Reporte de Cheques'!I:I) -> 0 | V34: =+SUMIF(H:H,U34,E:E) -> 0
A35: AMOMPY | B35: *MAV140100871 | C35: 46038 | D35: $ | E35: 5000000 | G35: PENDIENTE | H35: GROCAL S.A. | I35: =+TODAY()-C35 -> 257 | K35: UKUMARI SOCIEDAD ANONIMA. | L35: 6812500 | M35: =+L35/$L$8 -> 9.056925e-05 | O35: =+SUMIF('Reporte de Cheques'!A:A,'Cheques pendientes'!K35,'Reporte de Cheques'!I:I) -> 0
A36: AMOMPY | B36: *MAV160100849 | C36: 46042 | D36: $ | E36: 10000000 | G36: PENDIENTE | H36: PORT PLA S.R.L. | I36: =+TODAY()-C36 -> 253 | K36: INVLAC CONSTRUCCIONES S.R.L | L36: 4000000 | M36: =+L36/$L$8 -> 5.3178275e-05 | O36: =+SUMIF('Reporte de Cheques'!A:A,'Cheques pendientes'!K36,'Reporte de Cheques'!I:I) -> 0
A37: AMOMPY | B37: *MAV160100806 | C37: 46042 | D37: $ | E37: 4000000 | G37: PREVISIONADO | H37: MASTER DESIGN HOME SRL | I37: =+TODAY()-C37 -> 253 | K37: MIANI CLARA A Y MIANI ADA CLELIA | L37: 3125000 | M37: =+L37/$L$8 -> 4.1545528e-05 | O37: =+SUMIF('Reporte de Cheques'!A:A,'Cheques pendientes'!K37,'Reporte de Cheques'!I:I) -> 0
A38: AMOMPY | B38: *MAV190100896 | C38: 46043 | D38: $ | E38: 10000000 | G38: PENDIENTE | H38: PORT PLA S.R.L. | I38: =+TODAY()-C38 -> 252 | K38: LOPEZ LUCIA SOLEDAD | L38: 995000 | M38: =+L38/$L$8 -> 1.3228096e-05 | O38: =+SUMIF('Reporte de Cheques'!A:A,'Cheques pendientes'!K38,'Reporte de Cheques'!I:I) -> 0
A39: AMOMPY | B39: *MAV200101319 | C39: 46044 | D39: $ | E39: 1395800 | G39: PENDIENTE | H39: Paccioli Group Sociedad Anonima | I39: =+TODAY()-C39 -> 251 | K39: 0 | L39: 0 | M39: =+L39/$L$8 -> 0 | O39: =+SUMIF('Reporte de Cheques'!A:A,'Cheques pendientes'!K39,'Reporte de Cheques'!I:I) -> 0
A40: AMOMPY | B40: *MAV200101320 | C40: 46044 | D40: $ | E40: 1395800 | G40: PENDIENTE | H40: Paccioli Group Sociedad Anonima | I40: =+TODAY()-C40 -> 251 | K40: 0 | L40: 0 | M40: =+L40/$L$8 -> 0 | O40: =+SUMIF('Reporte de Cheques'!A:A,'Cheques pendientes'!K40,'Reporte de Cheques'!I:I) -> 0
A41: AMOMPY | B41: *MAV200101321 | C41: 46044 | D41: $ | E41: 1395800 | G41: PENDIENTE | H41: Paccioli Group Sociedad Anonima | I41: =+TODAY()-C41 -> 251 | K41: 0 | L41: 0 | M41: =+L41/$L$8 -> 0 | O41: =+SUMIF('Reporte de Cheques'!A:A,'Cheques pendientes'!K41,'Reporte de Cheques'!I:I) -> 0
A42: AMOMPY | B42: *MAV200101322 | C42: 46044 | D42: $ | E42: 1395800 | G42: PENDIENTE | H42: Paccioli Group Sociedad Anonima | I42: =+TODAY()-C42 -> 251 | K42: 0 | L42: 0 | M42: =+L42/$L$8 -> 0 | O42: =+SUMIF('Reporte de Cheques'!A:A,'Cheques pendientes'!K42,'Reporte de Cheques'!I:I) -> 0
A43: AMOMPY | B43: *MAV210100855 | C43: 46045 | D43: $ | E43: 1395800 | G43: PENDIENTE | H43: Paccioli Group Sociedad Anonima | I43: =+TODAY()-C43 -> 250 | K43: 0 | L43: 0 | M43: =+L43/$L$8 -> 0 | O43: =+SUMIF('Reporte de Cheques'!A:A,'Cheques pendientes'!K43,'Reporte de Cheques'!I:I) -> 0
A44: AMOMPY | B44: *MAV210100764 | C44: 46045 | D44: $ | E44: 4000000 | G44: PREVISIONADO | H44: MASTER DESIGN HOME SRL | I44: =+TODAY()-C44 -> 250 | K44: 0 | L44: 0 | M44: =+L44/$L$8 -> 0 | O44: =+SUMIF('Reporte de Cheques'!A:A,'Cheques pendientes'!K44,'Reporte de Cheques'!I:I) -> 0
A45: AMOMPY | B45: *MAV210100850 | C45: 46045 | D45: $ | E45: 15900000 | G45: PENDIENTE | H45: FINEX CABA S. A. | I45: =+TODAY()-C45 -> 250 | K45: 0 | L45: 0 | M45: =+L45/$L$8 -> 0 | O45: =+SUMIF('Reporte de Cheques'!A:A,'Cheques pendientes'!K45,'Reporte de Cheques'!I:I) -> 0
A46: AMOMPY | B46: *MAV210100774 | C46: 46045 | D46: $ | E46: 5000000 | G46: PENDIENTE | H46: GROCAL S.A. | I46: =+TODAY()-C46 -> 250 | K46: 0 | L46: 0 | M46: =+L46/$L$8 -> 0 | O46: =+SUMIF('Reporte de Cheques'!A:A,'Cheques pendientes'!K46,'Reporte de Cheques'!I:I) -> 0
A47: AMOMPY | B47: *MAV220100909 | C47: 46048 | D47: $ | E47: 1395800 | G47: PENDIENTE | H47: Paccioli Group Sociedad Anonima | I47: =+TODAY()-C47 -> 247 | K47: 0 | L47: 0 | M47: =+L47/$L$8 -> 0 | O47: =+SUMIF('Reporte de Cheques'!A:A,'Cheques pendientes'!K47,'Reporte de Cheques'!I:I) -> 0
A48: AMOMPY | B48: *MAV230100842 | C48: 46049 | D48: $ | E48: 10000000 | G48: PENDIENTE | H48: PORT PLA S.R.L. | I48: =+TODAY()-C48 -> 246 | K48: 0 | L48: 0 | M48: =+L48/$L$8 -> 0 | O48: =+SUMIF('Reporte de Cheques'!A:A,'Cheques pendientes'!K48,'Reporte de Cheques'!I:I) -> 0
A49: AMOMPY | B49: *MAV230100905 | C49: 46049 | D49: $ | E49: 1395800 | G49: PENDIENTE | H49: Paccioli Group Sociedad Anonima | I49: =+TODAY()-C49 -> 246 | K49: 0 | L49: 0 | M49: =+L49/$L$8 -> 0 | O49: =+SUMIF('Reporte de Cheques'!A:A,'Cheques pendientes'!K49,'Reporte de Cheques'!I:I) -> 0
A50: AMOMPY | B50: *MAV230100906 | C50: 46049 | D50: $ | E50: 1395800 | G50: PENDIENTE | H50: Paccioli Group Sociedad Anonima | I50: =+TODAY()-C50 -> 246 | K50: 0 | L50: 0 | M50: =+L50/$L$8 -> 0 | O50: =+SUMIF('Reporte de Cheques'!A:A,'Cheques pendientes'!K50,'Reporte de Cheques'!I:I) -> 0
... A52: AMOMPY | B52: *MAV230100908 | C52: 46049 | D52: $ | E52: 1395800 | G52: PENDIENTE | H52: Paccioli Group Sociedad Anonima | I52: =+TODAY()-C52 -> 246 | K52: 0 | L52: 0 | M52: =+L52/$L$8 -> 0 | O52: =+SUMIF('Reporte de Cheques'!A:A,'Cheques pendientes'!K52,'Reporte de Cheques'!I:I) -> 0
A53: AMOMPY | B53: *MAV260100839 | C53: 46050 | D53: $ | E53: 6250000 | G53: PENDIENTE | H53: TRADICION VALORES S.A. | I53: =+TODAY()-C53 -> 245
A54: AMOMPY | B54: *MAV260100805 | C54: 46050 | D54: $ | E54: 4000000 | G54: PREVISIONADO | H54: MASTER DESIGN HOME SRL | I54: =+TODAY()-C54 -> 245
A55: AMOMPY | B55: *MAV240101107 | C55: 46050 | D55: $ | E55: 22000000 | G55: PENDIENTE | H55: Maradona Wines | I55: =+TODAY()-C55 -> 245
A56: AMOMPY | B56: *MAV270100949 | C56: 46051 | D56: $ | E56: 10000000 | G56: PENDIENTE | H56: PORT PLA S.R.L. | I56: =+TODAY()-C56 -> 244
A57: AMOMPY | B57: *MAV280100704 | C57: 46052 | D57: $ | E57: 6250000 | G57: PENDIENTE | H57: TRADICION VALORES S.A. | I57: =+TODAY()-C57 -> 243
A58: AMOMPY | B58: *MAV300100888 | C58: 46056 | D58: $ | E58: 6250000 | G58: PENDIENTE | H58: TRADICION VALORES S.A. | I58: =+TODAY()-C58 -> 239
A59: AMOMPY | B59: *MAV300100901 | C59: 46056 | D59: $ | E59: 995000 | G59: PENDIENTE | H59: LOPEZ LUCIA SOLEDAD | I59: =+TODAY()-C59 -> 239
A60: AMOMPY | B60: *MAV300100900 | C60: 46056 | D60: $ | E60: 2398100 | G60: PENDIENTE | H60: RABU INVERSIONES SRL | I60: =+TODAY()-C60 -> 239
A61: AMOMPY | B61: *MAV300100917 | C61: 46056 | D61: $ | E61: 10000000 | G61: PENDIENTE | H61: PORT PLA S.R.L. | I61: =+TODAY()-C61 -> 239
A62: AMOMPY | B62: *MAV310101295 | C62: 46057 | D62: $ | E62: 6250000 | G62: PENDIENTE | H62: TRADICION VALORES S.A. | I62: =+TODAY()-C62 -> 238
A63: AMOMPY | B63: *MAV020200696 | C63: 46057 | D63: $ | E63: 2398100 | G63: PENDIENTE | H63: RABU INVERSIONES SRL | I63: =+TODAY()-C63 -> 238
A64: AMOMPY | B64: *MAV020200731 | C64: 46057 | D64: $ | E64: 10000000 | G64: PENDIENTE | H64: PORT PLA S.R.L. | I64: =+TODAY()-C64 -> 238
... A100: AMOMPY | B100: *MIL250900034 | C100: 46294 | D100: $ | E100: 5000000 | G100: PENDIENTE | H100: MILLS S.G.R. | I100: =+TODAY()-C100 -> 1

Sheet Reporte de Cheques
A1: Reporte de Cheques de Pago Diferido | W1: Valor Patrimonial del Fondo
A2: Cheque de Pago Diferido y Pagaré | B2: Moneda | C2: Cheque de Pago Diferido y Pagaré | D2: Fecha | E2: Precio | F2: Tipo de Cambio (Cheque/Fondo) | G2: Moneda Cheque | H2: Moneda Cheque | I2: Moneda Fondo | J2: Moneda Fondo | K2: Compra | L2: Fondo | M2: Compra | N2: Compra | O2: Compra | P2: Compra | Q2: Vendido | R2: Venta | S2: Venta | T2: Venta | U2: Cheque de Pago Diferido y Pagaré | V2: Cheque de Pago Diferido y Pagaré | W2: =+VLOOKUP(W1,'GESTION MOMENTUM'!A:B,2,0) -> 7.5218686e+10
A3: Sociedad de Garantía Recíproca / Librador | B3: Descripción | C3: Fecha de Vencimiento | D3: Fecha | E3: Precio | F3: Tipo de Cambio (Cheque/Fondo) | G3: Importe Nominal | H3: Importe Actual | I3: Importe Nominal | J3: Importe Actual | K3: Nro. de Operación | L3: Nombre | M3: Agente | N3: Fecha Concertación | O3: Fecha Liquidación | P3: Tasa de Descuento | Q3: Vendido | R3: Nro. de Operación | S3: Fecha Concertación | T3: Fecha Liquidación | U3: Abreviatura | V3: Código CAFCI | W3: %
A4: PAPEZOPP S.A.S. | B4: Pesos | C4: 46294 | D4: 29/09/2026 | E4: 1 | G4: 2097348.4 | H4: 2097348.4 | I4: 2097348.4 | J4: 2097348.4 | K4: 76510842 | L4: AMOMPY | M4: Momentum Capital Investment S.A. | N4: 22/07/2026 | O4: 22/07/2026 | P4: 32 | Q4: No | U4: *MAV250901366 | V4: *MAV250901366 | W4: =+J4/$W$2 -> 2.7883343e-05
A5: TOYOS CASIMIRO FELIX E HIJOS | B5: Pesos | C5: 46294 | D5: 29/09/2026 | E5: 1 | G5: 12000000 | H5: 12000000 | I5: 12000000 | J5: 12000000 | K5: 29830738 | L5: AMOMPY | M5: Momentum Capital Investment S.A. | N5: 10/08/2026 | O5: 10/08/2026 | P5: 28 | Q5: No | U5: *MAV250901494 | V5: *MAV250901494 | W5: =+J5/$W$2 -> 0.00015953483
A6: Casa Hutton SA | B6: Pesos | C6: 46294 | D6: 29/09/2026 | E6: 1 | G6: 40000000 | H6: 40000000 | I6: 40000000 | J6: 40000000 | K6: 13662791 | L6: AMOMPY | M6: Momentum Capital Investment S.A. | N6: 12/06/2026 | O6: 12/06/2026 | P6: 32 | Q6: No | U6: *MAV250901177 | V6: *MAV250901177 | W6: =+J6/$W$2 -> 0.00053178275
A7: HENDEL HOGAR SA | B7: Pesos | C7: 46294 | D7: 29/09/2026 | E7: 1 | G7: 7560000 | H7: 7560000 | I7: 7560000 | J7: 7560000 | K7: 10537648 | L7: AMOMPY | M7: Momentum Capital Investment S.A. | N7: 10/08/2026 | O7: 10/08/2026 | P7: 28 | Q7: No | U7: *MAV250901491 | V7: *MAV250901491 | W7: =+J7/$W$2 -> 0.00010050694
A8: TRANSPORTES C Y S 2011 SRL | B8: Pesos | C8: 46294 | D8: 29/09/2026 | E8: 1 | G8: 1382744 | H8: 1382744 | I8: 1382744 | J8: 1382744 | K8: 5365 | L8: AMOMPY | M8: Momentum Capital Investment S.A. | N8: 08/09/2026 | O8: 08/09/2026 | P8: 31 | Q8: No | U8: *MAV250901852 | V8: *MAV250901852 | W8: =+J8/$W$2 -> 1.8382985e-05
A9: TRAN SER SA | B9: Pesos | C9: 46294 | D9: 29/09/2026 | E9: 1 | G9: 1509475 | H9: 1509475 | I9: 1509475 | J9: 1509475 | K9: 3848023 | L9: AMOMPY | M9: Momentum Capital Investment S.A. | N9: 15/09/2026 | O9: 15/09/2026 | P9: 32 | Q9: No | U9: *MAV250901938 | V9: *MAV250901938 | W9: =+J9/$W$2 -> 2.0067819e-05
A10: LOS GROBO SGR | B10: Pesos | C10: 46294 | D10: 29/09/2026 | E10: 1 | G10: 4000000 | H10: 4000000 | I10: 4000000 | J10: 4000000 | K10: 16821013 | L10: AMOMPY | M10: Momentum Capital Investment S.A. | N10: 17/07/2026 | O10: 17/07/2026 | P10: 24 | Q10: No | U10: *PRO250900021 | V10: *PRO250900021 | W10: =+J10/$W$2 -> 5.3178275e-05
A11: LOS GROBO SGR | B11: Pesos | C11: 46294 | D11: 29/09/2026 | E11: 1 | G11: 10950000 | H11: 10950000 | I11: 10950000 | J11: 10950000 | K11: 90000869 | L11: AMOMPY | M11: Momentum Capital Investment S.A. | N11: 13/08/2026 | O11: 13/08/2026 | P11: 28 | Q11: No | U11: *PRO250900023 | V11: *PRO250900023 | W11: =+J11/$W$2 -> 0.00014557553
A12: LOS GROBO SGR | B12: Pesos | C12: 46294 | D12: 29/09/2026 | E12: 1 | G12: 20000000 | H12: 20000000 | I12: 20000000 | J12: 20000000 | K12: 67970141 | L12: AMOMPY | M12: Momentum Capital Investment S.A. | N12: 29/06/2026 | O12: 29/06/2026 | P12: 27 | Q12: No | U12: *PRO250900016 | V12: *PRO250900016 | W12: =+J12/$W$2 -> 0.00026589138
A13: GENERAC TECHNOLOGY MANAGEMENT | B13: Pesos | C13: 46294 | D13: 29/09/2026 | E13: 1 | G13: 100000000 | H13: 100000000 | I13: 100000000 | J13: 100000000 | K13: 83 | L13: AMOMPY | M13: Momentum Capital Investment S.A. | N13: 12/08/2026 | O13: 12/08/2026 | P13: 28 | Q13: No | U13: *MAV250901519 | V13: *MAV250901519 | W13: =+J13/$W$2 -> 0.0013294569
A14: MILLS S.G.R. | B14: Pesos | C14: 46294 | D14: 29/09/2026 | E14: 1 | G14: 5000000 | H14: 5000000 | I14: 5000000 | J14: 5000000 | K14: 8743 | L14: AMOMPY | M14: Momentum Capital Investment S.A. | N14: 17/07/2026 | O14: 17/07/2026 | P14: 25 | Q14: No | U14: *MIL250900034 | V14: *MIL250900034 | W14: =+J14/$W$2 -> 6.6472844e-05
A15: MILLS S.G.R. | B15: Pesos | C15: 46294 | D15: 29/09/2026 | E15: 1 | G15: 9000000 | H15: 9000000 | I15: 9000000 | J15: 9000000 | K15: 68958371 | L15: AMOMPY | M15: Momentum Capital Investment S.A. | N15: 14/08/2026 | O15: 14/08/2026 | P15: 28 | Q15: No | U15: *MIL250900037 | V15: *MIL250900037 | W15: =+J15/$W$2 -> 0.00011965112
... A169: TEXTUM SA | B169: Pesos | C169: 46300 | D169: 29/09/2026 | E169: 0.99476729 | G169: 10000000 | H169: 9947672.9 | I169: 10000000 | J169: 9947672.9 | K169: 14422562 | L169: AMOMPY | M169: Momentum Capital Investment S.A. | N169: 01/09/2026 | O169: 01/09/2026 | P169: 32 | Q169: No | U169: *MAV011001420 | V169: *MAV011001420 | W169: =+J169/$W$2 -> 0.00013225002
A170: BSP LARTI SA | B170: Dolar 3500 | C170: 46300 | D170: 29/09/2026 | E170: 0.998359 | F170: 1 US3 = 1523,9697583441 $ | G170: 70000 | H170: 69885.13 | I170: 1.0667788e+08 | J170: 1.0650282e+08 | K170: 163087 | L170: AMOMPY | M170: Momentum Capital Investment S.A. | N170: 31/08/2026 | O170: 31/08/2026 | P170: 10 | Q170: No | U170: #UMV011060031 | V170: #UMV011060031 | W170: =+J170/$W$2 -> 0.0014159091
A171: COOPERATIVA DE TABACALEROS DE JUJUY LTDA | B171: Dolar 3500 | C171: 46300 | D171: 29/09/2026 | E171: 0.9986866 | F171: 1 US3 = 1523,9697583441 $ | G171: 188100 | H171: 187852.95 | I171: 2.8665871e+08 | J171: 2.8628221e+08 | K171: 160721 | L171: AMOMPY | M171: Momentum Capital Investment S.A. | N171: 12/08/2026 | O171: 12/08/2026 | P171: 8 | Q171: No | U171: #UMV011060030 | V171: #UMV011060030 | W171: =+J171/$W$2 -> 0.0038059986
A172: COOPERATIVA DE TABACALEROS DE JUJUY LTDA | B172: Dolar 3500 | C172: 46300 | D172: 29/09/2026 | E172: 0.9988506 | F172: 1 US3 = 1523,9697583441 $ | G172: 50000 | H172: 49942.53 | I172: 76198488 | J172: 76110905 | K172: 150093 | L172: AMOMPY | M172: Momentum Capital Investment S.A. | N172: 15/05/2026 | O172: 15/05/2026 | P172: 7 | Q172: No | U172: #UMV011060013 | V172: #UMV011060013 | W172: =+J172/$W$2 -> 0.0010118617
A173: COOPERATIVA DE TABACALEROS DE JUJUY LTDA | B173: Dolar 3500 | C173: 46300 | D173: 29/09/2026 | E173: 0.9985228 | F173: 1 US3 = 1523,9697583441 $ | G173: 25000 | H173: 24963.07 | I173: 38099244 | J173: 38042964 | K173: 150614 | L173: AMOMPY | M173: Momentum Capital Investment S.A. | N173: 19/05/2026 | O173: 19/05/2026 | P173: 9 | Q173: No | U173: #UMV011060014 | V173: #UMV011060014 | W173: =+J173/$W$2 -> 0.0005057648
A174: ESPECIALIDADES AGROPECUARIAS S.A. | B174: Pesos | C174: 46300 | D174: 29/09/2026 | E174: 0.99476729 | G174: 3000000 | H174: 2984301.9 | I174: 3000000 | J174: 2984301.9 | K174: 1034 | L174: AMOMPY | M174: Momentum Capital Investment S.A. | N174: 25/08/2026 | O174: 25/08/2026 | P174: 32 | Q174: No | U174: *MAV011001354 | V174: *MAV011001354 | W174: =+J174/$W$2 -> 3.9675007e-05
A175: ESPECIALIDADES AGROPECUARIAS S.A. | B175: Pesos | C175: 46300 | D175: 29/09/2026 | E175: 0.99476726 | G175: 2000000 | H175: 1989534.5 | I175: 2000000 | J175: 1989534.5 | K175: 1081 | L175: AMOMPY | M175: Momentum Capital Investment S.A. | N175: 26/08/2026 | O175: 26/08/2026 | P175: 32 | Q175: No | U175: *MAV011001375 | V175: *MAV011001375 | W175: =+J175/$W$2 -> 2.6450003e-05
A176: ESPECIALIDADES AGROPECUARIAS S.A. | B176: Pesos | C176: 46300 | D176: 29/09/2026 | E176: 0.99509272 | G176: 3300000 | H176: 3283806 | I176: 3300000 | J176: 3283806 | K176: 922 | L176: AMOMPY | M176: Momentum Capital Investment S.A. | N176: 11/08/2026 | O176: 11/08/2026 | P176: 30 | Q176: No | U176: *MAV011001284 | V176: *MAV011001284 | W176: =+J176/$W$2 -> 4.3656785e-05
A177: ESPECIALIDADES AGROPECUARIAS S.A. | B177: Pesos | C177: 46300 | D177: 29/09/2026 | E177: 0.99509272 | G177: 2500000 | H177: 2487731.8 | I177: 2500000 | J177: 2487731.8 | K177: 904 | L177: AMOMPY | M177: Momentum Capital Investment S.A. | N177: 07/08/2026 | O177: 07/08/2026 | P177: 30 | Q177: No | U177: *MAV011001237 | V177: *MAV011001237 | W177: =+J177/$W$2 -> 3.3073321e-05
A178: INTEGRA PYMES SGR | B178: Pesos | C178: 46301 | D178: 29/09/2026 | E178: 0.99541837 | G178: 5000000 | H178: 4977091.8 | I178: 5000000 | J178: 4977091.8 | K178: 16831529 | L178: AMOMPY | M178: Momentum Capital Investment S.A. | N178: 21/07/2026 | O178: 21/07/2026 | P178: 24 | Q178: No | U178: *INP021000033 | V178: *INP021000033 | W178: =+J178/$W$2 -> 6.616829e-05
A179: NEXTRANS SRL | B179: Pesos | C179: 46301 | D179: 29/09/2026 | E179: 0.9942795 | G179: 5577023 | H179: 5545119.7 | I179: 5577023 | J179: 5545119.7 | K179: 90017209 | L179: AMOMPY | M179: Momentum Capital Investment S.A. | N179: 11/09/2026 | O179: 11/09/2026 | P179: 30 | Q179: No | U179: *MAV021001538 | V179: *MAV021001538 | W179: =+J179/$W$2 -> 7.3719975e-05
A180: SIGMA AGRO S.A. | B180: Pesos | C180: 46301 | D180: 29/09/2026 | E180: 0.99427949 | G180: 100000000 | H180: 99427949 | I180: 100000000 | J180: 99427949 | K180: 90003952 | L180: AMOMPY | M180: Momentum Capital Investment S.A. | N180: 29/07/2026 | O180: 29/07/2026 | P180: 30 | Q180: No | U180: *MAV021001096 | V180: *MAV021001096 | W180: =+J180/$W$2 -> 0.0013218517
A181: CAL/WEST SEEDS SRL | B181: Dolar Link | C181: 46301 | D181: 29/09/2026 | E181: 0.99713139 | F181: 1 BNA = 1544,9999783700 $ | G181: 6619.93 | H181: 6600.94 | I181: 10227792 | J181: 10198452 | K181: 65 | L181: AMOMPY | M181: Momentum Capital Investment S.A. | N181: 17/09/2026 | O181: 17/09/2026 | P181: 15 | Q181: No | U181: %UZV041000001 | V181: %UZV041000001 | W181: =+J181/$W$2 -> 0.00013558402
A182: ESPECIALIDADES AGROPECUARIAS S.A. | B182: Pesos | C182: 46301 | D182: 29/09/2026 | E182: 0.99390051 | G182: 4000000 | H182: 3975602 | I182: 4000000 | J182: 3975602 | K182: 1144 | L182: AMOMPY | M182: Momentum Capital Investment S.A. | N182: 03/09/2026 | O182: 03/09/2026 | P182: 32 | Q182: No | U182: *MAV021001360 | V182: *MAV021001360 | W182: =+J182/$W$2 -> 5.2853915e-05
A183: ESPECIALIDADES AGROPECUARIAS S.A. | B183: Pesos | C183: 46301 | D183: 29/09/2026 | E183: 0.9942795 | G183: 5000000 | H183: 4971397.5 | I183: 5000000 | J183: 4971397.5 | K183: 1215 | L183: AMOMPY | M183: Momentum Capital Investment S.A. | N183: 11/09/2026 | O183: 11/09/2026 | P183: 30 | Q183: No | U183: *MAV021001525 | V183: *MAV021001525 | W183: =+J183/$W$2 -> 6.6092586e-05
A184: ESPECIALIDADES AGROPECUARIAS S.A. | B184: Pesos | C184: 46301 | D184: 29/09/2026 | E184: 0.99427958 | G184: 5000000 | H184: 4971397.9 | I184: 5000000 | J184: 4971397.9 | K184: 1221 | L184: AMOMPY | M184: Momentum Capital Investment S.A. | N184: 14/09/2026 | O184: 14/09/2026 | P184: 30 | Q184: No | U184: *MAV021001541 | V184: *MAV021001541 | W184: =+J184/$W$2 -> 6.6092592e-05
A185: ESPECIALIDADES AGROPECUARIAS S.A. | B185: Pesos | C185: 46301 | D185: 29/09/2026 | E185: 0.99427954 | G185: 5000000 | H185: 4971397.7 | I185: 5000000 | J185: 4971397.7 | K185: 1225 | L185: AMOMPY | M185: Momentum Capital Investment S.A. | N185: 16/09/2026 | O185: 16/09/2026 | P185: 30 | Q185: No | U185: *MAV021001569 | V185: *MAV021001569 | W185: =+J185/$W$2 -> 6.6092589e-05
A186: ESPECIALIDADES AGROPECUARIAS S.A. | B186: Pesos | C186: 46301 | D186: 29/09/2026 | E186: 0.99390047 | G186: 3000000 | H186: 2981701.4 | I186: 3000000 | J186: 2981701.4 | K186: 1035 | L186: AMOMPY | M186: Momentum Capital Investment S.A. | N186: 25/08/2026 | O186: 25/08/2026 | P186: 32 | Q186: No | U186: *MAV021001284 | V186: *MAV021001284 | W186: =+J186/$W$2 -> 3.9640435e-05
A187: TARJETA NARANJA SA | B187: Pesos | C187: 46301 | D187: 29/09/2026 | E187: 0.99465883 | G187: 8584261 | H187: 8538411 | I187: 8584261 | J187: 8538411 | K187: 629236 | L187: AMOMPY | M187: Momentum Capital Investment S.A. | N187: 10/08/2026 | O187: 10/08/2026 | P187: 28 | Q187: No | U187: *MAV021001181 | V187: *MAV021001181 | W187: =+J187/$W$2 -> 0.00011351449
A188: TARJETA NARANJA SA | B188: Pesos | C188: 46301 | D188: 29/09/2026 | E188: 0.99465883 | G188: 8584261 | H188: 8538411 | I188: 8584261 | J188: 8538411 | K188: 629242 | L188: AMOMPY | M188: Momentum Capital Investment S.A. | N188: 10/08/2026 | O188: 10/08/2026 | P188: 28 | Q188: No | U188: *MAV021001182 | V188: *MAV021001182 | W188: =+J188/$W$2 -> 0.00011351449
A189: TARJETA NARANJA SA | B189: Pesos | C189: 46301 | D189: 29/09/2026 | E189: 0.99465883 | G189: 8584261 | H189: 8538411 | I189: 8584261 | J189: 8538411 | K189: 629234 | L189: AMOMPY | M189: Momentum Capital Investment S.A. | N189: 10/08/2026 | O189: 10/08/2026 | P189: 28 | Q189: No | U189: *MAV021001183 | V189: *MAV021001183 | W189: =+J189/$W$2 -> 0.00011351449
A190: DROGUERIA GARZON SA | B190: Pesos | C190: 46301 | D190: 29/09/2026 | E190: 0.99371117 | G190: 34382424 | H190: 34166199 | I190: 34382424 | J190: 34166199 | K190: 90022563 | L190: AMOMPY | M190: Momentum Capital Investment S.A. | N190: 24/09/2026 | O190: 24/09/2026 | P190: 33 | Q190: No | U190: *MAV021001704 | V190: *MAV021001704 | W190: =+J190/$W$2 -> 0.00045422488
A191: BEROLI SAS | B191: Pesos | C191: 46301 | D191: 29/09/2026 | E191: 0.9942795 | G191: 6150126.3 | H191: 6114944.5 | I191: 6150126.3 | J191: 6114944.5 | K191: 57 | L191: AMOMPY | M191: Momentum Capital Investment S.A. | N191: 11/09/2026 | O191: 11/09/2026 | P191: 30 | Q191: No | U191: *MAV021001539 | V191: *MAV021001539 | W191: =+J191/$W$2 -> 8.1295551e-05
A192: LOS GROBO SGR | B192: Pesos | C192: 46301 | D192: 29/09/2026 | E192: 0.99541837 | G192: 2500000 | H192: 2488545.9 | I192: 2500000 | J192: 2488545.9 | K192: 16821015 | L192: AMOMPY | M192: Momentum Capital Investment S.A. | N192: 17/07/2026 | O192: 17/07/2026 | P192: 24 | Q192: No | U192: *PRO021000009 | V192: *PRO021000009 | W192: =+J192/$W$2 -> 3.3084145e-05
A193: PAMPA VIDA S.R.L. | B193: Pesos | C193: 46301 | D193: 29/09/2026 | E193: 0.99371106 | G193: 5000000 | H193: 4968555.3 | I193: 5000000 | J193: 4968555.3 | K193: 3040 | L193: AMOMPY | M193: Momentum Capital Investment S.A. | N193: 21/07/2026 | O193: 21/07/2026 | P193: 33 | Q193: No | U193: *MAV021001048 | V193: *MAV021001048 | W193: =+J193/$W$2 -> 6.60548e-05
... A212: EMEPA S A | B212: Pesos | C212: 46301 | D212: 29/09/2026 | E212: 0.99352174 | G212: 5150760.3 | H212: 5117392.3 | I212: 5150760.3 | J212: 5117392.3 | K212: 1324 | L212: AMOMPY | M212: Momentum Capital Investment S.A. | N212: 26/08/2026 | O212: 26/08/2026 | P212: 34 | Q212: No | U212: *MAV021001304 | V212: *MAV021001304 | W212: =+J212/$W$2 -> 6.8033524e-05
A213: SERVICIOS Y PRODUCTOS PARA BEBIDAS REFRESCANTES SRL | B213: Dolar Link | C213: 46301 | D213: 29/09/2026 | E213: 0.99770539 | F213: 1 BNA = 1544,9999783700 $ | G213: 4105.28 | H213: 4095.86 | I213: 6342657.5 | J213: 6328103.6 | K213: 70 | L213: AMOMPY | M213: Momentum Capital Investment S.A. | N213: 31/08/2026 | O213: 31/08/2026 | P213: 12 | Q213: No | U213: %USP031000001 | V213: %USP031000001 | W213: =+J213/$W$2 -> 8.4129409e-05
A214: Movil SGR | B214: Pesos | C214: 46301 | D214: 29/09/2026 | E214: 0.99465882 | G214: 2500000 | H214: 2486647.1 | I214: 2500000 | J214: 2486647.1 | K214: 90031811 | L214: AMOMPY | M214: Momentum Capital Investment S.A. | N214: 22/04/2026 | O214: 22/04/2026 | P214: 28 | Q214: No | U214: *MOV021000044 | V214: *MOV021000044 | W214: =+J214/$W$2 -> 3.30589e-05
A215: Movil SGR | B215: Pesos | C215: 46301 | D215: 29/09/2026 | E215: 0.99465883 | G215: 25000000 | H215: 24866471 | I215: 25000000 | J215: 24866471 | K215: 360569 | L215: AMOMPY | M215: Momentum Capital Investment S.A. | N215: 21/04/2026 | O215: 21/04/2026 | P215: 28 | Q215: No | U215: *MOV021000043 | V215: *MOV021000043 | W215: =+J215/$W$2 -> 0.00033058901
A216: METALFOR SA | B216: Pesos | C216: 46301 | D216: 29/09/2026 | E216: 0.99579855 | G216: 13000000 | H216: 12945381 | I216: 13000000 | J216: 12945381 | K216: 34113 | L216: AMOMPY | M216: Momentum Capital Investment S.A. | N216: 30/06/2026 | O216: 30/06/2026 | P216: 22 | Q216: No | U216: *MAV021000966 | V216: *MAV021000966 | W216: =+J216/$W$2 -> 0.00017210326
A217: ESPECIALIDADES AGROPECUARIAS S.A. | B217: Pesos | C217: 46301 | D217: 29/09/2026 | E217: 0.99390049 | G217: 2000000 | H217: 1987801 | I217: 2000000 | J217: 1987801 | K217: 1067 | L217: AMOMPY | M217: Momentum Capital Investment S.A. | N217: 26/08/2026 | O217: 26/08/2026 | P217: 32 | Q217: No | U217: *MAV021001309 | V217: *MAV021001309 | W217: =+J217/$W$2 -> 2.6426957e-05
A218: COOPERATIVA DE VIVIENDA CREDITO Y CONSUMO PARA EL DESARROLLO LIMITADA | B218: Pesos | C218: 46301 | D218: 29/09/2026 | E218: 0.99276507 | G218: 20000000 | H218: 19855301 | I218: 20000000 | J218: 19855301 | K218: 70219564 | L218: AMOMPY | M218: Momentum Capital Investment S.A. | N218: 03/08/2026 | O218: 03/08/2026 | P218: 38 | Q218: No | U218: *MAV021001116 | V218: *MAV021001116 | W218: =+J218/$W$2 -> 0.00026396767
A219: COOPERATIVA DE VIVIENDA CREDITO Y CONSUMO PARA EL DESARROLLO LIMITADA | B219: Pesos | C219: 46301 | D219: 29/09/2026 | E219: 0.99276507 | G219: 20000000 | H219: 19855301 | I219: 20000000 | J219: 19855301 | K219: 70219565 | L219: AMOMPY | M219: Momentum Capital Investment S.A. | N219: 03/08/2026 | O219: 03/08/2026 | P219: 38 | Q219: No | U219: *MAV021001117 | V219: *MAV021001117 | W219: =+J219/$W$2 -> 0.00026396767
A220: SERVILLETAS PALLMAR S.R.L. | B220: Pesos | C220: 46302 | D220: 29/09/2026 | E220: 0.99303517 | G220: 3216984.1 | H220: 3194578.4 | I220: 3216984.1 | J220: 3194578.4 | K220: 98 | L220: AMOMPY | M220: Momentum Capital Investment S.A. | N220: 14/07/2026 | O220: 14/07/2026 | P220: 32 | Q220: No | U220: *MAV031001194 | V220: *MAV031001194 | W220: =+J220/$W$2 -> 4.2470542e-05
A221: ESPECIALIDADES AGROPECUARIAS S.A. | B221: Pesos | C221: 46302 | D221: 29/09/2026 | E221: 0.9930352 | G221: 4000000 | H221: 3972140.8 | I221: 4000000 | J221: 3972140.8 | K221: 1145 | L221: AMOMPY | M221: Momentum Capital Investment S.A. | N221: 03/09/2026 | O221: 03/09/2026 | P221: 32 | Q221: No | U221: *MAV051001367 | V221: *MAV051001367 | W221: =+J221/$W$2 -> 5.2807899e-05
A222: ESPECIALIDADES AGROPECUARIAS S.A. | B222: Pesos | C222: 46302 | D222: 29/09/2026 | E222: 0.99346769 | G222: 5000000 | H222: 4967338.5 | I222: 5000000 | J222: 4967338.5 | K222: 1216 | L222: AMOMPY | M222: Momentum Capital Investment S.A. | N222: 11/09/2026 | O222: 11/09/2026 | P222: 30 | Q222: No | U222: *MAV051001506 | V222: *MAV051001506 | W222: =+J222/$W$2 -> 6.6038623e-05
A223: ESPECIALIDADES AGROPECUARIAS S.A. | B223: Pesos | C223: 46302 | D223: 29/09/2026 | E223: 0.99346762 | G223: 5000000 | H223: 4967338.1 | I223: 5000000 | J223: 4967338.1 | K223: 1195 | L223: AMOMPY | M223: Momentum Capital Investment S.A. | N223: 08/09/2026 | O223: 08/09/2026 | P223: 30 | Q223: No | U223: *MAV051001476 | V223: *MAV051001476 | W223: =+J223/$W$2 -> 6.6038618e-05
A224: ESPECIALIDADES AGROPECUARIAS S.A. | B224: Pesos | C224: 46302 | D224: 29/09/2026 | E224: 0.99346768 | G224: 5000000 | H224: 4967338.4 | I224: 5000000 | J224: 4967338.4 | K224: 1222 | L224: AMOMPY | M224: Momentum Capital Investment S.A. | N224: 14/09/2026 | O224: 14/09/2026 | P224: 30 | Q224: No | U224: *MAV051001515 | V224: *MAV051001515 | W224: =+J224/$W$2 -> 6.6038622e-05
A225: PERALTA CLAUDIO SANTIAGO | B225: Pesos | C225: 46302 | D225: 29/09/2026 | E225: 0.99346769 | G225: 3000000 | H225: 2980403.1 | I225: 3000000 | J225: 2980403.1 | K225: 2661 | L225: AMOMPY | M225: Momentum Capital Investment S.A. | N225: 24/09/2026 | O225: 24/09/2026 | P225: 30 | Q225: No | U225: *MAV031001514 | V225: *MAV031001514 | W225: =+J225/$W$2 -> 3.9623174e-05
... A374: INTEGRA PYMES SGR | B374: Pesos | C374: 46309 | D374: 29/09/2026 | E374: 0.99023335 | G374: 5000000 | H374: 4951166.7 | I374: 5000000 | J374: 4951166.7 | K374: 16831531 | L374: AMOMPY | M374: Momentum Capital Investment S.A. | N374: 21/07/2026 | O374: 21/07/2026 | P374: 24 | Q374: No | U374: *INP091000050 | V374: *INP091000050 | W374: =+J374/$W$2 -> 6.5823627e-05
A375: CAL/WEST SEEDS SRL | B375: Dolar Link | C375: 46309 | D375: 29/09/2026 | E375: 0.99387333 | F375: 1 BNA = 1544,9999783700 $ | G375: 33187.68 | H375: 32984.35 | I375: 51274965 | J375: 50960820 | K375: 6359 | L375: AMOMPY | M375: Momentum Capital Investment S.A. | N375: 21/09/2026 | O375: 21/09/2026 | P375: 15 | Q375: No | U375: %UZV121000001 | V375: %UZV121000001 | W375: =+J375/$W$2 -> 0.00067750213
A376: ESPECIALIDADES AGROPECUARIAS S.A. | B376: Pesos | C376: 46309 | D376: 29/09/2026 | E376: 0.98702009 | G376: 10000000 | H376: 9870200.9 | I376: 10000000 | J376: 9870200.9 | K376: 1085 | L376: AMOMPY | M376: Momentum Capital Investment S.A. | N376: 27/08/2026 | O376: 27/08/2026 | P376: 32 | Q376: No | U376: *MAV091001544 | V376: *MAV091001544 | W376: =+J376/$W$2 -> 0.00013122007
A377: ESPECIALIDADES AGROPECUARIAS S.A. | B377: Pesos | C377: 46309 | D377: 29/09/2026 | E377: 0.98702003 | G377: 3000000 | H377: 2961060.1 | I377: 3000000 | J377: 2961060.1 | K377: 1039 | L377: AMOMPY | M377: Momentum Capital Investment S.A. | N377: 25/08/2026 | O377: 25/08/2026 | P377: 32 | Q377: No | U377: *MAV091001512 | V377: *MAV091001512 | W377: =+J377/$W$2 -> 3.9366017e-05
A378: LEIVA HERMANOS SA | B378: Pesos | C378: 46309 | D378: 29/09/2026 | E378: 0.98662002 | G378: 1448241.7 | H378: 1428864.2 | I378: 1448241.7 | J378: 1428864.2 | K378: 18652221 | L378: AMOMPY | M378: Momentum Capital Investment S.A. | N378: 25/09/2026 | O378: 25/09/2026 | P378: 33 | Q378: No | U378: *MAV091001993 | V378: *MAV091001993 | W378: =+J378/$W$2 -> 1.8996134e-05
A379: Grupo Grafico del Norte SA | B379: Pesos | C379: 46309 | D379: 29/09/2026 | E379: 0.98702006 | G379: 3023662.8 | H379: 2984415.8 | I379: 3023662.8 | J379: 2984415.8 | K379: 2527 | L379: AMOMPY | M379: Momentum Capital Investment S.A. | N379: 14/07/2026 | O379: 14/07/2026 | P379: 32 | Q379: No | U379: *MAV091001182 | V379: *MAV091001182 | W379: =+J379/$W$2 -> 3.9676521e-05
A380: Casa Hutton SA | B380: Pesos | C380: 46309 | D380: 29/09/2026 | E380: 0.98702005 | G380: 15000000 | H380: 14805301 | I380: 15000000 | J380: 14805301 | K380: 13953461 | L380: AMOMPY | M380: Momentum Capital Investment S.A. | N380: 14/07/2026 | O380: 14/07/2026 | P380: 32 | Q380: No | U380: *MAV091001183 | V380: *MAV091001183 | W380: =+J380/$W$2 -> 0.00019683009
A381: Casa Hutton SA | B381: Pesos | C381: 46309 | D381: 29/09/2026 | E381: 0.98702004 | G381: 40000000 | H381: 39480801 | I381: 40000000 | J381: 39480801 | K381: 13795908 | L381: AMOMPY | M381: Momentum Capital Investment S.A. | N381: 25/06/2026 | O381: 25/06/2026 | P381: 32 | Q381: No | U381: *MAV091001118 | V381: *MAV091001118 | W381: =+J381/$W$2 -> 0.00052488023
A382: MONDELEZ ARG SA | B382: Dolar Link | C382: 46309 | D382: 29/09/2026 | E382: 0.99387381 | F382: 1 BNA = 1544,9999783700 $ | G382: 6354.68 | H382: 6315.75 | I382: 9817980.5 | J382: 9757833.6 | K382: 72 | L382: AMOMPY | M382: Momentum Capital Investment S.A. | N382: 16/09/2026 | O382: 16/09/2026 | P382: 15 | Q382: No | U382: %UON101000001 | V382: %UON101000001 | W382: =+J382/$W$2 -> 0.00012972619
A383: TRANSPORTES C Y S 2011 SRL | B383: Pesos | C383: 46309 | D383: 29/09/2026 | E383: 0.98742055 | G383: 388276.23 | H383: 383391.93 | I383: 388276.23 | J383: 383391.93 | K383: 5473 | L383: AMOMPY | M383: Momentum Capital Investment S.A. | N383: 08/09/2026 | O383: 08/09/2026 | P383: 31 | Q383: No | U383: *MAV091001697 | V383: *MAV091001697 | W383: =+J383/$W$2 -> 5.0970304e-06
A384: LOS GROBO SGR | B384: Pesos | C384: 46309 | D384: 29/09/2026 | E384: 0.98862405 | G384: 10950000 | H384: 10825433 | I384: 10950000 | J384: 10825433 | K384: 90000870 | L384: AMOMPY | M384: Momentum Capital Investment S.A. | N384: 13/08/2026 | O384: 13/08/2026 | P384: 28 | Q384: No | U384: *PRO091000013 | V384: *PRO091000013 | W384: =+J384/$W$2 -> 0.00014391947
A385: GOBIERNO DE LA CUIDAD DE BUENOS AIRES | B385: Pesos | C385: 46309 | D385: 29/09/2026 | E385: 0.9886241 | G385: 43906518 | H385: 43407042 | I385: 43906518 | J385: 43407042 | K385: 40292985 | L385: AMOMPY | M385: Momentum Capital Investment S.A. | N385: 12/08/2026 | O385: 12/08/2026 | P385: 28 | Q385: No | U385: *MAV091001340 | V385: *MAV091001340 | W385: =+J385/$W$2 -> 0.00057707791
A386: GOBIERNO DE LA CUIDAD DE BUENOS AIRES | B386: Pesos | C386: 46309 | D386: 29/09/2026 | E386: 0.9886241 | G386: 42705929 | H386: 42220111 | I386: 42705929 | J386: 42220111 | K386: 40293026 | L386: AMOMPY | M386: Momentum Capital Investment S.A. | N386: 12/08/2026 | O386: 12/08/2026 | P386: 28 | Q386: No | U386: *MAV091001341 | V386: *MAV091001341 | W386: =+J386/$W$2 -> 0.00056129817
A387: GOBIERNO DE LA CUIDAD DE BUENOS AIRES | B387: Pesos | C387: 46309 | D387: 29/09/2026 | E387: 0.9886241 | G387: 43306224 | H387: 42813576 | I387: 43306224 | J387: 42813576 | K387: 40293006 | L387: AMOMPY | M387: Momentum Capital Investment S.A. | N387: 12/08/2026 | O387: 12/08/2026 | P387: 28 | Q387: No | U387: *MAV091001342 | V387: *MAV091001342 | W387: =+J387/$W$2 -> 0.00056918804
A388: CELULOSA CAMPANA SA | B388: Pesos | C388: 46309 | D388: 29/09/2026 | E388: 0.98702001 | G388: 14479900 | H388: 14291951 | I388: 14479900 | J388: 14291951 | K388: 9933004 | L388: AMOMPY | M388: Momentum Capital Investment S.A. | N388: 12/06/2026 | O388: 12/06/2026 | P388: 32 | Q388: No | U388: *MAV091001103 | V388: *MAV091001103 | W388: =+J388/$W$2 -> 0.00019000532
A389: MILLS S.G.R. | B389: Pesos | C389: 46309 | D389: 29/09/2026 | E389: 0.98983053 | G389: 50000000 | H389: 49491526 | I389: 50000000 | J389: 49491526 | K389: 14032588 | L389: AMOMPY | M389: Momentum Capital Investment S.A. | N389: 20/07/2026 | O389: 20/07/2026 | P389: 25 | Q389: No | U389: *MIL091000034 | V389: *MIL091000034 | W389: =+J389/$W$2 -> 0.0006579685
A390: MILLS S.G.R. | B390: Pesos | C390: 46309 | D390: 29/09/2026 | E390: 0.98983053 | G390: 8650000 | H390: 8562034.1 | I390: 8650000 | J390: 8562034.1 | K390: 34386 | L390: AMOMPY | M390: Momentum Capital Investment S.A. | N390: 20/07/2026 | O390: 20/07/2026 | P390: 25 | Q390: No | U390: *MIL091000035 | V390: *MIL091000035 | W390: =+J390/$W$2 -> 0.00011382855
A391: MILLS S.G.R. | B391: Pesos | C391: 46309 | D391: 29/09/2026 | E391: 0.9878214 | G391: 5000000 | H391: 4939107 | I391: 5000000 | J391: 4939107 | K391: 8777 | L391: AMOMPY | M391: Momentum Capital Investment S.A. | N391: 14/08/2026 | O391: 14/08/2026 | P391: 30 | Q391: No | U391: *MIL091000039 | V391: *MIL091000039 | W391: =+J391/$W$2 -> 6.5663298e-05
A392: SUPERMERCADOS LA ECONOMIA SA | B392: Pesos | C392: 46309 | D392: 29/09/2026 | E392: 0.98702009 | G392: 18239769 | H392: 18003019 | I392: 18239769 | J392: 18003019 | K392: 3494369 | L392: AMOMPY | M392: Momentum Capital Investment S.A. | N392: 20/08/2026 | O392: 20/08/2026 | P392: 32 | Q392: No | U392: *MAV091001460 | V392: *MAV091001460 | W392: =+J392/$W$2 -> 0.00023934237
A393: ULAN SRL | B393: Pesos | C393: 46309 | D393: 29/09/2026 | E393: 0.98742063 | G393: 40000000 | H393: 39496825 | I393: 40000000 | J393: 39496825 | K393: 88 | L393: AMOMPY | M393: Momentum Capital Investment S.A. | N393: 31/08/2026 | O393: 31/08/2026 | P393: 31 | Q393: No | U393: *MAV091001586 | V393: *MAV091001586 | W393: =+J393/$W$2 -> 0.00052509326
A394: CARNICELLINI SRL | B394: Pesos | C394: 46309 | D394: 29/09/2026 | E394: 0.98742064 | G394: 6742842 | H394: 6658021.3 | I394: 6742842 | J394: 6658021.3 | K394: 182672 | L394: AMOMPY | M394: Momentum Capital Investment S.A. | N394: 07/09/2026 | O394: 07/09/2026 | P394: 31 | Q394: No | U394: *MAV091001679 | V394: *MAV091001679 | W394: =+J394/$W$2 -> 8.8515523e-05
... A534: BUROMAHTIK SA | B534: Pesos | C534: 46311 | D534: 29/09/2026 | E534: 0.98396012 | G534: 3455000 | H534: 3399582.2 | I534: 3455000 | J534: 3399582.2 | K534: 40773792 | L534: AMOMPY | M534: Momentum Capital Investment S.A. | N534: 12/08/2026 | O534: 12/08/2026 | P534: 35 | Q534: No | U534: *MAV141001567 | V534: *MAV141001567 | W534: =+J534/$W$2 -> 4.519598e-05
A535: PUNTO PACK SRL | B535: Dolar 3500 | C535: 46311 | D535: 29/09/2026 | E535: 0.99628799 | F535: 1 US3 = 1523,9697583441 $ | G535: 18230 | H535: 18162.33 | I535: 27781969 | J535: 27678842 | K535: 146445 | L535: AMOMPY | M535: Momentum Capital Investment S.A. | N535: 17/04/2026 | O535: 17/04/2026 | P535: 8 | Q535: No | U535: #UMV141060033 | V535: #UMV141060033 | W535: =+J535/$W$2 -> 0.00036797827
A536: TEXTUM SA | B536: Pesos | C536: 46311 | D536: 29/09/2026 | E536: 0.98486283 | G536: 36666666 | H536: 36111637 | I536: 36666666 | J536: 36111637 | K536: 14537769 | L536: AMOMPY | M536: Momentum Capital Investment S.A. | N536: 14/09/2026 | O536: 14/09/2026 | P536: 33 | Q536: No | U536: *MAV141001911 | V536: *MAV141001911 | W536: =+J536/$W$2 -> 0.00048008864
A537: TEXTUM SA | B537: Pesos | C537: 46311 | D537: 29/09/2026 | E537: 0.98486291 | G537: 25000000 | H537: 24621573 | I537: 25000000 | J537: 24621573 | K537: 14422592 | L537: AMOMPY | M537: Momentum Capital Investment S.A. | N537: 02/09/2026 | O537: 02/09/2026 | P537: 33 | Q537: No | U537: *MAV141001747 | V537: *MAV141001747 | W537: =+J537/$W$2 -> 0.00032733319
A538: TEXTUM SA | B538: Pesos | C538: 46311 | D538: 29/09/2026 | E538: 0.98531484 | G538: 10000000 | H538: 9853148.4 | I538: 10000000 | J538: 9853148.4 | K538: 14422565 | L538: AMOMPY | M538: Momentum Capital Investment S.A. | N538: 01/09/2026 | O538: 01/09/2026 | P538: 32 | Q538: No | U538: *MAV141001736 | V538: *MAV141001736 | W538: =+J538/$W$2 -> 0.00013099336
A539: CAMPOS ORGANICOS S.A | B539: Pesos | C539: 46311 | D539: 29/09/2026 | E539: 0.9844113 | G539: 10000000 | H539: 9844113 | I539: 10000000 | J539: 9844113 | K539: 6034859 | L539: AMOMPY | M539: Momentum Capital Investment S.A. | N539: 27/07/2026 | O539: 27/07/2026 | P539: 34 | Q539: No | U539: *MAV141001459 | V539: *MAV141001459 | W539: =+J539/$W$2 -> 0.00013087324
A540: INNOVA S.G.R. | B540: Pesos | C540: 46311 | D540: 29/09/2026 | E540: 0.98803549 | G540: 5000000 | H540: 4940177.5 | I540: 5000000 | J540: 4940177.5 | K540: 92147552 | L540: AMOMPY | M540: Momentum Capital Investment S.A. | N540: 24/09/2026 | O540: 24/09/2026 | P540: 26 | Q540: No | U540: NOVA141000008 | V540: NOVA141000008 | W540: =+J540/$W$2 -> 6.5677529e-05
A541: TREND SGR | B541: Pesos | C541: 46311 | D541: 29/09/2026 | E541: 0.98803535 | G541: 4636054.5 | H541: 4580585.7 | I541: 4636054.5 | J541: 4580585.7 | K541: 69910366 | L541: AMOMPY | M541: Momentum Capital Investment S.A. | N541: 25/09/2026 | O541: 25/09/2026 | P541: 26 | Q541: No | U541: *TRD141000160 | V541: *TRD141000160 | W541: =+J541/$W$2 -> 6.0896912e-05
A542: SOMOS INTEGRA SRL | B542: Pesos | C542: 46311 | D542: 29/09/2026 | E542: 0.98622 | G542: 5674198 | H542: 5596007.5 | I542: 5674198 | J542: 5596007.5 | K542: 90044976 | L542: AMOMPY | M542: Momentum Capital Investment S.A. | N542: 11/09/2026 | O542: 11/09/2026 | P542: 30 | Q542: No | U542: *MAV141001878 | V542: *MAV141001878 | W542: =+J542/$W$2 -> 7.4396507e-05
A543: ESPECIALIDADES AGROPECUARIAS S.A. | B543: Pesos | C543: 46311 | D543: 29/09/2026 | E543: 0.98621996 | G543: 4000000 | H543: 3944879.8 | I543: 4000000 | J543: 3944879.8 | K543: 860 | L543: AMOMPY | M543: Momentum Capital Investment S.A. | N543: 05/08/2026 | O543: 05/08/2026 | P543: 30 | Q543: No | U543: *MAV141001515 | V543: *MAV141001515 | W543: =+J543/$W$2 -> 5.2445476e-05
A544: ESPECIALIDADES AGROPECUARIAS S.A. | B544: Pesos | C544: 46311 | D544: 29/09/2026 | E544: 0.98621998 | G544: 2500000 | H544: 2465550 | I544: 2500000 | J544: 2465550 | K544: 883 | L544: AMOMPY | M544: Momentum Capital Investment S.A. | N544: 06/08/2026 | O544: 06/08/2026 | P544: 30 | Q544: No | U544: *MAV141001530 | V544: *MAV141001530 | W544: =+J544/$W$2 -> 3.2778423e-05
A545: ESPECIALIDADES AGROPECUARIAS S.A. | B545: Pesos | C545: 46311 | D545: 29/09/2026 | E545: 0.98621999 | G545: 2500000 | H545: 2465550 | I545: 2500000 | J545: 2465550 | K545: 913 | L545: AMOMPY | M545: Momentum Capital Investment S.A. | N545: 10/08/2026 | O545: 10/08/2026 | P545: 30 | Q545: No | U545: *MAV141001541 | V545: *MAV141001541 | W545: =+J545/$W$2 -> 3.2778424e-05
A546: INTEGRA PYMES SGR | B546: Pesos | C546: 46314 | D546: 29/09/2026 | E546: 0.9848894 | G546: 30000000 | H546: 29546682 | I546: 30000000 | J546: 29546682 | K546: 29600865 | L546: AMOMPY | M546: Momentum Capital Investment S.A. | N546: 07/07/2026 | O546: 07/07/2026 | P546: 28 | Q546: No | U546: *INP151000082 | V546: *INP151000082 | W546: =+J546/$W$2 -> 0.0003928104
A547: ESPECIALIDADES AGROPECUARIAS S.A. | B547: Pesos | C547: 46314 | D547: 29/09/2026 | E547: 0.98382753 | G547: 10000000 | H547: 9838275.2 | I547: 10000000 | J547: 9838275.2 | K547: 726 | L547: AMOMPY | M547: Momentum Capital Investment S.A. | N547: 30/06/2026 | O547: 30/06/2026 | P547: 30 | Q547: No | U547: *MAV151001396 | V547: *MAV151001396 | W547: =+J547/$W$2 -> 0.00013079563
... A636: TECNOGRAFIC | B636: Pesos | C636: 46316 | D636: 29/09/2026 | E636: 0.98107735 | G636: 27150000 | H636: 26636250 | I636: 27150000 | J636: 26636250 | K636: 29768697 | L636: AMOMPY | M636: Momentum Capital Investment S.A. | N636: 31/07/2026 | O636: 31/07/2026 | P636: 32 | Q636: No | U636: *MAV191000908 | V636: *MAV191000908 | W636: =+J636/$W$2 -> 0.00035411746
A637: MONDELEZ ARG SA | B637: Dolar Link | C637: 46316 | D637: 29/09/2026 | E637: 0.99104012 | F637: 1 BNA = 1544,9999783700 $ | G637: 20534.87 | H637: 20350.88 | I637: 31726374 | J637: 31442109 | K637: 70 | L637: AMOMPY | M637: Momentum Capital Investment S.A. | N637: 16/09/2026 | O637: 16/09/2026 | P637: 15 | Q637: No | U637: %UON201000003 | V637: %UON201000003 | W637: =+J637/$W$2 -> 0.00041800928
A638: MONDELEZ ARG SA | B638: Dolar Link | C638: 46316 | D638: 29/09/2026 | E638: 0.99103984 | F638: 1 BNA = 1544,9999783700 $ | G638: 24316.54 | H638: 24098.66 | I638: 37569054 | J638: 37232429 | K638: 71 | L638: AMOMPY | M638: Momentum Capital Investment S.A. | N638: 16/09/2026 | O638: 16/09/2026 | P638: 15 | Q638: No | U638: %UON201000002 | V638: %UON201000002 | W638: =+J638/$W$2 -> 0.00049498909
A639: MONDELEZ ARG SA | B639: Dolar Link | C639: 46316 | D639: 29/09/2026 | E639: 0.99104005 | F639: 1 BNA = 1544,9999783700 $ | G639: 16608.35 | H639: 16459.54 | I639: 25659900 | J639: 25429989 | K639: 74 | L639: AMOMPY | M639: Momentum Capital Investment S.A. | N639: 16/09/2026 | O639: 16/09/2026 | P639: 15 | Q639: No | U639: %UON201000001 | V639: %UON201000001 | W639: =+J639/$W$2 -> 0.00033808074
A640: PAPEL IMPORTANTE SA | B640: Pesos | C640: 46316 | D640: 29/09/2026 | E640: 0.98049753 | G640: 284785 | H640: 279230.99 | I640: 284785 | J640: 279230.99 | K640: 13757767 | L640: AMOMPY | M640: Momentum Capital Investment S.A. | N640: 15/09/2026 | O640: 15/09/2026 | P640: 33 | Q640: No | U640: *MAV171001550 | V640: *MAV171001550 | W640: =+J640/$W$2 -> 3.7122556e-06
A641: EDGAR E PASTORE Y CIA S R L | B641: Pesos | C641: 46316 | D641: 29/09/2026 | E641: 0.98165782 | G641: 30000000 | H641: 29449734 | I641: 30000000 | J641: 29449734 | K641: 8713 | L641: AMOMPY | M641: Momentum Capital Investment S.A. | N641: 15/09/2026 | O641: 15/09/2026 | P641: 31 | Q641: No | U641: *MAV191001190 | V641: *MAV191001190 | W641: =+J641/$W$2 -> 0.00039152152
A642: EDGAR E PASTORE Y CIA S R L | B642: Pesos | C642: 46316 | D642: 29/09/2026 | E642: 0.98165782 | G642: 30000000 | H642: 29449734 | I642: 30000000 | J642: 29449734 | K642: 8712 | L642: AMOMPY | M642: Momentum Capital Investment S.A. | N642: 15/09/2026 | O642: 15/09/2026 | P642: 31 | Q642: No | U642: *MAV191001191 | V642: *MAV191001191 | W642: =+J642/$W$2 -> 0.00039152152
A643: EDGAR E PASTORE Y CIA S R L | B643: Pesos | C643: 46316 | D643: 29/09/2026 | E643: 0.98165782 | G643: 30000000 | H643: 29449734 | I643: 30000000 | J643: 29449734 | K643: 8714 | L643: AMOMPY | M643: Momentum Capital Investment S.A. | N643: 15/09/2026 | O643: 15/09/2026 | P643: 31 | Q643: No | U643: *MAV191001193 | V643: *MAV191001193 | W643: =+J643/$W$2 -> 0.00039152152
A644: EDGAR E PASTORE Y CIA S R L | B644: Pesos | C644: 46316 | D644: 29/09/2026 | E644: 0.98165782 | G644: 30000000 | H644: 29449734 | I644: 30000000 | J644: 29449734 | K644: 8715 | L644: AMOMPY | M644: Momentum Capital Investment S.A. | N644: 15/09/2026 | O644: 15/09/2026 | P644: 31 | Q644: No | U644: *MAV191001194 | V644: *MAV191001194 | W644: =+J644/$W$2 -> 0.00039152152
A645: LOS GROBO SGR | B645: Pesos | C645: 46316 | D645: 29/09/2026 | E645: 0.98515531 | G645: 599708.56 | H645: 590806.07 | I645: 599708.56 | J645: 590806.07 | K645: 40791017 | L645: AMOMPY | M645: Momentum Capital Investment S.A. | N645: 24/09/2026 | O645: 24/09/2026 | P645: 25 | Q645: No | U645: *PRO171000012 | V645: *PRO171000012 | W645: =+J645/$W$2 -> 7.854512e-06
A646: LOS GROBO SGR | B646: Pesos | C646: 46316 | D646: 29/09/2026 | E646: 0.98515532 | G646: 899857.14 | H646: 886499.05 | I646: 899857.14 | J646: 886499.05 | K646: 1150215 | L646: AMOMPY | M646: Momentum Capital Investment S.A. | N646: 24/09/2026 | O646: 24/09/2026 | P646: 25 | Q646: No | U646: *PRO171000013 | V646: *PRO171000013 | W646: =+J646/$W$2 -> 1.1785623e-05
...

Sheet Posicion cuotapartista
A1: Posición de Cuotapartista
A2: Fondo | B2: Cuotapartista | C2: Tipo de Valor Cuotaparte | D2: Cuotapartes | E2: Inversión | F2: Moneda | G2: Fondo | H2: Tipo de Inversor | I2: Fondo | J2: Porcentaje
A3: Nombre | B3: Nombre | F3: Símbolo | G3: Fecha Valor Cuotaparte | I3: Valor Cuotaparte
A4: AMOMPY | B4: ZOFINGEN SECURITIES S.A. (ACDI) | C4: C | D4: 1.4303235e+09 | E4: 2.6192799e+09 | F4: $ | G4: 29/09/2026 | H4: Agentes de Colocación y Distribución Integral de FCIs | I4: 1.83125 | J4: 4.5658608
A5: AMOMPY | B5: BANCO DE LA CIUDAD DE BUENOS AIRES | C5: C | D5: 1.8078341e+09 | E5: 3.3105962e+09 | F5: $ | G5: 29/09/2026 | H5: Agentes de Colocación y Distribución Integral de FCIs | I5: 1.83125 | J5: 5.7709456
A6: AMOMPY | B6: MOMENTUM CAPITAL INVESTMENT S.A. (ACDI) | C6: C | D6: 2.5797363e+10 | E6: 4.724142e+10 | F6: $ | G6: 29/09/2026 | H6: Agentes de Colocación y Distribución Integral de FCIs | I6: 1.83125 | J6: 82.35002
A7: AMOMPY | B7: ALYCBUR S.A. (ACDI) | C7: C | D7: 3.1629211e+08 | E7: 5.7920992e+08 | F7: $ | G7: 29/09/2026 | H7: Agentes de Colocación y Distribución Integral de FCIs | I7: 1.83125 | J7: 1.0096637
A8: AMOMPY | B8: BANCO DE SAN JUAN SA ( ACDI ) | C8: C | D8: 1.683916e+09 | E8: 3.0836712e+09 | F8: $ | G8: 29/09/2026 | H8: Agentes de Colocación y Distribución Integral de FCIs | I8: 1.83125 | J8: 5.3753757
A9: AMOMPY | B9: BANCO DE SANTA CRUZ SA (ACDI) | C9: C | D9: 2.9075177e+08 | E9: 5.3243917e+08 | F9: $ | G9: 29/09/2026 | H9: Agentes de Colocación y Distribución Integral de FCIs | I9: 1.83125 | J9: 0.92813418
A10: AMOMPY | B10: MOMENTUM CAPITAL INVESTMENT S.A. (ACDI) | C10: A | D10: 4.2636536e+09 | E10: 6.467873e+09 | F10: $ | G10: 29/09/2026 | H10: Agentes de Colocación y Distribución Integral de FCIs | I10: 1.516979 | J10: 93.939655
A11: AMOMPY | B11: ALYCBUR S.A. (ACDI) | C11: A | D11: 2.7506183e+08 | E11: 4.1726302e+08 | F11: $ | G11: 29/09/2026 | H11: Agentes de Colocación y Distribución Integral de FCIs | I11: 1.516979 | J11: 6.0603454
A12: AMOMPY | B12: MOMENTUM CAPITAL INVESTMENT S.A. (ACDI) | C12: B | D12: 5.8641128e+09 | E12: 1.0659479e+10 | F12: $ | G12: 29/09/2026 | H12: Agentes de Colocación y Distribución Integral de FCIs | I12: 1.817748 | J12: 97.196525
A13: AMOMPY | B13: ALYCBUR S.A. (ACDI) | C13: B | D13: 1.6914077e+08 | E13: 3.074553e+08 | F13: $ | G13: 29/09/2026 | H13: Agentes de Colocación y Distribución Integral de FCIs | I13: 1.817748 | J13: 2.8034753
D14: 4.1898449e+10 | E14: 7.5218687e+10
